Workbook
Name TRANSFER: #REF!
Name TRANSFER: #REF!
Name ID: 'INVONTERY FEB'!$A$6:$A$131
Name MANAGER: #REF!
Name DEPARTMENT: #REF!
Name TOTAL_CHICKEN_AMOUNT: #REF!
Name TRANSFER: #REF!
Name TRANSFER: #REF!
Name DEPARTMENT: #REF!
Name DEPARTMENT: #REF!
Name MANAGER: #REF!
Name SUPPLIERS: 'AMOUNT UPDATE'!$B$4:$B$19
Name MANAGER: #REF!

Sheet P&L WITH EXP.
A1: TU
A2: 45839
A3: DETAILS | B3: Actual | C3: %
A4: Product Sales | B4: ='DAILY UPDATE'!BR36 -> 2800162 | C4: 1
A5: FOOD | B5: ='INVONTERY FEB'!P108 -> 1379224.3 | C5: =B5/B$4 -> 0.4925516
A6: PAPER ITEMS | B6: ='INVONTERY FEB'!P131 -> 56947 | C6: =B6/B$4 -> 0.020337038
A7: DISTRIBUTION COST | B7: =SUMIF(EXPENSES!$B:$B,'P&L WITH EXP.'!A7,EXPENSES!$F:$F) -> 20500 | C7: =B7/B$4 -> 0.007321005
A8: CLEANING | B8: ='INVONTERY FEB'!P147 -> 1849 | C8: =B8/B$4 -> 0.00066031894
A9: PAYROLL | B9: =SUMIF(EXPENSES!$B:$B,'P&L WITH EXP.'!A9,EXPENSES!$F:$F) -> 390667 | C9: =B9/B$4 -> 0.13951586
A10: EMPLOYEE MEAL | B10: =SUMIF(EXPENSES!$B:$B,'P&L WITH EXP.'!A10,EXPENSES!$F:$F) -> 45000 | C10: =B10/B$4 -> 0.016070499
A11: APARTMENT | B11: =SUMIF(EXPENSES!$B:$B,'P&L WITH EXP.'!A11,EXPENSES!$F:$F) -> 0 | C11: =B11/B$4 -> 0
A12: M&R | B12: =SUMIF(EXPENSES!$B:$B,'P&L WITH EXP.'!A12,EXPENSES!$F:$F) -> 0 | C12: =B12/B$4 -> 0
A13: UNIFORM | B13: =SUMIF(EXPENSES!$B:$B,'P&L WITH EXP.'!A13,EXPENSES!$F:$F) -> 0 | C13: =B13/B$4 -> 0
A14: UTILITIES | B14: =SUMIF(EXPENSES!$B:$B,'P&L WITH EXP.'!A14,EXPENSES!$F:$F) -> 283634 | C14: =B14/B$4 -> 0.101292
A15: CROCKERY | B15: =SUMIF(EXPENSES!$B:$B,'P&L WITH EXP.'!A15,EXPENSES!$F:$F) -> 0 | C15: =B15/B$4 -> 0
A17: Total Con. Exp | B17: =SUM(B5:B16) -> 2177821.3 | C17: =B17/B$4 -> 0.77774832
A19: PAC | B19: =B4-B17 -> 622340.72 | C19: =B19/B$4 -> 0.22225168
A21: DIRECTOR | B21: =SUMIF(EXPENSES!$B:$B,'P&L WITH EXP.'!A21,EXPENSES!$F:$F) -> 620000 | C21: =B21/B$4 -> 0.22141576
A23: REMAINING CASH | B23: =B19-B21 -> 2340.7175 | C23: =B23/B$4 -> 0.00083592218
A24: TOTAL EXP AMOUNT | B24: =+B21+B17 -> 2797821.3
A26: CASH DETAIL
A27: OP. CASH | B27: ='DAILY UPDATE'!BQ5 -> 420
A28: SALE | B28: =B4 -> 2800162
A29: EXP | B29: =EXPENSES!F1 -> 2796174
A30: BAL | B30: =B27+B29-B29 -> 420
A31: DIFF | B31: =+B30-B27 -> 0
A32: DIFF FROM PNL CASH | B32: =+B23-B31 -> 2340.7175
A33: INVENTORY | B33: CURRENT MONTH | C33: LAST MONTH | D33: DIFF
A34: ='INVONTERY FEB'!C326 -> PHYSICAL INVENTORY | B34: ='INVONTERY FEB'!L326 -> 2010397.1 | C34: ='INVONTERY FEB'!F326 -> 2019838 | D34: =+B34-C34 -> -9440.906
A35: ='INVONTERY FEB'!C327 -> CREDIT AMOUNT | B35: ='INVONTERY FEB'!L327 -> -0.37652036 | C35: ='INVONTERY FEB'!F327 -> 0 | D35: =+B35-C35 -> -0.37652036
A36: ='INVONTERY FEB'!C328 -> STOCK IN HAND | B36: ='INVONTERY FEB'!L328 -> 2010396.8 | C36: ='INVONTERY FEB'!F328 -> 2019838 | D36: =+B36-C36 -> -9441.2825
A38: CASH HANDOVER | B38: =+B21 -> 620000
A39: CASH DIFF | B39: =+B31 -> 0
A40: STOCK DIFF | B40: =+D36 -> -9441.2825
A41: ACTUAL PROFIT & LOSS | B41: =+B40+B39+B38 -> 610558.72

Sheet PURCHASE
A1: (PURCHASE / STOCK IN/ RECEIVE) PRODUCTS FROM VENDOR
A2: INV # | B2: DATE | C2: SUPPLIER NAME | D2: ID | E2: PRODUCT DETAIL | F2: UNIT | G2: RATE | H2: QTY | I2: CREDIT AMOUNT | J2: DEBIT AMOUNT | K2: COMMENTS
B3: 46055 | C3: ELAHE EGGS TRADER | D3: 7 | E3: =IFERROR(VLOOKUP(D3,'INVONTERY FEB'!$A$6:$B$432,2,FALSE),"") -> EGGS | F3: =IFERROR(VLOOKUP(E3,'INVONTERY FEB'!$B$6:$C$432,2,FALSE),"") -> PCS | G3: =20600/720 -> 28.611111 | H3: 720 | I3: =IFERROR((H3*G3),"") -> 20600
B4: 46056 | C4: MIAN SHOUKAT TRADERS | D4: 42 | E4: =IFERROR(VLOOKUP(D4,'INVONTERY FEB'!$A$6:$B$432,2,FALSE),"") -> PISTACHIO SAPREAD | F4: =IFERROR(VLOOKUP(E4,'INVONTERY FEB'!$B$6:$C$432,2,FALSE),"") -> KG | G4: =IFERROR(VLOOKUP(E4,'INVONTERY FEB'!$B$6:$D$131,3,FALSE),"") -> 5200 | H4: 9 | I4: =IFERROR((H4*G4),"") -> 46800
B5: 46057 | C5: ELAHE EGGS TRADER | D5: 7 | E5: =IFERROR(VLOOKUP(D5,'INVONTERY FEB'!$A$6:$B$432,2,FALSE),"") -> EGGS | F5: =IFERROR(VLOOKUP(E5,'INVONTERY FEB'!$B$6:$C$432,2,FALSE),"") -> PCS | G5: =9500/360 -> 26.388889 | H5: 360 | I5: =IFERROR((H5*G5),"") -> 9500
B6: 46057 | C6: HAFFIZ MAHMOOD | D6: 56 | E6: =IFERROR(VLOOKUP(D6,'INVONTERY FEB'!$A$6:$B$432,2,FALSE),"") -> FERRY ROSE | F6: =IFERROR(VLOOKUP(E6,'INVONTERY FEB'!$B$6:$C$432,2,FALSE),"") -> BOX | G6: =IFERROR(VLOOKUP(E6,'INVONTERY FEB'!$B$6:$D$131,3,FALSE),"") -> 1000 | H6: 10 | I6: =IFERROR((H6*G6),"") -> 10000
B7: 46057 | C7: HAFFIZ MAHMOOD | D7: 37 | E7: =IFERROR(VLOOKUP(D7,'INVONTERY FEB'!$A$6:$B$432,2,FALSE),"") -> HISS CHOCLATE 2 RINGS | F7: =IFERROR(VLOOKUP(E7,'INVONTERY FEB'!$B$6:$C$432,2,FALSE),"") -> BOX | G7: =16000/18 -> 888.88889 | H7: 18 | I7: =IFERROR((H7*G7),"") -> 16000
B8: 46057 | C8: HAFFIZ MAHMOOD | D8: 38 | E8: =IFERROR(VLOOKUP(D8,'INVONTERY FEB'!$A$6:$B$432,2,FALSE),"") -> DAIRY MILK | F8: =IFERROR(VLOOKUP(E8,'INVONTERY FEB'!$B$6:$C$432,2,FALSE),"") -> BOX | G8: =10500/24 -> 437.5 | H8: 24 | I8: =IFERROR((H8*G8),"") -> 10500
B9: 46057 | C9: HAFFIZ MAHMOOD | D9: 50 | E9: =IFERROR(VLOOKUP(D9,'INVONTERY FEB'!$A$6:$B$432,2,FALSE),"") -> ALMONDS | F9: =IFERROR(VLOOKUP(E9,'INVONTERY FEB'!$B$6:$C$432,2,FALSE),"") -> KG | G9: =13250/5 -> 2650 | H9: 5 | I9: =IFERROR((H9*G9),"") -> 13250
B10: 46057 | C10: HAFFIZ MAHMOOD | D10: 52 | E10: =IFERROR(VLOOKUP(D10,'INVONTERY FEB'!$A$6:$B$432,2,FALSE),"") -> PISTACHIO | F10: =IFERROR(VLOOKUP(E10,'INVONTERY FEB'!$B$6:$C$432,2,FALSE),"") -> KG | G10: =18600/3 -> 6200 | H10: 3 | I10: =IFERROR((H10*G10),"") -> 18600
B11: 46057 | C11: HAFFIZ MAHMOOD | D11: 83 | E11: =IFERROR(VLOOKUP(D11,'INVONTERY FEB'!$A$6:$B$432,2,FALSE),"") -> RED SPONCH FOOD COLOUR 400GMS | F11: =IFERROR(VLOOKUP(E11,'INVONTERY FEB'!$B$6:$C$432,2,FALSE),"") -> BOTT | G11: =IFERROR(VLOOKUP(E11,'INVONTERY FEB'!$B$6:$D$131,3,FALSE),"") -> 650 | H11: 2 | I11: =IFERROR((H11*G11),"") -> 1300
B12: 46057 | C12: HAFFIZ MAHMOOD | D12: 13 | E12: =IFERROR(VLOOKUP(D12,'INVONTERY FEB'!$A$6:$B$432,2,FALSE),"") -> BAKING POWDER HOLIDAY | F12: =IFERROR(VLOOKUP(E12,'INVONTERY FEB'!$B$6:$C$432,2,FALSE),"") -> KG | G12: =IFERROR(VLOOKUP(E12,'INVONTERY FEB'!$B$6:$D$131,3,FALSE),"") -> 2000 | H12: 5 | I12: =IFERROR((H12*G12),"") -> 10000
B13: 46057 | C13: LOCAL MARKET | D13: 56 | E13: =IFERROR(VLOOKUP(D13,'INVONTERY FEB'!$A$6:$B$432,2,FALSE),"") -> FERRY ROSE | F13: =IFERROR(VLOOKUP(E13,'INVONTERY FEB'!$B$6:$C$432,2,FALSE),"") -> BOX | G13: =IFERROR(VLOOKUP(E13,'INVONTERY FEB'!$B$6:$D$131,3,FALSE),"") -> 1000 | H13: 1 | I13: =IFERROR((H13*G13),"") -> 1000
B14: 46057 | C14: LOCAL MARKET | D14: 122 | E14: =IFERROR(VLOOKUP(D14,'INVONTERY FEB'!$A$6:$B$432,2,FALSE),"") -> DISSPOSSABLE PACKING | F14: =IFERROR(VLOOKUP(E14,'INVONTERY FEB'!$B$6:$C$432,2,FALSE),"") -> PCS | G14: =4200/600 -> 7 | H14: 600 | I14: =IFERROR((H14*G14),"") -> 4200
B15: 46058 | C15: ELAHE EGGS TRADER | D15: 7 | E15: =IFERROR(VLOOKUP(D15,'INVONTERY FEB'!$A$6:$B$432,2,FALSE),"") -> EGGS | F15: =IFERROR(VLOOKUP(E15,'INVONTERY FEB'!$B$6:$C$432,2,FALSE),"") -> PCS | G15: =9000/360 -> 25 | H15: 360 | I15: =IFERROR((H15*G15),"") -> 9000
B16: 46061 | C16: ELAHE EGGS TRADER | D16: 7 | E16: =IFERROR(VLOOKUP(D16,'INVONTERY FEB'!$A$6:$B$432,2,FALSE),"") -> EGGS | F16: =IFERROR(VLOOKUP(E16,'INVONTERY FEB'!$B$6:$C$432,2,FALSE),"") -> PCS | G16: =9000/360 -> 25 | H16: 360 | I16: =IFERROR((H16*G16),"") -> 9000
B17: 46062 | C17: ELAHE EGGS TRADER | D17: 7 | E17: =IFERROR(VLOOKUP(D17,'INVONTERY FEB'!$A$6:$B$432,2,FALSE),"") -> EGGS | F17: =IFERROR(VLOOKUP(E17,'INVONTERY FEB'!$B$6:$C$432,2,FALSE),"") -> PCS | G17: =8500/360 -> 23.611111 | H17: 360 | I17: =IFERROR((H17*G17),"") -> 8500
B18: 46062 | C18: S.N TRADERS | D18: 43 | E18: =IFERROR(VLOOKUP(D18,'INVONTERY FEB'!$A$6:$B$432,2,FALSE),"") -> OLPERS CREAM 200 ML | F18: =IFERROR(VLOOKUP(E18,'INVONTERY FEB'!$B$6:$C$432,2,FALSE),"") -> PCS | G18: =IFERROR(VLOOKUP(E18,'INVONTERY FEB'!$B$6:$D$131,3,FALSE),"") -> 207.28197 | H18: 240 | I18: =IFERROR((H18*G18),"") -> 49747.672
B19: 46062 | C19: LOCAL MARKET | D19: 31 | E19: =IFERROR(VLOOKUP(D19,'INVONTERY FEB'!$A$6:$B$432,2,FALSE),"") -> NURPUR BUTTER | F19: =IFERROR(VLOOKUP(E19,'INVONTERY FEB'!$B$6:$C$432,2,FALSE),"") -> KG | G19: =19500/10 -> 1950 | H19: 10 | I19: =IFERROR((H19*G19),"") -> 19500
B20: 46062 | C20: MIAN SHOUKAT TRADERS | D20: 61 | E20: =IFERROR(VLOOKUP(D20,'INVONTERY FEB'!$A$6:$B$432,2,FALSE),"") -> LOTO SPREAD 400G | F20: =IFERROR(VLOOKUP(E20,'INVONTERY FEB'!$B$6:$C$432,2,FALSE),"") -> PCS | G20: =IFERROR(VLOOKUP(E20,'INVONTERY FEB'!$B$6:$D$131,3,FALSE),"") -> 1750 | H20: =12*12 -> 144 | I20: =IFERROR((H20*G20),"") -> 252000
B21: 46063 | C21: MIAN SHOUKAT TRADERS | D21: 47 | E21: =IFERROR(VLOOKUP(D21,'INVONTERY FEB'!$A$6:$B$432,2,FALSE),"") -> LOTUS BISCOFF | F21: =IFERROR(VLOOKUP(E21,'INVONTERY FEB'!$B$6:$C$432,2,FALSE),"") -> PKT | G21: =IFERROR(VLOOKUP(E21,'INVONTERY FEB'!$B$6:$D$131,3,FALSE),"") -> 1100 | H21: 50 | I21: =IFERROR((H21*G21),"") -> 55000
B22: 46064 | C22: MIAN SHOUKAT TRADERS | D22: 29 | E22: =IFERROR(VLOOKUP(D22,'INVONTERY FEB'!$A$6:$B$432,2,FALSE),"") -> WHIPPING CREAM | F22: =IFERROR(VLOOKUP(E22,'INVONTERY FEB'!$B$6:$C$432,2,FALSE),"") -> PCS | G22: =IFERROR(VLOOKUP(E22,'INVONTERY FEB'!$B$6:$D$131,3,FALSE),"") -> 700 | H22: 216 | I22: =IFERROR((H22*G22),"") -> 151200
B23: 46064 | C23: MIAN SHOUKAT TRADERS | D23: 10 | E23: =IFERROR(VLOOKUP(D23,'INVONTERY FEB'!$A$6:$B$432,2,FALSE),"") -> COCO POWDER MALASIAN | F23: =IFERROR(VLOOKUP(E23,'INVONTERY FEB'!$B$6:$C$432,2,FALSE),"") -> KG | G23: =195800/50 -> 3916 | H23: 50 | I23: =IFERROR((H23*G23),"") -> 195800
B24: 46064 | C24: BAKERZ SOLUTIONS | D24: 98 | E24: =IFERROR(VLOOKUP(D24,'INVONTERY FEB'!$A$6:$B$432,2,FALSE),"") -> VIBGOR FOOD COLOUR | F24: =IFERROR(VLOOKUP(E24,'INVONTERY FEB'!$B$6:$C$432,2,FALSE),"") -> BOTT | G24: =1875/3 -> 625 | H24: 3 | I24: =IFERROR((H24*G24),"") -> 1875
B25: 46064 | C25: ELAHE EGGS TRADER | D25: 7 | E25: =IFERROR(VLOOKUP(D25,'INVONTERY FEB'!$A$6:$B$432,2,FALSE),"") -> EGGS | F25: =IFERROR(VLOOKUP(E25,'INVONTERY FEB'!$B$6:$C$432,2,FALSE),"") -> PCS | G25: =8500/360 -> 23.611111 | H25: 360 | I25: =IFERROR((H25*G25),"") -> 8500
B26: 46064 | C26: HAFFIZ MAHMOOD | D26: 19 | E26: =IFERROR(VLOOKUP(D26,'INVONTERY FEB'!$A$6:$B$432,2,FALSE),"") -> GULCOSE LIQUID | F26: =IFERROR(VLOOKUP(E26,'INVONTERY FEB'!$B$6:$C$432,2,FALSE),"") -> BOTT | G26: =1750/1 -> 1750 | H26: 1 | I26: =IFERROR((H26*G26),"") -> 1750
B27: 46064 | C27: HAFFIZ MAHMOOD | D27: 8 | E27: =IFERROR(VLOOKUP(D27,'INVONTERY FEB'!$A$6:$B$432,2,FALSE),"") -> POLAC CONDENSED MILK 1-LTR | F27: =IFERROR(VLOOKUP(E27,'INVONTERY FEB'!$B$6:$C$432,2,FALSE),"") -> TIN | G27: =11900/17 -> 700 | H27: 17 | I27: =IFERROR((H27*G27),"") -> 11900
B28: 46065 | C28: ELAHE EGGS TRADER | D28: 7 | E28: =IFERROR(VLOOKUP(D28,'INVONTERY FEB'!$A$6:$B$432,2,FALSE),"") -> EGGS | F28: =IFERROR(VLOOKUP(E28,'INVONTERY FEB'!$B$6:$C$432,2,FALSE),"") -> PCS | G28: =8500/360 -> 23.611111 | H28: 360 | I28: =IFERROR((H28*G28),"") -> 8500
B29: 46066 | C29: NESTLE | D29: 28 | E29: =IFERROR(VLOOKUP(D29,'INVONTERY FEB'!$A$6:$B$432,2,FALSE),"") -> NESTLE BUTTER | F29: =IFERROR(VLOOKUP(E29,'INVONTERY FEB'!$B$6:$C$432,2,FALSE),"") -> KG | G29: =IFERROR(VLOOKUP(E29,'INVONTERY FEB'!$B$6:$D$131,3,FALSE),"") -> 1850 | H29: 20 | I29: =IFERROR((H29*G29),"") -> 37000
B30: 46066 | C30: ELAHE EGGS TRADER | D30: 7 | E30: =IFERROR(VLOOKUP(D30,'INVONTERY FEB'!$A$6:$B$432,2,FALSE),"") -> EGGS | F30: =IFERROR(VLOOKUP(E30,'INVONTERY FEB'!$B$6:$C$432,2,FALSE),"") -> PCS | G30: =8500/360 -> 23.611111 | H30: 360 | I30: =IFERROR((H30*G30),"") -> 8500
B31: 46066 | C31: LOCAL MARKET | D31: 138 | E31: =IFERROR(VLOOKUP(D31,'INVONTERY FEB'!$A$6:$B$432,2,FALSE),"") -> DUSTER | F31: =IFERROR(VLOOKUP(E31,'INVONTERY FEB'!$B$6:$C$432,2,FALSE),"") -> KG | G31: =25069/58.3 -> 430 | H31: 58.3 | I31: =IFERROR((H31*G31),"") -> 25069
B32: 46067 | C32: ELAHE EGGS TRADER | D32: 7 | E32: =IFERROR(VLOOKUP(D32,'INVONTERY FEB'!$A$6:$B$432,2,FALSE),"") -> EGGS | F32: =IFERROR(VLOOKUP(E32,'INVONTERY FEB'!$B$6:$C$432,2,FALSE),"") -> PCS | G32: =8000/360 -> 22.222222 | H32: 360 | I32: =IFERROR((H32*G32),"") -> 8000
B33: 46067 | C33: BAKERZ SOLUTIONS | D33: 85 | E33: =IFERROR(VLOOKUP(D33,'INVONTERY FEB'!$A$6:$B$432,2,FALSE),"") -> VIBGYOR BASE FOUNDANT COLOURE | F33: =IFERROR(VLOOKUP(E33,'INVONTERY FEB'!$B$6:$C$432,2,FALSE),"") -> BOTT | G33: =11130/9 -> 1236.6667 | H33: 9 | I33: =IFERROR((H33*G33),"") -> 11130
B34: 46067 | C34: BAKERZ SOLUTIONS | D34: 96 | E34: =IFERROR(VLOOKUP(D34,'INVONTERY FEB'!$A$6:$B$432,2,FALSE),"") -> SILVER EATABLE COLOURE | F34: =IFERROR(VLOOKUP(E34,'INVONTERY FEB'!$B$6:$C$432,2,FALSE),"") -> BOTT | G34: =1000/1 -> 1000 | H34: 1 | I34: =IFERROR((H34*G34),"") -> 1000
B35: 46067 | C35: S.N TRADERS | D35: 9 | E35: =IFERROR(VLOOKUP(D35,'INVONTERY FEB'!$A$6:$B$432,2,FALSE),"") -> OLPERS MILK 1.5 LTR | F35: =IFERROR(VLOOKUP(E35,'INVONTERY FEB'!$B$6:$C$432,2,FALSE),"") -> PCS | G35: =39195/80 -> 489.9375 | H35: 80 | I35: =IFERROR((H35*G35),"") -> 39195
B36: 46068 | C36: ELAHE EGGS TRADER | D36: 7 | E36: =IFERROR(VLOOKUP(D36,'INVONTERY FEB'!$A$6:$B$432,2,FALSE),"") -> EGGS | F36: =IFERROR(VLOOKUP(E36,'INVONTERY FEB'!$B$6:$C$432,2,FALSE),"") -> PCS | G36: =7500/360 -> 20.833333 | H36: 360 | I36: =IFERROR((H36*G36),"") -> 7500
B37: 46068 | C37: LOCAL MARKET | D37: 108 | E37: =IFERROR(VLOOKUP(D37,'INVONTERY FEB'!$A$6:$B$432,2,FALSE),"") -> PAPER TRAY 5 POUND | F37: =IFERROR(VLOOKUP(E37,'INVONTERY FEB'!$B$6:$C$432,2,FALSE),"") -> PCS | G37: =IFERROR(VLOOKUP(E37,'INVONTERY FEB'!$B$6:$D$131,3,FALSE),"") -> 40 | H37: 20 | I37: =IFERROR((H37*G37),"") -> 800
B38: 46068 | C38: LOCAL MARKET | D38: 110 | E38: =IFERROR(VLOOKUP(D38,'INVONTERY FEB'!$A$6:$B$432,2,FALSE),"") -> PAPER TRAY 7 POUND | F38: =IFERROR(VLOOKUP(E38,'INVONTERY FEB'!$B$6:$C$432,2,FALSE),"") -> PCS | G38: =1100/20 -> 55 | H38: 20 | I38: =IFERROR((H38*G38),"") -> 1100
B39: 46068 | C39: LOCAL MARKET | D39: 111 | E39: =IFERROR(VLOOKUP(D39,'INVONTERY FEB'!$A$6:$B$432,2,FALSE),"") -> PAPER TRAY 8 POUND | F39: =IFERROR(VLOOKUP(E39,'INVONTERY FEB'!$B$6:$C$432,2,FALSE),"") -> PCS | G39: =1300/20 -> 65 | H39: 20 | I39: =IFERROR((H39*G39),"") -> 1300
B40: 46068 | C40: LOCAL MARKET | D40: 107 | E40: =IFERROR(VLOOKUP(D40,'INVONTERY FEB'!$A$6:$B$432,2,FALSE),"") -> CAKE SHEET 4 POUND | F40: =IFERROR(VLOOKUP(E40,'INVONTERY FEB'!$B$6:$C$432,2,FALSE),"") -> PKT | G40: =700/20 -> 35 | H40: 20 | I40: =IFERROR((H40*G40),"") -> 700
B41: 46068 | C41: LOCAL MARKET | D41: 116 | E41: =IFERROR(VLOOKUP(D41,'INVONTERY FEB'!$A$6:$B$432,2,FALSE),"") -> BROWN PAPER RIM | F41: =IFERROR(VLOOKUP(E41,'INVONTERY FEB'!$B$6:$C$432,2,FALSE),"") -> RIM | G41: =7000/1 -> 7000 | H41: 1 | I41: =IFERROR((H41*G41),"") -> 7000
B42: 46068 | C42: LOCAL MARKET | D42: 117 | E42: =IFERROR(VLOOKUP(D42,'INVONTERY FEB'!$A$6:$B$432,2,FALSE),"") -> CAKE PAN PAPER | F42: =IFERROR(VLOOKUP(E42,'INVONTERY FEB'!$B$6:$C$432,2,FALSE),"") -> PKT | G42: =IFERROR(VLOOKUP(E42,'INVONTERY FEB'!$B$6:$D$131,3,FALSE),"") -> 100 | H42: 50 | I42: =IFERROR((H42*G42),"") -> 5000
B43: 46068 | C43: LOCAL MARKET | D43: 119 | E43: =IFERROR(VLOOKUP(D43,'INVONTERY FEB'!$A$6:$B$432,2,FALSE),"") -> THERMAPOL BOLL SHEET | F43: =IFERROR(VLOOKUP(E43,'INVONTERY FEB'!$B$6:$C$432,2,FALSE),"") -> PKT | G43: =1400/7 -> 200 | H43: 7 | I43: =IFERROR((H43*G43),"") -> 1400
B44: 46068 | C44: LOCAL MARKET | D44: 113 | E44: =IFERROR(VLOOKUP(D44,'INVONTERY FEB'!$A$6:$B$432,2,FALSE),"") -> MINI MUFFIN CASE | F44: =IFERROR(VLOOKUP(E44,'INVONTERY FEB'!$B$6:$C$432,2,FALSE),"") -> PCS | G44: =2000/4 -> 500 | H44: 4 | I44: =IFERROR((H44*G44),"") -> 2000
B45: 46069 | C45: HAFFIZ MAHMOOD | D45: 20 | E45: =IFERROR(VLOOKUP(D45,'INVONTERY FEB'!$A$6:$B$432,2,FALSE),"") -> POLAC MILK 390 GM | F45: =IFERROR(VLOOKUP(E45,'INVONTERY FEB'!$B$6:$C$432,2,FALSE),"") -> TIN | G45: =25000/96 -> 260.41667 | H45: =48+48 -> 96 | I45: =IFERROR((H45*G45),"") -> 25000
B46: 46069 | C46: HAFFIZ MAHMOOD | D46: 11 | E46: =IFERROR(VLOOKUP(D46,'INVONTERY FEB'!$A$6:$B$432,2,FALSE),"") -> VANILLA ESSENCE 500 GM | F46: =IFERROR(VLOOKUP(E46,'INVONTERY FEB'!$B$6:$C$432,2,FALSE),"") -> BOTT | G46: =13200/12 -> 1100 | H46: 12 | I46: =IFERROR((H46*G46),"") -> 13200
B47: 46070 | C47: ELAHE EGGS TRADER | D47: 7 | E47: =IFERROR(VLOOKUP(D47,'INVONTERY FEB'!$A$6:$B$432,2,FALSE),"") -> EGGS | F47: =IFERROR(VLOOKUP(E47,'INVONTERY FEB'!$B$6:$C$432,2,FALSE),"") -> PCS | G47: =7500/360 -> 20.833333 | H47: 360 | I47: =IFERROR((H47*G47),"") -> 7500
B48: 46070 | C48: HAFFIZ MAHMOOD | D48: 133 | E48: =IFERROR(VLOOKUP(D48,'INVONTERY FEB'!$A$6:$B$432,2,FALSE),"") -> VISORS | F48: =IFERROR(VLOOKUP(E48,'INVONTERY FEB'!$B$6:$C$432,2,FALSE),"") -> PKT | G48: =1800/10 -> 180 | H48: 10 | I48: =IFERROR((H48*G48),"") -> 1800
B49: 46073 | C49: ELAHE EGGS TRADER | D49: 7 | E49: =IFERROR(VLOOKUP(D49,'INVONTERY FEB'!$A$6:$B$432,2,FALSE),"") -> EGGS | F49: =IFERROR(VLOOKUP(E49,'INVONTERY FEB'!$B$6:$C$432,2,FALSE),"") -> PCS | G49: =7500/360 -> 20.833333 | H49: 360 | I49: =IFERROR((H49*G49),"") -> 7500
B50: 46075 | C50: ELAHE EGGS TRADER | D50: 7 | E50: =IFERROR(VLOOKUP(D50,'INVONTERY FEB'!$A$6:$B$432,2,FALSE),"") -> EGGS | F50: =IFERROR(VLOOKUP(E50,'INVONTERY FEB'!$B$6:$C$432,2,FALSE),"") -> PCS | G50: =7500/360 -> 20.833333 | H50: 360 | I50: =IFERROR((H50*G50),"") -> 7500
B51: 46075 | C51: LOCAL MARKET | D51: 8 | E51: =IFERROR(VLOOKUP(D51,'INVONTERY FEB'!$A$6:$B$432,2,FALSE),"") -> POLAC CONDENSED MILK 1-LTR | F51: =IFERROR(VLOOKUP(E51,'INVONTERY FEB'!$B$6:$C$432,2,FALSE),"") -> TIN | G51: =IFERROR(VLOOKUP(E51,'INVONTERY FEB'!$B$6:$D$131,3,FALSE),"") -> 625 | H51: =24*3 -> 72 | I51: =IFERROR((H51*G51),"") -> 45000
B52: 46076 | C52: SULTANI PRINTING | D52: 105 | E52: =IFERROR(VLOOKUP(D52,'INVONTERY FEB'!$A$6:$B$432,2,FALSE),"") -> CAKE BOARD PRINTED | F52: =IFERROR(VLOOKUP(E52,'INVONTERY FEB'!$B$6:$C$432,2,FALSE),"") -> PCS | G52: 31.5 | H52: 2000 | I52: =IFERROR((H52*G52),"") -> 63000
B53: 46074 | C53: S.N TRADERS | D53: 43 | E53: =IFERROR(VLOOKUP(D53,'INVONTERY FEB'!$A$6:$B$432,2,FALSE),"") -> OLPERS CREAM 200 ML | F53: =IFERROR(VLOOKUP(E53,'INVONTERY FEB'!$B$6:$C$432,2,FALSE),"") -> PCS | G53: =IFERROR(VLOOKUP(E53,'INVONTERY FEB'!$B$6:$D$131,3,FALSE),"") -> 207.28197 | H53: 240 | I53: =IFERROR((H53*G53),"") -> 49747.672
B54: 46081 | C54: S.N TRADERS | D54: 9 | E54: =IFERROR(VLOOKUP(D54,'INVONTERY FEB'!$A$6:$B$432,2,FALSE),"") -> OLPERS MILK 1.5 LTR | F54: =IFERROR(VLOOKUP(E54,'INVONTERY FEB'!$B$6:$C$432,2,FALSE),"") -> PCS | G54: =IFERROR(VLOOKUP(E54,'INVONTERY FEB'!$B$6:$D$131,3,FALSE),"") -> 488.1129 | H54: 80 | I54: =IFERROR((H54*G54),"") -> 39049.032
B55: 46081 | C55: NESTLE | D55: 28 | E55: =IFERROR(VLOOKUP(D55,'INVONTERY FEB'!$A$6:$B$432,2,FALSE),"") -> NESTLE BUTTER | F55: =IFERROR(VLOOKUP(E55,'INVONTERY FEB'!$B$6:$C$432,2,FALSE),"") -> KG | G55: =IFERROR(VLOOKUP(E55,'INVONTERY FEB'!$B$6:$D$131,3,FALSE),"") -> 1850 | H55: 20 | I55: =IFERROR((H55*G55),"") -> 37000
B56: 46081 | C56: HAFFIZ MAHMOOD | D56: 6 | E56: =IFERROR(VLOOKUP(D56,'INVONTERY FEB'!$A$6:$B$432,2,FALSE),"") -> LOSSE SUGAR 50KG | F56: =IFERROR(VLOOKUP(E56,'INVONTERY FEB'!$B$6:$C$432,2,FALSE),"") -> KG | G56: 184 | H56: 100 | I56: =IFERROR((H56*G56),"") -> 18400
B57: 46081 | C57: GMSA LPG | D57: 315 | E57: =IFERROR(VLOOKUP(D57,'INVONTERY FEB'!$A$6:$B$432,2,FALSE),"") -> LPG | F57: =IFERROR(VLOOKUP(E57,'INVONTERY FEB'!$B$6:$C$432,2,FALSE),"") -> CLY | G57: =97610/H57 -> 13944.286 | H57: 7 | I57: =IFERROR((H57*G57),"") -> 97610
E58: =IFERROR(VLOOKUP(D58,'INVONTERY FEB'!$A$6:$B$432,2,FALSE),"") | F58: =IFERROR(VLOOKUP(E58,'INVONTERY FEB'!$B$6:$C$432,2,FALSE),"") | G58: =IFERROR(VLOOKUP(E58,'INVONTERY FEB'!$B$6:$D$131,3,FALSE),"") | I58: =IFERROR((H58*G58),"") -> 0
E59: =IFERROR(VLOOKUP(D59,'INVONTERY FEB'!$A$6:$B$432,2,FALSE),"") | F59: =IFERROR(VLOOKUP(E59,'INVONTERY FEB'!$B$6:$C$432,2,FALSE),"") | G59: =IFERROR(VLOOKUP(E59,'INVONTERY FEB'!$B$6:$D$131,3,FALSE),"") | I59: =IFERROR((H59*G59),"") -> 0
E60: =IFERROR(VLOOKUP(D60,'INVONTERY FEB'!$A$6:$B$432,2,FALSE),"") | F60: =IFERROR(VLOOKUP(E60,'INVONTERY FEB'!$B$6:$C$432,2,FALSE),"") | G60: =IFERROR(VLOOKUP(E60,'INVONTERY FEB'!$B$6:$D$131,3,FALSE),"") | I60: =IFERROR((H60*G60),"") -> 0
E61: =IFERROR(VLOOKUP(D61,'INVONTERY FEB'!$A$6:$B$432,2,FALSE),"") | F61: =IFERROR(VLOOKUP(E61,'INVONTERY FEB'!$B$6:$C$432,2,FALSE),"") | G61: =IFERROR(VLOOKUP(E61,'INVONTERY FEB'!$B$6:$D$131,3,FALSE),"") | I61: =IFERROR((H61*G61),"") -> 0
E62: =IFERROR(VLOOKUP(D62,'INVONTERY FEB'!$A$6:$B$432,2,FALSE),"") | F62: =IFERROR(VLOOKUP(E62,'INVONTERY FEB'!$B$6:$C$432,2,FALSE),"") | G62: =IFERROR(VLOOKUP(E62,'INVONTERY FEB'!$B$6:$D$131,3,FALSE),"") | I62: =IFERROR((H62*G62),"") -> 0
E63: =IFERROR(VLOOKUP(D63,'INVONTERY FEB'!$A$6:$B$432,2,FALSE),"") | F63: =IFERROR(VLOOKUP(E63,'INVONTERY FEB'!$B$6:$C$432,2,FALSE),"") | G63: =IFERROR(VLOOKUP(E63,'INVONTERY FEB'!$B$6:$D$131,3,FALSE),"") | I63: =IFERROR((H63*G63),"") -> 0
E64: =IFERROR(VLOOKUP(D64,'INVONTERY FEB'!$A$6:$B$432,2,FALSE),"") | F64: =IFERROR(VLOOKUP(E64,'INVONTERY FEB'!$B$6:$C$432,2,FALSE),"") | G64: =IFERROR(VLOOKUP(E64,'INVONTERY FEB'!$B$6:$D$131,3,FALSE),"") | I64: =IFERROR((H64*G64),"") -> 0
E65: =IFERROR(VLOOKUP(D65,'INVONTERY FEB'!$A$6:$B$432,2,FALSE),"") | F65: =IFERROR(VLOOKUP(E65,'INVONTERY FEB'!$B$6:$C$432,2,FALSE),"") | G65: =IFERROR(VLOOKUP(E65,'INVONTERY FEB'!$B$6:$D$131,3,FALSE),"") | I65: =IFERROR((H65*G65),"") -> 0
E66: =IFERROR(VLOOKUP(D66,'INVONTERY FEB'!$A$6:$B$432,2,FALSE),"") | F66: =IFERROR(VLOOKUP(E66,'INVONTERY FEB'!$B$6:$C$432,2,FALSE),"") | G66: =IFERROR(VLOOKUP(E66,'INVONTERY FEB'!$B$6:$D$131,3,FALSE),"") | I66: =IFERROR((H66*G66),"") -> 0
E67: =IFERROR(VLOOKUP(D67,'INVONTERY FEB'!$A$6:$B$432,2,FALSE),"") | F67: =IFERROR(VLOOKUP(E67,'INVONTERY FEB'!$B$6:$C$432,2,FALSE),"") | G67: =IFERROR(VLOOKUP(E67,'INVONTERY FEB'!$B$6:$D$131,3,FALSE),"") | I67: =IFERROR((H67*G67),"") -> 0
E68: =IFERROR(VLOOKUP(D68,'INVONTERY FEB'!$A$6:$B$432,2,FALSE),"") | F68: =IFERROR(VLOOKUP(E68,'INVONTERY FEB'!$B$6:$C$432,2,FALSE),"") | G68: =IFERROR(VLOOKUP(E68,'INVONTERY FEB'!$B$6:$D$131,3,FALSE),"") | I68: =IFERROR((H68*G68),"") -> 0
E69: =IFERROR(VLOOKUP(D69,'INVONTERY FEB'!$A$6:$B$432,2,FALSE),"") | F69: =IFERROR(VLOOKUP(E69,'INVONTERY FEB'!$B$6:$C$432,2,FALSE),"") | G69: =IFERROR(VLOOKUP(E69,'INVONTERY FEB'!$B$6:$D$131,3,FALSE),"") | I69: =IFERROR((H69*G69),"") -> 0
... E398: =IFERROR(VLOOKUP(D398,'INVONTERY FEB'!$A$6:$B$432,2,FALSE),"") | F398: =IFERROR(VLOOKUP(E398,'INVONTERY FEB'!$B$6:$C$432,2,FALSE),"") | G398: =IFERROR(VLOOKUP(E398,'INVONTERY FEB'!$B$6:$D$131,3,FALSE),"") | I398: =IFERROR((H398*G398),"") -> 0
E399: =IFERROR(VLOOKUP(D399,'INVONTERY FEB'!$A$6:$B$131,2,FALSE),"") | F399: =IFERROR(VLOOKUP(E399,'INVONTERY FEB'!$B$6:$C$131,2,FALSE),"") | G399: =IFERROR(VLOOKUP(E399,'INVONTERY FEB'!$B$6:$D$131,3,FALSE),"") | I399: =IFERROR((H399*G399),"") -> 0
E400: =IFERROR(VLOOKUP(D400,'INVONTERY FEB'!$A$6:$B$131,2,FALSE),"") | F400: =IFERROR(VLOOKUP(E400,'INVONTERY FEB'!$B$6:$C$131,2,FALSE),"") | G400: =IFERROR(VLOOKUP(E400,'INVONTERY FEB'!$B$6:$D$131,3,FALSE),"") | I400: =IFERROR((H400*G400),"") -> 0
E401: =IFERROR(VLOOKUP(D401,'INVONTERY FEB'!$A$6:$B$131,2,FALSE),"") | F401: =IFERROR(VLOOKUP(E401,'INVONTERY FEB'!$B$6:$C$131,2,FALSE),"") | G401: =IFERROR(VLOOKUP(E401,'INVONTERY FEB'!$B$6:$D$131,3,FALSE),"") | I401: =IFERROR((H401*G401),"") -> 0
E402: =IFERROR(VLOOKUP(D402,'INVONTERY FEB'!$A$6:$B$131,2,FALSE),"") | F402: =IFERROR(VLOOKUP(E402,'INVONTERY FEB'!$B$6:$C$131,2,FALSE),"") | G402: =IFERROR(VLOOKUP(E402,'INVONTERY FEB'!$B$6:$D$131,3,FALSE),"") | I402: =IFERROR((H402*G402),"") -> 0
E403: =IFERROR(VLOOKUP(D403,'INVONTERY FEB'!$A$6:$B$131,2,FALSE),"") | F403: =IFERROR(VLOOKUP(E403,'INVONTERY FEB'!$B$6:$C$131,2,FALSE),"") | G403: =IFERROR(VLOOKUP(E403,'INVONTERY FEB'!$B$6:$D$131,3,FALSE),"") | I403: =IFERROR((H403*G403),"") -> 0
E404: =IFERROR(VLOOKUP(D404,'INVONTERY FEB'!$A$6:$B$131,2,FALSE),"") | F404: =IFERROR(VLOOKUP(E404,'INVONTERY FEB'!$B$6:$C$131,2,FALSE),"") | G404: =IFERROR(VLOOKUP(E404,'INVONTERY FEB'!$B$6:$D$131,3,FALSE),"") | I404: =IFERROR((H404*G404),"") -> 0
E405: =IFERROR(VLOOKUP(D405,'INVONTERY FEB'!$A$6:$B$131,2,FALSE),"") | F405: =IFERROR(VLOOKUP(E405,'INVONTERY FEB'!$B$6:$C$131,2,FALSE),"") | G405: =IFERROR(VLOOKUP(E405,'INVONTERY FEB'!$B$6:$D$131,3,FALSE),"") | I405: =IFERROR((H405*G405),"") -> 0
E406: =IFERROR(VLOOKUP(D406,'INVONTERY FEB'!$A$6:$B$131,2,FALSE),"") | F406: =IFERROR(VLOOKUP(E406,'INVONTERY FEB'!$B$6:$C$131,2,FALSE),"") | G406: =IFERROR(VLOOKUP(E406,'INVONTERY FEB'!$B$6:$D$131,3,FALSE),"") | I406: =IFERROR((H406*G406),"") -> 0
E407: =IFERROR(VLOOKUP(D407,'INVONTERY FEB'!$A$6:$B$131,2,FALSE),"") | F407: =IFERROR(VLOOKUP(E407,'INVONTERY FEB'!$B$6:$C$131,2,FALSE),"") | G407: =IFERROR(VLOOKUP(E407,'INVONTERY FEB'!$B$6:$D$131,3,FALSE),"") | I407: =IFERROR((H407*G407),"") -> 0
E408: =IFERROR(VLOOKUP(D408,'INVONTERY FEB'!$A$6:$B$131,2,FALSE),"") | F408: =IFERROR(VLOOKUP(E408,'INVONTERY FEB'!$B$6:$C$131,2,FALSE),"") | G408: =IFERROR(VLOOKUP(E408,'INVONTERY FEB'!$B$6:$D$131,3,FALSE),"") | I408: =IFERROR((H408*G408),"") -> 0
E409: =IFERROR(VLOOKUP(D409,'INVONTERY FEB'!$A$6:$B$131,2,FALSE),"") | F409: =IFERROR(VLOOKUP(E409,'INVONTERY FEB'!$B$6:$C$131,2,FALSE),"") | G409: =IFERROR(VLOOKUP(E409,'INVONTERY FEB'!$B$6:$D$131,3,FALSE),"") | I409: =IFERROR((H409*G409),"") -> 0
E410: =IFERROR(VLOOKUP(D410,'INVONTERY FEB'!$A$6:$B$131,2,FALSE),"") | F410: =IFERROR(VLOOKUP(E410,'INVONTERY FEB'!$B$6:$C$131,2,FALSE),"") | G410: =IFERROR(VLOOKUP(E410,'INVONTERY FEB'!$B$6:$D$131,3,FALSE),"") | I410: =IFERROR((H410*G410),"") -> 0
... E468: =IFERROR(VLOOKUP(D468,'INVONTERY FEB'!$A$6:$B$131,2,FALSE),"") | F468: =IFERROR(VLOOKUP(E468,'INVONTERY FEB'!$B$6:$C$131,2,FALSE),"") | G468: =IFERROR(VLOOKUP(E468,'INVONTERY FEB'!$B$6:$D$131,3,FALSE),"") | I468: =IFERROR((H468*G468),"") -> 0
E469: =IFERROR(VLOOKUP(D469,'INVONTERY FEB'!$A$6:$B$131,2,FALSE),"") | F469: =IFERROR(VLOOKUP(E469,'INVONTERY FEB'!$B$6:$C$131,2,FALSE),"")
E470: =IFERROR(VLOOKUP(D470,'INVONTERY FEB'!$A$6:$B$131,2,FALSE),"") | F470: =IFERROR(VLOOKUP(E470,'INVONTERY FEB'!$B$6:$C$131,2,FALSE),"") | G470: =IFERROR(VLOOKUP(E470,'INVONTERY FEB'!$B$6:$D$131,3,FALSE),"")
E471: =IFERROR(VLOOKUP(D471,'INVONTERY FEB'!$A$6:$B$131,2,FALSE),"") | F471: =IFERROR(VLOOKUP(E471,'INVONTERY FEB'!$B$6:$C$131,2,FALSE),"") | G471: =IFERROR(VLOOKUP(E471,'INVONTERY FEB'!$B$6:$D$131,3,FALSE),"")
E472: =IFERROR(VLOOKUP(D472,'INVONTERY FEB'!$A$6:$B$131,2,FALSE),"") | F472: =IFERROR(VLOOKUP(E472,'INVONTERY FEB'!$B$6:$C$131,2,FALSE),"") | G472: =IFERROR(VLOOKUP(E472,'INVONTERY FEB'!$B$6:$D$131,3,FALSE),"")
E473: =IFERROR(VLOOKUP(D473,'INVONTERY FEB'!$A$6:$B$131,2,FALSE),"") | F473: =IFERROR(VLOOKUP(E473,'INVONTERY FEB'!$B$6:$C$131,2,FALSE),"") | G473: =IFERROR(VLOOKUP(E473,'INVONTERY FEB'!$B$6:$D$131,3,FALSE),"")
E474: =IFERROR(VLOOKUP(D474,'INVONTERY FEB'!$A$6:$B$131,2,FALSE),"") | F474: =IFERROR(VLOOKUP(E474,'INVONTERY FEB'!$B$6:$C$131,2,FALSE),"") | G474: =IFERROR(VLOOKUP(E474,'INVONTERY FEB'!$B$6:$D$131,3,FALSE),"")
E475: =IFERROR(VLOOKUP(D475,'INVONTERY FEB'!$A$6:$B$131,2,FALSE),"") | F475: =IFERROR(VLOOKUP(E475,'INVONTERY FEB'!$B$6:$C$131,2,FALSE),"") | G475: =IFERROR(VLOOKUP(E475,'INVONTERY FEB'!$B$6:$D$131,3,FALSE),"")
E476: =IFERROR(VLOOKUP(D476,'INVONTERY FEB'!$A$6:$B$131,2,FALSE),"") | F476: =IFERROR(VLOOKUP(E476,'INVONTERY FEB'!$B$6:$C$131,2,FALSE),"") | G476: =IFERROR(VLOOKUP(E476,'INVONTERY FEB'!$B$6:$D$131,3,FALSE),"")
E477: =IFERROR(VLOOKUP(D477,'INVONTERY FEB'!$A$6:$B$131,2,FALSE),"") | F477: =IFERROR(VLOOKUP(E477,'INVONTERY FEB'!$B$6:$C$131,2,FALSE),"") | G477: =IFERROR(VLOOKUP(E477,'INVONTERY FEB'!$B$6:$D$131,3,FALSE),"")
E478: =IFERROR(VLOOKUP(D478,'INVONTERY FEB'!$A$6:$B$131,2,FALSE),"") | F478: =IFERROR(VLOOKUP(E478,'INVONTERY FEB'!$B$6:$C$131,2,FALSE),"") | G478: =IFERROR(VLOOKUP(E478,'INVONTERY FEB'!$B$6:$D$131,3,FALSE),"")
E479: =IFERROR(VLOOKUP(D479,'INVONTERY FEB'!$A$6:$B$131,2,FALSE),"") | F479: =IFERROR(VLOOKUP(E479,'INVONTERY FEB'!$B$6:$C$131,2,FALSE),"") | G479: =IFERROR(VLOOKUP(E479,'INVONTERY FEB'!$B$6:$D$131,3,FALSE),"")
E480: =IFERROR(VLOOKUP(D480,'INVONTERY FEB'!$A$6:$B$131,2,FALSE),"") | F480: =IFERROR(VLOOKUP(E480,'INVONTERY FEB'!$B$6:$C$131,2,FALSE),"") | G480: =IFERROR(VLOOKUP(E480,'INVONTERY FEB'!$B$6:$D$131,3,FALSE),"")
E481: =IFERROR(VLOOKUP(D481,'INVONTERY FEB'!$A$6:$B$131,2,FALSE),"") | F481: =IFERROR(VLOOKUP(E481,'INVONTERY FEB'!$B$6:$C$131,2,FALSE),"") | G481: =IFERROR(VLOOKUP(E481,'INVONTERY FEB'!$B$6:$D$131,3,FALSE),"")
... E506: =IFERROR(VLOOKUP(D506,'INVONTERY FEB'!$A$6:$B$131,2,FALSE),"") | F506: =IFERROR(VLOOKUP(E506,'INVONTERY FEB'!$B$6:$C$131,2,FALSE),"") | G506: =IFERROR(VLOOKUP(E506,'INVONTERY FEB'!$B$6:$D$131,3,FALSE),"")

Sheet EXPENSES
F1: =SUM(F3:F840) -> 2796174 | G1: =SUM(G3:G840) -> 2796174 | H1: =G1-'DAILY UPDATE'!#REF! -> #ERROR! | K1: =G1-F1 -> 0
A2: DATE | B2: HEAD | C2: ID | D2: SUB HEAD | E2: DETAIL | F2: AMOUNT | G2: TOTAL | H2: UNIT | I2: QTY | J2: RATE | K2: VENDOR
A3: 46057 | B3: EMPLOYEE MEAL | D3: MEAL | E3: BAKERY TEAM MEAL MA/O FEB | F3: 40475
A4: 46057 | B4: FOOD | D4: SPONGEE | E4: EGGS | F4: 30100 | K4: ELAHE EGGS TRADER
A5: 46057 | B5: FOOD | D5: CAKE TOPPING | E5: FERRARO CHOCLATE | F5: 1000 | K5: LOCAL MARKET
A6: 46057 | B6: PAPER ITEM | D6: PAPER ITEM | E6: DISSPOSSABLE PACKING | F6: 4200 | H6: PCS | I6: 600 | J6: =4200/600 -> 7 | K6: LOCAL MARKET
A7: 46057 | B7: FOUNDANT | D7: ORDER CAKE | E7: ORDER CAKE PICS AND FLOWER | F7: 2010
A8: 46057 | B8: DISTRIBUTION COST | D8: EVAN FUEL | E8: EVAN FUEL | F8: 3000
A9: 46057 | B9: DISTRIBUTION COST | D9: AUTO RENT | E9: AUTO RENT | F9: 300
A10: 46057 | B10: UTILITIES | D10: PTCL | E10: PTCL BILL PAID M/O FEB | F10: 5310
A11: 46057 | B11: UTILITIES | D11: FUMIGATION | E11: FUMIGATION | F11: 8000
A12: 46057 | B12: MISC | D12: MISC | E12: BAKERY WASHROOM MIROR AND CEMRA WIRE COVERD | F12: 2480 | G12: =SUM(F3:F12) -> 96875
A13: 46061 | B13: EMPLOYEE MEAL | D13: MEAL | E13: BAKERY TEAM MEAL MA/O FEB | F13: 3525
A14: 46061 | B14: FOOD | D14: SPONGEE | E14: EGGS | F14: 26500 | K14: ELAHE EGGS TRADER
A15: 46061 | B15: FOOD | D15: CAKE CREAM | E15: BUTTER | F15: 19500 | K15: LOCAL MARKET
A16: 46061 | B16: PAYROLL | D16: SALARY | E16: BAKERY TEAM SALARY M/O JAN | F16: 286167
A17: 46061 | B17: FOUNDANT | D17: ORDER CAKE | E17: ORDER CAKE FLOWERS AND TOOTH PICK STICKS | F17: 1990
A18: 46061 | B18: FOUNDANT | D18: ORDER CAKE | E18: ORDER CAKE PIC | F18: 150
A19: 46061 | B19: DISTRIBUTION COST | D19: EVAN FUEL | E19: EVAN FUEL | F19: 6000
A20: 46061 | B20: UTILITIES | D20: FESCO | E20: BAKERY DEPARTMENT FESCO BILL PAID M/O FEB | F20: 136234
A21: 46061 | B21: UTILITIES | D21: RENT | E21: BAKERY TEAM HOME RENT M/O JAN | F21: 28480
A22: 46061 | B22: MISC | D22: M&R | E22: BAKERY DISHWASHING SPINDEL CHANGE | F22: 600 | G22: =SUM(F13:F22) -> 509146
A23: 46063 | B23: FOOD | D23: CAKE CREAM | E23: PISTA SAPREAD | F23: 46800 | K23: MIAN SHOUKAT TRADERS
A24: 46063 | B24: UTILITIES | D24: RENT | E24: IKRAM HOME RENT M/O JAN | F24: 8000
A25: 46063 | B25: FOUNDANT | D25: ORDER CAKE | E25: ORDER CAKE PICS AND FLOWERS | F25: 1830 | G25: =SUM(F23:F25) -> 56630
A26: 46064 | B26: DIRECTOR | D26: YASIR SB | E26: CASH HAND OVER TO YASIR SB | F26: 350000
A27: 46064 | B27: FOOD | D27: SPONGEE | E27: EGGS | F27: 17000 | K27: ELAHE EGGS TRADER
A28: 46064 | B28: FOOD | D28: CAKE TOPPING | E28: FOOD COLOURE | F28: 1875 | K28: BAKERZ SOLUTIONS
A29: 46066 | B29: PAYROLL | D29: SAJID | E29: SAJID BAKERY CASH CHARGE TO SALARY | F29: 15000 | G29: =SUM(F26:F29) -> 383875
A30: 46066 | B30: FOOD | D30: SPONGEE | E30: EGGS | F30: 16500 | K30: ELAHE EGGS TRADER
A31: 46066 | B31: FOOD | D31: ORDER CAKE | E31: FOUNDANT | F31: 11130 | K31: BAKERZ SOLUTIONS
A32: 46066 | B32: FOOD | D32: ORDER CAKE | E32: FOOD COLOURE | F32: 1000 | K32: BAKERZ SOLUTIONS
A33: 46066 | B33: CLEANING | D33: CLEANING | E33: DUSTER | F33: 25069 | K33: LOCAL MARKET
A34: 46066 | B34: FOUNDANT | D34: ORDER CAKE | E34: ORDER CAKE BOWL | F34: 350
A35: 46066 | B35: FOUNDANT | D35: ORDER CAKE | E35: ORDER CAKE PIPE | F35: 500
A36: 46066 | B36: FOUNDANT | D36: ORDER CAKE | E36: ORDER CAKE PIC | F36: 450
A37: 46066 | B37: FOUNDANT | D37: ORDER CAKE | E37: ORDER CAKE SHEET | F37: 400 | G37: =SUM(F30:F37) -> 55399
A38: 46068 | B38: FOOD | D38: CAKE TOPPING | E38: HAFIZ MEHMOOD PAYMENT | F38: 93300 | K38: HAFFIZ MAHMOOD
A39: 46068 | B39: FOOD | D39: SPONGEE | E39: EGGS | F39: 7500 | K39: ELAHE EGGS TRADER
A40: 46068 | B40: FOOD | D40: CAKE CREAM | E40: SHUKAT TRADERS PAYMENT | F40: 307000 | K40: MIAN SHOUKAT TRADERS
A41: 46068 | B41: FOOD | D41: CAKE CREAM | E41: BUTTER PAYMENT | F41: 37000 | K41: NESTLE
A42: 46068 | B42: FOOD | D42: CAKE CREAM | E42: OLPER CREAM S.N TRADERS PAYMENT | F42: 49748 | K42: S.N TRADERS
A43: 46068 | B43: DISTRIBUTION COST | D43: EVAN FUEL | E43: EVAN FUEL | F43: 3000
A44: 46068 | B44: DISTRIBUTION COST | D44: AUTO RENT | E44: AUTO RENT | F44: 1400
A45: 46068 | B45: PAPER ITEM | D45: PAPER ITEM | E45: CAKE SHEET 5 POUND | F45: 800 | K45: LOCAL MARKET
A46: 46068 | B46: PAPER ITEM | D46: PAPER ITEM | E46: CAKE SHEET 7 POUND | F46: 1100 | K46: LOCAL MARKET
A47: 46068 | B47: PAPER ITEM | D47: PAPER ITEM | E47: CAKE SHEET 8 POUND | F47: 1300 | K47: LOCAL MARKET
A48: 46068 | B48: PAPER ITEM | D48: PAPER ITEM | E48: CAKE SHEET 4 POUND | F48: 700 | K48: LOCAL MARKET
A49: 46068 | B49: PAPER ITEM | D49: PAPER ITEM | E49: BROWN PAPER RIM | F49: 7000 | K49: LOCAL MARKET
A50: 46068 | B50: PAPER ITEM | D50: PAPER ITEM | E50: PAN PAPER | F50: 5000 | K50: LOCAL MARKET
A51: 46068 | B51: PAPER ITEM | D51: PAPER ITEM | E51: THERMAPOL BOWL PKT | F51: 1400 | K51: LOCAL MARKET
A52: 46068 | B52: PAPER ITEM | D52: PAPER ITEM | E52: MUFFIN CASES | F52: 2000 | K52: LOCAL MARKET
A53: 46068 | B53: FOUNDANT | D53: ORDER CAKE | E53: ORDER CAKE FLOWERS | F53: 1000
A54: 46068 | B54: FOUNDANT | D54: ORDER CAKE | E54: ORDER CAKE DOLL AND PICS | F54: 630
A55: 46068 | B55: PAYROLL | D55: HAMAIYOUN | E55: HAMAIYOUN ORDER CHARGE TO SALARY | F55: 2500
A56: 46068 | B56: MISC | D56: MISC | E56: BAKERY VESSICOLOR FAN | F56: 2500 | G56: =SUM(F38:F56) -> 524878
A57: 46070 | B57: DIRECTOR | D57: YASIR SB | E57: CASH HAND OVER TO YASIR SB | F57: 200000
A58: 46070 | B58: FOOD | D58: CAKE CREAM | E58: WHIPPY CREAM 12 CTN | F58: 100800 | K58: MIAN SHOUKAT TRADERS
A59: 46070 | B59: FOUNDANT | D59: ORDER CAKE | E59: ORDER CAKEBUTTERFLY AND PICS AND DOLL | F59: 3040 | G59: =SUM(F57:F59) -> 303840
A60: 46073 | B60: FOOD | D60: SPONGEE | E60: HAFIZ MEHMOOD PAYMENT PAID | F60: 40000 | K60: HAFFIZ MAHMOOD
A61: 46073 | B61: FOOD | D61: SPONGEE | E61: S.N TRADERS PAYMENT PAID | F61: 39195 | K61: S.N TRADERS
A62: 46073 | B62: PAYROLL | D62: IKRAM | E62: ADVANCE | F62: 25000
A63: 46073 | B63: PAYROLL | D63: SAJID | E63: ADVANCE | F63: 10000
A64: 46073 | B64: PAYROLL | D64: ASMAT | E64: ADVANCE | F64: 7000
A65: 46073 | B65: PAYROLL | D65: KHURAM | E65: ADVANCE | F65: 7000
A66: 46073 | B66: PAYROLL | D66: SABIR | E66: ADVANCE | F66: 3000
A67: 46073 | B67: PAYROLL | D67: HAMAIYOUN | E67: ADVANCE | F67: 20000
A68: 46073 | B68: DISTRIBUTION COST | D68: EVAN | E68: EVAN FUEL | F68: 3000
A69: 46073 | B69: MISC | D69: MISC | E69: BAKERY DISHWASH SPINDEL | F69: 1280 | G69: =SUM(F60:F69) -> 155475
A70: 46078 | B70: FOOD | D70: SPONGEE | E70: EGGS | F70: 22500 | K70: ELAHE EGGS TRADER
A71: 46078 | B71: UTILITIES | D71: LPG | E71: 04-CLY LPG | F71: 55388 | K71: GMSA LPG
A72: 46078 | B72: FOUNDANT | D72: ORDER CAKE | E72: MFD SHHET FOR ORDER CAKE | F72: 1550
A73: 46078 | B73: PAYROLL | D73: HAMMAD | E73: HAMMAD ADVANCE | F73: 15000
A74: 46078 | B74: EMPLOYEE MEAL | D74: MEAL | E74: EMPLOYE MEAL | F74: 1000
A75: 46078 | B75: UTILITIES | D75: LPG | E75: 03-CLY LPG | F75: 42222 | K75: GMSA LPG
A76: 46078 | B76: DISTRIBUTION COST | D76: EVAN | E76: VEN FULE | F76: 3000
A77: 46078 | B77: FOUNDANT | D77: ORDER CAKE | E77: FLOWER FOR ORDER CAKE | F77: 200 | G77: 140860
A78: 46079 | B78: FOOD | D78: SPONGEE | E78: PULACK MILK | F78: 45000 | K78: LOCAL MARKET
A79: 46079 | B79: PAPER ITEM | D79: PAPER ITEM | E79: CAKE SHEET | F79: 63000 | K79: SULTANI PRINTING
A80: 46079 | B80: FOOD | D80: SPONGEE | E80: MIAN SHOUKAT TRADERS BILL CLEAR | F80: 246200 | K80: MIAN SHOUKAT TRADERS
A81: 46079 | B81: FOOD | D81: SPONGEE | E81: OLPER CREAM S.N TRADERS PAYMENT | F81: 49747 | G81: 403947 | K81: S.N TRADERS
A82: 46080 | B82: FOOD | D82: SPONGEE | E82: OLPER MILK S.N TRADERS PAYMENT | F82: 39049 | K82: S.N TRADERS
A83: 46080 | B83: FOOD | D83: CAKE CAREAM | E83: BUTTER | F83: 37000 | K83: NESTLE
A84: 46080 | B84: FOOD | D84: SPONGEE | E84: SUGAR | F84: 18400 | K84: HAFFIZ MAHMOOD
A85: 46080 | B85: DISTRIBUTION COST | D85: RENT | E85: RENT FOR SUGAR | F85: 800 | G85: =SUM(F82:F85) -> 95249
A86: 46081 | B86: DIRECTOR | D86: DIRECTOR | E86: YASIR SB | F86: 70000 | G86: 70000
M453: =13440/280 -> 48
U461: =30*24 -> 720
U462: 720
M530: =2975/35 -> 85

Sheet INVONTERY FEB
A2: INVENTORY REPORT
A3: ID | B3: PRODUCT DETAIL | C3: UNIT | D3: RATE | E3: OPENING INV | F3: OPENING AMOUNT | G3: PURCHASE | I3: ISSUE | J3: DAILY USAGE AVERAGE | K3: CLOSING INV | L3: CLOSING AMOUNT | M3: NEW RATE | N3: PRICE COMP. | O3: COST INCREASE | P3: COST | Q3: COMPANY NAME
G4: QTY | H4: AMOUNT
A5: 1.1 | B5: SPONAGE | S5: EOD | T5: OUT | U5: OUT | V5: OPENING
A6: 1 | B6: RED VELVET CONCENTRATE 10 KG | C6: KG | F6: =E6*D6 -> 0 | G6: =SUMIF(PURCHASE!$E$3:$E$506,'INVONTERY FEB'!B6:B326,PURCHASE!$H$3:$H$506) -> 0 | H6: =SUMIF(PURCHASE!$E$3:$E$506,'INVONTERY FEB'!B6:B326,PURCHASE!$I$3:$I$506) -> 0 | I6: =ISSU!AL6 -> 0 | J6: =I6/9 -> 0 | K6: =E6+G6-I6 -> 0 | L6: =K6*M6 -> 0 | N6: =M6-D6 -> 0 | O6: =N6*I6 -> 0 | P6: =F6+H6-L6 -> 0 | Q6: VENUS | S6: 0 | V6: =+S6+T6+U6 -> 0
A7: 2 | B7: LA OLA CONCENTRATE | C7: KG | F7: =E7*D7 -> 0 | G7: =SUMIF(PURCHASE!$E$3:$E$506,'INVONTERY FEB'!B7:B327,PURCHASE!$H$3:$H$506) -> 0 | H7: =SUMIF(PURCHASE!$E$3:$E$506,'INVONTERY FEB'!B7:B327,PURCHASE!$I$3:$I$506) -> 0 | I7: =ISSU!AL7 -> 0 | J7: =I7/9 -> 0 | K7: =E7+G7-I7 -> 0 | L7: =K7*M7 -> 0 | N7: =M7-D7 -> 0 | O7: =N7*I7 -> 0 | P7: =F7+H7-L7 -> 0 | Q7: LOCAL | S7: 0 | V7: =+S7+T7+U7 -> 0
A8: 3 | B8: AUSTRIA SPONGE MIX CONCENTRATE (269) | C8: KG | F8: =E8*D8 -> 0 | G8: =SUMIF(PURCHASE!$E$3:$E$506,'INVONTERY FEB'!B8:B328,PURCHASE!$H$3:$H$506) -> 0 | H8: =SUMIF(PURCHASE!$E$3:$E$506,'INVONTERY FEB'!B8:B328,PURCHASE!$I$3:$I$506) -> 0 | I8: =ISSU!AL8 -> 0 | J8: =I8/29 -> 0 | K8: =E8+G8-I8 -> 0 | L8: =K8*M8 -> 0 | N8: =M8-D8 -> 0 | O8: =N8*I8 -> 0 | P8: =F8+H8-L8 -> 0 | Q8: VENUS | S8: 0 | V8: =+S8+T8+U8 -> 0
A9: 4 | B9: KISAN CANOLA OIL 5 LTR | C9: BOX | D9: 560 | E9: 290 | F9: =E9*D9 -> 162400 | G9: =SUMIF(PURCHASE!$E$3:$E$506,'INVONTERY FEB'!B9:B328,PURCHASE!$H$3:$H$506) -> 0 | H9: =SUMIF(PURCHASE!$E$3:$E$506,'INVONTERY FEB'!B9:B328,PURCHASE!$I$3:$I$506) -> 0 | I9: =ISSU!AL9 -> 170 | J9: =I9/28 -> 6.0714286 | K9: =E9+G9-I9 -> 120 | L9: =K9*M9 -> 67200 | M9: =D9 -> 560 | N9: =M9-D9 -> 0 | O9: =N9*I9 -> 0 | P9: =F9+H9-L9 -> 95200 | Q9: VENUS | S9: 0 | V9: =+S9+T9+U9 -> 0
A10: 5 | B10: FLOUR | C10: BAG | D10: 134 | E10: 300 | F10: =E10*D10 -> 40200 | G10: =SUMIF(PURCHASE!$E$3:$E$506,'INVONTERY FEB'!B10:B328,PURCHASE!$H$3:$H$506) -> 0 | H10: =SUMIF(PURCHASE!$E$3:$E$506,'INVONTERY FEB'!B10:B328,PURCHASE!$I$3:$I$506) -> 0 | I10: =ISSU!AL10 -> 250 | J10: =I10/28 -> 8.9285714 | K10: =E10+G10-I10 -> 50 | L10: =K10*M10 -> 6700 | M10: =D10 -> 134 | N10: =M10-D10 -> 0 | O10: =N10*I10 -> 0 | P10: =F10+H10-L10 -> 33500 | Q10: LOCAL | U10: 1 | V10: =+S10+T10+U10 -> 1
A11: 6 | B11: LOSSE SUGAR 50KG | C11: KG | D11: 184 | E11: 300 | F11: =E11*D11 -> 55200 | G11: =SUMIF(PURCHASE!$E$3:$E$506,'INVONTERY FEB'!B11:B329,PURCHASE!$H$3:$H$506) -> 100 | H11: =SUMIF(PURCHASE!$E$3:$E$506,'INVONTERY FEB'!B11:B329,PURCHASE!$I$3:$I$506) -> 18400 | I11: =ISSU!AL11 -> 300 | J11: =I11/28 -> 10.714286 | K11: =E11+G11-I11 -> 100 | L11: =K11*M11 -> 18400 | M11: =D11 -> 184 | N11: =M11-D11 -> 0 | O11: =N11*I11 -> 0 | P11: =F11+H11-L11 -> 55200 | Q11: LOCAL | S11: =50*2 -> 100 | V11: =+S11+T11+U11 -> 100
A12: 7 | B12: EGGS | C12: PCS | D12: =5067/160 -> 31.66875 | E12: 380 | F12: =E12*D12 -> 12034.125 | G12: =SUMIF(PURCHASE!$E$3:$E$506,'INVONTERY FEB'!B12:B483,PURCHASE!$H$3:$H$506) -> 5040 | H12: =SUMIF(PURCHASE!$E$3:$E$506,'INVONTERY FEB'!B12:B433,PURCHASE!$I$3:$I$506) -> 120100 | I12: =ISSU!AL12 -> 5170 | J12: =I12/28 -> 184.64286 | K12: =E12+G12-I12 -> 250 | L12: =K12*M12 -> 7917.1875 | M12: =D12 -> 31.66875 | N12: =M12-D12 -> 0 | O12: =N12*I12 -> 0 | P12: =F12+H12-L12 -> 124216.94 | S12: 0 | V12: =+S12+T12+U12 -> 0
A13: 8 | B13: POLAC CONDENSED MILK 1-LTR | C13: TIN | D13: 625 | E13: 30 | F13: =E13*D13 -> 18750 | G13: =SUMIF(PURCHASE!$E$3:$E$506,'INVONTERY FEB'!B13:B501,PURCHASE!$H$3:$H$506) -> 89 | H13: =SUMIF(PURCHASE!$E$3:$E$506,'INVONTERY FEB'!B13:B451,PURCHASE!$I$3:$I$506) -> 56900 | I13: =ISSU!AL13 -> 54 | J13: =I13/28 -> 1.9285714 | K13: =E13+G13-I13 -> 65 | L13: =K13*M13 -> 40625 | M13: =D13 -> 625 | N13: =M13-D13 -> 0 | O13: =N13*I13 -> 0 | P13: =F13+H13-L13 -> 35025 | S13: 22 | T13: 2 | U13: 2 | V13: =+S13+T13+U13 -> 26
A14: 9 | B14: OLPERS MILK 1.5 LTR | C14: PCS | D14: =30263/62 -> 488.1129 | E14: 126 | F14: =E14*D14 -> 61502.226 | G14: =SUMIF(PURCHASE!$E$3:$E$506,'INVONTERY FEB'!B14:B490,PURCHASE!$H$3:$H$506) -> 160 | H14: =SUMIF(PURCHASE!$E$3:$E$506,'INVONTERY FEB'!B14:B440,PURCHASE!$I$3:$I$506) -> 78244.032 | I14: =ISSU!AL14 -> 190 | J14: =I14/28 -> 6.7857143 | K14: =E14+G14-I14 -> 96 | L14: =K14*M14 -> 46858.839 | M14: =D14 -> 488.1129 | N14: =M14-D14 -> 0 | O14: =N14*I14 -> 0 | P14: =F14+H14-L14 -> 92887.419 | Q14: LOCAL | S14: 8 | T14: 8 | V14: =+S14+T14+U14 -> 16
A15: 10 | B15: COCO POWDER MALASIAN | C15: KG | D15: =137098/35 -> 3917.0857 | E15: 57 | F15: =E15*D15 -> 223273.89 | G15: =SUMIF(PURCHASE!$E$3:$E$506,'INVONTERY FEB'!B15:B328,PURCHASE!$H$3:$H$506) -> 50 | H15: =SUMIF(PURCHASE!$E$3:$E$506,'INVONTERY FEB'!B15:B328,PURCHASE!$I$3:$I$506) -> 195800 | I15: =ISSU!AL15 -> 37 | J15: =I15/28 -> 1.3214286 | K15: =E15+G15-I15 -> 70 | L15: =K15*M15 -> 274196 | M15: =D15 -> 3917.0857 | N15: =M15-D15 -> 0 | O15: =N15*I15 -> 0 | P15: =F15+H15-L15 -> 144877.89 | Q15: LOCAL | S15: 0 | V15: =+S15+T15+U15 -> 0
A16: 11 | B16: VANILLA ESSENCE 500 GM | C16: BOTT | D16: 1150 | E16: 2 | F16: =E16*D16 -> 2300 | G16: =SUMIF(PURCHASE!$E$3:$E$506,'INVONTERY FEB'!B16:B341,PURCHASE!$H$3:$H$506) -> 12 | H16: =SUMIF(PURCHASE!$E$3:$E$506,'INVONTERY FEB'!B16:B336,PURCHASE!$I$3:$I$506) -> 13200 | I16: =ISSU!AL16 -> 5 | J16: =I16/28 -> 0.17857143 | K16: =E16+G16-I16 -> 9 | L16: =K16*M16 -> 10350 | M16: =D16 -> 1150 | N16: =M16-D16 -> 0 | O16: =N16*I16 -> 0 | P16: =F16+H16-L16 -> 5150 | Q16: K'E'H | S16: 0 | V16: =+S16+T16+U16 -> 0
A17: 12 | B17: SALT 800GM | C17: PKT | D17: 29 | E17: 0 | F17: =E17*D17 -> 0 | G17: =SUMIF(PURCHASE!$E$3:$E$506,'INVONTERY FEB'!B17:B344,PURCHASE!$H$3:$H$506) -> 0 | H17: =SUMIF(PURCHASE!$E$3:$E$506,'INVONTERY FEB'!B17:B339,PURCHASE!$I$3:$I$506) -> 0 | I17: =ISSU!AL17 -> 0 | J17: =I17/28 -> 0 | K17: =E17+G17-I17 -> 0 | L17: =K17*M17 -> 0 | M17: =D17 -> 29 | N17: =M17-D17 -> 0 | O17: =N17*I17 -> 0 | P17: =F17+H17-L17 -> 0 | S17: 0 | V17: =+S17+T17+U17 -> 0
A18: 13 | B18: BAKING POWDER HOLIDAY | C18: KG | D18: 2000 | E18: 0 | F18: =E18*D18 -> 0 | G18: =SUMIF(PURCHASE!$E$3:$E$506,'INVONTERY FEB'!B18:B362,PURCHASE!$H$3:$H$506) -> 5 | H18: =SUMIF(PURCHASE!$E$3:$E$506,'INVONTERY FEB'!B18:B362,PURCHASE!$I$3:$I$506) -> 10000 | I18: =ISSU!AL19 -> 3 | J18: =I18/28 -> 0.10714286 | K18: =E18+G18-I18 -> 2 | L18: =K18*M18 -> 4000 | M18: =D18 -> 2000 | N18: =M18-D18 -> 0 | O18: =N18*I18 -> 0 | P18: =F18+H18-L18 -> 6000 | Q18: LOCAL | S18: 0 | V18: =+S18+T18+U18 -> 0
A19: 14 | B19: BAKING SODA 1- KG | C19: KG | D19: 160 | E19: 5 | F19: =E19*D19 -> 800 | G19: =SUMIF(PURCHASE!$E$3:$E$506,'INVONTERY FEB'!B19:B338,PURCHASE!$H$3:$H$506) -> 0 | H19: =SUMIF(PURCHASE!$E$3:$E$506,'INVONTERY FEB'!B19:B333,PURCHASE!$I$3:$I$506) -> 0 | I19: =ISSU!AL18 -> 0 | J19: =I19/28 -> 0 | K19: =E19+G19-I19 -> 5 | L19: =K19*M19 -> 800 | M19: =D19 -> 160 | N19: =M19-D19 -> 0 | O19: =N19*I19 -> 0 | P19: =F19+H19-L19 -> 0 | Q19: LOCAL | S19: 0 | V19: =+S19+T19+U19 -> 0
A20: 15 | B20: STARCH | C20: KG | D20: 200 | E20: 5 | F20: =E20*D20 -> 1000 | G20: =SUMIF(PURCHASE!$E$3:$E$506,'INVONTERY FEB'!B20:B351,PURCHASE!$H$3:$H$506) -> 0 | H20: =SUMIF(PURCHASE!$E$3:$E$506,'INVONTERY FEB'!B20:B346,PURCHASE!$I$3:$I$506) -> 0 | I20: =ISSU!AL20 -> 0 | J20: =I20/28 -> 0 | K20: =E20+G20-I20 -> 5 | L20: =K20*M20 -> 1000 | M20: =D20 -> 200 | N20: =M20-D20 -> 0 | O20: =N20*I20 -> 0 | P20: =F20+H20-L20 -> 0 | Q20: LOCAL | V20: =+S20+T20+U20 -> 0
A21: 16 | B21: KHOYA ESSANSE | C21: PCS | E21: 0 | F21: =E21*D21 -> 0 | G21: =SUMIF(PURCHASE!$E$3:$E$506,'INVONTERY FEB'!B21:B377,PURCHASE!$H$3:$H$506) -> 0 | H21: =SUMIF(PURCHASE!$E$3:$E$506,'INVONTERY FEB'!B21:B375,PURCHASE!$I$3:$I$506) -> 0 | I21: =ISSU!AL21 -> 0 | J21: =I21/28 -> 0 | K21: =E21+G21-I21 -> 0 | L21: =K21*M21 -> 0 | M21: =D21 | N21: =M21-D21 -> 0 | O21: =N21*I21 -> 0 | P21: =F21+H21-L21 -> 0 | Q21: NESTLE | S21: 0 | V21: =+S21+T21+U21 -> 0
A22: 17 | B22: HABIB OIL 4.5 L BOT | C22: BOTT | F22: =E22*D22 -> 0 | G22: =SUMIF(PURCHASE!$E$3:$E$506,'INVONTERY FEB'!B22:B339,PURCHASE!$H$3:$H$506) -> 0 | H22: =SUMIF(PURCHASE!$E$3:$E$506,'INVONTERY FEB'!B22:B334,PURCHASE!$I$3:$I$506) -> 0 | I22: =ISSU!AL22 -> 0 | J22: =I22/30 -> 0 | K22: =E22+G22-I22 -> 0 | L22: =K22*M22 -> 0 | M22: =D22 | N22: =M22-D22 -> 0 | O22: =N22*I22 -> 0 | P22: =F22+H22-L22 -> 0 | S22: 0 | U22: 1 | V22: =+S22+T22+U22 -> 1
A23: 18 | B23: PUCK CHEESE | C23: JAR | F23: =E23*D23 -> 0 | G23: =SUMIF(PURCHASE!$E$3:$E$506,'INVONTERY FEB'!B23:B338,PURCHASE!$H$3:$H$506) -> 0 | H23: =SUMIF(PURCHASE!$E$3:$E$506,'INVONTERY FEB'!B23:B333,PURCHASE!$I$3:$I$506) -> 0 | I23: =ISSU!AL23 -> 0 | J23: =I23/30 -> 0 | K23: =E23+G23-I23 -> 0 | L23: =K23*M23 -> 0 | M23: =D23 | N23: =M23-D23 -> 0 | O23: =N23*I23 -> 0 | P23: =F23+H23-L23 -> 0 | Q23: K'E'H | S23: 0 | V23: =+S23+T23+U23 -> 0
A24: 19 | B24: GULCOSE LIQUID | C24: BOTT | F24: =E24*D24 -> 0 | G24: =SUMIF(PURCHASE!$E$3:$E$506,'INVONTERY FEB'!B24:B339,PURCHASE!$H$3:$H$506) -> 1 | H24: =SUMIF(PURCHASE!$E$3:$E$506,'INVONTERY FEB'!B24:B334,PURCHASE!$I$3:$I$506) -> 1750 | I24: =ISSU!AL24 -> 0 | J24: =I24/30 -> 0 | K24: =E24+G24-I24 -> 1 | L24: =K24*M24 -> 0 | M24: =D24 | N24: =M24-D24 -> 0 | O24: =N24*I24 -> 0 | P24: =F24+H24-L24 -> 1750 | S24: 0 | V24: =+S24+T24+U24 -> 0
A25: 20 | B25: POLAC MILK 390 GM | C25: TIN | D25: 0 | F25: =E25*D25 -> 0 | G25: =SUMIF(PURCHASE!$E$3:$E$506,'INVONTERY FEB'!B25:B340,PURCHASE!$H$3:$H$506) -> 96 | H25: =SUMIF(PURCHASE!$E$3:$E$506,'INVONTERY FEB'!B25:B335,PURCHASE!$I$3:$I$506) -> 25000 | I25: =ISSU!AL25 -> 42 | J25: =I25/30 -> 1.4 | K25: =E25+G25-I25 -> 54 | L25: =K25*M25 -> 0 | M25: =D25 -> 0 | N25: =M25-D25 -> 0 | O25: =N25*I25 -> 0 | P25: =F25+H25-L25 -> 25000 | V25: =+S25+T25+U25 -> 0
A26: 21 | D26: 0 | F26: =E26*D26 -> 0 | G26: =SUMIF(PURCHASE!$E$3:$E$506,'INVONTERY FEB'!B26:B341,PURCHASE!$H$3:$H$506) -> 0 | H26: =SUMIF(PURCHASE!$E$3:$E$506,'INVONTERY FEB'!B26:B336,PURCHASE!$I$3:$I$506) -> 0 | I26: =ISSU!AL26 -> 0 | J26: =I26/30 -> 0 | K26: =E26+G26-I26 -> 0 | L26: =K26*M26 -> 0 | M26: =D26 -> 0 | N26: =M26-D26 -> 0 | O26: =N26*I26 -> 0 | P26: =F26+H26-L26 -> 0 | V26: =+S26+T26+U26 -> 0
A27: 22 | D27: 0 | F27: =E27*D27 -> 0 | G27: =SUMIF(PURCHASE!$E$3:$E$506,'INVONTERY FEB'!B27:B342,PURCHASE!$H$3:$H$506) -> 0 | H27: =SUMIF(PURCHASE!$E$3:$E$506,'INVONTERY FEB'!B27:B337,PURCHASE!$I$3:$I$506) -> 0 | I27: =ISSU!AL27 -> 0 | J27: =I27/30 -> 0 | K27: =E27+G27-I27 -> 0 | L27: =K27*M27 -> 0 | M27: =D27 -> 0 | N27: =M27-D27 -> 0 | O27: =N27*I27 -> 0 | P27: =F27+H27-L27 -> 0 | V27: =+S27+T27+U27 -> 0
A28: 23 | D28: 0 | F28: =E28*D28 -> 0 | G28: =SUMIF(PURCHASE!$E$3:$E$506,'INVONTERY FEB'!B28:B333,PURCHASE!$H$3:$H$506) -> 0 | H28: =SUMIF(PURCHASE!$E$3:$E$506,'INVONTERY FEB'!B28:B333,PURCHASE!$I$3:$I$506) -> 0 | I28: =ISSU!AL28 -> 0 | J28: =I28/30 -> 0 | K28: =E28+G28-I28 -> 0 | L28: =K28*M28 -> 0 | M28: =D28 -> 0 | N28: =M28-D28 -> 0 | O28: =N28*I28 -> 0 | P28: =F28+H28-L28 -> 0 | Q28: LOCAL | V28: =+S28+T28+U28 -> 0
A29: 24 | B29: TOTA SPONAGE AMOUNT | E29: =SUM(E9:E21) -> 1495 | F29: =SUM(F6:F28) -> 577460.24 | G29: =SUM(G6:G28) -> 5553 | H29: =SUM(H6:H28) -> 519394.03 | I29: =SUM(I6:I28) -> 6221 | J29: =SUM(J6:J28) -> 222.07857 | K29: =SUM(K6:K28) -> 827 | L29: =SUM(L6:L28) -> 478047.03 | M29: =SUM(M6:M28) -> 9478.8674 | ... Q29: =SUM(Q6:Q28) -> 0 | V29: =+S29+T29+U29 -> 0
A30: 25 | B30: CAKE CRÈME | V30: =+S30+T30+U30 -> 0
A31: 26 | B31: CHOCO KNOC | C31: BUCKET | D31: 7800 | E31: 0 | F31: =E31*D31 -> 0 | G31: =SUMIF(PURCHASE!$E$3:$E$506,'INVONTERY FEB'!B31:B328,PURCHASE!$H$3:$H$506) -> 0 | H31: =SUMIF(PURCHASE!$E$3:$E$506,'INVONTERY FEB'!B31:B328,PURCHASE!$I$3:$I$506) -> 0 | I31: =ISSU!AL31 -> 0 | J31: =I31/28 -> 0 | K31: =E31+G31-I31 -> 0 | L31: =K31*M31 -> 0 | M31: =D31 -> 7800 | N31: =M31-D31 -> 0 | O31: =N31*I31 -> 0 | P31: =F31+H31-L31 -> 0 | S31: 0 | V31: =+S31+T31+U31 -> 0
A32: 27 | B32: MILK PACK CREAM200ML | C32: PCS | D32: 211 | E32: 0 | F32: =E32*D32 -> 0 | G32: =SUMIF(PURCHASE!$E$3:$E$506,'INVONTERY FEB'!B32:B328,PURCHASE!$H$3:$H$506) -> 0 | H32: =SUMIF(PURCHASE!$E$3:$E$506,'INVONTERY FEB'!B32:B328,PURCHASE!$I$3:$I$506) -> 0 | I32: =ISSU!AL32 -> 0 | J32: =I32/28 -> 0 | K32: =E32+G32-I32 -> 0 | L32: =K32*M32 -> 0 | M32: =D32 -> 211 | N32: =M32-D32 -> 0 | O32: =N32*I32 -> 0 | P32: =F32+H32-L32 -> 0 | Q32: LOCAL | S32: 0 | U32: 12 | V32: =+S32+T32+U32 -> 12
A33: 28 | B33: NESTLE BUTTER | C33: KG | D33: 1850 | E33: 0 | F33: =E33*D33 -> 0 | G33: =SUMIF(PURCHASE!$E$3:$E$506,'INVONTERY FEB'!B33:B375,PURCHASE!$H$3:$H$506) -> 40 | H33: =SUMIF(PURCHASE!$E$3:$E$506,'INVONTERY FEB'!B33:B373,PURCHASE!$I$3:$I$506) -> 74000 | I33: =ISSU!AL33 -> 15 | J33: =I33/28 -> 0.53571429 | K33: =E33+G33-I33 -> 25 | L33: =K33*M33 -> 46250 | M33: =55500/30 -> 1850 | N33: =M33-D33 -> 0 | O33: =N33*I33 -> 0 | P33: =F33+H33-L33 -> 27750 | Q33: NESTLE | S33: 10 | V33: =+S33+T33+U33 -> 10
A34: 29 | B34: WHIPPING CREAM | C34: PCS | D34: 700 | E34: 126 | F34: =E34*D34 -> 88200 | G34: =SUMIF(PURCHASE!$E$3:$E$506,'INVONTERY FEB'!B34:B328,PURCHASE!$H$3:$H$506) -> 216 | H34: =SUMIF(PURCHASE!$E$3:$E$506,'INVONTERY FEB'!B34:B328,PURCHASE!$I$3:$I$506) -> 151200 | I34: =ISSU!AL34 -> 269 | J34: =I34/28 -> 9.6071429 | K34: =E34+G34-I34 -> 73 | L34: =K34*M34 -> 51100 | M34: =168000/240 -> 700 | N34: =M34-D34 -> 0 | O34: =N34*I34 -> 0 | P34: =F34+H34-L34 -> 188300 | Q34: VENUS | V34: =+S34+T34+U34 -> 0
A35: 30 | B35: ROXELLA CRUNCHY CREAM | C35: KG | D35: 4281 | E35: 5 | F35: =E35*D35 -> 21405 | G35: =SUMIF(PURCHASE!$E$3:$E$506,'INVONTERY FEB'!B35:B328,PURCHASE!$H$3:$H$506) -> 0 | H35: =SUMIF(PURCHASE!$E$3:$E$506,'INVONTERY FEB'!B35:B328,PURCHASE!$I$3:$I$506) -> 0 | I35: =ISSU!AL35 -> 3 | J35: =I35/28 -> 0.10714286 | K35: =E35+G35-I35 -> 2 | L35: =K35*M35 -> 8562 | M35: =D35 -> 4281 | N35: =M35-D35 -> 0 | O35: =N35*I35 -> 0 | P35: =F35+H35-L35 -> 12843 | Q35: VENUS | S35: 0 | V35: =+S35+T35+U35 -> 0
A36: 31 | B36: NURPUR BUTTER | C36: KG | D36: 1800 | E36: 15 | F36: =E36*D36 -> 27000 | G36: =SUMIF(PURCHASE!$E$3:$E$506,'INVONTERY FEB'!B36:B328,PURCHASE!$H$3:$H$506) -> 10 | H36: =SUMIF(PURCHASE!$E$3:$E$506,'INVONTERY FEB'!B36:B328,PURCHASE!$I$3:$I$506) -> 19500 | I36: =ISSU!AL36 -> 25 | J36: =I36/28 -> 0.89285714 | K36: =E36+G36-I36 -> 0 | L36: =K36*M36 -> 0 | M36: =D36 -> 1800 | N36: =M36-D36 -> 0 | O36: =N36*I36 -> 0 | P36: =F36+H36-L36 -> 46500 | Q36: VENUS | S36: 0 | V36: =+S36+T36+U36 -> 0
A37: 32 | B37: CHEESE CREAM | C37: LTR | D37: 2500 | E37: 2 | F37: =E37*D37 -> 5000 | G37: =SUMIF(PURCHASE!$E$3:$E$506,'INVONTERY FEB'!B37:B329,PURCHASE!$H$3:$H$506) -> 0 | H37: =SUMIF(PURCHASE!$E$3:$E$506,'INVONTERY FEB'!B37:B329,PURCHASE!$I$3:$I$506) -> 0 | I37: =ISSU!AL37 -> 1 | J37: =I37/28 -> 0.035714286 | K37: =E37+G37-I37 -> 1 | L37: =K37*M37 -> 2500 | M37: =D37 -> 2500 | N37: =M37-D37 -> 0 | O37: =N37*I37 -> 0 | P37: =F37+H37-L37 -> 2500 | S37: 0 | T37: 12 | V37: =+S37+T37+U37 -> 12
A38: 33 | B38: G.P ICING SUGAR | C38: PCS | D38: 155 | E38: 88 | F38: =E38*D38 -> 13640 | G38: =SUMIF(PURCHASE!$E$3:$E$506,'INVONTERY FEB'!B38:B330,PURCHASE!$H$3:$H$506) -> 0 | H38: =SUMIF(PURCHASE!$E$3:$E$506,'INVONTERY FEB'!B38:B330,PURCHASE!$I$3:$I$506) -> 0 | I38: =ISSU!AL38 -> 32 | J38: =I38/28 -> 1.1428571 | K38: =E38+G38-I38 -> 56 | L38: =K38*M38 -> 8680 | M38: =D38 -> 155 | N38: =M38-D38 -> 0 | O38: =N38*I38 -> 0 | P38: =F38+H38-L38 -> 4960 | S38: =36+10 -> 46 | U38: 12 | V38: =+S38+T38+U38 -> 58
A39: 34 | B39: DARK CHOCLATE SLAB 2 KG | C39: PKT | D39: 1400 | E39: 69 | F39: =E39*D39 -> 96600 | G39: =SUMIF(PURCHASE!$E$3:$E$506,'INVONTERY FEB'!B39:B331,PURCHASE!$H$3:$H$506) -> 0 | H39: =SUMIF(PURCHASE!$E$3:$E$506,'INVONTERY FEB'!B39:B441,PURCHASE!$I$3:$I$506) -> 0 | I39: =ISSU!AL39 -> 33 | J39: =I39/28 -> 1.1785714 | K39: =E39+G39-I39 -> 36 | L39: =K39*M39 -> 50400 | M39: =D39 -> 1400 | N39: =M39-D39 -> 0 | O39: =N39*I39 -> 0 | P39: =F39+H39-L39 -> 46200 | Q39: LOCAL | S39: 20 | V39: =+S39+T39+U39 -> 20
A40: 35 | B40: MILKI CHOCLATE SLAB 2 KG | C40: PKT | D40: 1600 | E40: 65 | F40: =E40*D40 -> 104000 | G40: =SUMIF(PURCHASE!$E$3:$E$506,'INVONTERY FEB'!B40:B501,PURCHASE!$H$3:$H$506) -> 0 | H40: =SUMIF(PURCHASE!$E$3:$E$506,'INVONTERY FEB'!B40:B451,PURCHASE!$I$3:$I$506) -> 0 | I40: =ISSU!AL40 -> 26 | J40: =I40/28 -> 0.92857143 | K40: =E40+G40-I40 -> 39 | L40: =K40*M40 -> 62400 | M40: =D40 -> 1600 | N40: =M40-D40 -> 0 | O40: =N40*I40 -> 0 | P40: =F40+H40-L40 -> 41600 | Q40: REHMAT WHEAT | S40: 0 | T40: 1 | V40: =+S40+T40+U40 -> 1
A41: 36 | B41: HISS CHOCLATE 4 RINGS | C41: BOX | D41: 1500 | E41: 0 | F41: =E41*D41 -> 0 | G41: =SUMIF(PURCHASE!$E$3:$E$506,'INVONTERY FEB'!B41:B335,PURCHASE!$H$3:$H$506) -> 0 | H41: =SUMIF(PURCHASE!$E$3:$E$506,'INVONTERY FEB'!B41:B335,PURCHASE!$I$3:$I$506) -> 0 | I41: =ISSU!AL41 -> 0 | J41: =I41/28 -> 0 | K41: =E41+G41-I41 -> 0 | L41: =K41*M41 -> 0 | M41: =D41 -> 1500 | N41: =M41-D41 -> 0 | O41: =N41*I41 -> 0 | P41: =F41+H41-L41 -> 0 | Q41: VENUS | S41: 3 | V41: =+S41+T41+U41 -> 3
A42: 37 | B42: HISS CHOCLATE 2 RINGS | C42: BOX | D42: 667 | E42: 3 | F42: =E42*D42 -> 2001 | G42: =SUMIF(PURCHASE!$E$3:$E$506,'INVONTERY FEB'!B42:B336,PURCHASE!$H$3:$H$506) -> 18 | H42: =SUMIF(PURCHASE!$E$3:$E$506,'INVONTERY FEB'!B42:B336,PURCHASE!$I$3:$I$506) -> 16000 | I42: =ISSU!AL42 -> 15 | J42: =I42/28 -> 0.53571429 | K42: =E42+G42-I42 -> 6 | L42: =K42*M42 -> 4002 | M42: =D42 -> 667 | N42: =M42-D42 -> 0 | O42: =N42*I42 -> 0 | P42: =F42+H42-L42 -> 13999 | Q42: VENUS | S42: 0 | V42: =+S42+T42+U42 -> 0 | AA42: =1270*12 -> 15240
A43: 38 | B43: DAIRY MILK | C43: BOX | D43: =9966/E43 -> 433.30435 | E43: 23 | F43: =E43*D43 -> 9966 | G43: =SUMIF(PURCHASE!$E$3:$E$506,'INVONTERY FEB'!B43:B349,PURCHASE!$H$3:$H$506) -> 24 | H43: =SUMIF(PURCHASE!$E$3:$E$506,'INVONTERY FEB'!B43:B349,PURCHASE!$I$3:$I$506) -> 10500 | I43: =ISSU!AL43 -> 23 | J43: =I43/28 -> 0.82142857 | K43: =E43+G43-I43 -> 24 | L43: =K43*M43 -> 10399.304 | M43: =D43 -> 433.30435 | N43: =M43-D43 -> 0 | O43: =N43*I43 -> 0 | P43: =F43+H43-L43 -> 10066.696 | S43: =24+11 -> 35 | U43: 2 | V43: =+S43+T43+U43 -> 37
A44: 39 | B44: CORN FLOURE | C44: KG | D44: 232 | E44: 0 | F44: =E44*D44 -> 0 | G44: =SUMIF(PURCHASE!$E$3:$E$506,'INVONTERY FEB'!B44:B350,PURCHASE!$H$3:$H$506) -> 0 | H44: =SUMIF(PURCHASE!$E$3:$E$506,'INVONTERY FEB'!B44:B350,PURCHASE!$I$3:$I$506) -> 0 | I44: =ISSU!AL44 -> 0 | J44: =I44/28 -> 0 | K44: =E44+G44-I44 -> 0 | L44: =K44*M44 -> 0 | M44: =D44 -> 232 | N44: =M44-D44 -> 0 | O44: =N44*I44 -> 0 | P44: =F44+H44-L44 -> 0 | S44: 0 | V44: =+S44+T44+U44 -> 0 | AA44: =+AA42*5 -> 76200
A45: 40 | B45: WHITE CHOCLATE SLAB 2 KG | C45: PKT | D45: 1600 | E45: 9 | F45: =E45*D45 -> 14400 | G45: =SUMIF(PURCHASE!$E$3:$E$506,'INVONTERY FEB'!B45:B351,PURCHASE!$H$3:$H$506) -> 0 | H45: =SUMIF(PURCHASE!$E$3:$E$506,'INVONTERY FEB'!B45:B351,PURCHASE!$I$3:$I$506) -> 0 | I45: =ISSU!AL45 -> 3 | J45: =I45/28 -> 0.10714286 | K45: =E45+G45-I45 -> 6 | L45: =K45*M45 -> 9600 | M45: =D45 -> 1600 | N45: =M45-D45 -> 0 | O45: =N45*I45 -> 0 | P45: =F45+H45-L45 -> 4800 | S45: 0 | V45: =+S45+T45+U45 -> 0
A46: 41 | B46: LUEVEN CREAM | C46: KG | D46: 3300 | E46: 15 | F46: =E46*D46 -> 49500 | G46: =SUMIF(PURCHASE!$E$3:$E$506,'INVONTERY FEB'!B46:B352,PURCHASE!$H$3:$H$506) -> 0 | H46: =SUMIF(PURCHASE!$E$3:$E$506,'INVONTERY FEB'!B46:B352,PURCHASE!$I$3:$I$506) -> 0 | I46: =ISSU!AL46 -> 5 | J46: =I46/28 -> 0.17857143 | K46: =E46+G46-I46 -> 10 | L46: =K46*M46 -> 33000 | M46: =D46 -> 3300 | N46: =M46-D46 -> 0 | O46: =N46*I46 -> 0 | P46: =F46+H46-L46 -> 16500 | S46: 0 | V46: =+S46+T46+U46 -> 0
A47: 42 | B47: PISTACHIO SAPREAD | C47: KG | D47: 5200 | E47: 0 | F47: =E47*D47 -> 0 | G47: =SUMIF(PURCHASE!$E$3:$E$506,'INVONTERY FEB'!B47:B353,PURCHASE!$H$3:$H$506) -> 9 | H47: =SUMIF(PURCHASE!$E$3:$E$506,'INVONTERY FEB'!B47:B353,PURCHASE!$I$3:$I$506) -> 46800 | I47: =ISSU!AL47 -> 3 | J47: =I47/28 -> 0.10714286 | K47: =E47+G47-I47 -> 6 | L47: =K47*M47 -> 31200 | M47: =D47 -> 5200 | N47: =M47-D47 -> 0 | O47: =N47*I47 -> 0 | P47: =F47+H47-L47 -> 15600 | S47: 0 | T47: 2 | U47: 1 | V47: =+S47+T47+U47 -> 3
A48: 43 | B48: OLPERS CREAM 200 ML | C48: PCS | D48: =63221/E48 -> 207.28197 | E48: 305 | F48: =E48*D48 -> 63221 | G48: =SUMIF(PURCHASE!$E$3:$E$506,'INVONTERY FEB'!B48:B354,PURCHASE!$H$3:$H$506) -> 480 | H48: =SUMIF(PURCHASE!$E$3:$E$506,'INVONTERY FEB'!B48:B354,PURCHASE!$I$3:$I$506) -> 99495.344 | I48: =ISSU!AL48 -> 665 | J48: =I48/28 -> 23.75 | K48: =E48+G48-I48 -> 120 | L48: =K48*M48 -> 24874 | M48: =49748/240 -> 207.28333 | N48: =M48-D48 -> 0.0013661202 | O48: =N48*I48 -> 0.90846995 | P48: =F48+H48-L48 -> 137842.34 | V48: =+S48+T48+U48 -> 0
A49: 44 | B49: SALBON CHOCLATE | C49: KG | D49: 0 | E49: 0 | F49: =E49*D49 -> 0 | G49: =SUMIF(PURCHASE!$E$3:$E$506,'INVONTERY FEB'!B49:B355,PURCHASE!$H$3:$H$506) -> 0 | H49: =SUMIF(PURCHASE!$E$3:$E$506,'INVONTERY FEB'!B49:B351,PURCHASE!$I$3:$I$506) -> 0 | I49: =ISSU!AL49 -> 0 | J49: =I49/28 -> 0 | K49: =E49+G49-I49 -> 0 | L49: =K49*M49 -> 0 | N49: =M49-D49 -> 0 | O49: =N49*I49 -> 0 | P49: =F49+H49-L49 -> 0 | V49: =+S49+T49+U49 -> 0
A50: 45 | B50: TOTAL CAKE CREME AMOUNT | E50: =SUM(E31:E49) -> 725 | F50: =SUM(F31:F49) -> 494933 | G50: =SUMIF(PURCHASE!$E$3:$E$506,'INVONTERY FEB'!B50:B356,PURCHASE!$H$3:$H$506) -> 0 | H50: =SUM(H31:H49) -> 417495.34 | I50: =SUM(I31:I49) -> 1118 | K50: =SUM(K31:K49) -> 404 | L50: =SUM(L31:L49) -> 342967.3 | N50: =SUM(N31:N49) -> 0.0013661202 | O50: =SUM(O31:O49) -> 0.90846995 | P50: =SUM(P31:P49) -> 569461.04 | V50: =+S50+T50+U50 -> 0
A51: 46 | B51: CAKE TOPPINGS | V51: =+S51+T51+U51 -> 0
A52: 47 | B52: LOTUS BISCOFF | C52: PKT | D52: 1100 | E52: 22 | F52: =E52*D52 -> 24200 | G52: =SUMIF(PURCHASE!$E$3:$E$506,'INVONTERY FEB'!B52:B411,PURCHASE!$H$3:$H$506) -> 50 | H52: =SUMIF(PURCHASE!$E$3:$E$506,'INVONTERY FEB'!B52:B406,PURCHASE!$I$3:$I$506) -> 55000 | I52: =ISSU!AL52 -> 21 | J52: =I52/29 -> 0.72413793 | K52: =E52+G52-I52 -> 51 | L52: =K52*M52 -> 56100 | M52: 1100 | N52: =M52-D52 -> 0 | O52: =N52*I52 -> 0 | P52: =F52+H52-L52 -> 23100 | Q52: LOCAL | S52: 0 | U52: 1 | V52: =+S52+T52+U52 -> 1
A53: 48 | B53: FRUIT COCTAIL | C53: TIN | D53: 1617 | E53: 0 | F53: =E53*D53 -> 0 | K53: =E53+G53-I53 -> 0 | M53: 1617
A54: 49 | B54: RED CHERRIES | C54: CASE | D54: 6600 | E54: 0 | F54: =E54*D54 -> 0 | G54: =SUMIF(PURCHASE!$E$3:$E$506,'INVONTERY FEB'!B54:B413,PURCHASE!$H$3:$H$506) -> 0 | H54: =SUMIF(PURCHASE!$E$3:$E$506,'INVONTERY FEB'!B54:B408,PURCHASE!$I$3:$I$506) -> 0 | I54: =ISSU!AL53 -> 0 | J54: =I54/29 -> 0 | K54: =E54+G54-I54 -> 0 | L54: =K54*M54 -> 0 | M54: 6600 | N54: =M54-D54 -> 0 | O54: =N54*I54 -> 0 | P54: =F54+H54-L54 -> 0 | Q54: LOCAL | S54: 0 | V54: =+S54+T54+U54 -> 0
A55: 50 | B55: ALMONDS | C55: KG | D55: =10400/4 -> 2600 | E55: 1 | F55: =E55*D55 -> 2600 | G55: =SUMIF(PURCHASE!$E$3:$E$506,'INVONTERY FEB'!B37:B328,PURCHASE!$H$3:$H$506) -> 5 | H55: =SUMIF(PURCHASE!$E$3:$E$506,'INVONTERY FEB'!B37:B328,PURCHASE!$I$3:$I$506) -> 13250 | I55: =ISSU!AL54 -> 4 | J55: =I55/29 -> 0.13793103 | K55: =E55+G55-I55 -> 2 | L55: =K55*M55 -> 5200 | M55: =5200/2 -> 2600 | N55: =M55-D55 -> 0 | O55: =N55*I55 -> 0 | P55: =F55+H55-L55 -> 10650 | Q55: LOCAL | S55: 0 | V55: =+S55+T55+U55 -> 0
A56: 51 | B56: CASHEW NUT | C56: KG | D56: 3300 | E56: 0 | F56: =E56*D56 -> 0 | G56: =SUMIF(PURCHASE!$E$3:$E$506,'INVONTERY FEB'!B56:B401,PURCHASE!$H$3:$H$506) -> 0 | H56: =SUMIF(PURCHASE!$E$3:$E$506,'INVONTERY FEB'!B56:B396,PURCHASE!$I$3:$I$506) -> 0 | I56: =ISSU!AL55 -> 0 | J56: =I56/29 -> 0 | K56: =E56+G56-I56 -> 0 | L56: =K56*M56 -> 0 | M56: 3300 | N56: =M56-D56 -> 0 | O56: =N56*I56 -> 0 | P56: =F56+H56-L56 -> 0 | Q56: LOCAL | S56: 0 | V56: =+S56+T56+U56 -> 0
A57: 52 | B57: PISTACHIO | C57: KG | D57: 5113 | E57: 0 | F57: =E57*D57 -> 0 | G57: =SUMIF(PURCHASE!$E$3:$E$506,'INVONTERY FEB'!B57:B402,PURCHASE!$H$3:$H$506) -> 3 | H57: =SUMIF(PURCHASE!$E$3:$E$506,'INVONTERY FEB'!B57:B397,PURCHASE!$I$3:$I$506) -> 18600 | I57: =ISSU!AL56 -> 2 | J57: =I57/29 -> 0.068965517 | K57: =E57+G57-I57 -> 1 | L57: =K57*M57 -> 5113 | M57: 5113 | N57: =M57-D57 -> 0 | O57: =N57*I57 -> 0 | P57: =F57+H57-L57 -> 13487 | Q57: LOCAL | S57: 0 | V57: =+S57+T57+U57 -> 0
A58: 53 | B58: PEANUTS | C58: KG | D58: 750 | E58: 1 | F58: =E58*D58 -> 750 | G58: =SUMIF(PURCHASE!$E$3:$E$506,'INVONTERY FEB'!B58:B403,PURCHASE!$H$3:$H$506) -> 0 | H58: =SUMIF(PURCHASE!$E$3:$E$506,'INVONTERY FEB'!B58:B398,PURCHASE!$I$3:$I$506) -> 0 | I58: =ISSU!AL57 -> 0 | J58: =I58/29 -> 0 | K58: =E58+G58-I58 -> 1 | L58: =K58*M58 -> 750 | M58: 750 | N58: =M58-D58 -> 0 | O58: =N58*I58 -> 0 | P58: =F58+H58-L58 -> 0 | Q58: LOCAL | S58: 0 | V58: =+S58+T58+U58 -> 0
A59: 54 | B59: CAKE SPRINKELS | C59: PCS | D59: 483 | E59: 0 | F59: =E59*D59 -> 0 | G59: =SUMIF(PURCHASE!$E$3:$E$506,'INVONTERY FEB'!B59:B407,PURCHASE!$H$3:$H$506) -> 0 | H59: =SUMIF(PURCHASE!$E$3:$E$506,'INVONTERY FEB'!B59:B402,PURCHASE!$I$3:$I$506) -> 0 | I59: =ISSU!AL58 -> 0 | J59: =I59/29 -> 0 | K59: =E59+G59-I59 -> 0 | L59: =K59*M59 -> 0 | M59: 483 | N59: =M59-D59 -> 0 | O59: =N59*I59 -> 0 | P59: =F59+H59-L59 -> 0 | S59: 0 | V59: =+S59+T59+U59 -> 0
A60: 55 | B60: COCONUT CRUMBULES | C60: KG | D60: 1000 | E60: 5 | F60: =E60*D60 -> 5000 | G60: =SUMIF(PURCHASE!$E$3:$E$506,'INVONTERY FEB'!B43:B339,PURCHASE!$H$3:$H$506) -> 0 | H60: =SUMIF(PURCHASE!$E$3:$E$506,'INVONTERY FEB'!B43:B339,PURCHASE!$I$3:$I$506) -> 0 | I60: =ISSU!AL59 -> 0 | J60: =I60/29 -> 0 | K60: =E60+G60-I60 -> 5 | L60: =K60*M60 -> 5000 | M60: =5000/5 -> 1000 | N60: =M60-D60 -> 0 | O60: =N60*I60 -> 0 | P60: =F60+H60-L60 -> 0 | Q60: LOCAL | S60: 0 | V60: =+S60+T60+U60 -> 0
A61: 56 | B61: FERRY ROSE | C61: BOX | D61: 1000 | E61: 0 | F61: =E61*D61 -> 0 | G61: =SUMIF(PURCHASE!$E$3:$E$506,'INVONTERY FEB'!B61:B340,PURCHASE!$H$3:$H$506) -> 11 | H61: =SUMIF(PURCHASE!$E$3:$E$506,'INVONTERY FEB'!B61:B340,PURCHASE!$I$3:$I$506) -> 11000 | I61: =ISSU!AL60 -> 4 | J61: =I61/29 -> 0.13793103 | K61: =E61+G61-I61 -> 7 | L61: =K61*M61 -> 7000 | M61: 1000 | N61: =M61-D61 -> 0 | O61: =N61*I61 -> 0 | P61: =F61+H61-L61 -> 4000 | Q61: LOCAL | S61: 0 | V61: =+S61+T61+U61 -> 0
A62: 57 | B62: LOTO CRUMBEL (885) | C62: KG | D62: 3440 | E62: 0 | F62: =E62*D62 -> 0 | G62: =SUMIF(PURCHASE!$E$3:$E$506,'INVONTERY FEB'!B62:B341,PURCHASE!$H$3:$H$506) -> 0 | H62: =SUMIF(PURCHASE!$E$3:$E$506,'INVONTERY FEB'!B62:B341,PURCHASE!$I$3:$I$506) -> 0 | I62: =ISSU!AL61 -> 0 | J62: =I62/29 -> 0 | K62: =E62+G62-I62 -> 0 | L62: =K62*M62 -> 0 | M62: 3440 | N62: =M62-D62 -> 0 | O62: =N62*I62 -> 0 | P62: =F62+H62-L62 -> 0 | Q62: LOCAL | S62: 2 | V62: =+S62+T62+U62 -> 2
A63: 58 | B63: CAREMAL SYRUP | C63: BOTT | D63: 1200 | E63: 0 | F63: =E63*D63 -> 0 | G63: =SUMIF(PURCHASE!$E$3:$E$506,'INVONTERY FEB'!B63:B342,PURCHASE!$H$3:$H$506) -> 0 | H63: =SUMIF(PURCHASE!$E$3:$E$506,'INVONTERY FEB'!B63:B342,PURCHASE!$I$3:$I$506) -> 0 | I63: =ISSU!AL62 -> 0 | J63: =I63/29 -> 0 | K63: =E63+G63-I63 -> 0 | L63: =K63*M63 -> 0 | M63: 1200 | N63: =M63-D63 -> 0 | O63: =N63*I63 -> 0 | P63: =F63+H63-L63 -> 0 | Q63: LOCAL | S63: 0 | V63: =+S63+T63+U63 -> 0
A64: 59 | B64: DARK CHOCLATE CHIPS | C64: KG | D64: 525 | E64: 22 | F64: =E64*D64 -> 11550 | G64: =SUMIF(PURCHASE!$E$3:$E$506,'INVONTERY FEB'!B64:B343,PURCHASE!$H$3:$H$506) -> 0 | H64: =SUMIF(PURCHASE!$E$3:$E$506,'INVONTERY FEB'!B64:B343,PURCHASE!$I$3:$I$506) -> 0 | I64: =ISSU!AL63 -> 4 | J64: =I64/29 -> 0.13793103 | K64: =E64+G64-I64 -> 18 | L64: =K64*M64 -> 9450 | M64: 525 | N64: =M64-D64 -> 0 | O64: =N64*I64 -> 0 | P64: =F64+H64-L64 -> 2100 | Q64: LOCAL | S64: 0 | V64: =+S64+T64+U64 -> 0
A65: 60 | B65: PICTURE CAKE | C65: PCS | D65: 180 | E65: 0 | F65: =E65*D65 -> 0 | G65: =SUMIF(PURCHASE!$E$3:$E$506,'INVONTERY FEB'!B65:B344,PURCHASE!$H$3:$H$506) -> 0 | H65: =SUMIF(PURCHASE!$E$3:$E$506,'INVONTERY FEB'!B65:B344,PURCHASE!$I$3:$I$506) -> 0 | I65: =ISSU!AL64 -> 0 | J65: =I65/29 -> 0 | K65: =E65+G65-I65 -> 0 | L65: =K65*M65 -> 0 | M65: 180 | N65: =M65-D65 -> 0 | O65: =N65*I65 -> 0 | P65: =F65+H65-L65 -> 0 | Q65: LOCAL | S65: 0 | V65: =+S65+T65+U65 -> 0
A66: 61 | B66: LOTO SPREAD 400G | C66: PCS | D66: 1750 | E66: 0 | F66: =E66*D66 -> 0 | G66: =SUMIF(PURCHASE!$E$3:$E$506,'INVONTERY FEB'!B66:B348,PURCHASE!$H$3:$H$506) -> 144 | H66: =SUMIF(PURCHASE!$E$3:$E$506,'INVONTERY FEB'!B66:B348,PURCHASE!$I$3:$I$506) -> 252000 | I66: =ISSU!AL65 -> 6 | J66: =I66/29 -> 0.20689655 | K66: =E66+G66-I66 -> 138 | L66: =K66*M66 -> 241500 | M66: 1750 | N66: =M66-D66 -> 0 | O66: =N66*I66 -> 0 | P66: =F66+H66-L66 -> 10500 | S66: 0 | V66: =+S66+T66+U66 -> 0
A67: 62 | B67: LOTO SPREAD | C67: KG | D67: =210000/48 -> 4375 | E67: 24 | F67: =E67*D67 -> 105000 | G67: =SUMIF(PURCHASE!$E$3:$E$506,'INVONTERY FEB'!B41:B334,PURCHASE!$H$3:$H$506) -> 0 | H67: =SUMIF(PURCHASE!$E$3:$E$506,'INVONTERY FEB'!B41:B334,PURCHASE!$I$3:$I$506) -> 0 | I67: =ISSU!AL66 -> 24 | J67: =I67/29 -> 0.82758621 | K67: =E67+G67-I67 -> 0 | L67: =K67*M67 -> 0 | M67: =210000/48 -> 4375 | N67: =M67-D67 -> 0 | O67: =N67*I67 -> 0 | P67: =F67+H67-L67 -> 105000 | Q67: VENUS | S67: 66 | V67: =+S67+T67+U67 -> 66
A68: 63 | B68: SPARK CHOCLATE OLD | C68: CTN | D68: 3520 | E68: 0 | F68: =E68*D68 -> 0 | G68: =SUMIF(PURCHASE!$E$3:$E$506,'INVONTERY FEB'!B68:B338,PURCHASE!$H$3:$H$506) -> 0 | H68: =SUMIF(PURCHASE!$E$3:$E$506,'INVONTERY FEB'!B68:B333,PURCHASE!$I$3:$I$506) -> 0 | I68: =ISSU!AL67 -> 0 | J68: =I68/29 -> 0 | K68: =E68+G68-I68 -> 0 | L68: =K68*M68 -> 0 | M68: 3520 | N68: =M68-D68 -> 0 | O68: =N68*I68 -> 0 | P68: =F68+H68-L68 -> 0 | Q68: VENUS | S68: 0 | V68: =+S68+T68+U68 -> 0
A69: 64 | B69: MIX FRUIT GELL | C69: CASE | D69: 2000 | E69: 2 | F69: =E69*D69 -> 4000 | G69: =SUMIF(PURCHASE!$E$3:$E$506,'INVONTERY FEB'!B69:B339,PURCHASE!$H$3:$H$506) -> 0 | H69: =SUMIF(PURCHASE!$E$3:$E$506,'INVONTERY FEB'!B69:B334,PURCHASE!$I$3:$I$506) -> 0 | I69: =ISSU!AL68 -> 0 | J69: =I69/29 -> 0 | K69: =E69+G69-I69 -> 2 | L69: =K69*M69 -> 4000 | M69: 2000 | N69: =M69-D69 -> 0 | O69: =N69*I69 -> 0 | P69: =F69+H69-L69 -> 0 | Q69: VENUS | S69: 0 | V69: =+S69+T69+U69 -> 0
A70: 65 | B70: CHECKPEAS | C70: PKT | D70: 450 | F70: =E70*D70 -> 0 | G70: =SUMIF(PURCHASE!$E$3:$E$506,'INVONTERY FEB'!B70:B340,PURCHASE!$H$3:$H$506) -> 0 | H70: =SUMIF(PURCHASE!$E$3:$E$506,'INVONTERY FEB'!B70:B335,PURCHASE!$I$3:$I$506) -> 0 | I70: =ISSU!AL69 -> 0 | J70: =I70/29 -> 0 | K70: =E70+G70-I70 -> 0 | L70: =K70*M70 -> 0 | M70: 450 | N70: =M70-D70 -> 0 | O70: =N70*I70 -> 0 | P70: =F70+H70-L70 -> 0 | Q70: VENUS | S70: 0 | V70: =+S70+T70+U70 -> 0
A71: 66 | B71: GOLOKOZ | C71: PKT | D71: 220 | F71: =E71*D71 -> 0 | G71: =SUMIF(PURCHASE!$E$3:$E$506,'INVONTERY FEB'!B71:B341,PURCHASE!$H$3:$H$506) -> 0 | H71: =SUMIF(PURCHASE!$E$3:$E$506,'INVONTERY FEB'!B71:B336,PURCHASE!$I$3:$I$506) -> 0 | I71: =ISSU!AL70 -> 0 | J71: =I71/29 -> 0 | K71: =E71+G71-I71 -> 0 | L71: =K71*M71 -> 0 | M71: 220 | N71: =M71-D71 -> 0 | O71: =N71*I71 -> 0 | P71: =F71+H71-L71 -> 0 | Q71: VENUS | S71: 0 | V71: =+S71+T71+U71 -> 0
A72: 67 | B72: EDIBLE COLOUR | C72: BOTT | D72: 250 | F72: =E72*D72 -> 0 | G72: =SUMIF(PURCHASE!$E$3:$E$506,'INVONTERY FEB'!B72:B342,PURCHASE!$H$3:$H$506) -> 0 | H72: =SUMIF(PURCHASE!$E$3:$E$506,'INVONTERY FEB'!B72:B337,PURCHASE!$I$3:$I$506) -> 0 | I72: =ISSU!AL71 -> 0 | J72: =I72/29 -> 0 | K72: =E72+G72-I72 -> 0 | L72: =K72*M72 -> 0 | M72: 250 | N72: =M72-D72 -> 0 | O72: =N72*I72 -> 0 | P72: =F72+H72-L72 -> 0 | Q72: VENUS | S72: 0 | V72: =+S72+T72+U72 -> 0
A73: 68 | B73: PINE APPLE | C73: TIN | D73: 1366 | F73: =E73*D73 -> 0 | G73: =SUMIF(PURCHASE!$E$3:$E$506,'INVONTERY FEB'!B73:B343,PURCHASE!$H$3:$H$506) -> 0 | H73: =SUMIF(PURCHASE!$E$3:$E$506,'INVONTERY FEB'!B73:B338,PURCHASE!$I$3:$I$506) -> 0 | I73: =ISSU!AL72 -> 0 | J73: =I73/29 -> 0 | K73: =E73+G73-I73 -> 0 | L73: =K73*M73 -> 0 | M73: 1366 | N73: =M73-D73 -> 0 | O73: =N73*I73 -> 0 | P73: =F73+H73-L73 -> 0 | Q73: K'E'H | S73: 0 | V73: =+S73+T73+U73 -> 0
A74: 69 | B74: SPARK CHOCLATE NEW | C74: BOX | D74: 550 | F74: =E74*D74 -> 0 | G74: =SUMIF(PURCHASE!$E$3:$E$506,'INVONTERY FEB'!B74:B339,PURCHASE!$H$3:$H$506) -> 0 | H74: =SUMIF(PURCHASE!$E$3:$E$506,'INVONTERY FEB'!B74:B334,PURCHASE!$I$3:$I$506) -> 0 | I74: =ISSU!AL73 -> 0 | J74: =I74/29 -> 0 | K74: =E74+G74-I74 -> 0 | L74: =K74*M74 -> 0 | M74: 550 | N74: =M74-D74 -> 0 | O74: =N74*I74 -> 0 | P74: =F74+H74-L74 -> 0 | Q74: LOCAL | S74: 0 | V74: =+S74+T74+U74 -> 0
A75: 70 | B75: SILVER MOTI | C75: BOTT | D75: 450 | F75: =E75*D75 -> 0 | G75: =SUMIF(PURCHASE!$E$3:$E$506,'INVONTERY FEB'!B75:B340,PURCHASE!$H$3:$H$506) -> 0 | H75: =SUMIF(PURCHASE!$E$3:$E$506,'INVONTERY FEB'!B75:B335,PURCHASE!$I$3:$I$506) -> 0 | I75: =ISSU!AL74 -> 0 | J75: =I75/29 -> 0 | K75: =E75+G75-I75 -> 0 | L75: =K75*M75 -> 0 | M75: 450 | N75: =M75-D75 -> 0 | O75: =N75*I75 -> 0 | P75: =F75+H75-L75 -> 0 | Q75: LOCAL | S75: 1 | V75: =+S75+T75+U75 -> 1
A76: 71 | B76: GOLDEN MOTI | C76: BOTT | D76: 450 | F76: =E76*D76 -> 0 | G76: =SUMIF(PURCHASE!$E$3:$E$506,'INVONTERY FEB'!B76:B341,PURCHASE!$H$3:$H$506) -> 0 | H76: =SUMIF(PURCHASE!$E$3:$E$506,'INVONTERY FEB'!B76:B336,PURCHASE!$I$3:$I$506) -> 0 | I76: =ISSU!AL75 -> 0 | J76: =I76/29 -> 0 | K76: =E76+G76-I76 -> 0 | L76: =K76*M76 -> 0 | M76: 450 | N76: =M76-D76 -> 0 | O76: =N76*I76 -> 0 | P76: =F76+H76-L76 -> 0 | Q76: VENUS | S76: 0 | V76: =+S76+T76+U76 -> 0
A77: 72 | B77: GOLDEN WORK | C77: PKT | D77: 3300 | F77: =E77*D77 -> 0 | G77: =SUMIF(PURCHASE!$E$3:$E$506,'INVONTERY FEB'!B77:B342,PURCHASE!$H$3:$H$506) -> 0 | H77: =SUMIF(PURCHASE!$E$3:$E$506,'INVONTERY FEB'!B77:B337,PURCHASE!$I$3:$I$506) -> 0 | I77: =ISSU!AL76 -> 0 | J77: =I77/29 -> 0 | K77: =E77+G77-I77 -> 0 | L77: =K77*M77 -> 0 | M77: 3300 | N77: =M77-D77 -> 0 | O77: =N77*I77 -> 0 | P77: =F77+H77-L77 -> 0 | Q77: LOCAL | S77: 0 | V77: =+S77+T77+U77 -> 0
A78: 73 | B78: SILVER WORK | C78: PKT | D78: 150 | F78: =E78*D78 -> 0 | G78: =SUMIF(PURCHASE!$E$3:$E$506,'INVONTERY FEB'!B78:B346,PURCHASE!$H$3:$H$506) -> 0 | H78: =SUMIF(PURCHASE!$E$3:$E$506,'INVONTERY FEB'!B78:B341,PURCHASE!$I$3:$I$506) -> 0 | I78: =ISSU!AL77 -> 0 | J78: =I78/29 -> 0 | K78: =E78+G78-I78 -> 0 | L78: =K78*M78 -> 0 | M78: 150 | N78: =M78-D78 -> 0 | O78: =N78*I78 -> 0 | P78: =F78+H78-L78 -> 0 | Q78: K'E'H | S78: 0 | V78: =+S78+T78+U78 -> 0
A79: 74 | B79: CHOCO LAVA BISCUIT | C79: BOX | D79: =3893/17 -> 229 | E79: 0 | F79: =E79*D79 -> 0 | G79: =SUMIF(PURCHASE!$E$3:$E$506,'INVONTERY FEB'!B79:B347,PURCHASE!$H$3:$H$506) -> 0 | H79: =SUMIF(PURCHASE!$E$3:$E$506,'INVONTERY FEB'!B79:B342,PURCHASE!$I$3:$I$506) -> 0 | I79: =ISSU!AL78 -> 0 | J79: =I79/29 -> 0 | K79: =E79+G79-I79 -> 0 | L79: =K79*M79 -> 0 | M79: 229 | N79: =M79-D79 -> 0 | O79: =N79*I79 -> 0 | P79: =F79+H79-L79 -> 0 | Q79: K'E'H | S79: =8*5 -> 40 | V79: =+S79+T79+U79 -> 40
A80: 75 | B80: OREO BISCUIT | C80: BOX | D80: =5320/19 -> 280 | E80: 0 | F80: =E80*D80 -> 0 | G80: =SUMIF(PURCHASE!$E$3:$E$506,'INVONTERY FEB'!B80:B348,PURCHASE!$H$3:$H$506) -> 0 | H80: =SUMIF(PURCHASE!$E$3:$E$506,'INVONTERY FEB'!B80:B343,PURCHASE!$I$3:$I$506) -> 0 | I80: =ISSU!AL79 -> 0 | J80: =I80/29 -> 0 | K80: =E80+G80-I80 -> 0 | L80: =K80*M80 -> 0 | M80: =5600/20 -> 280 | N80: =M80-D80 -> 0 | O80: =N80*I80 -> 0 | P80: =F80+H80-L80 -> 0 | Q80: K'E'H | S80: 1 | V80: =+S80+T80+U80 -> 1
A81: 76 | D81: 0 | E81: 0 | F81: =E81*D81 -> 0 | G81: =SUMIF(PURCHASE!$E$3:$E$506,'INVONTERY FEB'!B81:B349,PURCHASE!$H$3:$H$506) -> 0 | H81: =SUMIF(PURCHASE!$E$3:$E$506,'INVONTERY FEB'!B81:B344,PURCHASE!$I$3:$I$506) -> 0 | I81: =ISSU!AL80 -> 0 | J81: =I81/29 -> 0 | K81: =E81+G81-I81 -> 0 | L81: =K81*M81 -> 0 | M81: 0 | N81: =M81-D81 -> 0 | O81: =N81*I81 -> 0 | P81: =F81+H81-L81 -> 0 | S81: 1 | V81: =+S81+T81+U81 -> 1
A82: 77 | E82: 0 | F82: =E82*D82 -> 0 | G82: =SUMIF(PURCHASE!$E$3:$E$506,'INVONTERY FEB'!B82:B350,PURCHASE!$H$3:$H$506) -> 0 | H82: =SUMIF(PURCHASE!$E$3:$E$506,'INVONTERY FEB'!B82:B345,PURCHASE!$I$3:$I$506) -> 0 | I82: =ISSU!AL81 -> 0 | J82: =I82/29 -> 0 | K82: =E82+G82-I82 -> 0 | L82: =K82*M82 -> 0 | N82: =M82-D82 -> 0 | O82: =N82*I82 -> 0 | P82: =F82+H82-L82 -> 0 | S82: 0 | V82: =+S82+T82+U82 -> 0
A83: 78 | E83: 0 | F83: =E83*D83 -> 0 | G83: =SUMIF(PURCHASE!$E$3:$E$506,'INVONTERY FEB'!B83:B351,PURCHASE!$H$3:$H$506) -> 0 | H83: =SUMIF(PURCHASE!$E$3:$E$506,'INVONTERY FEB'!B83:B346,PURCHASE!$I$3:$I$506) -> 0 | I83: =ISSU!AL82 -> 0 | J83: =I83/29 -> 0 | K83: =E83+G83-I83 -> 0 | L83: =K83*M83 -> 0 | N83: =M83-D83 -> 0 | O83: =N83*I83 -> 0 | P83: =F83+H83-L83 -> 0 | S83: 0 | V83: =+S83+T83+U83 -> 0
A84: 79 | E84: 0 | F84: =E84*D84 -> 0 | G84: =SUMIF(PURCHASE!$E$3:$E$506,'INVONTERY FEB'!B84:B352,PURCHASE!$H$3:$H$506) -> 0 | H84: =SUMIF(PURCHASE!$E$3:$E$506,'INVONTERY FEB'!B84:B347,PURCHASE!$I$3:$I$506) -> 0 | I84: =ISSU!AL83 -> 0 | J84: =I84/29 -> 0 | K84: =E84+G84-I84 -> 0 | L84: =K84*M84 -> 0 | N84: =M84-D84 -> 0 | O84: =N84*I84 -> 0 | P84: =F84+H84-L84 -> 0 | V84: =+S84+T84+U84 -> 0
A85: 80 | E85: 0 | F85: =E85*D85 -> 0 | G85: =SUMIF(PURCHASE!$E$3:$E$506,'INVONTERY FEB'!B85:B353,PURCHASE!$H$3:$H$506) -> 0 | H85: =SUMIF(PURCHASE!$E$3:$E$506,'INVONTERY FEB'!B85:B348,PURCHASE!$I$3:$I$506) -> 0 | I85: =ISSU!AL84 -> 0 | J85: =I85/29 -> 0 | K85: =E85+G85-I85 -> 0 | L85: =K85*M85 -> 0 | N85: =M85-D85 -> 0 | O85: =N85*I85 -> 0 | P85: =F85+H85-L85 -> 0 | V85: =+S85+T85+U85 -> 0
A86: 81 | B86: TOTAL CAKE TOPPING AMOUNT | E86: =SUM(E52:E80) -> 77 | F86: =SUM(F52:F85) -> 153100 | G86: =SUM(G52:G85) -> 213 | H86: =SUM(H52:H85) -> 349850 | I86: =SUM(I52:I85) -> 65 | K86: =SUM(K52:K85) -> 225 | L86: =SUM(L52:L85) -> 334113 | N86: =SUM(N52:N85) -> 0 | O86: =SUM(O52:O85) -> 0 | P86: =SUM(P52:P85) -> 168837 | V86: =+S86+T86+U86 -> 0
A87: 82 | B87: FOUNDANT CAKE | V87: =+S87+T87+U87 -> 0
A88: 83 | B88: RED SPONCH FOOD COLOUR 400GMS | C88: BOTT | D88: 650 | E88: 1 | F88: =E88*D88 -> 650 | G88: =SUMIF(PURCHASE!$E$3:$E$506,'INVONTERY FEB'!B88:B352,PURCHASE!$H$3:$H$506) -> 2 | H88: =SUMIF(PURCHASE!$E$3:$E$506,'INVONTERY FEB'!B88:B347,PURCHASE!$I$3:$I$506) -> 1300 | I88: =ISSU!AL89 -> 0 | J88: =I88/29 -> 0 | K88: =E88+G88-I88 -> 3 | L88: =K88*M88 -> 1950 | M88: 650 | N88: =M88-D88 -> 0 | O88: =N88*I88 -> 0 | P88: =F88+H88-L88 -> 0 | Q88: LOCAL | S88: 2 | V88: =+S88+T88+U88 -> 2
A89: 84 | B89: ORANGE SPONCH FOOD COLOUR 400GMS | C89: BOTT | D89: 650 | E89: 2 | F89: =E89*D89 -> 1300 | G89: =SUMIF(PURCHASE!$E$3:$E$506,'INVONTERY FEB'!B89:B371,PURCHASE!$H$3:$H$506) -> 0 | H89: =SUMIF(PURCHASE!$E$3:$E$506,'INVONTERY FEB'!B89:B366,PURCHASE!$I$3:$I$506) -> 0 | I89: =ISSU!AL90 -> 0 | J89: =I89/29 -> 0 | K89: =E89+G89-I89 -> 2 | L89: =K89*M89 -> 1300 | M89: 650 | N89: =M89-D89 -> 0 | O89: =N89*I89 -> 0 | P89: =F89+H89-L89 -> 0 | Q89: LOCAL | S89: 3 | V89: =+S89+T89+U89 -> 3
A90: 85 | B90: VIBGYOR BASE FOUNDANT COLOURE | C90: BOTT | D90: =12308/10 -> 1230.8 | E90: 16 | F90: =E90*D90 -> 19692.8 | G90: =SUMIF(PURCHASE!$E$3:$E$506,'INVONTERY FEB'!B90:B353,PURCHASE!$H$3:$H$506) -> 9 | H90: =SUMIF(PURCHASE!$E$3:$E$506,'INVONTERY FEB'!B90:B348,PURCHASE!$I$3:$I$506) -> 11130 | I90: =ISSU!AL91 -> 14 | J90: =I90/29 -> 0.48275862 | K90: =E90+G90-I90 -> 11 | L90: =K90*M90 -> 13538.8 | M90: =D90 -> 1230.8 | N90: =M90-D90 -> 0 | O90: =N90*I90 -> 0 | P90: =F90+H90-L90 -> 17284 | Q90: LOCAL | S90: 0 | V90: =+S90+T90+U90 -> 0
A91: 86 | B91: ALMOND SYRUP | C91: BOTT | D91: 380 | E91: 4 | F91: =E91*D91 -> 1520 | G91: =SUMIF(PURCHASE!$E$3:$E$506,'INVONTERY FEB'!B91:B355,PURCHASE!$H$3:$H$506) -> 0 | H91: =SUMIF(PURCHASE!$E$3:$E$506,'INVONTERY FEB'!B91:B350,PURCHASE!$I$3:$I$506) -> 0 | I91: =ISSU!AL92 -> 2 | J91: =I91/29 -> 0.068965517 | K91: =E91+G91-I91 -> 2 | L91: =K91*M91 -> 760 | M91: 380 | N91: =M91-D91 -> 0 | O91: =N91*I91 -> 0 | P91: =F91+H91-L91 -> 760 | Q91: LOCAL | S91: 0 | V91: =+S91+T91+U91 -> 0
A92: 87 | B92: CARDMOM SYRUP | C92: BOTT | D92: 450 | E92: 3 | F92: =E92*D92 -> 1350 | G92: =SUMIF(PURCHASE!$E$3:$E$506,'INVONTERY FEB'!B92:B356,PURCHASE!$H$3:$H$506) -> 0 | H92: =SUMIF(PURCHASE!$E$3:$E$506,'INVONTERY FEB'!B92:B351,PURCHASE!$I$3:$I$506) -> 0 | I92: =ISSU!AL93 -> 3 | J92: =I92/29 -> 0.10344828 | K92: =E92+G92-I92 -> 0 | L92: =K92*M92 -> 0 | M92: 450 | N92: =M92-D92 -> 0 | O92: =N92*I92 -> 0 | P92: =F92+H92-L92 -> 1350 | Q92: LOCAL | S92: 0 | V92: =+S92+T92+U92 -> 0
A93: 88 | B93: VIZYON CHOCLATE SAYRUP | C93: BOTT | D93: 1300 | E93: 0 | F93: =E93*D93 -> 0 | G93: =SUMIF(PURCHASE!$E$3:$E$506,'INVONTERY FEB'!B93:B372,PURCHASE!$H$3:$H$506) -> 0 | H93: =SUMIF(PURCHASE!$E$3:$E$506,'INVONTERY FEB'!B93:B367,PURCHASE!$I$3:$I$506) -> 0 | I93: =ISSU!AL94 -> 0 | J93: =I93/29 -> 0 | K93: =E93+G93-I93 -> 0 | L93: =K93*M93 -> 0 | M93: =15600/12 -> 1300 | N93: =M93-D93 -> 0 | O93: =N93*I93 -> 0 | P93: =F93+H93-L93 -> 0 | Q93: LOCAL | S93: 0 | V93: =+S93+T93+U93 -> 0
A94: 89 | B94: VIZYON TOPPING CERAMAL | C94: BOTT | D94: 1267 | E94: 0 | F94: =E94*D94 -> 0 | G94: =SUMIF(PURCHASE!$E$3:$E$506,'INVONTERY FEB'!B94:B372,PURCHASE!$H$3:$H$506) -> 0 | H94: =SUMIF(PURCHASE!$E$3:$E$506,'INVONTERY FEB'!B94:B367,PURCHASE!$I$3:$I$506) -> 0 | I94: =ISSU!AL95 -> 0 | J94: =I94/29 -> 0 | K94: =E94+G94-I94 -> 0 | L94: =K94*M94 -> 0 | M94: 1267 | N94: =M94-D94 -> 0 | O94: =N94*I94 -> 0 | P94: =F94+H94-L94 -> 0 | Q94: LOCAL | S94: 0 | V94: =+S94+T94+U94 -> 0
A95: 90 | B95: FOUNDANT | C95: BOTT | D95: 1230 | E95: 0 | F95: =E95*D95 -> 0 | G95: =SUMIF(PURCHASE!$E$3:$E$506,'INVONTERY FEB'!B95:B373,PURCHASE!$H$3:$H$506) -> 0 | H95: =SUMIF(PURCHASE!$E$3:$E$506,'INVONTERY FEB'!B95:B368,PURCHASE!$I$3:$I$506) -> 0 | I95: =ISSU!AL96 -> 0 | J95: =I95/29 -> 0 | K95: =E95+G95-I95 -> 0 | L95: =K95*M95 -> 0 | M95: 1230 | N95: =M95-D95 -> 0 | O95: =N95*I95 -> 0 | P95: =F95+H95-L95 -> 0 | Q95: LOCAL | S95: 9 | V95: =+S95+T95+U95 -> 9
A96: 91 | B96: LEMON ESSENCE | C96: BOTT | D96: 820 | E96: 0 | F96: =E96*D96 -> 0 | G96: =SUMIF(PURCHASE!$E$3:$E$506,'INVONTERY FEB'!B96:B374,PURCHASE!$H$3:$H$506) -> 0 | H96: =SUMIF(PURCHASE!$E$3:$E$506,'INVONTERY FEB'!B96:B369,PURCHASE!$I$3:$I$506) -> 0 | I96: =ISSU!AL97 -> 0 | J96: =I96/29 -> 0 | K96: =E96+G96-I96 -> 0 | L96: =K96*M96 -> 0 | M96: 820 | N96: =M96-D96 -> 0 | O96: =N96*I96 -> 0 | P96: =F96+H96-L96 -> 0 | S96: 0 | V96: =+S96+T96+U96 -> 0
A97: 92 | B97: NESTLE COFFEE | C97: BOTT | D97: 1072 | E97: 0 | F97: =E97*D97 -> 0 | G97: =SUMIF(PURCHASE!$E$3:$E$506,'INVONTERY FEB'!B97:B375,PURCHASE!$H$3:$H$506) -> 0 | H97: =SUMIF(PURCHASE!$E$3:$E$506,'INVONTERY FEB'!B97:B370,PURCHASE!$I$3:$I$506) -> 0 | I97: =ISSU!AL98 -> 0 | J97: =I97/29 -> 0 | K97: =E97+G97-I97 -> 0 | L97: =K97*M97 -> 0 | M97: 1072 | N97: =M97-D97 -> 0 | O97: =N97*I97 -> 0 | P97: =F97+H97-L97 -> 0 | S97: 0 | V97: =+S97+T97+U97 -> 0
A98: 93 | B98: MITHA SODA | C98: KG | D98: 160 | E98: 0 | F98: =E98*D98 -> 0 | G98: =SUMIF(PURCHASE!$E$3:$E$506,'INVONTERY FEB'!B98:B376,PURCHASE!$H$3:$H$506) -> 0 | H98: =SUMIF(PURCHASE!$E$3:$E$506,'INVONTERY FEB'!B98:B371,PURCHASE!$I$3:$I$506) -> 0 | I98: =ISSU!AL99 -> 0 | J98: =I98/29 -> 0 | K98: =E98+G98-I98 -> 0 | L98: =K98*M98 -> 0 | M98: 160 | N98: =M98-D98 -> 0 | O98: =N98*I98 -> 0 | P98: =F98+H98-L98 -> 0 | S98: 0 | V98: =+S98+T98+U98 -> 0
A99: 94 | B99: BISCOTTO WAFER | C99: PCS | D99: 695 | E99: 0 | F99: =E99*D99 -> 0 | G99: =SUMIF(PURCHASE!$E$3:$E$506,'INVONTERY FEB'!B99:B376,PURCHASE!$H$3:$H$506) -> 0 | H99: =SUMIF(PURCHASE!$E$3:$E$506,'INVONTERY FEB'!B99:B374,PURCHASE!$I$3:$I$506) -> 0 | I99: =ISSU!AL100 -> 0 | J99: =I99/29 -> 0 | K99: =E99+G99-I99 -> 0 | L99: =K99*M99 -> 0 | M99: 695 | N99: =M99-D99 -> 0 | O99: =N99*I99 -> 0 | P99: =F99+H99-L99 -> 0 | Q99: NESTLE | S99: 0 | V99: =+S99+T99+U99 -> 0
A100: 95 | B100: GOLDEN EATABLE COLOUR | C100: BOTT | D100: 900 | E100: 0 | F100: =E100*D100 -> 0 | G100: =SUMIF(PURCHASE!$E$3:$E$506,'INVONTERY FEB'!B100:B377,PURCHASE!$H$3:$H$506) -> 0 | H100: =SUMIF(PURCHASE!$E$3:$E$506,'INVONTERY FEB'!B100:B375,PURCHASE!$I$3:$I$506) -> 0 | I100: =ISSU!AL101 -> 0 | J100: =I100/29 -> 0 | K100: =E100+G100-I100 -> 0 | L100: =K100*M100 -> 0 | M100: 900 | N100: =M100-D100 -> 0 | O100: =N100*I100 -> 0 | P100: =F100+H100-L100 -> 0 | S100: 0 | V100: =+S100+T100+U100 -> 0
A101: 96 | B101: SILVER EATABLE COLOURE | C101: BOTT | D101: 900 | E101: 0 | F101: =E101*D101 -> 0 | G101: =SUMIF(PURCHASE!$E$3:$E$506,'INVONTERY FEB'!B101:B378,PURCHASE!$H$3:$H$506) -> 1 | H101: =SUMIF(PURCHASE!$E$3:$E$506,'INVONTERY FEB'!B101:B376,PURCHASE!$I$3:$I$506) -> 1000 | I101: =ISSU!AL102 -> 0 | J101: =I101/29 -> 0 | K101: =E101+G101-I101 -> 1 | L101: =K101*M101 -> 900 | M101: 900 | N101: =M101-D101 -> 0 | O101: =N101*I101 -> 0 | P101: =F101+H101-L101 -> 100 | S101: 0 | V101: =+S101+T101+U101 -> 0
...

Sheet ISSU
A2: ='INVONTERY FEB'!A3 -> ID | B2: ='INVONTERY FEB'!B3 -> PRODUCT DETAIL | C2: ='INVONTERY FEB'!C3 -> UNIT | D2: ='INVONTERY FEB'!D3 -> RATE | E2: FSD FLOUR ISSU | F2: 46054 | G2: =1+F2 -> 46055 | H2: =1+G2 -> 46056 | I2: =1+H2 -> 46057 | J2: =1+I2 -> 46058 | K2: =1+J2 -> 46059 | L2: =1+K2 -> 46060 | M2: =1+L2 -> 46061 | N2: =1+M2 -> 46062 | ... AJ2: =1+AI2 -> 46084 | AK2: STOCK ON FLOUR | AL2: TOTAL | AM2: AVERAGE USAGE
A5: ='INVONTERY FEB'!A5 -> 1.1 | B5: ='INVONTERY FEB'!B5 -> SPONAGE | C5: ='INVONTERY FEB'!C5 | D5: ='INVONTERY FEB'!D5 | AL5: =SUM(E5:AK5) -> 0 | AM5: =AVERAGE(E5:AL5) -> 0
A6: ='INVONTERY FEB'!A6 -> 1 | B6: ='INVONTERY FEB'!B6 -> RED VELVET CONCENTRATE 10 KG | C6: ='INVONTERY FEB'!C6 -> KG | D6: ='INVONTERY FEB'!D6 | AL6: =SUM(E6:AK6) -> 0 | AM6: =AVERAGE(E6:AL6) -> 0
A7: ='INVONTERY FEB'!A7 -> 2 | B7: ='INVONTERY FEB'!B7 -> LA OLA CONCENTRATE | C7: ='INVONTERY FEB'!C7 -> KG | D7: ='INVONTERY FEB'!D7 | AL7: =SUM(E7:AK7) -> 0 | AM7: =AVERAGE(E7:AL7) -> 0
A8: ='INVONTERY FEB'!A8 -> 3 | B8: ='INVONTERY FEB'!B8 -> AUSTRIA SPONGE MIX CONCENTRATE (269) | C8: ='INVONTERY FEB'!C8 -> KG | D8: ='INVONTERY FEB'!D8 | AL8: =SUM(E8:AK8) -> 0 | AM8: =AVERAGE(E8:AL8) -> 0
A9: ='INVONTERY FEB'!A9 -> 4 | B9: ='INVONTERY FEB'!B9 -> KISAN CANOLA OIL 5 LTR | C9: ='INVONTERY FEB'!C9 -> BOX | D9: ='INVONTERY FEB'!D9 -> 560 | F9: 5 | I9: 2 | J9: 10 | K9: 15 | L9: 10 | N9: 10 | Q9: 5 | R9: 15 | S9: 10 | U9: 13 | V9: 10 | W9: 5 | X9: 5 | Y9: 10 | Z9: 5 | AB9: 10 | AD9: 10 | AE9: 5 | AF9: 5 | AG9: 10 | AL9: =SUM(E9:AK9) -> 170 | AM9: =AVERAGE(E9:AL9) -> 16.190476
A10: ='INVONTERY FEB'!A10 -> 5 | B10: ='INVONTERY FEB'!B10 -> FLOUR | C10: ='INVONTERY FEB'!C10 -> BAG | D10: ='INVONTERY FEB'!D10 -> 134 | F10: 50 | K10: 50 | Q10: 50 | U10: 50 | AF10: 50 | AL10: =SUM(E10:AK10) -> 250 | AM10: =AVERAGE(E10:AL10) -> 83.333333 | AO10: =9296-9325 -> -29
A11: ='INVONTERY FEB'!A11 -> 6 | B11: ='INVONTERY FEB'!B11 -> LOSSE SUGAR 50KG | C11: ='INVONTERY FEB'!C11 -> KG | D11: ='INVONTERY FEB'!D11 -> 184 | J11: 50 | N11: 50 | R11: 50 | V11: 50 | AE11: 50 | AF11: 50 | AL11: =SUM(E11:AK11) -> 300 | AM11: =AVERAGE(E11:AL11) -> 85.714286
A12: ='INVONTERY FEB'!A12 -> 7 | B12: ='INVONTERY FEB'!B12 -> EGGS | C12: ='INVONTERY FEB'!C12 -> PCS | D12: ='INVONTERY FEB'!D12 -> 31.66875 | F12: 200 | G12: 200 | H12: 0 | I12: 200 | J12: 370 | K12: 300 | L12: 200 | M12: 300 | N12: 270 | O12: 100 | P12: 200 | Q12: 200 | R12: 500 | S12: 470 | U12: 200 | V12: 300 | X12: 260 | Z12: 200 | AA12: 100 | AB12: 200 | AE12: 100 | AF12: 100 | AG12: 200 | AL12: =SUM(E12:AK12) -> 5170 | AM12: =AVERAGE(E12:AL12) -> 430.83333
A13: ='INVONTERY FEB'!A13 -> 8 | B13: ='INVONTERY FEB'!B13 -> POLAC CONDENSED MILK 1-LTR | C13: ='INVONTERY FEB'!C13 -> TIN | D13: ='INVONTERY FEB'!D13 -> 625 | F13: 4 | G13: 2 | H13: 2 | I13: 1 | L13: 3 | M13: 4 | N13: 4 | O13: 2 | P13: 3 | Q13: 3 | R13: 4 | S13: 5 | T13: 3 | U13: 3 | V13: 3 | AB13: 4 | AE13: 3 | AF13: 1 | AL13: =SUM(E13:AK13) -> 54 | AM13: =AVERAGE(E13:AL13) -> 5.6842105
A14: ='INVONTERY FEB'!A14 -> 9 | B14: ='INVONTERY FEB'!B14 -> OLPERS MILK 1.5 LTR | C14: ='INVONTERY FEB'!C14 -> PCS | D14: ='INVONTERY FEB'!D14 -> 488.1129 | F14: 8 | H14: 8 | I14: 8 | J14: 8 | K14: 16 | L14: 8 | N14: 8 | O14: 3 | Q14: 9 | R14: 16 | S14: 8 | U14: 8 | V14: 8 | W14: 8 | X14: 8 | Z14: 8 | AB14: 8 | AC14: 16 | AE14: 10 | AG14: 8 | AH14: 8 | AL14: =SUM(E14:AK14) -> 190 | AM14: =AVERAGE(E14:AL14) -> 17.272727
A15: ='INVONTERY FEB'!A15 -> 10 | B15: ='INVONTERY FEB'!B15 -> COCO POWDER MALASIAN | C15: ='INVONTERY FEB'!C15 -> KG | D15: ='INVONTERY FEB'!D15 -> 3917.0857 | F15: 2 | H15: 2 | I15: 2 | K15: 4 | L15: 2 | N15: 2 | O15: 2 | P15: 2 | Q15: 2 | R15: 3 | S15: 2 | U15: 2 | X15: 3 | AA15: 3 | AE15: 2 | AG15: 2 | AL15: =SUM(E15:AK15) -> 37 | AM15: =AVERAGE(E15:AL15) -> 4.3529412
A16: ='INVONTERY FEB'!A16 -> 11 | B16: ='INVONTERY FEB'!B16 -> VANILLA ESSENCE 500 GM | C16: ='INVONTERY FEB'!C16 -> BOTT | D16: ='INVONTERY FEB'!D16 -> 1150 | O16: 1 | V16: 1 | Y16: 1 | AE16: 2 | AL16: =SUM(E16:AK16) -> 5 | AM16: =AVERAGE(E16:AL16) -> 2
A17: ='INVONTERY FEB'!A17 -> 12 | B17: ='INVONTERY FEB'!B17 -> SALT 800GM | C17: ='INVONTERY FEB'!C17 -> PKT | D17: ='INVONTERY FEB'!D17 -> 29 | AL17: =SUM(E17:AK17) -> 0 | AM17: =AVERAGE(E17:AL17) -> 0
A18: ='INVONTERY FEB'!A18 -> 13 | B18: ='INVONTERY FEB'!B19 -> BAKING SODA 1- KG | C18: ='INVONTERY FEB'!C19 -> KG | D18: ='INVONTERY FEB'!D19 -> 160 | AL18: =SUM(E18:AK18) -> 0 | AM18: =AVERAGE(E18:AL18) -> 0
A19: ='INVONTERY FEB'!A19 -> 14 | B19: ='INVONTERY FEB'!B18 -> BAKING POWDER HOLIDAY | C19: ='INVONTERY FEB'!C18 -> KG | D19: ='INVONTERY FEB'!D18 -> 2000 | J19: 1 | Q19: 1 | Y19: 1 | AL19: =SUM(E19:AK19) -> 3 | AM19: =AVERAGE(E19:AL19) -> 1.5
A20: ='INVONTERY FEB'!A20 -> 15 | B20: ='INVONTERY FEB'!B20 -> STARCH | C20: ='INVONTERY FEB'!C20 -> KG | D20: ='INVONTERY FEB'!D20 -> 200 | AL20: =SUM(E20:AK20) -> 0 | AM20: =AVERAGE(E20:AL20) -> 0
A21: ='INVONTERY FEB'!A21 -> 16 | B21: ='INVONTERY FEB'!B21 -> KHOYA ESSANSE | C21: ='INVONTERY FEB'!C21 -> PCS | D21: ='INVONTERY FEB'!D21 | AL21: =SUM(E21:AK21) -> 0 | AM21: =AVERAGE(E21:AL21) -> 0
A22: ='INVONTERY FEB'!A22 -> 17 | B22: ='INVONTERY FEB'!B22 -> HABIB OIL 4.5 L BOT | C22: ='INVONTERY FEB'!C22 -> BOTT | D22: ='INVONTERY FEB'!D22 | AL22: =SUM(E22:AK22) -> 0 | AM22: =AVERAGE(E22:AL22) -> 0
A23: ='INVONTERY FEB'!A23 -> 18 | B23: ='INVONTERY FEB'!B23 -> PUCK CHEESE | C23: ='INVONTERY FEB'!C23 -> JAR | D23: ='INVONTERY FEB'!D23 | AL23: =SUM(E23:AK23) -> 0 | AM23: =AVERAGE(E23:AL23) -> 0
A24: ='INVONTERY FEB'!A24 -> 19 | B24: ='INVONTERY FEB'!B24 -> GULCOSE LIQUID | C24: ='INVONTERY FEB'!C24 -> BOTT | D24: ='INVONTERY FEB'!D24 | AL24: =SUM(E24:AK24) -> 0 | AM24: =AVERAGE(E24:AL24) -> 0
A25: ='INVONTERY FEB'!A25 -> 20 | B25: ='INVONTERY FEB'!B25 -> POLAC MILK 390 GM | C25: ='INVONTERY FEB'!C25 -> TIN | D25: ='INVONTERY FEB'!D25 -> 0 | H25: 2 | L25: 10 | W25: 9 | X25: 2 | Y25: 10 | AA25: 3 | AG25: 6 | AL25: =SUM(E25:AK25) -> 42 | AM25: =AVERAGE(E25:AL25) -> 10.5
A26: ='INVONTERY FEB'!A26 -> 21 | B26: ='INVONTERY FEB'!B26 | C26: ='INVONTERY FEB'!C26 | D26: ='INVONTERY FEB'!D26 -> 0 | AL26: =SUM(E26:AK26) -> 0 | AM26: =AVERAGE(E26:AL26) -> 0
A27: ='INVONTERY FEB'!A27 -> 22 | B27: ='INVONTERY FEB'!B27 | C27: ='INVONTERY FEB'!C27 | D27: ='INVONTERY FEB'!D27 -> 0 | AL27: =SUM(E27:AK27) -> 0 | AM27: =AVERAGE(E27:AL27) -> 0
A28: ='INVONTERY FEB'!A28 -> 23 | B28: ='INVONTERY FEB'!B28 | C28: ='INVONTERY FEB'!C28 | D28: ='INVONTERY FEB'!D28 -> 0 | AL28: =SUM(E28:AK28) -> 0 | AM28: =AVERAGE(E28:AL28) -> 0
A29: ='INVONTERY FEB'!A29 -> 24 | B29: ='INVONTERY FEB'!B29 -> TOTA SPONAGE AMOUNT | C29: ='INVONTERY FEB'!C29 | D29: ='INVONTERY FEB'!D29 | AL29: =SUM(E29:AK29) -> 0 | AM29: =AVERAGE(E29:AL29) -> 0
A30: ='INVONTERY FEB'!A30 -> 25 | B30: ='INVONTERY FEB'!B30 -> CAKE CRÈME | C30: ='INVONTERY FEB'!C30 | D30: ='INVONTERY FEB'!D30 | AL30: =SUM(E30:AK30) -> 0 | AM30: =AVERAGE(E30:AL30) -> 0
A31: ='INVONTERY FEB'!A31 -> 26 | B31: ='INVONTERY FEB'!B31 -> CHOCO KNOC | C31: ='INVONTERY FEB'!C31 -> BUCKET | D31: ='INVONTERY FEB'!D31 -> 7800 | AL31: =SUM(E31:AK31) -> 0 | AM31: =AVERAGE(E31:AL31) -> 0
A32: ='INVONTERY FEB'!A32 -> 27 | B32: ='INVONTERY FEB'!B32 -> MILK PACK CREAM200ML | C32: ='INVONTERY FEB'!C32 -> PCS | D32: ='INVONTERY FEB'!D32 -> 211 | AL32: =SUM(E32:AK32) -> 0 | AM32: =AVERAGE(E32:AL32) -> 0
A33: ='INVONTERY FEB'!A33 -> 28 | B33: ='INVONTERY FEB'!B33 -> NESTLE BUTTER | C33: ='INVONTERY FEB'!C33 -> KG | D33: ='INVONTERY FEB'!D33 -> 1850 | M33: 10 | S33: 5 | AL33: =SUM(E33:AK33) -> 15 | AM33: =AVERAGE(E33:AL33) -> 10
A34: ='INVONTERY FEB'!A34 -> 29 | B34: ='INVONTERY FEB'!B34 -> WHIPPING CREAM | C34: ='INVONTERY FEB'!C34 -> PCS | D34: ='INVONTERY FEB'!D34 -> 700 | F34: 12 | G34: 9 | H34: 8 | I34: 10 | J34: 11 | K34: 11 | L34: 10 | M34: 13 | N34: 13 | O34: 13 | P34: 10 | Q34: 9 | R34: 15 | S34: 18 | T34: 12 | U34: 12 | V34: 14 | W34: 7 | X34: 10 | Y34: 10 | Z34: 0 | AA34: 10 | AB34: 6 | AE34: 13 | AF34: 6 | AG34: 7 | AL34: =SUM(E34:AK34) -> 269 | AM34: =AVERAGE(E34:AL34) -> 19.925926
A35: ='INVONTERY FEB'!A35 -> 30 | B35: ='INVONTERY FEB'!B35 -> ROXELLA CRUNCHY CREAM | C35: ='INVONTERY FEB'!C35 -> KG | D35: ='INVONTERY FEB'!D35 -> 4281 | F35: 1 | K35: 1 | N35: 1 | AL35: =SUM(E35:AK35) -> 3 | AM35: =AVERAGE(E35:AL35) -> 1.5
A36: ='INVONTERY FEB'!A36 -> 31 | B36: ='INVONTERY FEB'!B36 -> NURPUR BUTTER | C36: ='INVONTERY FEB'!C36 -> KG | D36: ='INVONTERY FEB'!D36 -> 1800 | F36: 10 | M36: 15 | O36: 0 | AL36: =SUM(E36:AK36) -> 25 | AM36: =AVERAGE(E36:AL36) -> 12.5
A37: ='INVONTERY FEB'!A37 -> 32 | B37: ='INVONTERY FEB'!B37 -> CHEESE CREAM | C37: ='INVONTERY FEB'!C37 -> LTR | D37: ='INVONTERY FEB'!D37 -> 2500 | J37: 1 | AL37: =SUM(E37:AK37) -> 1 | AM37: =AVERAGE(E37:AL37) -> 1
A38: ='INVONTERY FEB'!A38 -> 33 | B38: ='INVONTERY FEB'!B38 -> G.P ICING SUGAR | C38: ='INVONTERY FEB'!C38 -> PCS | D38: ='INVONTERY FEB'!D38 -> 155 | S38: 10 | W38: 10 | AC38: 10 | AG38: 2 | AL38: =SUM(E38:AK38) -> 32 | AM38: =AVERAGE(E38:AL38) -> 12.8
A39: ='INVONTERY FEB'!A39 -> 34 | B39: ='INVONTERY FEB'!B39 -> DARK CHOCLATE SLAB 2 KG | C39: ='INVONTERY FEB'!C39 -> PKT | D39: ='INVONTERY FEB'!D39 -> 1400 | F39: 3 | J39: 3 | K39: 4 | N39: 3 | O39: 3 | P39: 2 | R39: 3 | S39: 3 | U39: 3 | AA39: 3 | AF39: 3 | AL39: =SUM(E39:AK39) -> 33 | AM39: =AVERAGE(E39:AL39) -> 5.5
A40: ='INVONTERY FEB'!A40 -> 35 | B40: ='INVONTERY FEB'!B40 -> MILKI CHOCLATE SLAB 2 KG | C40: ='INVONTERY FEB'!C40 -> PKT | D40: ='INVONTERY FEB'!D40 -> 1600 | H40: 2 | K40: 2 | N40: 5 | P40: 5 | R40: 2 | S40: 2 | U40: 2 | Y40: 2 | AB40: 2 | AG40: 2 | AL40: =SUM(E40:AK40) -> 26 | AM40: =AVERAGE(E40:AL40) -> 4.7272727
A41: ='INVONTERY FEB'!A41 -> 36 | B41: ='INVONTERY FEB'!B41 -> HISS CHOCLATE 4 RINGS | C41: ='INVONTERY FEB'!C41 -> BOX | D41: ='INVONTERY FEB'!D41 -> 1500 | AL41: =SUM(E41:AK41) -> 0 | AM41: =AVERAGE(E41:AL41) -> 0
A42: ='INVONTERY FEB'!A42 -> 37 | B42: ='INVONTERY FEB'!B42 -> HISS CHOCLATE 2 RINGS | C42: ='INVONTERY FEB'!C42 -> BOX | D42: ='INVONTERY FEB'!D42 -> 667 | F42: 2 | I42: 1 | K42: 2 | N42: 2 | S42: 1 | V42: 1 | W42: 1 | AA42: 1 | AC42: 3 | AG42: 1 | AL42: =SUM(E42:AK42) -> 15 | AM42: =AVERAGE(E42:AL42) -> 2.7272727
A43: ='INVONTERY FEB'!A43 -> 38 | B43: ='INVONTERY FEB'!B43 -> DAIRY MILK | C43: ='INVONTERY FEB'!C43 -> BOX | D43: ='INVONTERY FEB'!D43 -> 433.30435 | H43: 3 | I43: 2 | K43: 3 | N43: 1 | P43: 1 | S43: 2 | V43: 3 | Z43: 3 | AE43: 3 | AG43: 2 | AL43: =SUM(E43:AK43) -> 23 | AM43: =AVERAGE(E43:AL43) -> 4.1818182
A44: ='INVONTERY FEB'!A44 -> 39 | B44: ='INVONTERY FEB'!B44 -> CORN FLOURE | C44: ='INVONTERY FEB'!C44 -> KG | D44: ='INVONTERY FEB'!D44 -> 232 | AL44: =SUM(E44:AK44) -> 0 | AM44: =AVERAGE(E44:AL44) -> 0
A45: ='INVONTERY FEB'!A45 -> 40 | B45: ='INVONTERY FEB'!B45 -> WHITE CHOCLATE SLAB 2 KG | C45: ='INVONTERY FEB'!C45 -> PKT | D45: ='INVONTERY FEB'!D45 -> 1600 | L45: 1 | T45: 1 | V45: 1 | AL45: =SUM(E45:AK45) -> 3 | AM45: =AVERAGE(E45:AL45) -> 1.5
A46: ='INVONTERY FEB'!A46 -> 41 | B46: ='INVONTERY FEB'!B46 -> LUEVEN CREAM | C46: ='INVONTERY FEB'!C46 -> KG | D46: ='INVONTERY FEB'!D46 -> 3300 | K46: 5 | AL46: =SUM(E46:AK46) -> 5 | AM46: =AVERAGE(E46:AL46) -> 5
A47: ='INVONTERY FEB'!A47 -> 42 | B47: ='INVONTERY FEB'!B47 -> PISTACHIO SAPREAD | C47: ='INVONTERY FEB'!C47 -> KG | D47: ='INVONTERY FEB'!D47 -> 5200 | I47: 3 | AL47: =SUM(E47:AK47) -> 3 | AM47: =AVERAGE(E47:AL47) -> 3
A48: ='INVONTERY FEB'!A48 -> 43 | B48: ='INVONTERY FEB'!B48 -> OLPERS CREAM 200 ML | C48: ='INVONTERY FEB'!C48 -> PCS | D48: ='INVONTERY FEB'!D48 -> 207.28197 | F48: 24 | H48: 24 | J48: 24 | K48: =24*3 -> 72 | M48: 48 | N48: 48 | O48: 24 | P48: 24 | S48: =24*3 -> 72 | U48: 48 | W48: 72 | Y48: 24 | AA48: 24 | AB48: 24 | AC48: 25 | AD48: 20 | AE48: 20 | AF48: 24 | AG48: 24 | AL48: =SUM(E48:AK48) -> 665 | AM48: =AVERAGE(E48:AL48) -> 66.5
A49: ='INVONTERY FEB'!A49 -> 44 | B49: ='INVONTERY FEB'!B49 -> SALBON CHOCLATE | C49: ='INVONTERY FEB'!C49 -> KG | D49: ='INVONTERY FEB'!D49 -> 0 | AL49: =SUM(E49:AK49) -> 0 | AM49: =AVERAGE(E49:AL49) -> 0
A50: ='INVONTERY FEB'!A50 -> 45 | B50: ='INVONTERY FEB'!B50 -> TOTAL CAKE CREME AMOUNT | C50: ='INVONTERY FEB'!C50 | D50: ='INVONTERY FEB'!D50 | AL50: =SUM(E50:AK50) -> 0 | AM50: =AVERAGE(E50:AL50) -> 0
A51: ='INVONTERY FEB'!A51 -> 46 | B51: ='INVONTERY FEB'!B51 -> CAKE TOPPINGS | C51: ='INVONTERY FEB'!C51 | D51: ='INVONTERY FEB'!D51 | AL51: =SUM(E51:AK51) -> 0 | AM51: =AVERAGE(E51:AL51) -> 0
A52: ='INVONTERY FEB'!A52 -> 47 | B52: ='INVONTERY FEB'!B52 -> LOTUS BISCOFF | C52: ='INVONTERY FEB'!C52 -> PKT | D52: ='INVONTERY FEB'!D52 -> 1100 | F52: 1 | G52: 2 | K52: 4 | N52: 2 | P52: 1 | R52: 1 | S52: 3 | V52: 1 | W52: 1 | AB52: 2 | AF52: 1 | AG52: 2 | AL52: =SUM(E52:AK52) -> 21 | AM52: =AVERAGE(E52:AL52) -> 3.2307692
A53: ='INVONTERY FEB'!A54 -> 49 | B53: ='INVONTERY FEB'!B54 -> RED CHERRIES | C53: ='INVONTERY FEB'!C54 -> CASE | D53: ='INVONTERY FEB'!D54 -> 6600 | AL53: =SUM(E53:AK53) -> 0 | AM53: =AVERAGE(E53:AL53) -> 0
A54: ='INVONTERY FEB'!A55 -> 50 | B54: ='INVONTERY FEB'!B55 -> ALMONDS | C54: ='INVONTERY FEB'!C55 -> KG | D54: ='INVONTERY FEB'!D55 -> 2600 | H54: 1 | I54: 1 | K54: 0.5 | S54: 1 | X54: 0.5 | AL54: =SUM(E54:AK54) -> 4 | AM54: =AVERAGE(E54:AL54) -> 1.3333333
A55: ='INVONTERY FEB'!A56 -> 51 | B55: ='INVONTERY FEB'!B56 -> CASHEW NUT | C55: ='INVONTERY FEB'!C56 -> KG | D55: ='INVONTERY FEB'!D56 -> 3300 | AL55: =SUM(E55:AK55) -> 0 | AM55: =AVERAGE(E55:AL55) -> 0
A56: ='INVONTERY FEB'!A57 -> 52 | B56: ='INVONTERY FEB'!B57 -> PISTACHIO | C56: ='INVONTERY FEB'!C57 -> KG | D56: ='INVONTERY FEB'!D57 -> 5113 | G56: 0.5 | K56: 0.5 | S56: 1 | AL56: =SUM(E56:AK56) -> 2 | AM56: =AVERAGE(E56:AL56) -> 1
A57: ='INVONTERY FEB'!A58 -> 53 | B57: ='INVONTERY FEB'!B58 -> PEANUTS | C57: ='INVONTERY FEB'!C58 -> KG | D57: ='INVONTERY FEB'!D58 -> 750 | AL57: =SUM(E57:AK57) -> 0 | AM57: =AVERAGE(E57:AL57) -> 0
A58: ='INVONTERY FEB'!A59 -> 54 | B58: ='INVONTERY FEB'!B59 -> CAKE SPRINKELS | C58: ='INVONTERY FEB'!C59 -> PCS | D58: ='INVONTERY FEB'!D59 -> 483 | AL58: =SUM(E58:AK58) -> 0 | AM58: =AVERAGE(E58:AL58) -> 0
A59: ='INVONTERY FEB'!A60 -> 55 | B59: ='INVONTERY FEB'!B60 -> COCONUT CRUMBULES | C59: ='INVONTERY FEB'!C60 -> KG | D59: ='INVONTERY FEB'!D60 -> 1000 | AL59: =SUM(E59:AK59) -> 0 | AM59: =AVERAGE(E59:AL59) -> 0
A60: ='INVONTERY FEB'!A61 -> 56 | B60: ='INVONTERY FEB'!B61 -> FERRY ROSE | C60: ='INVONTERY FEB'!C61 -> BOX | D60: ='INVONTERY FEB'!D61 -> 1000 | J60: 1 | K60: 1 | N60: 1 | P60: 1 | AL60: =SUM(E60:AK60) -> 4 | AM60: =AVERAGE(E60:AL60) -> 1.6
A61: ='INVONTERY FEB'!A62 -> 57 | B61: ='INVONTERY FEB'!B62 -> LOTO CRUMBEL (885) | C61: ='INVONTERY FEB'!C62 -> KG | D61: ='INVONTERY FEB'!D62 -> 3440 | AL61: =SUM(E61:AK61) -> 0 | AM61: =AVERAGE(E61:AL61) -> 0
A62: ='INVONTERY FEB'!A63 -> 58 | B62: ='INVONTERY FEB'!B63 -> CAREMAL SYRUP | C62: ='INVONTERY FEB'!C63 -> BOTT | D62: ='INVONTERY FEB'!D63 -> 1200 | AL62: =SUM(E62:AK62) -> 0 | AM62: =AVERAGE(E62:AL62) -> 0
A63: ='INVONTERY FEB'!A64 -> 59 | B63: ='INVONTERY FEB'!B64 -> DARK CHOCLATE CHIPS | C63: ='INVONTERY FEB'!C64 -> KG | D63: ='INVONTERY FEB'!D64 -> 525 | G63: 1 | K63: 1 | O63: 1 | S63: 1 | AL63: =SUM(E63:AK63) -> 4 | AM63: =AVERAGE(E63:AL63) -> 1.6
A64: ='INVONTERY FEB'!A65 -> 60 | B64: ='INVONTERY FEB'!B65 -> PICTURE CAKE | C64: ='INVONTERY FEB'!C65 -> PCS | D64: ='INVONTERY FEB'!D65 -> 180 | AL64: =SUM(E64:AK64) -> 0 | AM64: =AVERAGE(E64:AL64) -> 0
A65: ='INVONTERY FEB'!A66 -> 61 | B65: ='INVONTERY FEB'!B66 -> LOTO SPREAD 400G | C65: ='INVONTERY FEB'!C66 -> PCS | D65: ='INVONTERY FEB'!D66 -> 1750 | AB65: 2 | AE65: 2 | AF65: 1 | AG65: 1 | AL65: =SUM(E65:AK65) -> 6 | AM65: =AVERAGE(E65:AL65) -> 2.4
A66: ='INVONTERY FEB'!A67 -> 62 | B66: ='INVONTERY FEB'!B67 -> LOTO SPREAD | C66: ='INVONTERY FEB'!C67 -> KG | D66: ='INVONTERY FEB'!D67 -> 4375 | G66: 8 | L66: 8 | R66: 8 | AL66: =SUM(E66:AK66) -> 24 | AM66: =AVERAGE(E66:AL66) -> 12
A67: ='INVONTERY FEB'!A68 -> 63 | B67: ='INVONTERY FEB'!B68 -> SPARK CHOCLATE OLD | C67: ='INVONTERY FEB'!C68 -> CTN | D67: ='INVONTERY FEB'!D68 -> 3520 | AL67: =SUM(E67:AK67) -> 0 | AM67: =AVERAGE(E67:AL67) -> 0
A68: ='INVONTERY FEB'!A69 -> 64 | B68: ='INVONTERY FEB'!B69 -> MIX FRUIT GELL | C68: ='INVONTERY FEB'!C69 -> CASE | D68: ='INVONTERY FEB'!D69 -> 2000 | AL68: =SUM(E68:AK68) -> 0 | AM68: =AVERAGE(E68:AL68) -> 0
A69: ='INVONTERY FEB'!A70 -> 65 | B69: ='INVONTERY FEB'!B70 -> CHECKPEAS | C69: ='INVONTERY FEB'!C70 -> PKT | D69: ='INVONTERY FEB'!D70 -> 450 | AL69: =SUM(E69:AK69) -> 0 | AM69: =AVERAGE(E69:AL69) -> 0
A70: ='INVONTERY FEB'!A71 -> 66 | B70: ='INVONTERY FEB'!B71 -> GOLOKOZ | C70: ='INVONTERY FEB'!C71 -> PKT | D70: ='INVONTERY FEB'!D71 -> 220 | AL70: =SUM(E70:AK70) -> 0 | AM70: =AVERAGE(E70:AL70) -> 0
A71: ='INVONTERY FEB'!A72 -> 67 | B71: ='INVONTERY FEB'!B72 -> EDIBLE COLOUR | C71: ='INVONTERY FEB'!C72 -> BOTT | D71: ='INVONTERY FEB'!D72 -> 250 | AL71: =SUM(E71:AK71) -> 0 | AM71: =AVERAGE(E71:AL71) -> 0
A72: ='INVONTERY FEB'!A73 -> 68 | B72: ='INVONTERY FEB'!B73 -> PINE APPLE | C72: ='INVONTERY FEB'!C73 -> TIN | D72: ='INVONTERY FEB'!D73 -> 1366 | AL72: =SUM(E72:AK72) -> 0 | AM72: =AVERAGE(E72:AL72) -> 0
A73: ='INVONTERY FEB'!A74 -> 69 | B73: ='INVONTERY FEB'!B74 -> SPARK CHOCLATE NEW | C73: ='INVONTERY FEB'!C74 -> BOX | D73: ='INVONTERY FEB'!D74 -> 550 | AL73: =SUM(E73:AK73) -> 0 | AM73: =AVERAGE(E73:AL73) -> 0
A74: ='INVONTERY FEB'!A75 -> 70 | B74: ='INVONTERY FEB'!B75 -> SILVER MOTI | C74: ='INVONTERY FEB'!C75 -> BOTT | D74: ='INVONTERY FEB'!D75 -> 450 | AL74: =SUM(E74:AK74) -> 0 | AM74: =AVERAGE(E74:AL74) -> 0
A75: ='INVONTERY FEB'!A76 -> 71 | B75: ='INVONTERY FEB'!B76 -> GOLDEN MOTI | C75: ='INVONTERY FEB'!C76 -> BOTT | D75: ='INVONTERY FEB'!D76 -> 450 | AL75: =SUM(E75:AK75) -> 0 | AM75: =AVERAGE(E75:AL75) -> 0
A76: ='INVONTERY FEB'!A77 -> 72 | B76: ='INVONTERY FEB'!B77 -> GOLDEN WORK | C76: ='INVONTERY FEB'!C77 -> PKT | D76: ='INVONTERY FEB'!D77 -> 3300 | AL76: =SUM(E76:AK76) -> 0 | AM76: =AVERAGE(E76:AL76) -> 0
A77: ='INVONTERY FEB'!A78 -> 73 | B77: ='INVONTERY FEB'!B78 -> SILVER WORK | C77: ='INVONTERY FEB'!C78 -> PKT | D77: ='INVONTERY FEB'!D78 -> 150 | AL77: =SUM(E77:AK77) -> 0 | AM77: =AVERAGE(E77:AL77) -> 0
A78: ='INVONTERY FEB'!A79 -> 74 | B78: ='INVONTERY FEB'!B79 -> CHOCO LAVA BISCUIT | C78: ='INVONTERY FEB'!C79 -> BOX | D78: ='INVONTERY FEB'!D79 -> 229 | AL78: =SUM(E78:AK78) -> 0 | AM78: =AVERAGE(E78:AL78) -> 0
... A84: ='INVONTERY FEB'!A85 -> 80 | B84: ='INVONTERY FEB'!B85 | C84: ='INVONTERY FEB'!C85 | D84: ='INVONTERY FEB'!D85 | AL84: =SUM(E84:AK84) -> 0 | AM84: =AVERAGE(E84:AL84) -> 0
A85: ='INVONTERY FEB'!A86 -> 81 | B85: ='INVONTERY FEB'!B86 -> TOTAL CAKE TOPPING AMOUNT | C85: ='INVONTERY FEB'!C86 | D85: =#REF! -> #REF! | AL85: =SUM(E85:AK85) -> 0 | AM85: =AVERAGE(E85:AL85) -> 0
A86: ='INVONTERY FEB'!A87 -> 82 | B86: ='INVONTERY FEB'!B86 -> TOTAL CAKE TOPPING AMOUNT | C86: ='INVONTERY FEB'!C87 | D86: ='INVONTERY FEB'!D86 | AL86: =SUM(E86:AK86) -> 0 | AM86: =AVERAGE(E86:AL86) -> 0
A87: ='INVONTERY FEB'!A88 -> 83 | B87: ='INVONTERY FEB'!B87 -> FOUNDANT CAKE | C87: ='INVONTERY FEB'!C88 -> BOTT | D87: ='INVONTERY FEB'!D87 | AL87: =SUM(E87:AK87) -> 0 | AM87: =AVERAGE(E87:AL87) -> 0
A88: ='INVONTERY FEB'!A89 -> 84 | B88: ='INVONTERY FEB'!B87 -> FOUNDANT CAKE | C88: ='INVONTERY FEB'!C89 -> BOTT | D88: ='INVONTERY FEB'!D87 | AL88: =SUM(E88:AK88) -> 0 | AM88: =AVERAGE(E88:AL88) -> 0
A89: ='INVONTERY FEB'!A90 -> 85 | B89: ='INVONTERY FEB'!B88 -> RED SPONCH FOOD COLOUR 400GMS | C89: ='INVONTERY FEB'!C90 -> BOTT | D89: ='INVONTERY FEB'!D88 -> 650 | AL89: =SUM(E89:AK89) -> 0 | AM89: =AVERAGE(E89:AL89) -> 0
A90: ='INVONTERY FEB'!A91 -> 86 | B90: ='INVONTERY FEB'!B89 -> ORANGE SPONCH FOOD COLOUR 400GMS | C90: ='INVONTERY FEB'!C91 -> BOTT | D90: ='INVONTERY FEB'!D89 -> 650 | AL90: =SUM(E90:AK90) -> 0 | AM90: =AVERAGE(E90:AL90) -> 0
A91: ='INVONTERY FEB'!A90 -> 85 | B91: ='INVONTERY FEB'!B90 -> VIBGYOR BASE FOUNDANT COLOURE | C91: ='INVONTERY FEB'!C92 -> BOTT | D91: ='INVONTERY FEB'!D90 -> 1230.8 | I91: 5 | K91: 1 | L91: 1 | O91: 3 | S91: 2 | W91: 2 | AL91: =SUM(E91:AK91) -> 14 | AM91: =AVERAGE(E91:AL91) -> 4
A92: ='INVONTERY FEB'!A91 -> 86 | B92: ='INVONTERY FEB'!B91 -> ALMOND SYRUP | C92: ='INVONTERY FEB'!C93 -> BOTT | D92: ='INVONTERY FEB'!D91 -> 380 | K92: 1 | AE92: 1 | AL92: =SUM(E92:AK92) -> 2 | AM92: =AVERAGE(E92:AL92) -> 1.3333333
A93: ='INVONTERY FEB'!A92 -> 87 | B93: ='INVONTERY FEB'!B92 -> CARDMOM SYRUP | C93: ='INVONTERY FEB'!C94 -> BOTT | D93: ='INVONTERY FEB'!D92 -> 450 | G93: 1 | U93: 1 | AE93: 1 | AL93: =SUM(E93:AK93) -> 3 | AM93: =AVERAGE(E93:AL93) -> 1.5
A94: ='INVONTERY FEB'!A93 -> 88 | B94: ='INVONTERY FEB'!B93 -> VIZYON CHOCLATE SAYRUP | C94: ='INVONTERY FEB'!C95 -> BOTT | D94: ='INVONTERY FEB'!D93 -> 1300 | AL94: =SUM(E94:AK94) -> 0 | AM94: =AVERAGE(E94:AL94) -> 0
A95: ='INVONTERY FEB'!A94 -> 89 | B95: ='INVONTERY FEB'!B94 -> VIZYON TOPPING CERAMAL | C95: ='INVONTERY FEB'!C96 -> BOTT | D95: ='INVONTERY FEB'!D94 -> 1267 | AL95: =SUM(E95:AK95) -> 0 | AM95: =AVERAGE(E95:AL95) -> 0
A96: ='INVONTERY FEB'!A95 -> 90 | B96: ='INVONTERY FEB'!B95 -> FOUNDANT | C96: ='INVONTERY FEB'!C97 -> BOTT | D96: ='INVONTERY FEB'!D95 -> 1230 | AL96: =SUM(E96:AK96) -> 0 | AM96: =AVERAGE(E96:AL96) -> 0
A97: ='INVONTERY FEB'!A96 -> 91 | B97: ='INVONTERY FEB'!B96 -> LEMON ESSENCE | C97: ='INVONTERY FEB'!C98 -> KG | D97: ='INVONTERY FEB'!D96 -> 820 | AL97: =SUM(E97:AK97) -> 0 | AM97: =AVERAGE(E97:AL97) -> 0
A98: ='INVONTERY FEB'!A97 -> 92 | B98: ='INVONTERY FEB'!B97 -> NESTLE COFFEE | C98: ='INVONTERY FEB'!C99 -> PCS | D98: ='INVONTERY FEB'!D97 -> 1072 | AL98: =SUM(E98:AK98) -> 0 | AM98: =AVERAGE(E98:AL98) -> 0
A99: ='INVONTERY FEB'!A98 -> 93 | B99: ='INVONTERY FEB'!B98 -> MITHA SODA | C99: ='INVONTERY FEB'!C100 -> BOTT | D99: ='INVONTERY FEB'!D98 -> 160 | AL99: =SUM(E99:AK99) -> 0 | AM99: =AVERAGE(E99:AL99) -> 0
A100: ='INVONTERY FEB'!A99 -> 94 | B100: ='INVONTERY FEB'!B99 -> BISCOTTO WAFER | C100: ='INVONTERY FEB'!C101 -> BOTT | D100: ='INVONTERY FEB'!D99 -> 695 | AL100: =SUM(E100:AK100) -> 0 | AM100: =AVERAGE(E100:AL100) -> 0
A101: ='INVONTERY FEB'!A100 -> 95 | B101: ='INVONTERY FEB'!B100 -> GOLDEN EATABLE COLOUR | C101: ='INVONTERY FEB'!C102 -> PCS | D101: ='INVONTERY FEB'!D100 -> 900 | AL101: =SUM(E101:AK101) -> 0 | AM101: =AVERAGE(E101:AL101) -> 0
A102: ='INVONTERY FEB'!A101 -> 96 | B102: ='INVONTERY FEB'!B101 -> SILVER EATABLE COLOURE | C102: ='INVONTERY FEB'!C103 -> BOTT | D102: ='INVONTERY FEB'!D101 -> 900 | AL102: =SUM(E102:AK102) -> 0 | AM102: =AVERAGE(E102:AL102) -> 0
A103: ='INVONTERY FEB'!A102 -> 97 | B103: ='INVONTERY FEB'!B102 -> BUTTERFLY | C103: ='INVONTERY FEB'!C104 -> KG | D103: ='INVONTERY FEB'!D102 -> 30 | AL103: =SUM(E103:AK103) -> 0 | AM103: =AVERAGE(E103:AL103) -> 0
A104: ='INVONTERY FEB'!A103 -> 98 | B104: ='INVONTERY FEB'!B103 -> VIBGOR FOOD COLOUR | C104: ='INVONTERY FEB'!C105 -> KG | D104: ='INVONTERY FEB'!D103 -> 750 | S104: 1 | Y104: 3 | AL104: =SUM(E104:AK104) -> 4 | AM104: =AVERAGE(E104:AL104) -> 2.6666667
A105: ='INVONTERY FEB'!A104 -> 99 | B105: ='INVONTERY FEB'!B105 -> PEANUTS | C105: ='INVONTERY FEB'!C106 -> PCS | D105: ='INVONTERY FEB'!D105 -> 700 | AL105: =SUM(E105:AK105) -> 0 | AM105: =AVERAGE(E105:AL105) -> 0
A106: ='INVONTERY FEB'!A105 -> 100 | B106: ='INVONTERY FEB'!B104 -> WALNUT | C106: ='INVONTERY FEB'!C107 | D106: ='INVONTERY FEB'!D104 -> 2400 | AL106: =SUM(E106:AK106) -> 0 | AM106: =AVERAGE(E106:AL106) -> 0
A107: ='INVONTERY FEB'!A106 -> 101 | B107: ='INVONTERY FEB'!B106 -> SNICKERS | C107: ='INVONTERY FEB'!C108 | D107: ='INVONTERY FEB'!D106 -> 188 | AL107: =SUM(E107:AK107) -> 0 | AM107: =AVERAGE(E107:AL107) -> 0
A108: ='INVONTERY FEB'!A107 -> 102 | B108: ='INVONTERY FEB'!B108 -> TOTAL FOOD COST | C108: ='INVONTERY FEB'!C109 | D108: ='INVONTERY FEB'!D108 | AL108: =SUM(E108:AK108) -> 0 | AM108: =AVERAGE(E108:AL108) -> 0
...

Sheet DAILY UPDATE
B1: C-1 (KOHINOOR) | S1: C-2 (SUSAN ROAD) | AJ1: C-5 (GULBERG) | BB1: TOTAL | BW1: DAILY CASH RECIVED | BX1: HOLD CASH | BY1: PHYSICIAL CASH IN HAND
B2: C/C | D2: CAKES | G2: PAS | H2: LAV | I2: CUPCAKE | K2: SUN | L2: 3 MILK | M2: C.B | N2: BRO | O2: DIM | P2: TOTAL | Q2: CASH | R2: CASH | S2: C/C | U2: CAKES | X2: PAS | Y2: LAV | Z2: CUPCAKE | AB2: SUN | AC2: 3 MILK | AD2: C.B | AE2: BRO | AF2: DIMI | AG2: TOTAL | AH2: CASH | AI2: CASH | AJ2: C/C | AM2: CAKES | AP2: PAS | AQ2: LAV | AR2: CUPCAKE | AT2: SUN | AU2: 3 MILKI | AV2: C.B | AW2: BRO | AX2: DIME | AY2: TOTAL | AZ2: CASH | BA2: CASH | BB2: C/C | BD2: FSD CAKES | BG2: PAS | BH2: LAV | BI2: CUPCAKE | BK2: SUN | BL2: T.M.S | BM2: C.B | BN2: BRO | BO2: DIMI | BP2: DATE | BQ2: OPENING | BR2: DAILY | BS2: TOTAL | BT2: DAILY | BU2: CLOSING
A3: DATE | B3: QTY | C3: PND | D3: CT-1 | E3: CT-2 | F3: CT-3 | G3: 250 | H3: CAK | I3: REG | J3: CUS | P3: SALE | Q3: REC. | R3: BAL | S3: QTY | T3: PND | U3: CT-1 | V3: CT-2 | W3: CT-3 | X3: 250 | Y3: CAK | Z3: REG | AA3: CUS | AF3: DMI | AG3: SALE | AH3: REC. | AI3: BAL | AJ3: QTY | AK3: PND | AL3: C.2.P | AM3: CT-1 | AN3: CT-2 | AO3: CT-3 | AP3: 250 | AQ3: CAK | AR3: REG | AS3: CUS | AY3: SALE | AZ3: REC. | BA3: BAL | BB3: QTY | BC3: PND | BD3: CT-1 | BE3: CT-2 | BF3: CT-3 | BG3: 225 | BH3: CAK | BI3: REG | BJ3: CUS | BQ3: BAL | BR3: SALE | BT3: EXPENSE | BU3: BAL | CA3: =NOW() -> 46167.182
B4: 1100 | D4: 1499 | E4: 1699 | F4: 1899 | G4: 250 | H4: 275 | I4: 220 | J4: 320 | K4: 220 | L4: 450 | M4: 120 | N4: 275 | O4: 1000 | S4: 1100 | U4: 1499 | V4: 1699 | W4: 1899 | X4: 250 | Y4: 275 | Z4: 220 | AA4: 320 | AB4: 220 | AC4: 450 | AD4: 120 | AE4: 275 | AF4: 1000 | AJ4: 1100 | AL4: 2399 | AM4: 1499 | AN4: 1699 | AO4: 1899 | AP4: 250 | AQ4: 275 | AR4: 220 | AS4: 320 | AT4: 220 | AU4: 450 | AV4: 120 | AW4: 275 | AX4: 1000 | CA4: BAKERY SAFE DETAIL
A5: 46054 | B5: 1 | C5: 3 | D5: 5 | E5: 4 | F5: =14+7 -> 21 | H5: 5 | K5: 6 | L5: 10 | M5: 10 | P5: =C5*$B$4+D5*$D$4+E5*$E$4+F5*$F$4+G5*$G$4+H5*$H$4+I5*$I$4+J5*$J$4+K5*$K$4+L5*$L$4+M5*$M$4+N5*$N$4+O5*$O$4 -> 65865 | Q5: 65865 | R5: =+R4+P5-Q5 -> 0 | S5: 2 | T5: 30 | U5: 3 | V5: 1 | W5: 6 | Y5: 1 | Z5: 6 | AB5: 5 | AC5: 5 | AD5: 5 | AG5: =T5*$B$4+U5*$D$4+V5*$E$4+W5*$F$4+X5*$G$4+Y5*$H$4+Z5*$I$4+AA5*$J$4+AB5*$K$4+AC5*$L$4+AD5*$M$4+AE5*$N$4+AF5*$O$4 -> 56135 | AH5: 56135 | AI5: =+AI4+AG5-AH5 -> 0 | AJ5: 2 | AK5: 11 | AM5: 3 | AN5: 1 | AO5: 7 | AQ5: 3 | AT5: 10 | AU5: 10 | AV5: 5 | AY5: =AK5*$AJ$4+AM5*$AM$4+AN5*$AN$4+AO5*$AO$4+AP5*$AP$4+AQ5*$AQ$4+AR5*$AR$4+AS5*$AS$4+AT5*$AT$4+AU5*$AU$4+AV5*$AV$4+AW5*$AW$4+AX5*$AX$4+$AL$4*AL5 -> 39714 | AZ5: 39714 | BA5: =+BA4+AY5-AZ5 -> 0 | BB5: =B5+S5+AJ5 -> 5 | BC5: =C5+T5+AK5 -> 44 | BD5: =D5+U5+AM5 -> 11 | BE5: =E5+V5+AN5 -> 6 | BF5: =F5+W5+AO5 -> 34 | BG5: =G5+X5+AP5 -> 0 | BH5: =H5+Y5+AQ5 -> 9 | BI5: =I5+Z5+AR5 -> 6 | BJ5: =J5+AA5+AS5 -> 0 | BK5: =K5+AB5+AT5 -> 21 | ... BO5: =O5+AF5+AX5 -> 0 | BP5: =A5 -> 46054 | BQ5: 420 | BR5: =AY5+AG5+P5 -> 161714 | BS5: =BR5+BQ5 -> 162134 | BT5: 0 | BU5: =BS5-BT5 -> 162134 | BW5: =Q5+AH5+AZ5 -> 161714 | BX5: =R5+AI5+BA5 -> 0 | BY5: =+BU5-BX5 -> 162134 | CA5: 5000 | CC5: =+CB5*CA5 -> 0
A6: =1+A5 -> 46055 | D6: 1 | E6: 1 | F6: 9 | K6: 5 | L6: 10 | P6: =C6*$B$4+D6*$D$4+E6*$E$4+F6*$F$4+G6*$G$4+H6*$H$4+I6*$I$4+J6*$J$4+K6*$K$4+L6*$L$4+M6*$M$4+N6*$N$4+O6*$O$4 -> 25889 | R6: =+R5+P6-Q6 -> 25889 | U6: 1 | V6: 1 | W6: 3 | Y6: 1 | AC6: 5 | AD6: 15 | AG6: =T6*$B$4+U6*$D$4+V6*$E$4+W6*$F$4+X6*$G$4+Y6*$H$4+Z6*$I$4+AA6*$J$4+AB6*$K$4+AC6*$L$4+AD6*$M$4+AE6*$N$4+AF6*$O$4 -> 13220 | AH6: 13220 | AI6: =+AI5+AG6-AH6 -> 0 | AJ6: 2 | AK6: 7 | AM6: 3 | AN6: 1 | AO6: 10 | AQ6: 3 | AT6: 5 | AU6: 10 | AW6: 20 | AY6: =AK6*$AJ$4+AM6*$AM$4+AN6*$AN$4+AO6*$AO$4+AP6*$AP$4+AQ6*$AQ$4+AR6*$AR$4+AS6*$AS$4+AT6*$AT$4+AU6*$AU$4+AV6*$AV$4+AW6*$AW$4+AX6*$AX$4+$AL$4*AL6 -> 44811 | AZ6: 44811 | BA6: =+BA5+AY6-AZ6 -> 0 | BB6: =B6+S6+AJ6 -> 2 | BC6: =C6+T6+AK6 -> 7 | BD6: =D6+U6+AM6 -> 5 | BE6: =E6+V6+AN6 -> 3 | BF6: =F6+W6+AO6 -> 22 | BG6: =G6+X6+AP6 -> 0 | BH6: =H6+Y6+AQ6 -> 4 | BI6: =I6+Z6+AR6 -> 0 | BJ6: =J6+AA6+AS6 -> 0 | BK6: =K6+AB6+AT6 -> 10 | ... BO6: =O6+AF6+AX6 -> 0 | BP6: =A6 -> 46055 | BQ6: =BU5 -> 162134 | BR6: =AY6+AG6+P6 -> 83920 | BS6: =BR6+BQ6 -> 246054 | BT6: 0 | BU6: =BS6-BT6 -> 246054 | BW6: =Q6+AH6+AZ6 -> 58031 | BX6: =R6+AI6+BA6 -> 25889 | BY6: =+BU6-BX6 -> 220165 | CA6: 1000 | CC6: =+CB6*CA6 -> 0
A7: =1+A6 -> 46056 | B7: 1 | C7: 5 | D7: 5 | E7: 3 | F7: 14 | I7: 3 | K7: 5 | L7: 10 | M7: 5 | N7: 20 | P7: =C7*$B$4+D7*$D$4+E7*$E$4+F7*$F$4+G7*$G$4+H7*$H$4+I7*$I$4+J7*$J$4+K7*$K$4+L7*$L$4+M7*$M$4+N7*$N$4+O7*$O$4 -> 57038 | R7: =+R6+P7-Q7 -> 82927 | U7: 2 | W7: 6 | Y7: 5 | Z7: 6 | AB7: 6 | AC7: 3 | AG7: =T7*$B$4+U7*$D$4+V7*$E$4+W7*$F$4+X7*$G$4+Y7*$H$4+Z7*$I$4+AA7*$J$4+AB7*$K$4+AC7*$L$4+AD7*$M$4+AE7*$N$4+AF7*$O$4 -> 19757 | AH7: 19757 | AI7: =+AI6+AG7-AH7 -> 0 | AJ7: 1 | AK7: 3 | AM7: 1 | AN7: 2 | AO7: 7 | AU7: 5 | AV7: 5 | AY7: =AK7*$AJ$4+AM7*$AM$4+AN7*$AN$4+AO7*$AO$4+AP7*$AP$4+AQ7*$AQ$4+AR7*$AR$4+AS7*$AS$4+AT7*$AT$4+AU7*$AU$4+AV7*$AV$4+AW7*$AW$4+AX7*$AX$4+$AL$4*AL7 -> 24340 | AZ7: 24340 | BA7: =+BA6+AY7-AZ7 -> 0 | BB7: =B7+S7+AJ7 -> 2 | BC7: =C7+T7+AK7 -> 8 | BD7: =D7+U7+AM7 -> 8 | BE7: =E7+V7+AN7 -> 5 | BF7: =F7+W7+AO7 -> 27 | BG7: =G7+X7+AP7 -> 0 | BH7: =H7+Y7+AQ7 -> 5 | BI7: =I7+Z7+AR7 -> 9 | BJ7: =J7+AA7+AS7 -> 0 | BK7: =K7+AB7+AT7 -> 11 | ... BO7: =O7+AF7+AX7 -> 0 | BP7: =A7 -> 46056 | BQ7: =BU6 -> 246054 | BR7: =AY7+AG7+P7 -> 101135 | BS7: =BR7+BQ7 -> 347189 | BT7: 0 | BU7: =BS7-BT7 -> 347189 | BW7: =Q7+AH7+AZ7 -> 44097 | BX7: =R7+AI7+BA7 -> 82927 | BY7: =+BU7-BX7 -> 264262 | CA7: 500 | CC7: =+CB7*CA7 -> 0
A8: =1+A7 -> 46057 | D8: 4 | E8: 2 | F8: 14 | H8: 9 | K8: 3 | L8: 10 | M8: 9 | P8: =C8*$B$4+D8*$D$4+E8*$E$4+F8*$F$4+G8*$G$4+H8*$H$4+I8*$I$4+J8*$J$4+K8*$K$4+L8*$L$4+M8*$M$4+N8*$N$4+O8*$O$4 -> 44695 | Q8: 127622 | R8: =+R7+P8-Q8 -> 0 | S8: 1 | T8: 2 | U8: 1 | V8: 2 | W8: 5 | Y8: 2 | AC8: 4 | AG8: =T8*$B$4+U8*$D$4+V8*$E$4+W8*$F$4+X8*$G$4+Y8*$H$4+Z8*$I$4+AA8*$J$4+AB8*$K$4+AC8*$L$4+AD8*$M$4+AE8*$N$4+AF8*$O$4 -> 18942 | AI8: =+AI7+AG8-AH8 -> 18942 | AM8: 2 | AN8: 0 | AO8: 6 | AQ8: 7 | AR8: 5 | AS8: 0 | AT8: 4 | AU8: 10 | AV8: 5 | AW8: 20 | AY8: =AK8*$AJ$4+AM8*$AM$4+AN8*$AN$4+AO8*$AO$4+AP8*$AP$4+AQ8*$AQ$4+AR8*$AR$4+AS8*$AS$4+AT8*$AT$4+AU8*$AU$4+AV8*$AV$4+AW8*$AW$4+AX8*$AX$4+$AL$4*AL8 -> 28897 | AZ8: 28897 | BA8: =+BA7+AY8-AZ8 -> 0 | BB8: =B8+S8+AJ8 -> 1 | BC8: =C8+T8+AK8 -> 2 | BD8: =D8+U8+AM8 -> 7 | BE8: =E8+V8+AN8 -> 4 | BF8: =F8+W8+AO8 -> 25 | BG8: =G8+X8+AP8 -> 0 | BH8: =H8+Y8+AQ8 -> 18 | BI8: =I8+Z8+AR8 -> 5 | BJ8: =J8+AA8+AS8 -> 0 | BK8: =K8+AB8+AT8 -> 7 | ... BO8: =O8+AF8+AX8 -> 0 | BP8: =A8 -> 46057 | BQ8: =BU7 -> 347189 | BR8: =AY8+AG8+P8 -> 92534 | BS8: =BR8+BQ8 -> 439723 | BT8: 96875 | BU8: =BS8-BT8 -> 342848 | BW8: =Q8+AH8+AZ8 -> 156519 | BX8: =R8+AI8+BA8 -> 18942 | BY8: =+BU8-BX8 -> 323906 | CA8: 100 | CC8: =+CB8*CA8 -> 0
A9: =1+A8 -> 46058 | D9: 4 | E9: 3 | F9: 18 | H9: 10 | K9: 5 | L9: 10 | M9: 9 | N9: 19 | P9: =C9*$B$4+D9*$D$4+E9*$E$4+F9*$F$4+G9*$G$4+H9*$H$4+I9*$I$4+J9*$J$4+K9*$K$4+L9*$L$4+M9*$M$4+N9*$N$4+O9*$O$4 -> 59930 | R9: =+R8+P9-Q9 -> 59930 | U9: 2 | W9: 5 | Y9: 1 | AB9: 6 | AC9: 5 | AD9: 10 | AG9: =T9*$B$4+U9*$D$4+V9*$E$4+W9*$F$4+X9*$G$4+Y9*$H$4+Z9*$I$4+AA9*$J$4+AB9*$K$4+AC9*$L$4+AD9*$M$4+AE9*$N$4+AF9*$O$4 -> 17538 | AH9: 36480 | AI9: =+AI8+AG9-AH9 -> 0 | AJ9: 1 | AK9: 5 | AM9: 3 | AN9: 2 | AO9: 14 | AQ9: 4 | AT9: 11 | AU9: 7 | AV9: 10 | AY9: =AK9*$AJ$4+AM9*$AM$4+AN9*$AN$4+AO9*$AO$4+AP9*$AP$4+AQ9*$AQ$4+AR9*$AR$4+AS9*$AS$4+AT9*$AT$4+AU9*$AU$4+AV9*$AV$4+AW9*$AW$4+AX9*$AX$4+$AL$4*AL9 -> 47851 | AZ9: 47851 | BA9: =+BA8+AY9-AZ9 -> 0 | BB9: =B9+S9+AJ9 -> 1 | BC9: =C9+T9+AK9 -> 5 | BD9: =D9+U9+AM9 -> 9 | BE9: =E9+V9+AN9 -> 5 | BF9: =F9+W9+AO9 -> 37 | BG9: =G9+X9+AP9 -> 0 | BH9: =H9+Y9+AQ9 -> 15 | BI9: =I9+Z9+AR9 -> 0 | BJ9: =J9+AA9+AS9 -> 0 | BK9: =K9+AB9+AT9 -> 22 | ... BO9: =O9+AF9+AX9 -> 0 | BP9: =A9 -> 46058 | BQ9: =BU8 -> 342848 | BR9: =AY9+AG9+P9 -> 125319 | BS9: =BR9+BQ9 -> 468167 | BT9: 0 | BU9: =BS9-BT9 -> 468167 | BW9: =Q9+AH9+AZ9 -> 84331 | BX9: =R9+AI9+BA9 -> 59930 | BY9: =+BU9-BX9 -> 408237 | CA9: 50 | CC9: =+CB9*CA9 -> 0
A10: =1+A9 -> 46059 | B10: 2 | C10: 9 | D10: 4 | E10: 4 | F10: 25 | H10: 10 | I10: 3 | K10: 5 | L10: 15 | M10: 10 | N10: 20 | P10: =C10*$B$4+D10*$D$4+E10*$E$4+F10*$F$4+G10*$G$4+H10*$H$4+I10*$I$4+J10*$J$4+K10*$K$4+L10*$L$4+M10*$M$4+N10*$N$4+O10*$O$4 -> 88127 | R10: =+R9+P10-Q10 -> 148057 | U10: 2 | V10: 1 | W10: 6 | Z10: 4 | AC10: 5 | AD10: 7 | AG10: =T10*$B$4+U10*$D$4+V10*$E$4+W10*$F$4+X10*$G$4+Y10*$H$4+Z10*$I$4+AA10*$J$4+AB10*$K$4+AC10*$L$4+AD10*$M$4+AE10*$N$4+AF10*$O$4 -> 20061 | AH10: 20061 | AI10: =+AI9+AG10-AH10 -> 0 | AJ10: 2 | AK10: 9 | AM10: 4 | AN10: 3 | AO10: 15 | AT10: 7 | AU10: 10 | AV10: 10 | AY10: =AK10*$AJ$4+AM10*$AM$4+AN10*$AN$4+AO10*$AO$4+AP10*$AP$4+AQ10*$AQ$4+AR10*$AR$4+AS10*$AS$4+AT10*$AT$4+AU10*$AU$4+AV10*$AV$4+AW10*$AW$4+AX10*$AX$4+$AL$4*AL10 -> 56718 | AZ10: 56718 | BA10: =+BA9+AY10-AZ10 -> 0 | BB10: =B10+S10+AJ10 -> 4 | BC10: =C10+T10+AK10 -> 18 | BD10: =D10+U10+AM10 -> 10 | BE10: =E10+V10+AN10 -> 8 | BF10: =F10+W10+AO10 -> 46 | BG10: =G10+X10+AP10 -> 0 | BH10: =H10+Y10+AQ10 -> 10 | BI10: =I10+Z10+AR10 -> 7 | BJ10: =J10+AA10+AS10 -> 0 | BK10: =K10+AB10+AT10 -> 12 | ... BO10: =O10+AF10+AX10 -> 0 | BP10: =A10 -> 46059 | BQ10: =BU9 -> 468167 | BR10: =AY10+AG10+P10 -> 164906 | BS10: =BR10+BQ10 -> 633073 | BT10: 0 | BU10: =BS10-BT10 -> 633073 | BW10: =Q10+AH10+AZ10 -> 76779 | BX10: =R10+AI10+BA10 -> 148057 | BY10: =+BU10-BX10 -> 485016 | CA10: 20 | CC10: =+CB10*CA10 -> 0
A11: =1+A10 -> 46060 | B11: 1 | C11: 15 | D11: 4 | E11: 2 | F11: 11 | K11: 5 | L11: 15 | M11: 10 | P11: =C11*$B$4+D11*$D$4+E11*$E$4+F11*$F$4+G11*$G$4+H11*$H$4+I11*$I$4+J11*$J$4+K11*$K$4+L11*$L$4+M11*$M$4+N11*$N$4+O11*$O$4 -> 55833 | Q11: 203890 | R11: =+R10+P11-Q11 -> 0 | U11: 1 | V11: 1 | W11: 6 | Y11: 2 | Z11: 6 | AB11: 5 | AC11: 5 | AD11: 5 | AE11: 20 | AG11: =T11*$B$4+U11*$D$4+V11*$E$4+W11*$F$4+X11*$G$4+Y11*$H$4+Z11*$I$4+AA11*$J$4+AB11*$K$4+AC11*$L$4+AD11*$M$4+AE11*$N$4+AF11*$O$4 -> 25912 | AI11: =+AI10+AG11-AH11 -> 25912 | AJ11: 1 | AK11: 7 | AM11: 1 | AN11: 1 | AO11: 2 | AR11: 5 | AT11: 5 | AU11: 6 | AW11: 20 | AY11: =AK11*$AJ$4+AM11*$AM$4+AN11*$AN$4+AO11*$AO$4+AP11*$AP$4+AQ11*$AQ$4+AR11*$AR$4+AS11*$AS$4+AT11*$AT$4+AU11*$AU$4+AV11*$AV$4+AW11*$AW$4+AX11*$AX$4+$AL$4*AL11 -> 25096 | BA11: =+BA10+AY11-AZ11 -> 25096 | BB11: =B11+S11+AJ11 -> 2 | BC11: =C11+T11+AK11 -> 22 | BD11: =D11+U11+AM11 -> 6 | BE11: =E11+V11+AN11 -> 4 | BF11: =F11+W11+AO11 -> 19 | BG11: =G11+X11+AP11 -> 0 | BH11: =H11+Y11+AQ11 -> 2 | BI11: =I11+Z11+AR11 -> 11 | BJ11: =J11+AA11+AS11 -> 0 | BK11: =K11+AB11+AT11 -> 15 | ... BO11: =O11+AF11+AX11 -> 0 | BP11: =A11 -> 46060 | BQ11: =BU10 -> 633073 | BR11: =AY11+AG11+P11 -> 106841 | BS11: =BR11+BQ11 -> 739914 | BT11: 0 | BU11: =BS11-BT11 -> 739914 | BW11: =Q11+AH11+AZ11 -> 203890 | BX11: =R11+AI11+BA11 -> 51008 | BY11: =+BU11-BX11 -> 688906 | CA11: 10 | CC11: =+CB11*CA11 -> 0
A12: =1+A11 -> 46061 | D12: 1 | E12: 2 | F12: =8+6 -> 14 | I12: 5 | K12: 5 | L12: 10 | M12: 30 | N12: 20 | P12: =C12*$B$4+D12*$D$4+E12*$E$4+F12*$F$4+G12*$G$4+H12*$H$4+I12*$I$4+J12*$J$4+K12*$K$4+L12*$L$4+M12*$M$4+N12*$N$4+O12*$O$4 -> 47283 | R12: =+R11+P12-Q12 -> 47283 | S12: 1 | T12: 3 | U12: 2 | V12: 1 | W12: 9 | Y12: 3 | AB12: 4 | AC12: 5 | AD12: 10 | AG12: =T12*$B$4+U12*$D$4+V12*$E$4+W12*$F$4+X12*$G$4+Y12*$H$4+Z12*$I$4+AA12*$J$4+AB12*$K$4+AC12*$L$4+AD12*$M$4+AE12*$N$4+AF12*$O$4 -> 30243 | AH12: 56155 | AI12: =+AI11+AG12-AH12 -> 0 | AL12: 1 | AM12: 5 | AN12: 2 | AO12: =6+7 -> 13 | AQ12: 7 | AR12: 5 | AT12: 11 | AU12: 8 | AV12: 5 | AY12: =AK12*$AJ$4+AM12*$AM$4+AN12*$AN$4+AO12*$AO$4+AP12*$AP$4+AQ12*$AQ$4+AR12*$AR$4+AS12*$AS$4+AT12*$AT$4+AU12*$AU$4+AV12*$AV$4+AW12*$AW$4+AX12*$AX$4+$AL$4*AL12 -> 47624 | AZ12: 72720 | BA12: =+BA11+AY12-AZ12 -> 0 | BB12: =B12+S12+AJ12 -> 1 | BC12: =C12+T12+AK12 -> 3 | BD12: =D12+U12+AM12 -> 8 | BE12: =E12+V12+AN12 -> 5 | BF12: =F12+W12+AO12 -> 36 | BG12: =G12+X12+AP12 -> 0 | BH12: =H12+Y12+AQ12 -> 10 | BI12: =I12+Z12+AR12 -> 10 | BJ12: =J12+AA12+AS12 -> 0 | BK12: =K12+AB12+AT12 -> 20 | ... BO12: =O12+AF12+AX12 -> 0 | BP12: =A12 -> 46061 | BQ12: =BU11 -> 739914 | BR12: =AY12+AG12+P12 -> 125150 | BS12: =BR12+BQ12 -> 865064 | BT12: 509146 | BU12: =BS12-BT12 -> 355918 | BW12: =Q12+AH12+AZ12 -> 128875 | BX12: =R12+AI12+BA12 -> 47283 | BY12: =+BU12-BX12 -> 308635 | CA12: TOTAL | CC12: =SUM(CC5:CC11) -> 0
A13: =1+A12 -> 46062 | D13: 5 | E13: 2 | F13: 19 | H13: 10 | I13: 3 | K13: 5 | L13: 10 | M13: 20 | N13: 20 | P13: =C13*$B$4+D13*$D$4+E13*$E$4+F13*$F$4+G13*$G$4+H13*$H$4+I13*$I$4+J13*$J$4+K13*$K$4+L13*$L$4+M13*$M$4+N13*$N$4+O13*$O$4 -> 63884 | R13: =+R12+P13-Q13 -> 111167 | U13: 1 | V13: 1 | W13: 4 | Z13: 5 | AB13: 5 | AC13: 5 | AD13: 5 | AG13: =T13*$B$4+U13*$D$4+V13*$E$4+W13*$F$4+X13*$G$4+Y13*$H$4+Z13*$I$4+AA13*$J$4+AB13*$K$4+AC13*$L$4+AD13*$M$4+AE13*$N$4+AF13*$O$4 -> 15844 | AH13: 15844 | AI13: =+AI12+AG13-AH13 -> 0 | AJ13: 1 | AK13: 4 | AM13: 2 | AN13: 2 | AO13: 7 | AQ13: 4 | AV13: 5 | AY13: =AK13*$AJ$4+AM13*$AM$4+AN13*$AN$4+AO13*$AO$4+AP13*$AP$4+AQ13*$AQ$4+AR13*$AR$4+AS13*$AS$4+AT13*$AT$4+AU13*$AU$4+AV13*$AV$4+AW13*$AW$4+AX13*$AX$4+$AL$4*AL13 -> 25789 | AZ13: 25789 | BA13: =+BA12+AY13-AZ13 -> 0 | BB13: =B13+S13+AJ13 -> 1 | BC13: =C13+T13+AK13 -> 4 | BD13: =D13+U13+AM13 -> 8 | BE13: =E13+V13+AN13 -> 5 | BF13: =F13+W13+AO13 -> 30 | BG13: =G13+X13+AP13 -> 0 | BH13: =H13+Y13+AQ13 -> 14 | BI13: =I13+Z13+AR13 -> 8 | BJ13: =J13+AA13+AS13 -> 0 | BK13: =K13+AB13+AT13 -> 10 | ... BO13: =O13+AF13+AX13 -> 0 | BP13: =A13 -> 46062 | BQ13: =BU12 -> 355918 | BR13: =AY13+AG13+P13 -> 105517 | BS13: =BR13+BQ13 -> 461435 | BT13: 0 | BU13: =BS13-BT13 -> 461435 | BW13: =Q13+AH13+AZ13 -> 41633 | BX13: =R13+AI13+BA13 -> 111167 | BY13: =+BU13-BX13 -> 350268 | CA13: HOLD
A14: =1+A13 -> 46063 | D14: 4 | E14: 3 | F14: 15 | H14: 5 | K14: 5 | L14: 10 | M14: 15 | P14: =C14*$B$4+D14*$D$4+E14*$E$4+F14*$F$4+G14*$G$4+H14*$H$4+I14*$I$4+J14*$J$4+K14*$K$4+L14*$L$4+M14*$M$4+N14*$N$4+O14*$O$4 -> 48353 | Q14: 159520 | R14: =+R13+P14-Q14 -> 0 | U14: 2 | V14: 1 | W14: 5 | Y14: 2 | Z14: 3 | AB14: 5 | AC14: 5 | AD14: 10 | AG14: =T14*$B$4+U14*$D$4+V14*$E$4+W14*$F$4+X14*$G$4+Y14*$H$4+Z14*$I$4+AA14*$J$4+AB14*$K$4+AC14*$L$4+AD14*$M$4+AE14*$N$4+AF14*$O$4 -> 19952 | AH14: 19952 | AI14: =+AI13+AG14-AH14 -> 0 | AM14: 4 | AN14: 1 | AO14: 8 | AT14: 11 | AU14: 10 | AW14: 20 | AY14: =AK14*$AJ$4+AM14*$AM$4+AN14*$AN$4+AO14*$AO$4+AP14*$AP$4+AQ14*$AQ$4+AR14*$AR$4+AS14*$AS$4+AT14*$AT$4+AU14*$AU$4+AV14*$AV$4+AW14*$AW$4+AX14*$AX$4+$AL$4*AL14 -> 35307 | AZ14: 35307 | BA14: =+BA13+AY14-AZ14 -> 0 | BB14: =B14+S14+AJ14 -> 0 | BC14: =C14+T14+AK14 -> 0 | BD14: =D14+U14+AM14 -> 10 | BE14: =E14+V14+AN14 -> 5 | BF14: =F14+W14+AO14 -> 28 | BG14: =G14+X14+AP14 -> 0 | BH14: =H14+Y14+AQ14 -> 7 | BI14: =I14+Z14+AR14 -> 3 | BJ14: =J14+AA14+AS14 -> 0 | BK14: =K14+AB14+AT14 -> 21 | ... BO14: =O14+AF14+AX14 -> 0 | BP14: =A14 -> 46063 | BQ14: =BU13 -> 461435 | BR14: =AY14+AG14+P14 -> 103612 | BS14: =BR14+BQ14 -> 565047 | BT14: 56630 | BU14: =BS14-BT14 -> 508417 | BW14: =Q14+AH14+AZ14 -> 214779 | BX14: =R14+AI14+BA14 -> 0 | BY14: =+BU14-BX14 -> 508417 | CA14: PHYSICIAL CASH IN HAND | CC14: =SUM(CC12:CC13) -> 0
A15: =1+A14 -> 46064 | D15: 4 | E15: 3 | F15: 16 | I15: 4 | K15: 5 | L15: 10 | M15: 15 | N15: 20 | P15: =C15*$B$4+D15*$D$4+E15*$E$4+F15*$F$4+G15*$G$4+H15*$H$4+I15*$I$4+J15*$J$4+K15*$K$4+L15*$L$4+M15*$M$4+N15*$N$4+O15*$O$4 -> 55257 | R15: =+R14+P15-Q15 -> 55257 | S15: 1 | T15: 3 | U15: 2 | V15: 2 | W15: 8 | Z15: 5 | AB15: 5 | AC15: 5 | AD15: 5 | AE15: 20 | AG15: =T15*$B$4+U15*$D$4+V15*$E$4+W15*$F$4+X15*$G$4+Y15*$H$4+Z15*$I$4+AA15*$J$4+AB15*$K$4+AC15*$L$4+AD15*$M$4+AE15*$N$4+AF15*$O$4 -> 35438 | AH15: 35438 | AI15: =+AI14+AG15-AH15 -> 0 | AO15: 6 | AU15: 6 | AW15: 20 | AY15: =AK15*$AJ$4+AM15*$AM$4+AN15*$AN$4+AO15*$AO$4+AP15*$AP$4+AQ15*$AQ$4+AR15*$AR$4+AS15*$AS$4+AT15*$AT$4+AU15*$AU$4+AV15*$AV$4+AW15*$AW$4+AX15*$AX$4+$AL$4*AL15 -> 19594 | AZ15: 19594 | BA15: =+BA14+AY15-AZ15 -> 0 | BB15: =B15+S15+AJ15 -> 1 | BC15: =C15+T15+AK15 -> 3 | BD15: =D15+U15+AM15 -> 6 | BE15: =E15+V15+AN15 -> 5 | BF15: =F15+W15+AO15 -> 30 | BG15: =G15+X15+AP15 -> 0 | BH15: =H15+Y15+AQ15 -> 0 | BI15: =I15+Z15+AR15 -> 9 | BJ15: =J15+AA15+AS15 -> 0 | BK15: =K15+AB15+AT15 -> 10 | ... BO15: =O15+AF15+AX15 -> 0 | BP15: =A15 -> 46064 | BQ15: =BU14 -> 508417 | BR15: =AY15+AG15+P15 -> 110289 | BS15: =BR15+BQ15 -> 618706 | BT15: 383875 | BU15: =BS15-BT15 -> 234831 | BW15: =Q15+AH15+AZ15 -> 55032 | BX15: =R15+AI15+BA15 -> 55257 | BY15: =+BU15-BX15 -> 179574
A16: =1+A15 -> 46065 | D16: 4 | E16: 3 | F16: =9+7 -> 16 | H16: 10 | I16: 6 | K16: 8 | L16: 10 | M16: 10 | N16: 20 | P16: =C16*$B$4+D16*$D$4+E16*$E$4+F16*$F$4+G16*$G$4+H16*$H$4+I16*$I$4+J16*$J$4+K16*$K$4+L16*$L$4+M16*$M$4+N16*$N$4+O16*$O$4 -> 58507 | R16: =+R15+P16-Q16 -> 113764 | U16: 2 | W16: 3 | AB16: 4 | AC16: 5 | AD16: 10 | AG16: =T16*$B$4+U16*$D$4+V16*$E$4+W16*$F$4+X16*$G$4+Y16*$H$4+Z16*$I$4+AA16*$J$4+AB16*$K$4+AC16*$L$4+AD16*$M$4+AE16*$N$4+AF16*$O$4 -> 13025 | AH16: 13025 | AI16: =+AI15+AG16-AH16 -> 0 | AM16: 3 | AN16: 2 | AO16: 12 | AQ16: 6 | AT16: 11 | AU16: 7 | AV16: 15 | AY16: =AK16*$AJ$4+AM16*$AM$4+AN16*$AN$4+AO16*$AO$4+AP16*$AP$4+AQ16*$AQ$4+AR16*$AR$4+AS16*$AS$4+AT16*$AT$4+AU16*$AU$4+AV16*$AV$4+AW16*$AW$4+AX16*$AX$4+$AL$4*AL16 -> 39703 | AZ16: 39703 | BA16: =+BA15+AY16-AZ16 -> 0 | BB16: =B16+S16+AJ16 -> 0 | BC16: =C16+T16+AK16 -> 0 | BD16: =D16+U16+AM16 -> 9 | BE16: =E16+V16+AN16 -> 5 | BF16: =F16+W16+AO16 -> 31 | BG16: =G16+X16+AP16 -> 0 | BH16: =H16+Y16+AQ16 -> 16 | BI16: =I16+Z16+AR16 -> 6 | BJ16: =J16+AA16+AS16 -> 0 | BK16: =K16+AB16+AT16 -> 23 | ... BO16: =O16+AF16+AX16 -> 0 | BP16: =A16 -> 46065 | BQ16: =BU15 -> 234831 | BR16: =AY16+AG16+P16 -> 111235 | BS16: =BR16+BQ16 -> 346066 | BT16: 0 | BU16: =BS16-BT16 -> 346066 | BW16: =Q16+AH16+AZ16 -> 52728 | BX16: =R16+AI16+BA16 -> 113764 | BY16: =+BU16-BX16 -> 232302 | CA16: SAFE CASH | CC16: =BY36 -> 4408
A17: =1+A16 -> 46066 | D17: 6 | E17: 5 | F17: 24 | H17: 10 | I17: 6 | K17: 8 | L17: 15 | M17: 15 | N17: 20 | P17: =C17*$B$4+D17*$D$4+E17*$E$4+F17*$F$4+G17*$G$4+H17*$H$4+I17*$I$4+J17*$J$4+K17*$K$4+L17*$L$4+M17*$M$4+N17*$N$4+O17*$O$4 -> 82945 | Q17: 196709 | R17: =+R16+P17-Q17 -> 0 | S17: 1 | T17: 4 | U17: 2 | V17: 2 | W17: 8 | AB17: 4 | AC17: 5 | AG17: =T17*$B$4+U17*$D$4+V17*$E$4+W17*$F$4+X17*$G$4+Y17*$H$4+Z17*$I$4+AA17*$J$4+AB17*$K$4+AC17*$L$4+AD17*$M$4+AE17*$N$4+AF17*$O$4 -> 29118 | AH17: 29118 | AI17: =+AI16+AG17-AH17 -> 0 | AJ17: 2 | AK17: 14 | AM17: 4 | AN17: 4 | AO17: 11 | AQ17: 3 | AR17: 10 | AT17: 8 | AU17: 10 | AV17: 5 | AW17: 20 | AY17: =AK17*$AJ$4+AM17*$AM$4+AN17*$AN$4+AO17*$AO$4+AP17*$AP$4+AQ17*$AQ$4+AR17*$AR$4+AS17*$AS$4+AT17*$AT$4+AU17*$AU$4+AV17*$AV$4+AW17*$AW$4+AX17*$AX$4+$AL$4*AL17 -> 64466 | AZ17: 64466 | BA17: =+BA16+AY17-AZ17 -> 0 | BB17: =B17+S17+AJ17 -> 3 | BC17: =C17+T17+AK17 -> 18 | BD17: =D17+U17+AM17 -> 12 | BE17: =E17+V17+AN17 -> 11 | BF17: =F17+W17+AO17 -> 43 | BG17: =G17+X17+AP17 -> 0 | BH17: =H17+Y17+AQ17 -> 13 | BI17: =I17+Z17+AR17 -> 16 | BJ17: =J17+AA17+AS17 -> 0 | BK17: =K17+AB17+AT17 -> 20 | ... BO17: =O17+AF17+AX17 -> 0 | BP17: =A17 -> 46066 | BQ17: =BU16 -> 346066 | BR17: =AY17+AG17+P17 -> 176529 | BS17: =BR17+BQ17 -> 522595 | BT17: 55399 | BU17: =BS17-BT17 -> 467196 | BW17: =Q17+AH17+AZ17 -> 290293 | BX17: =R17+AI17+BA17 -> 0 | BY17: =+BU17-BX17 -> 467196 | CA17: DIFFERENCE | CC17: =CC14-CC16 -> -4408
A18: =1+A17 -> 46067 | B18: 3 | C18: 13 | D18: 7 | E18: 5 | F18: 24 | K18: 8 | L18: 15 | M18: 15 | P18: =C18*$B$4+D18*$D$4+E18*$E$4+F18*$F$4+G18*$G$4+H18*$H$4+I18*$I$4+J18*$J$4+K18*$K$4+L18*$L$4+M18*$M$4+N18*$N$4+O18*$O$4 -> 89174 | R18: =+R17+P18-Q18 -> 89174 | S18: 3 | T18: 10 | U18: 3 | W18: 7 | Y18: 3 | Z18: 5 | AA18: 6 | AB18: 5 | AC18: 5 | AD18: 5 | AG18: =T18*$B$4+U18*$D$4+V18*$E$4+W18*$F$4+X18*$G$4+Y18*$H$4+Z18*$I$4+AA18*$J$4+AB18*$K$4+AC18*$L$4+AD18*$M$4+AE18*$N$4+AF18*$O$4 -> 36585 | AH18: 36585 | AI18: =+AI17+AG18-AH18 -> 0 | AJ18: 4 | AK18: =5+6 -> 11 | AM18: 6 | AN18: 4 | AO18: 23 | AQ18: 7 | AR18: 9 | AT18: 11 | AU18: 10 | AV18: 15 | AW18: 20 | AY18: =AK18*$AJ$4+AM18*$AM$4+AN18*$AN$4+AO18*$AO$4+AP18*$AP$4+AQ18*$AQ$4+AR18*$AR$4+AS18*$AS$4+AT18*$AT$4+AU18*$AU$4+AV18*$AV$4+AW18*$AW$4+AX18*$AX$4+$AL$4*AL18 -> 89692 | AZ18: 89692 | BA18: =+BA17+AY18-AZ18 -> 0 | BB18: =B18+S18+AJ18 -> 10 | BC18: =C18+T18+AK18 -> 34 | BD18: =D18+U18+AM18 -> 16 | BE18: =E18+V18+AN18 -> 9 | BF18: =F18+W18+AO18 -> 54 | BG18: =G18+X18+AP18 -> 0 | BH18: =H18+Y18+AQ18 -> 10 | BI18: =I18+Z18+AR18 -> 14 | BJ18: =J18+AA18+AS18 -> 6 | BK18: =K18+AB18+AT18 -> 24 | ... BO18: =O18+AF18+AX18 -> 0 | BP18: =A18 -> 46067 | BQ18: =BU17 -> 467196 | BR18: =AY18+AG18+P18 -> 215451 | BS18: =BR18+BQ18 -> 682647 | BT18: 0 | BU18: =BS18-BT18 -> 682647 | BW18: =Q18+AH18+AZ18 -> 126277 | BX18: =R18+AI18+BA18 -> 89174 | BY18: =+BU18-BX18 -> 593473
A19: =1+A18 -> 46068 | B19: 2 | C19: 10 | D19: 6 | E19: 4 | F19: 19 | I19: 5 | K19: 4 | L19: 10 | M19: 15 | N19: 20 | P19: =C19*$B$4+D19*$D$4+E19*$E$4+F19*$F$4+G19*$G$4+H19*$H$4+I19*$I$4+J19*$J$4+K19*$K$4+L19*$L$4+M19*$M$4+N19*$N$4+O19*$O$4 -> 76651 | R19: =+R18+P19-Q19 -> 165825 | U19: 3 | V19: 2 | W19: 7 | Z19: 2 | AC19: 5 | AD19: 5 | AG19: =T19*$B$4+U19*$D$4+V19*$E$4+W19*$F$4+X19*$G$4+Y19*$H$4+Z19*$I$4+AA19*$J$4+AB19*$K$4+AC19*$L$4+AD19*$M$4+AE19*$N$4+AF19*$O$4 -> 24478 | AH19: 24478 | AI19: =+AI18+AG19-AH19 -> 0 | AJ19: 2 | AK19: 9 | AM19: 2 | AN19: 1 | AO19: 3 | AQ19: 7 | AR19: 4 | AT19: 6 | AU19: 10 | AV19: 15 | AW19: 20 | AY19: =AK19*$AJ$4+AM19*$AM$4+AN19*$AN$4+AO19*$AO$4+AP19*$AP$4+AQ19*$AQ$4+AR19*$AR$4+AS19*$AS$4+AT19*$AT$4+AU19*$AU$4+AV19*$AV$4+AW19*$AW$4+AX19*$AX$4+$AL$4*AL19 -> 36219 | AZ19: 36219 | BA19: =+BA18+AY19-AZ19 -> 0 | BB19: =B19+S19+AJ19 -> 4 | BC19: =C19+T19+AK19 -> 19 | BD19: =D19+U19+AM19 -> 11 | BE19: =E19+V19+AN19 -> 7 | BF19: =F19+W19+AO19 -> 29 | BG19: =G19+X19+AP19 -> 0 | BH19: =H19+Y19+AQ19 -> 7 | BI19: =I19+Z19+AR19 -> 11 | BJ19: =J19+AA19+AS19 -> 0 | BK19: =K19+AB19+AT19 -> 10 | ... BO19: =O19+AF19+AX19 -> 0 | BP19: =A19 -> 46068 | BQ19: =BU18 -> 682647 | BR19: =AY19+AG19+P19 -> 137348 | BS19: =BR19+BQ19 -> 819995 | BT19: 524878 | BU19: =BS19-BT19 -> 295117 | BW19: =Q19+AH19+AZ19 -> 60697 | BX19: =R19+AI19+BA19 -> 165825 | BY19: =+BU19-BX19 -> 129292
A20: =1+A19 -> 46069 | D20: 3 | E20: 3 | F20: =13 -> 13 | I20: 2 | K20: 4 | L20: 10 | M20: 20 | P20: =C20*$B$4+D20*$D$4+E20*$E$4+F20*$F$4+G20*$G$4+H20*$H$4+I20*$I$4+J20*$J$4+K20*$K$4+L20*$L$4+M20*$M$4+N20*$N$4+O20*$O$4 -> 42501 | Q20: 208326 | R20: =+R19+P20-Q20 -> 0 | U20: 2 | V20: 2 | W20: 4 | Z20: 4 | AB20: 5 | AC20: 5 | AD20: 15 | AG20: =T20*$B$4+U20*$D$4+V20*$E$4+W20*$F$4+X20*$G$4+Y20*$H$4+Z20*$I$4+AA20*$J$4+AB20*$K$4+AC20*$L$4+AD20*$M$4+AE20*$N$4+AF20*$O$4 -> 20022 | AI20: =+AI19+AG20-AH20 -> 20022 | AM20: 2 | AO20: 6 | AQ20: 7 | AR20: 8 | AT20: 0 | AU20: 6 | AV20: 5 | AY20: =AK20*$AJ$4+AM20*$AM$4+AN20*$AN$4+AO20*$AO$4+AP20*$AP$4+AQ20*$AQ$4+AR20*$AR$4+AS20*$AS$4+AT20*$AT$4+AU20*$AU$4+AV20*$AV$4+AW20*$AW$4+AX20*$AX$4+$AL$4*AL20 -> 21377 | AZ20: 21377 | BA20: =+BA19+AY20-AZ20 -> 0 | BB20: =B20+S20+AJ20 -> 0 | BC20: =C20+T20+AK20 -> 0 | BD20: =D20+U20+AM20 -> 7 | BE20: =E20+V20+AN20 -> 5 | BF20: =F20+W20+AO20 -> 23 | BG20: =G20+X20+AP20 -> 0 | BH20: =H20+Y20+AQ20 -> 7 | BI20: =I20+Z20+AR20 -> 14 | BJ20: =J20+AA20+AS20 -> 0 | BK20: =K20+AB20+AT20 -> 9 | ... BO20: =O20+AF20+AX20 -> 0 | BP20: =A20 -> 46069 | BQ20: =BU19 -> 295117 | BR20: =AY20+AG20+P20 -> 83900 | BS20: =BR20+BQ20 -> 379017 | BT20: 0 | BU20: =BS20-BT20 -> 379017 | BW20: =Q20+AH20+AZ20 -> 229703 | BX20: =R20+AI20+BA20 -> 20022 | BY20: =+BU20-BX20 -> 358995
A21: =1+A20 -> 46070 | D21: 5 | E21: 4 | F21: 22 | I21: 2 | K21: 4 | L21: 13 | M21: 15 | N21: 20 | P21: =C21*$B$4+D21*$D$4+E21*$E$4+F21*$F$4+G21*$G$4+H21*$H$4+I21*$I$4+J21*$J$4+K21*$K$4+L21*$L$4+M21*$M$4+N21*$N$4+O21*$O$4 -> 70539 | R21: =+R20+P21-Q21 -> 70539 | U21: 3 | V21: 2 | W21: 8 | AB21: 30 | AC21: 5 | AD21: 20 | AE21: 60 | AG21: =T21*$B$4+U21*$D$4+V21*$E$4+W21*$F$4+X21*$G$4+Y21*$H$4+Z21*$I$4+AA21*$J$4+AB21*$K$4+AC21*$L$4+AD21*$M$4+AE21*$N$4+AF21*$O$4 -> 50837 | AH21: 70859 | AI21: =+AI20+AG21-AH21 -> 0 | AJ21: 1 | AK21: 5 | AM21: 4 | AN21: 4 | AO21: 14 | AQ21: 6 | AR21: 5 | AT21: 5 | AU21: 6 | AV21: 10 | AW21: 20 | AY21: =AK21*$AJ$4+AM21*$AM$4+AN21*$AN$4+AO21*$AO$4+AP21*$AP$4+AQ21*$AQ$4+AR21*$AR$4+AS21*$AS$4+AT21*$AT$4+AU21*$AU$4+AV21*$AV$4+AW21*$AW$4+AX21*$AX$4+$AL$4*AL21 -> 58128 | AZ21: 58128 | BA21: =+BA20+AY21-AZ21 -> 0 | BB21: =B21+S21+AJ21 -> 1 | BC21: =C21+T21+AK21 -> 5 | BD21: =D21+U21+AM21 -> 12 | BE21: =E21+V21+AN21 -> 10 | BF21: =F21+W21+AO21 -> 44 | BG21: =G21+X21+AP21 -> 0 | BH21: =H21+Y21+AQ21 -> 6 | BI21: =I21+Z21+AR21 -> 7 | BJ21: =J21+AA21+AS21 -> 0 | BK21: =K21+AB21+AT21 -> 39 | ... BO21: =O21+AF21+AX21 -> 0 | BP21: =A21 -> 46070 | BQ21: =BU20 -> 379017 | BR21: =AY21+AG21+P21 -> 179504 | BS21: =BR21+BQ21 -> 558521 | BT21: 303840 | BU21: =BS21-BT21 -> 254681 | BW21: =Q21+AH21+AZ21 -> 128987 | BX21: =R21+AI21+BA21 -> 70539 | BY21: =+BU21-BX21 -> 184142
A22: =1+A21 -> 46071 | D22: 2 | E22: 2 | F22: 11 | H22: 10 | I22: 2 | K22: 4 | L22: 5 | N22: 20 | P22: =C22*$B$4+D22*$D$4+E22*$E$4+F22*$F$4+G22*$G$4+H22*$H$4+I22*$I$4+J22*$J$4+K22*$K$4+L22*$L$4+M22*$M$4+N22*$N$4+O22*$O$4 -> 39105 | R22: =+R21+P22-Q22 -> 109644 | U22: 2 | V22: 1 | W22: 6 | Y22: 3 | AB22: 3 | AC22: 5 | AD22: 10 | AG22: =T22*$B$4+U22*$D$4+V22*$E$4+W22*$F$4+X22*$G$4+Y22*$H$4+Z22*$I$4+AA22*$J$4+AB22*$K$4+AC22*$L$4+AD22*$M$4+AE22*$N$4+AF22*$O$4 -> 21026 | AH22: 21026 | AI22: =+AI21+AG22-AH22 -> 0 | AJ22: 1 | AK22: 4 | AM22: 3 | AO22: 7 | AQ22: 4 | AR22: 5 | AT22: 5 | AU22: 5 | AV22: 8 | AY22: =AK22*$AJ$4+AM22*$AM$4+AN22*$AN$4+AO22*$AO$4+AP22*$AP$4+AQ22*$AQ$4+AR22*$AR$4+AS22*$AS$4+AT22*$AT$4+AU22*$AU$4+AV22*$AV$4+AW22*$AW$4+AX22*$AX$4+$AL$4*AL22 -> 28700 | AZ22: 28700 | BA22: =+BA21+AY22-AZ22 -> 0 | BB22: =B22+S22+AJ22 -> 1 | BC22: =C22+T22+AK22 -> 4 | BD22: =D22+U22+AM22 -> 7 | BE22: =E22+V22+AN22 -> 3 | BF22: =F22+W22+AO22 -> 24 | BG22: =G22+X22+AP22 -> 0 | BH22: =H22+Y22+AQ22 -> 17 | BI22: =I22+Z22+AR22 -> 7 | BJ22: =J22+AA22+AS22 -> 0 | BK22: =K22+AB22+AT22 -> 12 | ... BO22: =O22+AF22+AX22 -> 0 | BP22: =A22 -> 46071 | BQ22: =BU21 -> 254681 | BR22: =AY22+AG22+P22 -> 88831 | BS22: =BR22+BQ22 -> 343512 | BT22: 0 | BU22: =BS22-BT22 -> 343512 | BW22: =Q22+AH22+AZ22 -> 49726 | BX22: =R22+AI22+BA22 -> 109644 | BY22: =+BU22-BX22 -> 233868
A23: =1+A22 -> 46072 | D23: 1 | E23: 1 | F23: 8 | H23: 5 | I23: 2 | K23: 4 | N23: 20 | P23: =C23*$B$4+D23*$D$4+E23*$E$4+F23*$F$4+G23*$G$4+H23*$H$4+I23*$I$4+J23*$J$4+K23*$K$4+L23*$L$4+M23*$M$4+N23*$N$4+O23*$O$4 -> 26585 | Q23: 136230 | R23: =+R22+P23-Q23 -> -1 | S23: 1 | T23: 25 | U23: 1 | V23: 1 | W23: 3 | Y23: 0 | AB23: 4 | AC23: 2 | AD23: 5 | AG23: =T23*$B$4+U23*$D$4+V23*$E$4+W23*$F$4+X23*$G$4+Y23*$H$4+Z23*$I$4+AA23*$J$4+AB23*$K$4+AC23*$L$4+AD23*$M$4+AE23*$N$4+AF23*$O$4 -> 38775 | AH23: 38775 | AI23: =+AI22+AG23-AH23 -> 0 | AM23: 2 | AO23: 4 | AQ23: 3 | AU23: 3 | AV23: 5 | AW23: 20 | AY23: =AK23*$AJ$4+AM23*$AM$4+AN23*$AN$4+AO23*$AO$4+AP23*$AP$4+AQ23*$AQ$4+AR23*$AR$4+AS23*$AS$4+AT23*$AT$4+AU23*$AU$4+AV23*$AV$4+AW23*$AW$4+AX23*$AX$4+$AL$4*AL23 -> 18869 | AZ23: 18869 | BA23: =+BA22+AY23-AZ23 -> 0 | BB23: =B23+S23+AJ23 -> 1 | BC23: =C23+T23+AK23 -> 25 | BD23: =D23+U23+AM23 -> 4 | BE23: =E23+V23+AN23 -> 2 | BF23: =F23+W23+AO23 -> 15 | BG23: =G23+X23+AP23 -> 0 | BH23: =H23+Y23+AQ23 -> 8 | BI23: =I23+Z23+AR23 -> 2 | BJ23: =J23+AA23+AS23 -> 0 | BK23: =K23+AB23+AT23 -> 8 | ... BO23: =O23+AF23+AX23 -> 0 | BP23: =A23 -> 46072 | BQ23: =BU22 -> 343512 | BR23: =AY23+AG23+P23 -> 84229 | BS23: =BR23+BQ23 -> 427741 | BT23: 0 | BU23: =BS23-BT23 -> 427741 | BW23: =Q23+AH23+AZ23 -> 193874 | BX23: =R23+AI23+BA23 -> -1 | BY23: =+BU23-BX23 -> 427742
A24: =1+A23 -> 46073 | E24: 1 | F24: 5 | H24: 5 | K24: 2 | P24: =C24*$B$4+D24*$D$4+E24*$E$4+F24*$F$4+G24*$G$4+H24*$H$4+I24*$I$4+J24*$J$4+K24*$K$4+L24*$L$4+M24*$M$4+N24*$N$4+O24*$O$4 -> 13009 | R24: =+R23+P24-Q24 -> 13008 | U24: 1 | W24: 1 | AB24: 2 | AC24: 2 | AG24: =T24*$B$4+U24*$D$4+V24*$E$4+W24*$F$4+X24*$G$4+Y24*$H$4+Z24*$I$4+AA24*$J$4+AB24*$K$4+AC24*$L$4+AD24*$M$4+AE24*$N$4+AF24*$O$4 -> 4738 | AH24: 4738 | AI24: =+AI23+AG24-AH24 -> 0 | AJ24: 1 | AK24: 4 | AM24: 1 | AN24: 1 | AO24: 3 | AR24: 1 | AT24: 5 | AV24: 5 | AY24: =AK24*$AJ$4+AM24*$AM$4+AN24*$AN$4+AO24*$AO$4+AP24*$AP$4+AQ24*$AQ$4+AR24*$AR$4+AS24*$AS$4+AT24*$AT$4+AU24*$AU$4+AV24*$AV$4+AW24*$AW$4+AX24*$AX$4+$AL$4*AL24 -> 15215 | AZ24: 15215 | BA24: =+BA23+AY24-AZ24 -> 0 | BB24: =B24+S24+AJ24 -> 1 | BC24: =C24+T24+AK24 -> 4 | BD24: =D24+U24+AM24 -> 2 | BE24: =E24+V24+AN24 -> 2 | BF24: =F24+W24+AO24 -> 9 | BG24: =G24+X24+AP24 -> 0 | BH24: =H24+Y24+AQ24 -> 5 | BI24: =I24+Z24+AR24 -> 1 | BJ24: =J24+AA24+AS24 -> 0 | BK24: =K24+AB24+AT24 -> 9 | ... BO24: =O24+AF24+AX24 -> 0 | BP24: =A24 -> 46073 | BQ24: =BU23 -> 427741 | BR24: =AY24+AG24+P24 -> 32962 | BS24: =BR24+BQ24 -> 460703 | BT24: 155475 | BU24: =BS24-BT24 -> 305228 | BW24: =Q24+AH24+AZ24 -> 19953 | BX24: =R24+AI24+BA24 -> 13008 | BY24: =+BU24-BX24 -> 292220
A25: =1+A24 -> 46074 | D25: 2 | E25: 3 | F25: 8 | I25: 2 | K25: 2 | L25: 2 | P25: =C25*$B$4+D25*$D$4+E25*$E$4+F25*$F$4+G25*$G$4+H25*$H$4+I25*$I$4+J25*$J$4+K25*$K$4+L25*$L$4+M25*$M$4+N25*$N$4+O25*$O$4 -> 25067 | R25: =+R24+P25-Q25 -> 38075 | U25: 1 | V25: 1 | W25: 2 | Z25: 4 | AB25: 4 | AC25: 2 | AG25: =T25*$B$4+U25*$D$4+V25*$E$4+W25*$F$4+X25*$G$4+Y25*$H$4+Z25*$I$4+AA25*$J$4+AB25*$K$4+AC25*$L$4+AD25*$M$4+AE25*$N$4+AF25*$O$4 -> 9656 | AI25: =+AI24+AG25-AH25 -> 9656 | AM25: 2 | AN25: 1 | AO25: 4 | AQ25: 3 | AR25: 6 | AT25: 5 | AU25: 5 | AV25: 9 | AY25: =AK25*$AJ$4+AM25*$AM$4+AN25*$AN$4+AO25*$AO$4+AP25*$AP$4+AQ25*$AQ$4+AR25*$AR$4+AS25*$AS$4+AT25*$AT$4+AU25*$AU$4+AV25*$AV$4+AW25*$AW$4+AX25*$AX$4+$AL$4*AL25 -> 18868 | BA25: =+BA24+AY25-AZ25 -> 18868 | BB25: =B25+S25+AJ25 -> 0 | BC25: =C25+T25+AK25 -> 0 | BD25: =D25+U25+AM25 -> 5 | BE25: =E25+V25+AN25 -> 5 | BF25: =F25+W25+AO25 -> 14 | BG25: =G25+X25+AP25 -> 0 | BH25: =H25+Y25+AQ25 -> 3 | BI25: =I25+Z25+AR25 -> 12 | BJ25: =J25+AA25+AS25 -> 0 | BK25: =K25+AB25+AT25 -> 11 | ... BO25: =O25+AF25+AX25 -> 0 | BP25: =A25 -> 46074 | BQ25: =BU24 -> 305228 | BR25: =AY25+AG25+P25 -> 53591 | BS25: =BR25+BQ25 -> 358819 | BU25: =BS25-BT25 -> 358819 | BW25: =Q25+AH25+AZ25 -> 0 | BX25: =R25+AI25+BA25 -> 66599 | BY25: =+BU25-BX25 -> 292220
A26: =1+A25 -> 46075 | D26: 1 | E26: 3 | F26: 7 | K26: 2 | L26: 2 | M26: 6 | P26: =C26*$B$4+D26*$D$4+E26*$E$4+F26*$F$4+G26*$G$4+H26*$H$4+I26*$I$4+J26*$J$4+K26*$K$4+L26*$L$4+M26*$M$4+N26*$N$4+O26*$O$4 -> 21949 | R26: =+R25+P26-Q26 -> 60024 | U26: 2 | V26: 1 | W26: 2 | Y26: 2 | AC26: 2 | AG26: =T26*$B$4+U26*$D$4+V26*$E$4+W26*$F$4+X26*$G$4+Y26*$H$4+Z26*$I$4+AA26*$J$4+AB26*$K$4+AC26*$L$4+AD26*$M$4+AE26*$N$4+AF26*$O$4 -> 9945 | AI26: =+AI25+AG26-AH26 -> 19601 | AM26: 1 | AN26: 1 | AO26: 5 | AQ26: 3 | AT26: 6 | AU26: 3 | AY26: =AK26*$AJ$4+AM26*$AM$4+AN26*$AN$4+AO26*$AO$4+AP26*$AP$4+AQ26*$AQ$4+AR26*$AR$4+AS26*$AS$4+AT26*$AT$4+AU26*$AU$4+AV26*$AV$4+AW26*$AW$4+AX26*$AX$4+$AL$4*AL26 -> 16188 | BA26: =+BA25+AY26-AZ26 -> 35056 | BB26: =B26+S26+AJ26 -> 0 | BC26: =C26+T26+AK26 -> 0 | BD26: =D26+U26+AM26 -> 4 | BE26: =E26+V26+AN26 -> 5 | BF26: =F26+W26+AO26 -> 14 | BG26: =G26+X26+AP26 -> 0 | BH26: =H26+Y26+AQ26 -> 5 | BI26: =I26+Z26+AR26 -> 0 | BJ26: =J26+AA26+AS26 -> 0 | BK26: =K26+AB26+AT26 -> 8 | ... BO26: =O26+AF26+AX26 -> 0 | BP26: =A26 -> 46075 | BQ26: =BU25 -> 358819 | BR26: =AY26+AG26+P26 -> 48082 | BS26: =BR26+BQ26 -> 406901 | BU26: =BS26-BT26 -> 406901 | BW26: =Q26+AH26+AZ26 -> 0 | BX26: =R26+AI26+BA26 -> 114681 | BY26: =+BU26-BX26 -> 292220
A27: =1+A26 -> 46076 | D27: 1 | E27: 2 | F27: 6 | K27: 2 | L27: 2 | M27: 6 | P27: =C27*$B$4+D27*$D$4+E27*$E$4+F27*$F$4+G27*$G$4+H27*$H$4+I27*$I$4+J27*$J$4+K27*$K$4+L27*$L$4+M27*$M$4+N27*$N$4+O27*$O$4 -> 18351 | R27: =+R26+P27-Q27 -> 78375 | W27: 2 | Z27: 3 | AC27: 2 | AD27: 10 | AG27: =T27*$B$4+U27*$D$4+V27*$E$4+W27*$F$4+X27*$G$4+Y27*$H$4+Z27*$I$4+AA27*$J$4+AB27*$K$4+AC27*$L$4+AD27*$M$4+AE27*$N$4+AF27*$O$4 -> 6558 | AI27: =+AI26+AG27-AH27 -> 26159 | AM27: 3 | AN27: 2 | AO27: 6 | AT27: 2 | AV27: 6 | AY27: =AK27*$AJ$4+AM27*$AM$4+AN27*$AN$4+AO27*$AO$4+AP27*$AP$4+AQ27*$AQ$4+AR27*$AR$4+AS27*$AS$4+AT27*$AT$4+AU27*$AU$4+AV27*$AV$4+AW27*$AW$4+AX27*$AX$4+$AL$4*AL27 -> 20449 | BA27: =+BA26+AY27-AZ27 -> 55505 | BB27: =B27+S27+AJ27 -> 0 | BC27: =C27+T27+AK27 -> 0 | BD27: =D27+U27+AM27 -> 4 | BE27: =E27+V27+AN27 -> 4 | BF27: =F27+W27+AO27 -> 14 | BG27: =G27+X27+AP27 -> 0 | BH27: =H27+Y27+AQ27 -> 0 | BI27: =I27+Z27+AR27 -> 3 | BJ27: =J27+AA27+AS27 -> 0 | BK27: =K27+AB27+AT27 -> 4 | ... BO27: =O27+AF27+AX27 -> 0 | BP27: =A27 -> 46076 | BQ27: =BU26 -> 406901 | BR27: =AY27+AG27+P27 -> 45358 | BS27: =BR27+BQ27 -> 452259 | BU27: =BS27-BT27 -> 452259 | BW27: =Q27+AH27+AZ27 -> 0 | BX27: =R27+AI27+BA27 -> 160039 | BY27: =+BU27-BX27 -> 292220
A28: =1+A27 -> 46077 | D28: 1 | E28: 1 | F28: 7 | L28: 2 | M28: 6 | P28: =C28*$B$4+D28*$D$4+E28*$E$4+F28*$F$4+G28*$G$4+H28*$H$4+I28*$I$4+J28*$J$4+K28*$K$4+L28*$L$4+M28*$M$4+N28*$N$4+O28*$O$4 -> 18111 | R28: =+R27+P28-Q28 -> 96486 | W28: 2 | Z28: 1 | AB28: 1 | AC28: 1 | AG28: =T28*$B$4+U28*$D$4+V28*$E$4+W28*$F$4+X28*$G$4+Y28*$H$4+Z28*$I$4+AA28*$J$4+AB28*$K$4+AC28*$L$4+AD28*$M$4+AE28*$N$4+AF28*$O$4 -> 4688 | AI28: =+AI27+AG28-AH28 -> 30847 | AM28: 2 | AN28: 1 | AO28: 2 | AY28: =AK28*$AJ$4+AM28*$AM$4+AN28*$AN$4+AO28*$AO$4+AP28*$AP$4+AQ28*$AQ$4+AR28*$AR$4+AS28*$AS$4+AT28*$AT$4+AU28*$AU$4+AV28*$AV$4+AW28*$AW$4+AX28*$AX$4+$AL$4*AL28 -> 8495 | BA28: =+BA27+AY28-AZ28 -> 64000 | BB28: =B28+S28+AJ28 -> 0 | BC28: =C28+T28+AK28 -> 0 | BD28: =D28+U28+AM28 -> 3 | BE28: =E28+V28+AN28 -> 2 | BF28: =F28+W28+AO28 -> 11 | BG28: =G28+X28+AP28 -> 0 | BH28: =H28+Y28+AQ28 -> 0 | BI28: =I28+Z28+AR28 -> 1 | BJ28: =J28+AA28+AS28 -> 0 | BK28: =K28+AB28+AT28 -> 1 | ... BO28: =O28+AF28+AX28 -> 0 | BP28: =A28 -> 46077 | BQ28: =BU27 -> 452259 | BR28: =AY28+AG28+P28 -> 31294 | BS28: =BR28+BQ28 -> 483553 | BU28: =BS28-BT28 -> 483553 | BW28: =Q28+AH28+AZ28 -> 0 | BX28: =R28+AI28+BA28 -> 191333 | BY28: =+BU28-BX28 -> 292220
A29: =1+A28 -> 46078 | D29: 2 | E29: 1 | F29: 2 | K29: 2 | P29: =C29*$B$4+D29*$D$4+E29*$E$4+F29*$F$4+G29*$G$4+H29*$H$4+I29*$I$4+J29*$J$4+K29*$K$4+L29*$L$4+M29*$M$4+N29*$N$4+O29*$O$4 -> 8935 | R29: =+R28+P29-Q29 -> 105421 | U29: 1 | V29: 1 | W29: 1 | AC29: 2 | AD29: 5 | AG29: =T29*$B$4+U29*$D$4+V29*$E$4+W29*$F$4+X29*$G$4+Y29*$H$4+Z29*$I$4+AA29*$J$4+AB29*$K$4+AC29*$L$4+AD29*$M$4+AE29*$N$4+AF29*$O$4 -> 6597 | AI29: =+AI28+AG29-AH29 -> 37444 | AM29: 3 | AO29: 2 | AT29: 4 | AV29: 5 | AW29: 20 | AY29: =AK29*$AJ$4+AM29*$AM$4+AN29*$AN$4+AO29*$AO$4+AP29*$AP$4+AQ29*$AQ$4+AR29*$AR$4+AS29*$AS$4+AT29*$AT$4+AU29*$AU$4+AV29*$AV$4+AW29*$AW$4+AX29*$AX$4+$AL$4*AL29 -> 15275 | BA29: =+BA28+AY29-AZ29 -> 79275 | BB29: =B29+S29+AJ29 -> 0 | BC29: =C29+T29+AK29 -> 0 | BD29: =D29+U29+AM29 -> 6 | BE29: =E29+V29+AN29 -> 2 | BF29: =F29+W29+AO29 -> 5 | BG29: =G29+X29+AP29 -> 0 | BH29: =H29+Y29+AQ29 -> 0 | BI29: =I29+Z29+AR29 -> 0 | BJ29: =J29+AA29+AS29 -> 0 | BK29: =K29+AB29+AT29 -> 6 | ... BO29: =O29+AF29+AX29 -> 0 | BP29: =A29 -> 46078 | BQ29: =BU28 -> 483553 | BR29: =AY29+AG29+P29 -> 30807 | BS29: =BR29+BQ29 -> 514360 | BT29: 140860 | BU29: =BS29-BT29 -> 373500 | BW29: =Q29+AH29+AZ29 -> 0 | BX29: =R29+AI29+BA29 -> 222140 | BY29: =+BU29-BX29 -> 151360
A30: =1+A29 -> 46079 | D30: 1 | E30: 1 | F30: 6 | H30: 3 | K30: 2 | L30: 2 | N30: 10 | P30: =C30*$B$4+D30*$D$4+E30*$E$4+F30*$F$4+G30*$G$4+H30*$H$4+I30*$I$4+J30*$J$4+K30*$K$4+L30*$L$4+M30*$M$4+N30*$N$4+O30*$O$4 -> 19507 | R30: =+R29+P30-Q30 -> 124928 | U30: 1 | W30: 3 | Y30: 2 | Z30: 3 | AB30: 3 | AC30: 1 | AD30: 5 | AG30: =T30*$B$4+U30*$D$4+V30*$E$4+W30*$F$4+X30*$G$4+Y30*$H$4+Z30*$I$4+AA30*$J$4+AB30*$K$4+AC30*$L$4+AD30*$M$4+AE30*$N$4+AF30*$O$4 -> 10116 | AH30: 46800 | AI30: =+AI29+AG30-AH30 -> 760 | AM30: 1 | AO30: 4 | AQ30: 2 | AR30: 5 | AT30: 4 | AY30: =AK30*$AJ$4+AM30*$AM$4+AN30*$AN$4+AO30*$AO$4+AP30*$AP$4+AQ30*$AQ$4+AR30*$AR$4+AS30*$AS$4+AT30*$AT$4+AU30*$AU$4+AV30*$AV$4+AW30*$AW$4+AX30*$AX$4+$AL$4*AL30 -> 11625 | AZ30: 95847 | BA30: =+BA29+AY30-AZ30 -> -4947 | BB30: =B30+S30+AJ30 -> 0 | BC30: =C30+T30+AK30 -> 0 | BD30: =D30+U30+AM30 -> 3 | BE30: =E30+V30+AN30 -> 1 | BF30: =F30+W30+AO30 -> 13 | BG30: =G30+X30+AP30 -> 0 | BH30: =H30+Y30+AQ30 -> 7 | BI30: =I30+Z30+AR30 -> 8 | BJ30: =J30+AA30+AS30 -> 0 | BK30: =K30+AB30+AT30 -> 9 | ... BO30: =O30+AF30+AX30 -> 0 | BP30: =A30 -> 46079 | BQ30: =BU29 -> 373500 | BR30: =AY30+AG30+P30 -> 41248 | BS30: =BR30+BQ30 -> 414748 | BT30: 403947 | BU30: =BS30-BT30 -> 10801 | BW30: =Q30+AH30+AZ30 -> 142647 | BX30: =R30+AI30+BA30 -> 120741 | BY30: =+BU30-BX30 -> -109940
A31: =1+A30 -> 46080 | D31: 3 | E31: 2 | F31: 4 | H31: 3 | I31: 2 | K31: 2 | L31: 2 | M31: 10 | N31: 10 | P31: =C31*$B$4+D31*$D$4+E31*$E$4+F31*$F$4+G31*$G$4+H31*$H$4+I31*$I$4+J31*$J$4+K31*$K$4+L31*$L$4+M31*$M$4+N31*$N$4+O31*$O$4 -> 22046 | R31: =+R30+P31-Q31 -> 146974 | U31: 1 | V31: 1 | W31: 2 | Y31: 2 | AC31: 3 | AG31: =T31*$B$4+U31*$D$4+V31*$E$4+W31*$F$4+X31*$G$4+Y31*$H$4+Z31*$I$4+AA31*$J$4+AB31*$K$4+AC31*$L$4+AD31*$M$4+AE31*$N$4+AF31*$O$4 -> 8896 | AI31: =+AI30+AG31-AH31 -> 9656 | AM31: 3 | AN31: 1 | AO31: 8 | AR31: 4 | AT31: 5 | AU31: 5 | AY31: =AK31*$AJ$4+AM31*$AM$4+AN31*$AN$4+AO31*$AO$4+AP31*$AP$4+AQ31*$AQ$4+AR31*$AR$4+AS31*$AS$4+AT31*$AT$4+AU31*$AU$4+AV31*$AV$4+AW31*$AW$4+AX31*$AX$4+$AL$4*AL31 -> 25618 | BA31: =+BA30+AY31-AZ31 -> 20671 | BB31: =B31+S31+AJ31 -> 0 | BC31: =C31+T31+AK31 -> 0 | BD31: =D31+U31+AM31 -> 7 | BE31: =E31+V31+AN31 -> 4 | BF31: =F31+W31+AO31 -> 14 | BG31: =G31+X31+AP31 -> 0 | BH31: =H31+Y31+AQ31 -> 5 | BI31: =I31+Z31+AR31 -> 6 | BJ31: =J31+AA31+AS31 -> 0 | BK31: =K31+AB31+AT31 -> 7 | ... BO31: =O31+AF31+AX31 -> 0 | BP31: =A31 -> 46080 | BQ31: =BU30 -> 10801 | BR31: =AY31+AG31+P31 -> 56560 | BS31: =BR31+BQ31 -> 67361 | BT31: 95249 | BU31: =BS31-BT31 -> -27888 | BW31: =Q31+AH31+AZ31 -> 0 | BX31: =R31+AI31+BA31 -> 177301 | BY31: =+BU31-BX31 -> -205189
A32: =1+A31 -> 46081 | B32: 1 | C32: 3 | D32: 3 | E32: 2 | F32: 9 | H32: 3 | I32: 3 | K32: 3 | L32: 2 | M32: 5 | P32: =C32*$B$4+D32*$D$4+E32*$E$4+F32*$F$4+G32*$G$4+H32*$H$4+I32*$I$4+J32*$J$4+K32*$K$4+L32*$L$4+M32*$M$4+N32*$N$4+O32*$O$4 -> 31931 | Q32: 178905 | R32: =+R31+P32-Q32 -> 0 | S32: 2 | T32: 31 | U32: 2 | W32: 3 | Z32: 2 | AB32: 3 | AC32: 2 | AG32: =T32*$B$4+U32*$D$4+V32*$E$4+W32*$F$4+X32*$G$4+Y32*$H$4+Z32*$I$4+AA32*$J$4+AB32*$K$4+AC32*$L$4+AD32*$M$4+AE32*$N$4+AF32*$O$4 -> 44795 | AH32: 54451 | AI32: =+AI31+AG32-AH32 -> 0 | AJ32: 1 | AK32: 6 | AL32: 1 | AM32: 3 | AN32: 1 | AO32: 5 | AR32: 2 | AT32: 2 | AY32: =AK32*$AJ$4+AM32*$AM$4+AN32*$AN$4+AO32*$AO$4+AP32*$AP$4+AQ32*$AQ$4+AR32*$AR$4+AS32*$AS$4+AT32*$AT$4+AU32*$AU$4+AV32*$AV$4+AW32*$AW$4+AX32*$AX$4+$AL$4*AL32 -> 25570 | AZ32: 46241 | BA32: =+BA31+AY32-AZ32 -> 0 | BB32: =B32+S32+AJ32 -> 4 | BC32: =C32+T32+AK32 -> 40 | BD32: =D32+U32+AM32 -> 8 | BE32: =E32+V32+AN32 -> 3 | BF32: =F32+W32+AO32 -> 17 | BG32: =G32+X32+AP32 -> 0 | BH32: =H32+Y32+AQ32 -> 3 | BI32: =I32+Z32+AR32 -> 7 | BJ32: =J32+AA32+AS32 -> 0 | BK32: =K32+AB32+AT32 -> 8 | ... BO32: =O32+AF32+AX32 -> 0 | BP32: =A32 -> 46081 | BQ32: =BU31 -> -27888 | BR32: =AY32+AG32+P32 -> 102296 | BS32: =BR32+BQ32 -> 74408 | BT32: 70000 | BU32: =BS32-BT32 -> 4408 | BW32: =Q32+AH32+AZ32 -> 279597 | BX32: =R32+AI32+BA32 -> 0 | BY32: =+BU32-BX32 -> 4408
A33: =1+A32 -> 46082 | P33: =C33*$B$4+D33*$D$4+E33*$E$4+F33*$F$4+G33*$G$4+H33*$H$4+I33*$I$4+J33*$J$4+K33*$K$4+L33*$L$4+M33*$M$4+N33*$N$4+O33*$O$4 -> 0 | R33: =+R32+P33-Q33 -> 0 | AG33: =T33*$B$4+U33*$D$4+V33*$E$4+W33*$F$4+X33*$G$4+Y33*$H$4+Z33*$I$4+AA33*$J$4+AB33*$K$4+AC33*$L$4+AD33*$M$4+AE33*$N$4+AF33*$O$4 -> 0 | AI33: =+AI32+AG33-AH33 -> 0 | AY33: =AK33*$AJ$4+AM33*$AM$4+AN33*$AN$4+AO33*$AO$4+AP33*$AP$4+AQ33*$AQ$4+AR33*$AR$4+AS33*$AS$4+AT33*$AT$4+AU33*$AU$4+AV33*$AV$4+AW33*$AW$4+AX33*$AX$4+$AL$4*AL33 -> 0 | BA33: =+BA32+AY33-AZ33 -> 0 | BB33: =B33+S33+AJ33 -> 0 | BC33: =C33+T33+AK33 -> 0 | BD33: =D33+U33+AM33 -> 0 | BE33: =E33+V33+AN33 -> 0 | BF33: =F33+W33+AO33 -> 0 | BG33: =G33+X33+AP33 -> 0 | BH33: =H33+Y33+AQ33 -> 0 | BI33: =I33+Z33+AR33 -> 0 | BJ33: =J33+AA33+AS33 -> 0 | BK33: =K33+AB33+AT33 -> 0 | ... BO33: =O33+AF33+AX33 -> 0 | BP33: =A33 -> 46082 | BQ33: =BU32 -> 4408 | BR33: =AY33+AG33+P33 -> 0 | BS33: =BR33+BQ33 -> 4408 | BU33: =BS33-BT33 -> 4408 | BW33: =Q33+AH33+AZ33 -> 0 | BX33: =R33+AI33+BA33 -> 0 | BY33: =+BU33-BX33 -> 4408
A34: =1+A33 -> 46083 | P34: =C34*$B$4+D34*$D$4+E34*$E$4+F34*$F$4+G34*$G$4+H34*$H$4+I34*$I$4+J34*$J$4+K34*$K$4+L34*$L$4+M34*$M$4+N34*$N$4+O34*$O$4 -> 0 | R34: =+R33+P34-Q34 -> 0 | AG34: =T34*$B$4+U34*$D$4+V34*$E$4+W34*$F$4+X34*$G$4+Y34*$H$4+Z34*$I$4+AA34*$J$4+AB34*$K$4+AC34*$L$4+AD34*$M$4+AE34*$N$4+AF34*$O$4 -> 0 | AI34: =+AI33+AG34-AH34 -> 0 | AY34: =AK34*$AJ$4+AM34*$AM$4+AN34*$AN$4+AO34*$AO$4+AP34*$AP$4+AQ34*$AQ$4+AR34*$AR$4+AS34*$AS$4+AT34*$AT$4+AU34*$AU$4+AV34*$AV$4+AW34*$AW$4+AX34*$AX$4+$AL$4*AL34 -> 0 | BA34: =+BA33+AY34-AZ34 -> 0 | BB34: =B34+S34+AJ34 -> 0 | BC34: =C34+T34+AK34 -> 0 | BD34: =D34+U34+AM34 -> 0 | BE34: =E34+V34+AN34 -> 0 | BF34: =F34+W34+AO34 -> 0 | BG34: =G34+X34+AP34 -> 0 | BH34: =H34+Y34+AQ34 -> 0 | BI34: =I34+Z34+AR34 -> 0 | BJ34: =J34+AA34+AS34 -> 0 | BK34: =K34+AB34+AT34 -> 0 | ... BO34: =O34+AF34+AX34 -> 0 | BP34: =A34 -> 46083 | BQ34: =BU33 -> 4408 | BR34: =AY34+AG34+P34 -> 0 | BS34: =BR34+BQ34 -> 4408 | BU34: =BS34-BT34 -> 4408 | BW34: =Q34+AH34+AZ34 -> 0 | BX34: =R34+AI34+BA34 -> 0 | BY34: =+BU34-BX34 -> 4408
A35: =1+A34 -> 46084 | P35: =C35*$B$4+D35*$D$4+E35*$E$4+F35*$F$4+G35*$G$4+H35*$H$4+I35*$I$4+J35*$J$4+K35*$K$4+L35*$L$4+M35*$M$4+N35*$N$4+O35*$O$4 -> 0 | R35: =+R34+P35-Q35 -> 0 | AG35: =T35*$B$4+U35*$D$4+V35*$E$4+W35*$F$4+X35*$G$4+Y35*$H$4+Z35*$I$4+AA35*$J$4+AB35*$K$4+AC35*$L$4+AD35*$M$4+AE35*$N$4+AF35*$O$4 -> 0 | AI35: =+AI34+AG35-AH35 -> 0 | AY35: =AK35*$AJ$4+AM35*$AM$4+AN35*$AN$4+AO35*$AO$4+AP35*$AP$4+AQ35*$AQ$4+AR35*$AR$4+AS35*$AS$4+AT35*$AT$4+AU35*$AU$4+AV35*$AV$4+AW35*$AW$4+AX35*$AX$4+$AL$4*AL35 -> 0 | BA35: =+BA34+AY35-AZ35 -> 0 | BB35: =B35+S35+AJ35 -> 0 | BC35: =C35+T35+AK35 -> 0 | BD35: =D35+U35+AM35 -> 0 | BE35: =E35+V35+AN35 -> 0 | BF35: =F35+W35+AO35 -> 0 | BG35: =G35+X35+AP35 -> 0 | BH35: =H35+Y35+AQ35 -> 0 | BI35: =I35+Z35+AR35 -> 0 | BJ35: =J35+AA35+AS35 -> 0 | BK35: =K35+AB35+AT35 -> 0 | ... BO35: =O35+AF35+AX35 -> 0 | BP35: =A35 -> 46084 | BQ35: =BU34 -> 4408 | BR35: =AY35+AG35+P35 -> 0 | BS35: =BR35+BQ35 -> 4408 | BU35: =BS35-BT35 -> 4408 | BW35: =Q35+AH35+AZ35 -> 0 | BX35: =R35+AI35+BA35 -> 0 | BY35: =+BU35-BX35 -> 4408
B36: =SUM(B5:B35) -> 11 | C36: =SUM(C5:C35) -> 58 | D36: =SUM(D5:D35) -> 89 | E36: =SUM(E5:E35) -> 72 | F36: =SUM(F5:F35) -> 367 | G36: =SUM(G5:G35) -> 0 | H36: =SUM(H5:H35) -> 98 | I36: =SUM(I5:I35) -> 50 | ... Q36: =SUM(Q5:Q35) -> 1277067 | R36: =R4+P36-Q36 -> 0 | S36: =SUM(S5:S35) -> 12 | T36: =SUM(T5:T35) -> 108 | U36: =SUM(U5:U35) -> 46 | V36: =SUM(V5:V35) -> 25 | W36: =SUM(W5:W35) -> 127 | X36: =SUM(X5:X35) -> 0 | Y36: =SUM(Y5:Y35) -> 29 | Z36: =SUM(Z5:Z35) -> 59 | ... AH36: =SUM(AH5:AH35) -> 612897 | AI36: =AI4+AG36-AH36 -> 0 | AJ36: =SUM(AJ5:AJ35) -> 22 | AK36: =SUM(AK5:AK35) -> 99 | AL36: =SUM(AL5:AL35) -> 2 | AM36: =SUM(AM5:AM35) -> 73 | AN36: =SUM(AN5:AN35) -> 38 | AO36: =SUM(AO5:AO35) -> 214 | AP36: =SUM(AP5:AP35) -> 0 | AQ36: =SUM(AQ5:AQ35) -> 79 | ... AZ36: =SUM(AZ5:AZ35) -> 910198 | BA36: =BA4+AY36-AZ36 -> 0 | BB36: =B36+S36+AJ36 -> 45 | BC36: =C36+T36+AK36 -> 265 | BD36: =D36+U36+AM36 -> 208 | BE36: =E36+V36+AN36 -> 135 | BF36: =F36+W36+AO36 -> 708 | BG36: =G36+X36+AP36 -> 0 | BH36: =H36+Y36+AQ36 -> 206 | BI36: =I36+Z36+AR36 -> 183 | BJ36: =SUM(BJ5:BJ35) -> 6 | BK36: =SUM(BK5:BK35) -> 367 | BL36: =SUM(BL5:BL35) -> 470 | BM36: =SUM(BM5:BM35) -> 566 | BN36: =SUM(BN5:BN35) -> 579 | BO36: =SUM(BO5:BO35) -> 0 | BQ36: =BQ5 -> 420 | BR36: =SUM(BR5:BR35) -> 2800162 | BS36: =+BQ36+BR36 -> 2800582 | BT36: =SUM(BT5:BT35) -> 2796174 | BU36: =+BQ36+BR36-BT36 -> 4408 | BW36: =SUM(BW5:BW35) -> 2800162 | BX36: =BX35 -> 0 | BY36: =BY35 -> 4408
B37: #DIV/0! | D37: =AVERAGE(D5:D35) -> 3.2962963 | E37: =AVERAGE(E5:E35) -> 2.5714286 | F37: =AVERAGE(F5:F35) -> 13.107143 | G37: =AVERAGE(G5:G35) -> #DIV/0! | H37: =AVERAGE(H5:H35) -> 7 | I37: =AVERAGE(I5:I35) -> 3.3333333 | J37: =AVERAGE(J5:J35) -> #DIV/0! | K37: =AVERAGE(K5:K35) -> 4.2592593 | ... R37: =AVERAGE(R5:R35) -> 56217.613 | S37: #DIV/0! | U37: =AVERAGE(U5:U35) -> 1.7692308 | V37: =AVERAGE(V5:V35) -> 1.3157895 | W37: =AVERAGE(W5:W35) -> 4.5357143 | X37: =AVERAGE(X5:X35) -> #DIV/0! | Y37: =AVERAGE(Y5:Y35) -> 2.0714286 | Z37: =AVERAGE(Z5:Z35) -> 3.9333333 | AA37: =AVERAGE(AA5:AA35) -> 6 | AB37: =AVERAGE(AB5:AB35) -> 5.45 | ... AG37: =AVERAGE(AG5:AG35) -> 19770.871 | AJ37: #DIV/0! | AM37: =AVERAGE(AM5:AM35) -> 2.7037037 | AN37: =AVERAGE(AN5:AN35) -> 1.7272727 | AO37: =AVERAGE(AO5:AO35) -> 7.6428571 | AP37: =AVERAGE(AP5:AP35) -> #DIV/0! | AQ37: =AVERAGE(AQ5:AQ35) -> 4.6470588 | AR37: =AVERAGE(AR5:AR35) -> 5.2857143 | AS37: =AVERAGE(AS5:AS35) -> 0 | AT37: =AVERAGE(AT5:AT35) -> 6.2173913 | ... AY37: =AVERAGE(AY5:AY35) -> 29361.226 | BB37: =BB36/12 -> 3.75 | BD37: =AVERAGE(BD5:BD35) -> 6.7096774 | BE37: =AVERAGE(BE5:BE35) -> 4.3548387 | BF37: =AVERAGE(BF5:BF35) -> 22.83871 | BG37: =AVERAGE(BG5:BG35) -> 0 | BH37: =AVERAGE(BH5:BH35) -> 6.6451613 | BI37: =AVERAGE(BI5:BI35) -> 5.9032258 | BJ37: =AVERAGE(BJ5:BJ35) -> 0.19354839 | BK37: =AVERAGE(BK5:BK35) -> 11.83871 | ... BO37: =AVERAGE(BO5:BO35) -> 0 | BR37: =BR36/27 -> 103709.7 | BT37: HOLD BILL | BU37: =R36+AI36+BA36 -> 0
P38: =P36/12 -> 106422.25 | AG38: =AG36/12 -> 51074.75 | AY38: =AY36/12 -> 75849.833 | BD38: . | BR38: . | BT38: CASH | BU38: =+BU36-BU37 -> 4408
BT40: 140860 | BX40: =279597 -> 279597
BT41: 402947 | BX41: =236640 -> 236640
Q42: BAKERY | BT42: =BT41+BT40-BU36 -> 539399 | BX42: =BX41+BX40 -> 516237
Q43: M.BO
Q44: TOTAL | R44: =SUM(R42:R43) -> 0

Sheet AMOUNT UPDATE
A1: UPDATE LEDGER AMOUNT (BAKERY)
A3: SR. | B3: SUPPLIER NAME | C3: LAST MONTH CREDIT | D3: CURRENT MONTH CREDIT | E3: CURRENT MONTH DEBIT | F3: AMOUNT PAID | G3: CASH/ CHEQUE | H3: BALANCE
A4: 1 | B4: GMSA LPG | D4: =SUMIF(PURCHASE!$C$3:$C$233,'AMOUNT UPDATE'!B4:B10,PURCHASE!$I$3:$I$233) -> 97610 | E4: =SUMIF(PURCHASE!$C$3:$C$233,'AMOUNT UPDATE'!B4:B10,PURCHASE!$J$3:$J$233) -> 0 | F4: =SUMIF(EXPENSES!$K$3:$K$925,SUPPLIERS,EXPENSES!$F$3:$F$925) -> 97610 | H4: =F4+E4+-D4+C4+G4 -> 0
A5: =1+A4 -> 2 | B5: AT-TAHUR LIMITED | D5: =SUMIF(PURCHASE!$C$3:$C$506,'AMOUNT UPDATE'!B5:B30,PURCHASE!$I$3:$I$506) -> 0 | E5: =SUMIF(PURCHASE!$C$3:$C$506,'AMOUNT UPDATE'!B5:B30,PURCHASE!$J$3:$J$506) -> 0 | F5: =SUMIF(EXPENSES!$K$3:$K$925,SUPPLIERS,EXPENSES!$F$3:$F$925) -> 0 | H5: =F5+E5+-D5+C5+G5 -> 0
A6: =1+A5 -> 3 | B6: VENUS FOODS | D6: =SUMIF(PURCHASE!$C$3:$C$506,'AMOUNT UPDATE'!B6:B31,PURCHASE!$I$3:$I$506) -> 0 | E6: =SUMIF(PURCHASE!$C$3:$C$506,'AMOUNT UPDATE'!B6:B31,PURCHASE!$J$3:$J$506) -> 0 | F6: =SUMIF(EXPENSES!$K$3:$K$925,SUPPLIERS,EXPENSES!$F$3:$F$925) -> 0 | H6: =F6+E6+-D6+C6+G6 -> 0
A7: =1+A6 -> 4 | B7: METRO | D7: =SUMIF(PURCHASE!$C$3:$C$506,'AMOUNT UPDATE'!B7:B50,PURCHASE!$I$3:$I$506) -> 0 | E7: =SUMIF(PURCHASE!$C$3:$C$506,'AMOUNT UPDATE'!B7:B50,PURCHASE!$J$3:$J$506) -> 0 | F7: =SUMIF(EXPENSES!$K$3:$K$925,SUPPLIERS,EXPENSES!$F$3:$F$925) -> 0 | H7: =F7+E7+-D7+C7+G7 -> 0
A8: =1+A7 -> 5 | B8: NESTLE | D8: =SUMIF(PURCHASE!$C$3:$C$506,'AMOUNT UPDATE'!B8:B51,PURCHASE!$I$3:$I$506) -> 74000 | E8: =SUMIF(PURCHASE!$C$3:$C$506,'AMOUNT UPDATE'!B8:B51,PURCHASE!$J$3:$J$506) -> 0 | F8: =SUMIF(EXPENSES!$K$3:$K$925,SUPPLIERS,EXPENSES!$F$3:$F$925) -> 74000 | H8: =F8+E8+-D8+C8+G8 -> 0
A9: =1+A8 -> 6 | B9: PUNJAB DRAY FRUIT | D9: =SUMIF(PURCHASE!$C$3:$C$506,'AMOUNT UPDATE'!B4:B19,PURCHASE!$I$3:$I$506) -> 0 | E9: =SUMIF(PURCHASE!$C$3:$C$506,'AMOUNT UPDATE'!B4:B19,PURCHASE!$J$3:$J$506) -> 0 | F9: =SUMIF(EXPENSES!$K$3:$K$925,SUPPLIERS,EXPENSES!$F$3:$F$925) -> 0 | H9: =F9+E9+-D9+C9+G9 -> 0
A10: =1+A9 -> 7 | B10: K.E.H | D10: =SUMIF(PURCHASE!$C$3:$C$506,'AMOUNT UPDATE'!B10:B27,PURCHASE!$I$3:$I$506) -> 0 | E10: =SUMIF(PURCHASE!$C$3:$C$506,'AMOUNT UPDATE'!B10:B27,PURCHASE!$J$3:$J$506) -> 0 | F10: =SUMIF(EXPENSES!$K$3:$K$925,SUPPLIERS,EXPENSES!$F$3:$F$925) -> 0 | H10: =F10+E10+-D10+C10+G10 -> 0
A11: =1+A10 -> 8 | B11: LOCAL MARKET | D11: =SUMIF(PURCHASE!$C$3:$C$506,'AMOUNT UPDATE'!B11:B57,PURCHASE!$I$3:$I$506) -> 114069 | E11: =SUMIF(PURCHASE!$C$3:$C$506,'AMOUNT UPDATE'!B11:B28,PURCHASE!$J$3:$J$506) -> 0 | F11: =SUMIF(EXPENSES!$K$3:$K$925,SUPPLIERS,EXPENSES!$F$3:$F$925) -> 114069 | H11: =F11+E11+-D11+C11+G11 -> 0
A12: =1+A11 -> 9 | B12: ELAHE EGGS TRADER | D12: =SUMIF(PURCHASE!$C$3:$C$506,'AMOUNT UPDATE'!B12:B58,PURCHASE!$I$3:$I$506) -> 120100 | E12: =SUMIF(PURCHASE!$C$3:$C$506,'AMOUNT UPDATE'!B12:B58,PURCHASE!$J$3:$J$506) -> 0 | F12: =SUMIF(EXPENSES!$K$3:$K$925,SUPPLIERS,EXPENSES!$F$3:$F$925) -> 120100 | H12: =F12+E12+-D12+C12+G12 -> 0
A13: =1+A12 -> 10 | B13: SULTANI PRINTING | D13: =SUMIF(PURCHASE!$C$3:$C$506,'AMOUNT UPDATE'!B13:B59,PURCHASE!$I$3:$I$506) -> 63000 | E13: =SUMIF(PURCHASE!$C$3:$C$506,'AMOUNT UPDATE'!B13:B59,PURCHASE!$J$3:$J$506) -> 0 | F13: =SUMIF(EXPENSES!$K$3:$K$925,SUPPLIERS,EXPENSES!$F$3:$F$925) -> 63000 | H13: =F13+E13+-D13+C13+G13 -> 0
A14: =1+A13 -> 11 | B14: AR PRINTERS | D14: =SUMIF(PURCHASE!$C$3:$C$506,'AMOUNT UPDATE'!B14:B60,PURCHASE!$I$3:$I$506) -> 0 | E14: =SUMIF(PURCHASE!$C$3:$C$506,'AMOUNT UPDATE'!B14:B60,PURCHASE!$J$3:$J$506) -> 0 | F14: =SUMIF(EXPENSES!$K$3:$K$925,SUPPLIERS,EXPENSES!$F$3:$F$925) -> 0 | H14: =F14+E14+-D14+C14+G14 -> 0
A15: =1+A14 -> 12 | B15: BAKERZ SOLUTIONS | D15: =SUMIF(PURCHASE!$C$3:$C$506,'AMOUNT UPDATE'!B15:B61,PURCHASE!$I$3:$I$506) -> 14005 | E15: =SUMIF(PURCHASE!$C$3:$C$506,'AMOUNT UPDATE'!B15:B61,PURCHASE!$J$3:$J$506) -> 0 | F15: =SUMIF(EXPENSES!$K$3:$K$925,SUPPLIERS,EXPENSES!$F$3:$F$925) -> 14005 | H15: =F15+E15+-D15+C15+G15 -> 0
A16: =1+A15 -> 13 | B16: NAFEES FLOURE | D16: =SUMIF(PURCHASE!$C$3:$C$506,'AMOUNT UPDATE'!B16:B62,PURCHASE!$I$3:$I$506) -> 0 | E16: =SUMIF(PURCHASE!$C$3:$C$506,'AMOUNT UPDATE'!B16:B62,PURCHASE!$J$3:$J$506) -> 0 | F16: =SUMIF(EXPENSES!$K$3:$K$925,SUPPLIERS,EXPENSES!$F$3:$F$925) -> 0 | H16: =F16+E16+-D16+C16+G16 -> 0
A17: =1+A16 -> 14 | B17: MIAN SHOUKAT TRADERS | D17: =SUMIF(PURCHASE!$C$3:$C$506,'AMOUNT UPDATE'!B17:B63,PURCHASE!$I$3:$I$506) -> 700800 | E17: =SUMIF(PURCHASE!$C$3:$C$506,'AMOUNT UPDATE'!B17:B63,PURCHASE!$J$3:$J$506) -> 0 | F17: =SUMIF(EXPENSES!$K$3:$K$925,SUPPLIERS,EXPENSES!$F$3:$F$925) -> 700800 | H17: =F17+E17+-D17+C17+G17 -> 0
A18: =1+A17 -> 15 | B18: S.N TRADERS | D18: =SUMIF(PURCHASE!$C$3:$C$506,'AMOUNT UPDATE'!B18:B59,PURCHASE!$I$3:$I$506) -> 177739.38 | E18: =SUMIF(PURCHASE!$C$3:$C$506,'AMOUNT UPDATE'!B18:B59,PURCHASE!$J$3:$J$506) -> 0 | F18: =SUMIF(EXPENSES!$K$3:$K$925,SUPPLIERS,EXPENSES!$F$3:$F$925) -> 177739 | H18: =F18+E18+-D18+C18+G18 -> -0.37652036
A19: =1+A18 -> 16 | B19: HAFFIZ MAHMOOD | D19: =SUMIF(PURCHASE!$C$3:$C$506,'AMOUNT UPDATE'!B19:B59,PURCHASE!$I$3:$I$506) -> 151700 | E19: =SUMIF(PURCHASE!$C$3:$C$506,'AMOUNT UPDATE'!B19:B59,PURCHASE!$J$3:$J$506) -> 0 | F19: =SUMIF(EXPENSES!$K$3:$K$925,SUPPLIERS,EXPENSES!$F$3:$F$925) -> 151700 | H19: =F19+E19+-D19+C19+G19 -> 0
A20: 17 | B20: AZIZ TRADERS(LINER) | D20: =SUMIF(PURCHASE!$C$3:$C$506,'AMOUNT UPDATE'!B20:B60,PURCHASE!$I$3:$I$506) -> 0 | E20: =SUMIF(PURCHASE!$C$3:$C$506,'AMOUNT UPDATE'!B20:B60,PURCHASE!$J$3:$J$506) -> 0 | F20: =SUMIF(EXPENSES!$K$3:$K$925,B5:B27,EXPENSES!$F$3:$F$925) -> 0 | H20: =F20+E20+-D20+C20+G20 -> 0
A21: 18 | B21: THE CHEFS LOUNGE | D21: =SUMIF(PURCHASE!$C$3:$C$506,'AMOUNT UPDATE'!B21:B60,PURCHASE!$I$3:$I$506) -> 0 | E21: =SUMIF(PURCHASE!$C$3:$C$506,'AMOUNT UPDATE'!B21:B60,PURCHASE!$J$3:$J$506) -> 0 | F21: =SUMIF(EXPENSES!$K$3:$K$925,B4:B27,EXPENSES!$F$3:$F$925) -> 0 | H21: =F21+E21+-D21+C21+G21 -> 0
A22: 19 | D22: =SUMIF(PURCHASE!$C$3:$C$506,'AMOUNT UPDATE'!B22:B61,PURCHASE!$I$3:$I$506) -> 0 | E22: =SUMIF(PURCHASE!$C$3:$C$506,'AMOUNT UPDATE'!B22:B61,PURCHASE!$J$3:$J$506) -> 0 | F22: =SUMIF(EXPENSES!$K$3:$K$925,B5:B28,EXPENSES!$F$3:$F$925) -> 0 | H22: =F22+E22+-D22+C22+G22 -> 0
A23: 19 | D23: =SUMIF(PURCHASE!$C$3:$C$506,'AMOUNT UPDATE'!B23:B62,PURCHASE!$I$3:$I$506) -> 0 | E23: =SUMIF(PURCHASE!$C$3:$C$506,'AMOUNT UPDATE'!B23:B62,PURCHASE!$J$3:$J$506) -> 0 | F23: =SUMIF(EXPENSES!$K$3:$K$925,B6:B29,EXPENSES!$F$3:$F$925) -> 0 | H23: =F23+E23+-D23+C23+G23 -> 0
A24: 20 | D24: =SUMIF(PURCHASE!$C$3:$C$506,'AMOUNT UPDATE'!B24:B63,PURCHASE!$I$3:$I$506) -> 0 | E24: =SUMIF(PURCHASE!$C$3:$C$506,'AMOUNT UPDATE'!B24:B63,PURCHASE!$J$3:$J$506) -> 0 | F24: =SUMIF(EXPENSES!$K$3:$K$925,B7:B30,EXPENSES!$F$3:$F$925) -> 0 | H24: =F24+E24+-D24+C24+G24 -> 0
A25: 21 | D25: =SUMIF(PURCHASE!$C$3:$C$506,'AMOUNT UPDATE'!B25:B64,PURCHASE!$I$3:$I$506) -> 0 | E25: =SUMIF(PURCHASE!$C$3:$C$506,'AMOUNT UPDATE'!B25:B64,PURCHASE!$J$3:$J$506) -> 0 | F25: =SUMIF(EXPENSES!$K$3:$K$925,B8:B31,EXPENSES!$F$3:$F$925) -> 0 | H25: =F25+E25+-D25+C25+G25 -> 0
A26: 22 | D26: =SUMIF(PURCHASE!$C$3:$C$506,'AMOUNT UPDATE'!B26:B65,PURCHASE!$I$3:$I$506) -> 0 | E26: =SUMIF(PURCHASE!$C$3:$C$506,'AMOUNT UPDATE'!B26:B65,PURCHASE!$J$3:$J$506) -> 0 | F26: =SUMIF(EXPENSES!$K$3:$K$925,B9:B32,EXPENSES!$F$3:$F$925) -> 0 | H26: =F26+E26+-D26+C26+G26 -> 0
A27: 23 | D27: =SUMIF(PURCHASE!$C$3:$C$506,'AMOUNT UPDATE'!B27:B60,PURCHASE!$I$3:$I$506) -> 0 | E27: =SUMIF(PURCHASE!$C$3:$C$506,'AMOUNT UPDATE'!B27:B66,PURCHASE!$J$3:$J$506) -> 0 | F27: =SUMIF(EXPENSES!$K$3:$K$925,B5:B28,EXPENSES!$F$3:$F$925) -> 0 | H27: =F27+E27+-D27+C27+G27 -> 0
B28: CREDIT PAYMENTS | C28: =SUM(C4:C19) -> 0 | F28: 0 | H28: =SUM(H4:H27) -> -0.37652036
K31: =236640-403947 -> -167307

Sheet PAY ROLL
A1: .
A2: HIRING | E2: Job Nature | G2: BASIC SALARY DETAIL | Q2: DUTY DETAIL | AW2: BASIC | BA2: ADVANCE DEDUCTIION | BD2: SALARY DETAIL | BG2: L.T ADVANCE DETAIL
A3: Hiring Date | B3: SR# | C3: Name | D3: Designation | E3: FT/PT | F3: HOURS | G3: MONTHLY SALARY | H3: PER DAY SALARY | I3: PER HOUR SALARY | J3: 44652 | K3: 44653 | L3: 44654 | M3: 44655 | N3: 44656 | O3: 44657 | P3: 44658 | Q3: 1ST WEEK | R3: 44659 | S3: 44660 | T3: 44661 | U3: 44662 | V3: 44663 | W3: 44664 | X3: 44665 | Y3: 2ND WEEK | Z3: 44666 | AA3: 44667 | AB3: 44668 | AC3: 44669 | AD3: 44670 | AE3: 44671 | AF3: 44672 | AG3: 3RD WEEK | AH3: 44673 | AI3: 44674 | AJ3: 44675 | AK3: 44676 | AL3: 44677 | AM3: 44678 | AN3: 44679 | AO3: 4TH WEEK | AP3: 44680 | AQ3: 44681 | AR3: 44682 | AS3: 5TH WEEK | AT3: TOTAL DAYS | AU3: HOURS | AV3: Late | AW3: SALARY AMOUNT | AX3: BONUS | AY3: Phone Load | AZ3: GROSS SALARY | BA3: (Deduction of LT Loan) | BB3: LT loan Paid | BC3: (Advance) | BD3: NET SALARY | BE3: PAID SALARY | BF3: DIFF | BG3: P.M Balance | BH3: Current Blance | BI3: REMARKS
A4: FSD TEAM
B5: 1 | C5: HAMZA B/H | D5: B.H | E5: FT | F5: 9 | G5: 110000 | H5: =+G5/26 -> 4230.7692 | I5: =+H5/F5 -> 470.08547 | J5: 1 | K5: 1 | L5: 1 | M5: 1 | N5: 1 | O5: 1 | P5: 1 | AT5: 26 | AW5: =(AT5*H5)+(AU5*H5)-(AV5*H5) -> 110000 | AZ5: =+AY5+AX5+AW5 -> 110000 | BC5: 30000 | BD5: =AZ5-BA5+BB5-BC5 -> 80000 | BF5: =BE5-BD5 -> -80000
B6: 2 | C6: HAMMAD | D6: HR | E6: FT | F6: 9 | G6: 25000 | H6: =G6/26 -> 961.53846 | I6: =+H6/F6 -> 106.83761 | J6: 1 | K6: 1 | L6: 1 | M6: OFF | N6: 1 | O6: 1 | P6: 1 | AT6: 26 | AW6: =(AT6*H6)+(AU6*H6)-(AV6*H6) -> 25000 | AZ6: =+AY6+AX6+AW6 -> 25000 | BC6: 2249 | BD6: =AZ6-BA6+BB6-BC6 -> 22751 | BF6: =BE6-BD6 -> -22751 | BH6: 0
B7: 3 | C7: IKRAM CHEF | D7: CHEF | E7: FT | F7: 9 | G7: 59000 | H7: =+G7/26 -> 2269.2308 | I7: =+H7/F7 -> 252.13675 | J7: 1 | K7: 1 | L7: 1 | M7: 1 | N7: 1 | O7: 1 | P7: 1 | AT7: 26 | AW7: =(AT7*H7)+(AU7*H7)-(AV7*H7) -> 59000 | AZ7: =+AY7+AX7+AW7 -> 59000 | BC7: 25240 | BD7: =AZ7-BA7+BB7-BC7 -> 33760 | BF7: =BE7-BD7 -> -33760
B8: 4 | C8: SAFDAR | D8: HELPER | E8: FT | F8: 9 | G8: 32000 | H8: =+G8/26 -> 1230.7692 | I8: =+H8/F8 -> 136.75214 | J8: 1 | K8: 1 | L8: 1 | M8: 1 | N8: 1 | O8: 1 | P8: 1 | AT8: 26 | AW8: =(AT8*H8)+(AU8*I8)-(AV8*H8) -> 32000 | AZ8: =+AY8+AX8+AW8 -> 32000 | BC8: 3000 | BD8: =AZ8-BA8+BB8-BC8 -> 29000 | BF8: =+BE8-BD8 -> -29000 | BH8: =BG8+BB8-BA8 -> 0
A9: 45184 | B9: 5 | C9: ASMAT | D9: HELPER | E9: FT | F9: 9 | G9: 32000 | H9: =+G9/26 -> 1230.7692 | I9: =+H9/F9 -> 136.75214 | J9: 1 | K9: 1 | L9: 1 | M9: 1 | N9: 1 | O9: 1 | P9: 1 | AT9: 26 | AW9: =(AT9*H9)+(AU9*H9)-(AV9*H9) -> 32000 | AZ9: =+AY9+AX9+AW9 -> 32000 | BC9: 10000 | BD9: =AZ9-BA9+BB9-BC9 -> 22000 | BF9: =+BE9-BD9 -> -22000 | BH9: =BG9+BB9-BA9 -> 0
A10: 45190 | B10: 6 | C10: KHURAM AHSAN | D10: HELPER | E10: FT | F10: 9 | G10: 34500 | H10: =+G10/26 -> 1326.9231 | I10: =+H10/F10 -> 147.4359 | J10: 1 | K10: 1 | L10: 1 | M10: 1 | N10: 1 | O10: 1 | AT10: 26 | AW10: =(AT10*H10)+(AU10*H10)-(AV10*H10) -> 34500 | AZ10: =+AY10+AX10+AW10 -> 34500 | BC10: 5000 | BD10: =AZ10-BA10+BB10-BC10 -> 29500 | BF10: =+BE10-BD10 -> -29500 | BH10: =BG10+BB10-BA10 -> 0
B11: 7 | C11: SAJAD | D11: ASSITANT | E11: FT | F11: 9 | G11: 45000 | H11: =+G11/26 -> 1730.7692 | I11: =+H11/F11 -> 192.30769 | J11: 1 | K11: 1 | L11: 1 | M11: 1 | N11: 1 | O11: 1 | P11: 1 | AT11: 26 | AW11: =(AT11*H11)+(AU11*H11)-(AV11*H11) -> 45000 | AZ11: =+AY11+AX11+AW11 -> 45000 | BC11: 30000 | BD11: =AZ11-BA11+BB11-BC11 -> 15000 | BF11: =+BE11-BD11 -> -15000 | BH11: =BG11+BB11-BA11 -> 0
B12: 8 | C12: SABIR ALI | D12: HELPER | E12: FT | F12: 9 | G12: 41500 | H12: =+G12/26 -> 1596.1538 | I12: =+H12/F12 -> 177.35043 | J12: 1 | K12: 1 | L12: 1 | M12: 1 | N12: 1 | O12: 1 | P12: 1 | AT12: 26 | AW12: =(AT12*H12)+(AU12*H12)-(AV12*H12) -> 41500 | AZ12: =+AY12+AX12+AW12 -> 41500 | BD12: =AZ12-BA12+BB12-BC12 -> 41500 | BF12: =+BE12-BD12 -> -41500 | BH12: =BG12+BB12-BA12 -> 0
H13: =+G13/26 -> 0 | I13: =+H13/F13 -> #DIV/0! | AT13: =AS13+AO13+AG13+Y13+Q13 -> 0 | AW13: =(AT13*H13)+(AU13*H13)-(AV13*H13) -> 0 | AZ13: =+AY13+AX13+AW13 -> 0 | BD13: =AZ13-BA13+BB13-BC13 -> 0 | BF13: =+BE13-BD13 -> 0 | BH13: =BG13+BB13-BA13 -> 0
A14: LAHORE | B14: 1 | C14: ASGAR SENIOR | D14: 1ST ASSISTANT | E14: FT | F14: 9 | H14: =+G14/26 -> 0 | I14: =+H14/F14 -> 0 | J14: 1 | K14: 1 | L14: 1 | M14: 1 | N14: 1 | O14: 1 | P14: OFF | AT14: =AS14+AO14+AG14+Y14+Q14 -> 0 | AW14: =(AT14*H14)+(AU14*H14)-(AV14*H14) -> 0 | AZ14: =+AY14+AX14+AW14 -> 0 | BD14: =AZ14-BA14+BB14-BC14 -> 0 | BF14: =+BE14-BD14 -> 0
A15: LHR TEAM | AT15: =AS15+AO15+AG15+Y15+Q15 -> 0 | AW15: =(AT15*H15)+(AU15*H15)-(AV15*H15) -> 0 | AZ15: =+AY15+AX15+AW15 -> 0 | BD15: =AZ15-BA15+BB15-BC15 -> 0 | BF15: =+BE15-BD15 -> 0 | BH15: =BG15+BB15-BA15 -> 0
A16: LAHORE | B16: 2 | C16: WAQAS | D16: HELPER | E16: FT | F16: 9 | H16: =+G16/26 -> 0 | I16: =+H16/F16 -> 0 | J16: 1 | K16: 1 | L16: 1 | M16: 1 | N16: 1 | O16: 1 | P16: 1 | AT16: =AS16+AO16+AG16+Y16+Q16 -> 0 | AW16: =(AT16*H16)+(AU16*H16)-(AV16*H16) -> 0 | AZ16: =+AY16+AX16+AW16 -> 0 | BD16: =AZ16-BA16+BB16-BC16 -> 0 | BF16: =+BE16-BD16 -> 0
A17: LAHORE | B17: 3 | C17: SOHAIL TARIQ | D17: HELPER | E17: FT | F17: 9 | H17: =+G17/26 -> 0 | I17: =+H17/F17 -> 0 | J17: 1 | K17: 1 | L17: 1 | M17: 1 | N17: 1 | O17: 1 | P17: 1 | AT17: =AS17+AO17+AG17+Y17+Q17 -> 0 | AW17: =(AT17*H17)+(AU17*H17)-(AV17*H17) -> 0 | AZ17: =+AY17+AX17+AW17 -> 0 | BD17: =AZ17-BA17+BB17-BC17 -> 0 | BF17: =+BE17-BD17 -> 0
A18: LAHORE | B18: 4 | C18: SALEEM | D18: HELPER | E18: FT | F18: 9 | H18: =+G18/26 -> 0 | I18: =+H18/F18 -> 0 | J18: 1 | K18: 1 | L18: 1 | M18: 1 | N18: 1 | O18: 1 | P18: 1 | AT18: =AS18+AO18+AG18+Y18+Q18 -> 0 | AW18: =(AT18*H18)+(AU18*H18)-(AV18*H18) -> 0 | AZ18: =+AY18+AX18+AW18 -> 0 | BD18: =AZ18-BA18+BB18-BC18 -> 0 | BF18: =+BE18-BD18 -> 0
A19: LAHORE | C19: IRFAN | D19: HELPER | E19: FT | F19: 9 | H19: =+G19/26 -> 0 | I19: =+H19/F19 -> 0 | J19: 1 | K19: 1 | L19: 1 | M19: 1 | N19: 1 | O19: 1 | AT19: =AS19+AO19+AG19+Y19+Q19 -> 0 | AW19: =(AT19*H19)+(AU19*H19)-(AV19*H19) -> 0 | AZ19: =+AY19+AX19+AW19 -> 0 | BD19: =AZ19-BA19+BB19-BC19 -> 0 | BF19: =+BE19-BD19 -> 0
B20: 9 | D20: CLEANER | E20: FT | F20: 9 | G20: 0 | H20: =G20/26 -> 0 | I20: =+H20/F20 -> 0 | AT20: =AS20+AO20+AG20+Y20+Q20 -> 0 | AW20: =(AT20*H20)+(AU20*H20)-(AV20*H20) -> 0 | AZ20: =+AY20+AX20+AW20 -> 0 | BD20: =AZ20-BA20+BB20-BC20 -> 0 | BF20: =+BE20-BD20 -> 0 | BH20: 0
B21: 9 | C21: HAMAIYON | D21: DRIVER | E21: FT | F21: 9 | G21: 34500 | H21: =+G21/26 -> 1326.9231 | I21: =+H21/F21 -> 147.4359 | J21: 1 | K21: 1 | L21: 1 | M21: 1 | N21: 1 | O21: 1 | P21: 1 | AT21: 26 | AW21: =(AT21*H21)+(AU21*H21)-(AV21*H21) -> 34500 | AZ21: =+AY21+AX21+AW21 -> 34500 | BC21: 21844 | BD21: =AZ21-BA21+BB21-BC21 -> 12656 | BF21: =+BE21-BD21 -> -12656 | BH21: 0
G22: =SUM(G5:G21) -> 413500 | Q22: =SUM(Q5:Q21) -> 0 | Y22: =SUM(Y5:Y21) -> 0 | AG22: =SUM(AG5:AG21) -> 0 | AO22: =SUM(AO5:AO21) -> 0 | AS22: =SUM(AS5:AS21) -> 0 | AT22: =SUM(AT5:AT21) -> 234 | AU22: =SUM(AU5:AU21) -> 0 | AV22: =SUM(AV5:AV21) -> 0 | AW22: =SUM(AW5:AW21) -> 413500 | AX22: =SUM(AX5:AX21) -> 0 | AY22: =SUM(AY5:AY21) -> 0 | AZ22: =SUM(AZ5:AZ21) -> 413500 | ... BH22: =SUM(BH5:BH21) -> 0

Sheet ENDING AND MAKE
C2: 44774 | I2: =1+C2 -> 44775 | O2: =1+I2 -> 44776 | U2: =1+O2 -> 44777 | AA2: =1+U2 -> 44778 | AG2: =1+AA2 -> 44779 | AM2: =1+AG2 -> 44780 | AS2: =1+AM2 -> 44781 | AY2: =1+AS2 -> 44782 | BE2: =1+AY2 -> 44783 | BK2: =1+BE2 -> 44784 | BQ2: =1+BK2 -> 44785 | BW2: =1+BQ2 -> 44786 | CC2: =1+BW2 -> 44787 | CI2: =1+CC2 -> 44788 | CO2: =1+CI2 -> 44789 | CU2: =1+CO2 -> 44790 | DA2: =1+CU2 -> 44791 | DG2: =1+DA2 -> 44792 | DM2: =1+DG2 -> 44793 | DS2: =1+DM2 -> 44794 | DY2: =1+DS2 -> 44795 | EE2: =1+DY2 -> 44796 | EK2: =1+EE2 -> 44797 | EQ2: =1+EK2 -> 44798 | EW2: =1+EQ2 -> 44799 | FC2: =1+EW2 -> 44800 | FI2: =1+FC2 -> 44801 | FO2: =1+FI2 -> 44802 | FU2: =1+FO2 -> 44803 | GA2: =1+FU2 -> 44804 | GG2: TOTAL | GM2: GRAND
C3: OP. | D3: ADD | E3: SENT | F3: IDL | G3: ACT. | H3: VAR. | I3: OP. | J3: ADD | K3: SENT | L3: IDL | M3: ACT. | N3: VAR. | O3: OP. | P3: ADD | Q3: SENT | R3: IDL | S3: ACT. | T3: VAR. | U3: OP. | V3: ADD | W3: SENT | X3: IDL | Y3: ACT. | Z3: VAR. | AA3: OP. | AB3: ADD | AC3: SENT | AD3: IDL | AE3: ACT. | AF3: VAR. | AG3: OP. | AH3: ADD | AI3: SENT | AJ3: IDL | AK3: ACT. | AL3: VAR. | AM3: OP. | AN3: ADD | AO3: SENT | AP3: IDL | AQ3: ACT. | AR3: VAR. | AS3: OP. | AT3: ADD | AU3: SENT | AV3: IDL | AW3: ACT. | AX3: VAR. | AY3: OP. | AZ3: ADD | BA3: SENT | BB3: IDL | BC3: ACT. | BD3: VAR. | BE3: OP. | BF3: ADD | BG3: SENT | BH3: IDL | BI3: ACT. | BJ3: VAR. | BK3: OP. | BL3: ADD | BM3: SENT | BN3: IDL | BO3: ACT. | BP3: VAR. | BQ3: OP. | BR3: ADD | BS3: SENT | BT3: IDL | BU3: ACT. | BV3: VAR. | BW3: OP. | BX3: ADD | BY3: SENT | BZ3: IDL | CA3: ACT. | CB3: VAR. | CC3: OP. | CD3: ADD | CE3: SENT | CF3: IDL | CG3: ACT. | CH3: VAR. | CI3: OP. | CJ3: ADD | CK3: SENT | CL3: IDL | CM3: ACT. | CN3: VAR. | CO3: OP. | CP3: ADD | CQ3: SENT | CR3: IDL | CS3: ACT. | CT3: VAR. | CU3: OP. | CV3: ADD | CW3: SENT | CX3: IDL | CY3: ACT. | CZ3: VAR. | DA3: OP. | DB3: ADD | DC3: SENT | DD3: IDL | DE3: ACT. | DF3: VAR. | DG3: OP. | DH3: ADD | DI3: SENT | DJ3: IDL | DK3: ACT. | DL3: VAR. | DM3: OP. | DN3: ADD | DO3: SENT | DP3: IDL | DQ3: ACT. | DR3: VAR. | DS3: OP. | DT3: ADD | DU3: SENT | DV3: IDL | DW3: ACT. | DX3: VAR. | DY3: OP. | DZ3: ADD | EA3: SENT | EB3: IDL | EC3: ACT. | ED3: VAR. | EE3: OP. | EF3: ADD | EG3: SENT | EH3: IDL | EI3: ACT. | EJ3: VAR. | EK3: OP. | EL3: ADD | EM3: SENT | EN3: IDL | EO3: ACT. | EP3: VAR. | EQ3: OP. | ER3: ADD | ES3: SENT | ET3: IDL | EU3: ACT. | EV3: VAR. | EW3: OP. | EX3: ADD | EY3: SENT | EZ3: IDL | FA3: ACT. | FB3: VAR. | FC3: OP. | FD3: ADD | FE3: SENT | FF3: IDL | FG3: ACT. | FH3: VAR. | FI3: OP. | FJ3: ADD | FK3: SENT | FL3: IDL | FM3: ACT. | FN3: VAR. | FO3: OP. | FP3: ADD | FQ3: SENT | FR3: IDL | FS3: ACT. | FT3: VAR. | FU3: OP. | FV3: ADD | FW3: SENT | FX3: IDL | FY3: ACT. | FZ3: VAR. | GA3: OP. | GB3: ADD | GC3: SENT | GD3: IDL | GE3: ACT. | GF3: VAR. | GG3: OP. | GH3: ADD | GI3: SENT | GJ3: IDL | GK3: ACT. | GL3: VAR. | GM3: TOTAL
B4: CAKE | D4: MAK | G4: END | J4: MAK | M4: END | P4: MAK | S4: END | V4: MAK | Y4: END | AB4: MAK | AE4: END | AH4: MAK | AK4: END | AN4: MAK | AQ4: END | AT4: MAK | AW4: END | AZ4: MAK | BC4: END | BF4: MAK | BI4: END | BL4: MAK | BO4: END | BR4: MAK | BU4: END | BX4: MAK | CA4: END | CD4: MAK | CG4: END | CJ4: MAK | CM4: END | CP4: MAK | CS4: END | CV4: MAK | CY4: END | DB4: MAK | DE4: END | DH4: MAK | DK4: END | DN4: MAK | DQ4: END | DT4: MAK | DW4: END | DZ4: MAK | EC4: END | EF4: MAK | EI4: END | EL4: MAK | EO4: END | ER4: MAK | EU4: END | EX4: MAK | FA4: END | FD4: MAK | FG4: END | FJ4: MAK | FM4: END | FP4: MAK | FS4: END | FV4: MAK | FY4: END | GB4: MAK | GE4: END | GH4: MAK | GK4: END
B5: KIT KAT | E5: ='ORDER SENT'!H5 -> 0 | F5: =+C5+D5-E5 -> 0 | H5: =SUM(C5:G5) -> 0 | I5: =G5 | K5: ='ORDER SENT'!N5 -> 0 | L5: =+I5+J5-K5 -> 0 | N5: =SUM(I5:M5) -> 0 | O5: =M5 | Q5: ='ORDER SENT'!T5 -> 0 | R5: =+O5+P5-Q5 -> 0 | T5: =SUM(O5:S5) -> 0 | U5: =S5 | W5: ='ORDER SENT'!Z5 -> 0 | X5: =+U5+V5-W5 -> 0 | Z5: =SUM(U5:Y5) -> 0 | AA5: =Y5 | AC5: ='ORDER SENT'!AF5 -> 0 | AD5: =+AA5+AB5-AC5 -> 0 | AF5: =SUM(AA5:AE5) -> 0 | AG5: =AE5 | AI5: ='ORDER SENT'!AL5 -> 0 | AJ5: =+AG5+AH5-AI5 -> 0 | AL5: =SUM(AG5:AK5) -> 0 | AM5: =AK5 | AO5: ='ORDER SENT'!AR5 -> 0 | AP5: =+AM5+AN5-AO5 -> 0 | AR5: =SUM(AM5:AQ5) -> 0 | AS5: =AQ5 | AU5: ='ORDER SENT'!AX5 -> 0 | AV5: =+AS5+AT5-AU5 -> 0 | AX5: =SUM(AS5:AW5) -> 0 | AY5: =AW5 | BA5: ='ORDER SENT'!BD5 -> 0 | BB5: =+AY5+AZ5-BA5 -> 0 | BD5: =SUM(AY5:BC5) -> 0 | BE5: =BC5 | BG5: ='ORDER SENT'!BJ5 -> 0 | BH5: =+BE5+BF5-BG5 -> 0 | BJ5: =SUM(BE5:BI5) -> 0 | BK5: =BI5 | BM5: ='ORDER SENT'!BP5 -> 0 | BN5: =+BK5+BL5-BM5 -> 0 | BP5: =SUM(BK5:BO5) -> 0 | BQ5: =BO5 | BS5: ='ORDER SENT'!BV5 -> 0 | BT5: =+BQ5+BR5-BS5 -> 0 | BV5: =SUM(BQ5:BU5) -> 0 | BW5: =BU5 | BY5: ='ORDER SENT'!CB5 -> 0 | BZ5: =+BW5+BX5-BY5 -> 0 | CB5: =SUM(BW5:CA5) -> 0 | CC5: =CA5 | CE5: ='ORDER SENT'!CH5 -> 0 | CF5: =+CC5+CD5-CE5 -> 0 | CH5: =SUM(CC5:CG5) -> 0 | CI5: =CG5 | CK5: ='ORDER SENT'!CN5 -> 0 | CL5: =+CI5+CJ5-CK5 -> 0 | CN5: =SUM(CI5:CM5) -> 0 | CO5: =CM5 | CQ5: ='ORDER SENT'!CT5 -> 0 | CR5: =+CO5+CP5-CQ5 -> 0 | CT5: =SUM(CO5:CS5) -> 0 | CU5: =CS5 | CW5: ='ORDER SENT'!CZ5 -> 0 | CX5: =+CU5+CV5-CW5 -> 0 | CZ5: =SUM(CU5:CY5) -> 0 | DA5: =CY5 | DC5: ='ORDER SENT'!DF5 -> 0 | DD5: =+DA5+DB5-DC5 -> 0 | DF5: =SUM(DA5:DE5) -> 0 | DG5: =DE5 | DI5: ='ORDER SENT'!DL5 -> 0 | DJ5: =+DG5+DH5-DI5 -> 0 | DL5: =SUM(DG5:DK5) -> 0 | DM5: =DK5 | DO5: ='ORDER SENT'!DR5 -> 0 | DP5: =+DM5+DN5-DO5 -> 0 | DR5: =SUM(DM5:DQ5) -> 0 | DS5: =DQ5 | DU5: ='ORDER SENT'!DX5 -> 0 | DV5: =+DS5+DT5-DU5 -> 0 | DX5: =SUM(DS5:DW5) -> 0 | DY5: =DW5 | EA5: ='ORDER SENT'!ED5 -> 0 | EB5: =+DY5+DZ5-EA5 -> 0 | ED5: =SUM(DY5:EC5) -> 0 | EE5: =EC5 | EG5: ='ORDER SENT'!EJ5 -> 0 | EH5: =+EE5+EF5-EG5 -> 0 | EJ5: =SUM(EE5:EI5) -> 0 | EK5: =EI5 | EM5: ='ORDER SENT'!EP5 -> 0 | EN5: =+EK5+EL5-EM5 -> 0 | EP5: =SUM(EK5:EO5) -> 0 | EQ5: =EO5 | ES5: ='ORDER SENT'!EV5 -> 0 | ET5: =+EQ5+ER5-ES5 -> 0 | EV5: =SUM(EQ5:EU5) -> 0 | EW5: =EU5 | EY5: ='ORDER SENT'!FB5 -> 0 | EZ5: =+EW5+EX5-EY5 -> 0 | FB5: =SUM(EW5:FA5) -> 0 | FC5: =FA5 | FE5: ='ORDER SENT'!FH5 -> 0 | FF5: =+FC5+FD5-FE5 -> 0 | FH5: =SUM(FC5:FG5) -> 0 | FI5: =FG5 | FK5: ='ORDER SENT'!FN5 -> 0 | FL5: =+FI5+FJ5-FK5 -> 0 | FN5: =SUM(FI5:FM5) -> 0 | FO5: =FM5 | FQ5: ='ORDER SENT'!FT5 -> 0 | FR5: =+FO5+FP5-FQ5 -> 0 | FT5: =SUM(FO5:FS5) -> 0 | FU5: =FS5 | FW5: ='ORDER SENT'!FZ5 -> 0 | FX5: =+FU5+FV5-FW5 -> 0 | FZ5: =SUM(FU5:FY5) -> 0 | GA5: =FY5 | GC5: ='ORDER SENT'!GF5 -> 0 | GD5: =+GA5+GB5-GC5 -> 0 | GF5: =SUM(GA5:GE5) -> 0 | GG5: =C5 | GH5: =+GB5+FV5+FP5+FJ5+FD5+EX5+ER5+EL5+EF5+DZ5+DT5+DN5+DH5+DB5+CV5+CP5+CJ5+CD5+BX5+BR5+BL5+BF5++AZ5+AT5+AN5+AH5+AB5+V5+P5+J5+D5 -> 0 | GI5: =+GC5+FW5+FQ5+FK5+FE5+EY5+ES5+EM5+EG5+EA5+DU5+DO5+DI5+DC5+CW5+CQ5+CK5+CE5+BY5+BS5+BM5+BG5++BA5+AU5+AO5+AI5+AC5+W5+Q5+K5+E5 -> 0 | GJ5: =+GD5+FX5+FR5+FL5+FF5+EZ5+ET5+EN5+EH5+EB5+DV5+DP5+DJ5+DD5+CX5+CR5+CL5+CF5+BZ5+BT5+BN5+BH5++BB5+AV5+AP5+AJ5+AD5+X5+R5+L5+F5 -> 0 | GK5: =+GE5+FY5+FS5+FM5+FG5+FA5+EU5+EO5+EI5+EC5+DW5+DQ5+DK5+DE5+CY5+CS5+CM5+CG5+CA5+BU5+BO5+BI5++BC5+AW5+AQ5+AK5+AE5+Y5+S5+M5+G5 -> 0 | GL5: =+GF5+FZ5+FT5+FN5+FH5+FB5+EV5+EP5+EJ5+ED5+DX5+DR5+DL5+DF5+CZ5+CT5+CN5+CH5+CB5+BV5+BP5+BJ5++BD5+AX5+AR5+AL5+AF5+Z5+T5+N5+H5 -> 0 | GM5: =+GK5+GJ5+GI5+GH5+GG5 -> 0
B6: ALMOND | E6: ='ORDER SENT'!H6 -> 0 | F6: =+C6+D6-E6 -> 0 | H6: =SUM(C6:G6) -> 0 | I6: =G6 | K6: ='ORDER SENT'!N6 -> 0 | L6: =+I6+J6-K6 -> 0 | N6: =SUM(I6:M6) -> 0 | O6: =M6 | Q6: ='ORDER SENT'!T6 -> 0 | R6: =+O6+P6-Q6 -> 0 | T6: =SUM(O6:S6) -> 0 | U6: =S6 | W6: ='ORDER SENT'!Z6 -> 0 | X6: =+U6+V6-W6 -> 0 | Z6: =SUM(U6:Y6) -> 0 | AA6: =Y6 | AC6: ='ORDER SENT'!AF6 -> 0 | AD6: =+AA6+AB6-AC6 -> 0 | AF6: =SUM(AA6:AE6) -> 0 | AG6: =AE6 | AI6: ='ORDER SENT'!AL6 -> 0 | AJ6: =+AG6+AH6-AI6 -> 0 | AL6: =SUM(AG6:AK6) -> 0 | AM6: =AK6 | AO6: ='ORDER SENT'!AR6 -> 0 | AP6: =+AM6+AN6-AO6 -> 0 | AR6: =SUM(AM6:AQ6) -> 0 | AS6: =AQ6 | AU6: ='ORDER SENT'!AX6 -> 0 | AV6: =+AS6+AT6-AU6 -> 0 | AX6: =SUM(AS6:AW6) -> 0 | AY6: =AW6 | BA6: ='ORDER SENT'!BD6 -> 0 | BB6: =+AY6+AZ6-BA6 -> 0 | BD6: =SUM(AY6:BC6) -> 0 | BE6: =BC6 | BG6: ='ORDER SENT'!BJ6 -> 0 | BH6: =+BE6+BF6-BG6 -> 0 | BJ6: =SUM(BE6:BI6) -> 0 | BK6: =BI6 | BM6: ='ORDER SENT'!BP6 -> 0 | BN6: =+BK6+BL6-BM6 -> 0 | BP6: =SUM(BK6:BO6) -> 0 | BQ6: =BO6 | BS6: ='ORDER SENT'!BV6 -> 0 | BT6: =+BQ6+BR6-BS6 -> 0 | BV6: =SUM(BQ6:BU6) -> 0 | BW6: =BU6 | BY6: ='ORDER SENT'!CB6 -> 0 | BZ6: =+BW6+BX6-BY6 -> 0 | CB6: =SUM(BW6:CA6) -> 0 | CC6: =CA6 | CE6: ='ORDER SENT'!CH6 -> 0 | CF6: =+CC6+CD6-CE6 -> 0 | CH6: =SUM(CC6:CG6) -> 0 | CI6: =CG6 | CK6: ='ORDER SENT'!CN6 -> 0 | CL6: =+CI6+CJ6-CK6 -> 0 | CN6: =SUM(CI6:CM6) -> 0 | CO6: =CM6 | CQ6: ='ORDER SENT'!CT6 -> 0 | CR6: =+CO6+CP6-CQ6 -> 0 | CT6: =SUM(CO6:CS6) -> 0 | CU6: =CS6 | CW6: ='ORDER SENT'!CZ6 -> 0 | CX6: =+CU6+CV6-CW6 -> 0 | CZ6: =SUM(CU6:CY6) -> 0 | DA6: =CY6 | DC6: ='ORDER SENT'!DF6 -> 0 | DD6: =+DA6+DB6-DC6 -> 0 | DF6: =SUM(DA6:DE6) -> 0 | DG6: =DE6 | DI6: ='ORDER SENT'!DL6 -> 0 | DJ6: =+DG6+DH6-DI6 -> 0 | DL6: =SUM(DG6:DK6) -> 0 | DM6: =DK6 | DO6: ='ORDER SENT'!DR6 -> 0 | DP6: =+DM6+DN6-DO6 -> 0 | DR6: =SUM(DM6:DQ6) -> 0 | DS6: =DQ6 | DU6: ='ORDER SENT'!DX6 -> 0 | DV6: =+DS6+DT6-DU6 -> 0 | DX6: =SUM(DS6:DW6) -> 0 | DY6: =DW6 | EA6: ='ORDER SENT'!ED6 -> 0 | EB6: =+DY6+DZ6-EA6 -> 0 | ED6: =SUM(DY6:EC6) -> 0 | EE6: =EC6 | EG6: ='ORDER SENT'!EJ6 -> 0 | EH6: =+EE6+EF6-EG6 -> 0 | EJ6: =SUM(EE6:EI6) -> 0 | EK6: =EI6 | EM6: ='ORDER SENT'!EP6 -> 0 | EN6: =+EK6+EL6-EM6 -> 0 | EP6: =SUM(EK6:EO6) -> 0 | EQ6: =EO6 | ES6: ='ORDER SENT'!EV6 -> 0 | ET6: =+EQ6+ER6-ES6 -> 0 | EV6: =SUM(EQ6:EU6) -> 0 | EW6: =EU6 | EY6: ='ORDER SENT'!FB6 -> 0 | EZ6: =+EW6+EX6-EY6 -> 0 | FB6: =SUM(EW6:FA6) -> 0 | FC6: =FA6 | FE6: ='ORDER SENT'!FH6 -> 0 | FF6: =+FC6+FD6-FE6 -> 0 | FH6: =SUM(FC6:FG6) -> 0 | FI6: =FG6 | FK6: ='ORDER SENT'!FN6 -> 0 | FL6: =+FI6+FJ6-FK6 -> 0 | FN6: =SUM(FI6:FM6) -> 0 | FO6: =FM6 | FQ6: ='ORDER SENT'!FT6 -> 0 | FR6: =+FO6+FP6-FQ6 -> 0 | FT6: =SUM(FO6:FS6) -> 0 | FU6: =FS6 | FW6: ='ORDER SENT'!FZ6 -> 0 | FX6: =+FU6+FV6-FW6 -> 0 | FZ6: =SUM(FU6:FY6) -> 0 | GA6: =FY6 | GC6: ='ORDER SENT'!GF6 -> 0 | GD6: =+GA6+GB6-GC6 -> 0 | GF6: =SUM(GA6:GE6) -> 0 | GG6: =C6 | GH6: =+GB6+FV6+FP6+FJ6+FD6+EX6+ER6+EL6+EF6+DZ6+DT6+DN6+DH6+DB6+CV6+CP6+CJ6+CD6+BX6+BR6+BL6+BF6++AZ6+AT6+AN6+AH6+AB6+V6+P6+J6+D6 -> 0 | GI6: =+GC6+FW6+FQ6+FK6+FE6+EY6+ES6+EM6+EG6+EA6+DU6+DO6+DI6+DC6+CW6+CQ6+CK6+CE6+BY6+BS6+BM6+BG6++BA6+AU6+AO6+AI6+AC6+W6+Q6+K6+E6 -> 0 | GJ6: =+GD6+FX6+FR6+FL6+FF6+EZ6+ET6+EN6+EH6+EB6+DV6+DP6+DJ6+DD6+CX6+CR6+CL6+CF6+BZ6+BT6+BN6+BH6++BB6+AV6+AP6+AJ6+AD6+X6+R6+L6+F6 -> 0 | GK6: =+GE6+FY6+FS6+FM6+FG6+FA6+EU6+EO6+EI6+EC6+DW6+DQ6+DK6+DE6+CY6+CS6+CM6+CG6+CA6+BU6+BO6+BI6++BC6+AW6+AQ6+AK6+AE6+Y6+S6+M6+G6 -> 0 | GL6: =+GF6+FZ6+FT6+FN6+FH6+FB6+EV6+EP6+EJ6+ED6+DX6+DR6+DL6+DF6+CZ6+CT6+CN6+CH6+CB6+BV6+BP6+BJ6++BD6+AX6+AR6+AL6+AF6+Z6+T6+N6+H6 -> 0 | GM6: =+GK6+GJ6+GI6+GH6+GG6 -> 0
B7: COFFEE KAJU | E7: ='ORDER SENT'!H7 -> 0 | F7: =+C7+D7-E7 -> 0 | H7: =SUM(C7:G7) -> 0 | I7: =G7 | K7: ='ORDER SENT'!N7 -> 0 | L7: =+I7+J7-K7 -> 0 | N7: =SUM(I7:M7) -> 0 | O7: =M7 | Q7: ='ORDER SENT'!T7 -> 0 | R7: =+O7+P7-Q7 -> 0 | T7: =SUM(O7:S7) -> 0 | U7: =S7 | W7: ='ORDER SENT'!Z7 -> 0 | X7: =+U7+V7-W7 -> 0 | Z7: =SUM(U7:Y7) -> 0 | AA7: =Y7 | AC7: ='ORDER SENT'!AF7 -> 0 | AD7: =+AA7+AB7-AC7 -> 0 | AF7: =SUM(AA7:AE7) -> 0 | AG7: =AE7 | AI7: ='ORDER SENT'!AL7 -> 0 | AJ7: =+AG7+AH7-AI7 -> 0 | AL7: =SUM(AG7:AK7) -> 0 | AM7: =AK7 | AO7: ='ORDER SENT'!AR7 -> 0 | AP7: =+AM7+AN7-AO7 -> 0 | AR7: =SUM(AM7:AQ7) -> 0 | AS7: =AQ7 | AU7: ='ORDER SENT'!AX7 -> 0 | AV7: =+AS7+AT7-AU7 -> 0 | AX7: =SUM(AS7:AW7) -> 0 | AY7: =AW7 | BA7: ='ORDER SENT'!BD7 -> 0 | BB7: =+AY7+AZ7-BA7 -> 0 | BD7: =SUM(AY7:BC7) -> 0 | BE7: =BC7 | BG7: ='ORDER SENT'!BJ7 -> 0 | BH7: =+BE7+BF7-BG7 -> 0 | BJ7: =SUM(BE7:BI7) -> 0 | BK7: =BI7 | BM7: ='ORDER SENT'!BP7 -> 0 | BN7: =+BK7+BL7-BM7 -> 0 | BP7: =SUM(BK7:BO7) -> 0 | BQ7: =BO7 | BS7: ='ORDER SENT'!BV7 -> 0 | BT7: =+BQ7+BR7-BS7 -> 0 | BV7: =SUM(BQ7:BU7) -> 0 | BW7: =BU7 | BY7: ='ORDER SENT'!CB7 -> 0 | BZ7: =+BW7+BX7-BY7 -> 0 | CB7: =SUM(BW7:CA7) -> 0 | CC7: =CA7 | CE7: ='ORDER SENT'!CH7 -> 0 | CF7: =+CC7+CD7-CE7 -> 0 | CH7: =SUM(CC7:CG7) -> 0 | CI7: =CG7 | CK7: ='ORDER SENT'!CN7 -> 0 | CL7: =+CI7+CJ7-CK7 -> 0 | CN7: =SUM(CI7:CM7) -> 0 | CO7: =CM7 | CQ7: ='ORDER SENT'!CT7 -> 0 | CR7: =+CO7+CP7-CQ7 -> 0 | CT7: =SUM(CO7:CS7) -> 0 | CU7: =CS7 | CW7: ='ORDER SENT'!CZ7 -> 0 | CX7: =+CU7+CV7-CW7 -> 0 | CZ7: =SUM(CU7:CY7) -> 0 | DA7: =CY7 | DC7: ='ORDER SENT'!DF7 -> 0 | DD7: =+DA7+DB7-DC7 -> 0 | DF7: =SUM(DA7:DE7) -> 0 | DG7: =DE7 | DI7: ='ORDER SENT'!DL7 -> 0 | DJ7: =+DG7+DH7-DI7 -> 0 | DL7: =SUM(DG7:DK7) -> 0 | DM7: =DK7 | DO7: ='ORDER SENT'!DR7 -> 0 | DP7: =+DM7+DN7-DO7 -> 0 | DR7: =SUM(DM7:DQ7) -> 0 | DS7: =DQ7 | DU7: ='ORDER SENT'!DX7 -> 0 | DV7: =+DS7+DT7-DU7 -> 0 | DX7: =SUM(DS7:DW7) -> 0 | DY7: =DW7 | EA7: ='ORDER SENT'!ED7 -> 0 | EB7: =+DY7+DZ7-EA7 -> 0 | ED7: =SUM(DY7:EC7) -> 0 | EE7: =EC7 | EG7: ='ORDER SENT'!EJ7 -> 0 | EH7: =+EE7+EF7-EG7 -> 0 | EJ7: =SUM(EE7:EI7) -> 0 | EK7: =EI7 | EM7: ='ORDER SENT'!EP7 -> 0 | EN7: =+EK7+EL7-EM7 -> 0 | EP7: =SUM(EK7:EO7) -> 0 | EQ7: =EO7 | ES7: ='ORDER SENT'!EV7 -> 0 | ET7: =+EQ7+ER7-ES7 -> 0 | EV7: =SUM(EQ7:EU7) -> 0 | EW7: =EU7 | EY7: ='ORDER SENT'!FB7 -> 0 | EZ7: =+EW7+EX7-EY7 -> 0 | FB7: =SUM(EW7:FA7) -> 0 | FC7: =FA7 | FE7: ='ORDER SENT'!FH7 -> 0 | FF7: =+FC7+FD7-FE7 -> 0 | FH7: =SUM(FC7:FG7) -> 0 | FI7: =FG7 | FK7: ='ORDER SENT'!FN7 -> 0 | FL7: =+FI7+FJ7-FK7 -> 0 | FN7: =SUM(FI7:FM7) -> 0 | FO7: =FM7 | FQ7: ='ORDER SENT'!FT7 -> 0 | FR7: =+FO7+FP7-FQ7 -> 0 | FT7: =SUM(FO7:FS7) -> 0 | FU7: =FS7 | FW7: ='ORDER SENT'!FZ7 -> 0 | FX7: =+FU7+FV7-FW7 -> 0 | FZ7: =SUM(FU7:FY7) -> 0 | GA7: =FY7 | GC7: ='ORDER SENT'!GF7 -> 0 | GD7: =+GA7+GB7-GC7 -> 0 | GF7: =SUM(GA7:GE7) -> 0 | GG7: =C7 | GH7: =+GB7+FV7+FP7+FJ7+FD7+EX7+ER7+EL7+EF7+DZ7+DT7+DN7+DH7+DB7+CV7+CP7+CJ7+CD7+BX7+BR7+BL7+BF7++AZ7+AT7+AN7+AH7+AB7+V7+P7+J7+D7 -> 0 | GI7: =+GC7+FW7+FQ7+FK7+FE7+EY7+ES7+EM7+EG7+EA7+DU7+DO7+DI7+DC7+CW7+CQ7+CK7+CE7+BY7+BS7+BM7+BG7++BA7+AU7+AO7+AI7+AC7+W7+Q7+K7+E7 -> 0 | GJ7: =+GD7+FX7+FR7+FL7+FF7+EZ7+ET7+EN7+EH7+EB7+DV7+DP7+DJ7+DD7+CX7+CR7+CL7+CF7+BZ7+BT7+BN7+BH7++BB7+AV7+AP7+AJ7+AD7+X7+R7+L7+F7 -> 0 | GK7: =+GE7+FY7+FS7+FM7+FG7+FA7+EU7+EO7+EI7+EC7+DW7+DQ7+DK7+DE7+CY7+CS7+CM7+CG7+CA7+BU7+BO7+BI7++BC7+AW7+AQ7+AK7+AE7+Y7+S7+M7+G7 -> 0 | GL7: =+GF7+FZ7+FT7+FN7+FH7+FB7+EV7+EP7+EJ7+ED7+DX7+DR7+DL7+DF7+CZ7+CT7+CN7+CH7+CB7+BV7+BP7+BJ7++BD7+AX7+AR7+AL7+AF7+Z7+T7+N7+H7 -> 0 | GM7: =+GK7+GJ7+GI7+GH7+GG7 -> 0
B8: BOUNTY | E8: ='ORDER SENT'!H8 -> 0 | F8: =+C8+D8-E8 -> 0 | H8: =SUM(C8:G8) -> 0 | I8: =G8 | K8: ='ORDER SENT'!N8 -> 0 | L8: =+I8+J8-K8 -> 0 | N8: =SUM(I8:M8) -> 0 | O8: =M8 | Q8: ='ORDER SENT'!T8 -> 0 | R8: =+O8+P8-Q8 -> 0 | T8: =SUM(O8:S8) -> 0 | U8: =S8 | W8: ='ORDER SENT'!Z8 -> 0 | X8: =+U8+V8-W8 -> 0 | Z8: =SUM(U8:Y8) -> 0 | AA8: =Y8 | AC8: ='ORDER SENT'!AF8 -> 0 | AD8: =+AA8+AB8-AC8 -> 0 | AF8: =SUM(AA8:AE8) -> 0 | AG8: =AE8 | AI8: ='ORDER SENT'!AL8 -> 0 | AJ8: =+AG8+AH8-AI8 -> 0 | AL8: =SUM(AG8:AK8) -> 0 | AM8: =AK8 | AO8: ='ORDER SENT'!AR8 -> 0 | AP8: =+AM8+AN8-AO8 -> 0 | AR8: =SUM(AM8:AQ8) -> 0 | AS8: =AQ8 | AU8: ='ORDER SENT'!AX8 -> 0 | AV8: =+AS8+AT8-AU8 -> 0 | AX8: =SUM(AS8:AW8) -> 0 | AY8: =AW8 | BA8: ='ORDER SENT'!BD8 -> 0 | BB8: =+AY8+AZ8-BA8 -> 0 | BD8: =SUM(AY8:BC8) -> 0 | BE8: =BC8 | BG8: ='ORDER SENT'!BJ8 -> 0 | BH8: =+BE8+BF8-BG8 -> 0 | BJ8: =SUM(BE8:BI8) -> 0 | BK8: =BI8 | BM8: ='ORDER SENT'!BP8 -> 0 | BN8: =+BK8+BL8-BM8 -> 0 | BP8: =SUM(BK8:BO8) -> 0 | BQ8: =BO8 | BS8: ='ORDER SENT'!BV8 -> 0 | BT8: =+BQ8+BR8-BS8 -> 0 | BV8: =SUM(BQ8:BU8) -> 0 | BW8: =BU8 | BY8: ='ORDER SENT'!CB8 -> 0 | BZ8: =+BW8+BX8-BY8 -> 0 | CB8: =SUM(BW8:CA8) -> 0 | CC8: =CA8 | CE8: ='ORDER SENT'!CH8 -> 0 | CF8: =+CC8+CD8-CE8 -> 0 | CH8: =SUM(CC8:CG8) -> 0 | CI8: =CG8 | CK8: ='ORDER SENT'!CN8 -> 0 | CL8: =+CI8+CJ8-CK8 -> 0 | CN8: =SUM(CI8:CM8) -> 0 | CO8: =CM8 | CQ8: ='ORDER SENT'!CT8 -> 0 | CR8: =+CO8+CP8-CQ8 -> 0 | CT8: =SUM(CO8:CS8) -> 0 | CU8: =CS8 | CW8: ='ORDER SENT'!CZ8 -> 0 | CX8: =+CU8+CV8-CW8 -> 0 | CZ8: =SUM(CU8:CY8) -> 0 | DA8: =CY8 | DC8: ='ORDER SENT'!DF8 -> 0 | DD8: =+DA8+DB8-DC8 -> 0 | DF8: =SUM(DA8:DE8) -> 0 | DG8: =DE8 | DI8: ='ORDER SENT'!DL8 -> 0 | DJ8: =+DG8+DH8-DI8 -> 0 | DL8: =SUM(DG8:DK8) -> 0 | DM8: =DK8 | DO8: ='ORDER SENT'!DR8 -> 0 | DP8: =+DM8+DN8-DO8 -> 0 | DR8: =SUM(DM8:DQ8) -> 0 | DS8: =DQ8 | DU8: ='ORDER SENT'!DX8 -> 0 | DV8: =+DS8+DT8-DU8 -> 0 | DX8: =SUM(DS8:DW8) -> 0 | DY8: =DW8 | EA8: ='ORDER SENT'!ED8 -> 0 | EB8: =+DY8+DZ8-EA8 -> 0 | ED8: =SUM(DY8:EC8) -> 0 | EE8: =EC8 | EG8: ='ORDER SENT'!EJ8 -> 0 | EH8: =+EE8+EF8-EG8 -> 0 | EJ8: =SUM(EE8:EI8) -> 0 | EK8: =EI8 | EM8: ='ORDER SENT'!EP8 -> 0 | EN8: =+EK8+EL8-EM8 -> 0 | EP8: =SUM(EK8:EO8) -> 0 | EQ8: =EO8 | ES8: ='ORDER SENT'!EV8 -> 0 | ET8: =+EQ8+ER8-ES8 -> 0 | EV8: =SUM(EQ8:EU8) -> 0 | EW8: =EU8 | EY8: ='ORDER SENT'!FB8 -> 0 | EZ8: =+EW8+EX8-EY8 -> 0 | FB8: =SUM(EW8:FA8) -> 0 | FC8: =FA8 | FE8: ='ORDER SENT'!FH8 -> 0 | FF8: =+FC8+FD8-FE8 -> 0 | FH8: =SUM(FC8:FG8) -> 0 | FI8: =FG8 | FK8: ='ORDER SENT'!FN8 -> 0 | FL8: =+FI8+FJ8-FK8 -> 0 | FN8: =SUM(FI8:FM8) -> 0 | FO8: =FM8 | FQ8: ='ORDER SENT'!FT8 -> 0 | FR8: =+FO8+FP8-FQ8 -> 0 | FT8: =SUM(FO8:FS8) -> 0 | FU8: =FS8 | FW8: ='ORDER SENT'!FZ8 -> 0 | FX8: =+FU8+FV8-FW8 -> 0 | FZ8: =SUM(FU8:FY8) -> 0 | GA8: =FY8 | GC8: ='ORDER SENT'!GF8 -> 0 | GD8: =+GA8+GB8-GC8 -> 0 | GF8: =SUM(GA8:GE8) -> 0 | GG8: =C8 | GH8: =+GB8+FV8+FP8+FJ8+FD8+EX8+ER8+EL8+EF8+DZ8+DT8+DN8+DH8+DB8+CV8+CP8+CJ8+CD8+BX8+BR8+BL8+BF8++AZ8+AT8+AN8+AH8+AB8+V8+P8+J8+D8 -> 0 | GI8: =+GC8+FW8+FQ8+FK8+FE8+EY8+ES8+EM8+EG8+EA8+DU8+DO8+DI8+DC8+CW8+CQ8+CK8+CE8+BY8+BS8+BM8+BG8++BA8+AU8+AO8+AI8+AC8+W8+Q8+K8+E8 -> 0 | GJ8: =+GD8+FX8+FR8+FL8+FF8+EZ8+ET8+EN8+EH8+EB8+DV8+DP8+DJ8+DD8+CX8+CR8+CL8+CF8+BZ8+BT8+BN8+BH8++BB8+AV8+AP8+AJ8+AD8+X8+R8+L8+F8 -> 0 | GK8: =+GE8+FY8+FS8+FM8+FG8+FA8+EU8+EO8+EI8+EC8+DW8+DQ8+DK8+DE8+CY8+CS8+CM8+CG8+CA8+BU8+BO8+BI8++BC8+AW8+AQ8+AK8+AE8+Y8+S8+M8+G8 -> 0 | GL8: =+GF8+FZ8+FT8+FN8+FH8+FB8+EV8+EP8+EJ8+ED8+DX8+DR8+DL8+DF8+CZ8+CT8+CN8+CH8+CB8+BV8+BP8+BJ8++BD8+AX8+AR8+AL8+AF8+Z8+T8+N8+H8 -> 0 | GM8: =+GK8+GJ8+GI8+GH8+GG8 -> 0
B9: LOTUS FUDGE | E9: ='ORDER SENT'!H9 -> 0 | F9: =+C9+D9-E9 -> 0 | H9: =SUM(C9:G9) -> 0 | I9: =G9 | K9: ='ORDER SENT'!N9 -> 0 | L9: =+I9+J9-K9 -> 0 | N9: =SUM(I9:M9) -> 0 | O9: =M9 | Q9: ='ORDER SENT'!T9 -> 0 | R9: =+O9+P9-Q9 -> 0 | T9: =SUM(O9:S9) -> 0 | U9: =S9 | W9: ='ORDER SENT'!Z9 -> 0 | X9: =+U9+V9-W9 -> 0 | Z9: =SUM(U9:Y9) -> 0 | AA9: =Y9 | AC9: ='ORDER SENT'!AF9 -> 0 | AD9: =+AA9+AB9-AC9 -> 0 | AF9: =SUM(AA9:AE9) -> 0 | AG9: =AE9 | AI9: ='ORDER SENT'!AL9 -> 0 | AJ9: =+AG9+AH9-AI9 -> 0 | AL9: =SUM(AG9:AK9) -> 0 | AM9: =AK9 | AO9: ='ORDER SENT'!AR9 -> 0 | AP9: =+AM9+AN9-AO9 -> 0 | AR9: =SUM(AM9:AQ9) -> 0 | AS9: =AQ9 | AU9: ='ORDER SENT'!AX9 -> 0 | AV9: =+AS9+AT9-AU9 -> 0 | AX9: =SUM(AS9:AW9) -> 0 | AY9: =AW9 | BA9: ='ORDER SENT'!BD9 -> 0 | BB9: =+AY9+AZ9-BA9 -> 0 | BD9: =SUM(AY9:BC9) -> 0 | BE9: =BC9 | BG9: ='ORDER SENT'!BJ9 -> 0 | BH9: =+BE9+BF9-BG9 -> 0 | BJ9: =SUM(BE9:BI9) -> 0 | BK9: =BI9 | BM9: ='ORDER SENT'!BP9 -> 0 | BN9: =+BK9+BL9-BM9 -> 0 | BP9: =SUM(BK9:BO9) -> 0 | BQ9: =BO9 | BS9: ='ORDER SENT'!BV9 -> 0 | BT9: =+BQ9+BR9-BS9 -> 0 | BV9: =SUM(BQ9:BU9) -> 0 | BW9: =BU9 | BY9: ='ORDER SENT'!CB9 -> 0 | BZ9: =+BW9+BX9-BY9 -> 0 | CB9: =SUM(BW9:CA9) -> 0 | CC9: =CA9 | CE9: ='ORDER SENT'!CH9 -> 0 | CF9: =+CC9+CD9-CE9 -> 0 | CH9: =SUM(CC9:CG9) -> 0 | CI9: =CG9 | CK9: ='ORDER SENT'!CN9 -> 0 | CL9: =+CI9+CJ9-CK9 -> 0 | CN9: =SUM(CI9:CM9) -> 0 | CO9: =CM9 | CQ9: ='ORDER SENT'!CT9 -> 0 | CR9: =+CO9+CP9-CQ9 -> 0 | CT9: =SUM(CO9:CS9) -> 0 | CU9: =CS9 | CW9: ='ORDER SENT'!CZ9 -> 0 | CX9: =+CU9+CV9-CW9 -> 0 | CZ9: =SUM(CU9:CY9) -> 0 | DA9: =CY9 | DC9: ='ORDER SENT'!DF9 -> 0 | DD9: =+DA9+DB9-DC9 -> 0 | DF9: =SUM(DA9:DE9) -> 0 | DG9: =DE9 | DI9: ='ORDER SENT'!DL9 -> 0 | DJ9: =+DG9+DH9-DI9 -> 0 | DL9: =SUM(DG9:DK9) -> 0 | DM9: =DK9 | DO9: ='ORDER SENT'!DR9 -> 0 | DP9: =+DM9+DN9-DO9 -> 0 | DR9: =SUM(DM9:DQ9) -> 0 | DS9: =DQ9 | DU9: ='ORDER SENT'!DX9 -> 0 | DV9: =+DS9+DT9-DU9 -> 0 | DX9: =SUM(DS9:DW9) -> 0 | DY9: =DW9 | EA9: ='ORDER SENT'!ED9 -> 0 | EB9: =+DY9+DZ9-EA9 -> 0 | ED9: =SUM(DY9:EC9) -> 0 | EE9: =EC9 | EG9: ='ORDER SENT'!EJ9 -> 0 | EH9: =+EE9+EF9-EG9 -> 0 | EJ9: =SUM(EE9:EI9) -> 0 | EK9: =EI9 | EM9: ='ORDER SENT'!EP9 -> 0 | EN9: =+EK9+EL9-EM9 -> 0 | EP9: =SUM(EK9:EO9) -> 0 | EQ9: =EO9 | ES9: ='ORDER SENT'!EV9 -> 0 | ET9: =+EQ9+ER9-ES9 -> 0 | EV9: =SUM(EQ9:EU9) -> 0 | EW9: =EU9 | EY9: ='ORDER SENT'!FB9 -> 0 | EZ9: =+EW9+EX9-EY9 -> 0 | FB9: =SUM(EW9:FA9) -> 0 | FC9: =FA9 | FE9: ='ORDER SENT'!FH9 -> 0 | FF9: =+FC9+FD9-FE9 -> 0 | FH9: =SUM(FC9:FG9) -> 0 | FI9: =FG9 | FK9: ='ORDER SENT'!FN9 -> 0 | FL9: =+FI9+FJ9-FK9 -> 0 | FN9: =SUM(FI9:FM9) -> 0 | FO9: =FM9 | FQ9: ='ORDER SENT'!FT9 -> 0 | FR9: =+FO9+FP9-FQ9 -> 0 | FT9: =SUM(FO9:FS9) -> 0 | FU9: =FS9 | FW9: ='ORDER SENT'!FZ9 -> 0 | FX9: =+FU9+FV9-FW9 -> 0 | FZ9: =SUM(FU9:FY9) -> 0 | GA9: =FY9 | GC9: ='ORDER SENT'!GF9 -> 0 | GD9: =+GA9+GB9-GC9 -> 0 | GF9: =SUM(GA9:GE9) -> 0 | GG9: =C9 | GH9: =+GB9+FV9+FP9+FJ9+FD9+EX9+ER9+EL9+EF9+DZ9+DT9+DN9+DH9+DB9+CV9+CP9+CJ9+CD9+BX9+BR9+BL9+BF9++AZ9+AT9+AN9+AH9+AB9+V9+P9+J9+D9 -> 0 | GI9: =+GC9+FW9+FQ9+FK9+FE9+EY9+ES9+EM9+EG9+EA9+DU9+DO9+DI9+DC9+CW9+CQ9+CK9+CE9+BY9+BS9+BM9+BG9++BA9+AU9+AO9+AI9+AC9+W9+Q9+K9+E9 -> 0 | GJ9: =+GD9+FX9+FR9+FL9+FF9+EZ9+ET9+EN9+EH9+EB9+DV9+DP9+DJ9+DD9+CX9+CR9+CL9+CF9+BZ9+BT9+BN9+BH9++BB9+AV9+AP9+AJ9+AD9+X9+R9+L9+F9 -> 0 | GK9: =+GE9+FY9+FS9+FM9+FG9+FA9+EU9+EO9+EI9+EC9+DW9+DQ9+DK9+DE9+CY9+CS9+CM9+CG9+CA9+BU9+BO9+BI9++BC9+AW9+AQ9+AK9+AE9+Y9+S9+M9+G9 -> 0 | GL9: =+GF9+FZ9+FT9+FN9+FH9+FB9+EV9+EP9+EJ9+ED9+DX9+DR9+DL9+DF9+CZ9+CT9+CN9+CH9+CB9+BV9+BP9+BJ9++BD9+AX9+AR9+AL9+AF9+Z9+T9+N9+H9 -> 0 | GM9: =+GK9+GJ9+GI9+GH9+GG9 -> 0
B10: CARAMEL | E10: ='ORDER SENT'!H10 -> 0 | F10: =+C10+D10-E10 -> 0 | H10: =SUM(C10:G10) -> 0 | I10: =G10 | K10: ='ORDER SENT'!N10 -> 0 | L10: =+I10+J10-K10 -> 0 | N10: =SUM(I10:M10) -> 0 | O10: =M10 | Q10: ='ORDER SENT'!T10 -> 0 | R10: =+O10+P10-Q10 -> 0 | T10: =SUM(O10:S10) -> 0 | U10: =S10 | W10: ='ORDER SENT'!Z10 -> 0 | X10: =+U10+V10-W10 -> 0 | Z10: =SUM(U10:Y10) -> 0 | AA10: =Y10 | AC10: ='ORDER SENT'!AF10 -> 0 | AD10: =+AA10+AB10-AC10 -> 0 | AF10: =SUM(AA10:AE10) -> 0 | AG10: =AE10 | AI10: ='ORDER SENT'!AL10 -> 0 | AJ10: =+AG10+AH10-AI10 -> 0 | AL10: =SUM(AG10:AK10) -> 0 | AM10: =AK10 | AO10: ='ORDER SENT'!AR10 -> 0 | AP10: =+AM10+AN10-AO10 -> 0 | AR10: =SUM(AM10:AQ10) -> 0 | AS10: =AQ10 | AU10: ='ORDER SENT'!AX10 -> 0 | AV10: =+AS10+AT10-AU10 -> 0 | AX10: =SUM(AS10:AW10) -> 0 | AY10: =AW10 | BA10: ='ORDER SENT'!BD10 -> 0 | BB10: =+AY10+AZ10-BA10 -> 0 | BD10: =SUM(AY10:BC10) -> 0 | BE10: =BC10 | BG10: ='ORDER SENT'!BJ10 -> 0 | BH10: =+BE10+BF10-BG10 -> 0 | BJ10: =SUM(BE10:BI10) -> 0 | BK10: =BI10 | BM10: ='ORDER SENT'!BP10 -> 0 | BN10: =+BK10+BL10-BM10 -> 0 | BP10: =SUM(BK10:BO10) -> 0 | BQ10: =BO10 | BS10: ='ORDER SENT'!BV10 -> 0 | BT10: =+BQ10+BR10-BS10 -> 0 | BV10: =SUM(BQ10:BU10) -> 0 | BW10: =BU10 | BY10: ='ORDER SENT'!CB10 -> 0 | BZ10: =+BW10+BX10-BY10 -> 0 | CB10: =SUM(BW10:CA10) -> 0 | CC10: =CA10 | CE10: ='ORDER SENT'!CH10 -> 0 | CF10: =+CC10+CD10-CE10 -> 0 | CH10: =SUM(CC10:CG10) -> 0 | CI10: =CG10 | CK10: ='ORDER SENT'!CN10 -> 0 | CL10: =+CI10+CJ10-CK10 -> 0 | CN10: =SUM(CI10:CM10) -> 0 | CO10: =CM10 | CQ10: ='ORDER SENT'!CT10 -> 0 | CR10: =+CO10+CP10-CQ10 -> 0 | CT10: =SUM(CO10:CS10) -> 0 | CU10: =CS10 | CW10: ='ORDER SENT'!CZ10 -> 0 | CX10: =+CU10+CV10-CW10 -> 0 | CZ10: =SUM(CU10:CY10) -> 0 | DA10: =CY10 | DC10: ='ORDER SENT'!DF10 -> 0 | DD10: =+DA10+DB10-DC10 -> 0 | DF10: =SUM(DA10:DE10) -> 0 | DG10: =DE10 | DI10: ='ORDER SENT'!DL10 -> 0 | DJ10: =+DG10+DH10-DI10 -> 0 | DL10: =SUM(DG10:DK10) -> 0 | DM10: =DK10 | DO10: ='ORDER SENT'!DR10 -> 0 | DP10: =+DM10+DN10-DO10 -> 0 | DR10: =SUM(DM10:DQ10) -> 0 | DS10: =DQ10 | DU10: ='ORDER SENT'!DX10 -> 0 | DV10: =+DS10+DT10-DU10 -> 0 | DX10: =SUM(DS10:DW10) -> 0 | DY10: =DW10 | EA10: ='ORDER SENT'!ED10 -> 0 | EB10: =+DY10+DZ10-EA10 -> 0 | ED10: =SUM(DY10:EC10) -> 0 | EE10: =EC10 | EG10: ='ORDER SENT'!EJ10 -> 0 | EH10: =+EE10+EF10-EG10 -> 0 | EJ10: =SUM(EE10:EI10) -> 0 | EK10: =EI10 | EM10: ='ORDER SENT'!EP10 -> 0 | EN10: =+EK10+EL10-EM10 -> 0 | EP10: =SUM(EK10:EO10) -> 0 | EQ10: =EO10 | ES10: ='ORDER SENT'!EV10 -> 0 | ET10: =+EQ10+ER10-ES10 -> 0 | EV10: =SUM(EQ10:EU10) -> 0 | EW10: =EU10 | EY10: ='ORDER SENT'!FB10 -> 0 | EZ10: =+EW10+EX10-EY10 -> 0 | FB10: =SUM(EW10:FA10) -> 0 | FC10: =FA10 | FE10: ='ORDER SENT'!FH10 -> 0 | FF10: =+FC10+FD10-FE10 -> 0 | FH10: =SUM(FC10:FG10) -> 0 | FI10: =FG10 | FK10: ='ORDER SENT'!FN10 -> 0 | FL10: =+FI10+FJ10-FK10 -> 0 | FN10: =SUM(FI10:FM10) -> 0 | FO10: =FM10 | FQ10: ='ORDER SENT'!FT10 -> 0 | FR10: =+FO10+FP10-FQ10 -> 0 | FT10: =SUM(FO10:FS10) -> 0 | FU10: =FS10 | FW10: ='ORDER SENT'!FZ10 -> 0 | FX10: =+FU10+FV10-FW10 -> 0 | FZ10: =SUM(FU10:FY10) -> 0 | GA10: =FY10 | GC10: ='ORDER SENT'!GF10 -> 0 | GD10: =+GA10+GB10-GC10 -> 0 | GF10: =SUM(GA10:GE10) -> 0 | GG10: =C10 | GH10: =+GB10+FV10+FP10+FJ10+FD10+EX10+ER10+EL10+EF10+DZ10+DT10+DN10+DH10+DB10+CV10+CP10+CJ10+CD10+BX10+BR10+BL10+BF10++AZ10+AT10+AN10+AH10+AB10+V10+P10+J10+D10 -> 0 | GI10: =+GC10+FW10+FQ10+FK10+FE10+EY10+ES10+EM10+EG10+EA10+DU10+DO10+DI10+DC10+CW10+CQ10+CK10+CE10+BY10+BS10+BM10+BG10++BA10+AU10+AO10+AI10+AC10+W10+Q10+K10+E10 -> 0 | GJ10: =+GD10+FX10+FR10+FL10+FF10+EZ10+ET10+EN10+EH10+EB10+DV10+DP10+DJ10+DD10+CX10+CR10+CL10+CF10+BZ10+BT10+BN10+BH10++BB10+AV10+AP10+AJ10+AD10+X10+R10+L10+F10 -> 0 | GK10: =+GE10+FY10+FS10+FM10+FG10+FA10+EU10+EO10+EI10+EC10+DW10+DQ10+DK10+DE10+CY10+CS10+CM10+CG10+CA10+BU10+BO10+BI10++BC10+AW10+AQ10+AK10+AE10+Y10+S10+M10+G10 -> 0 | GL10: =+GF10+FZ10+FT10+FN10+FH10+FB10+EV10+EP10+EJ10+ED10+DX10+DR10+DL10+DF10+CZ10+CT10+CN10+CH10+CB10+BV10+BP10+BJ10++BD10+AX10+AR10+AL10+AF10+Z10+T10+N10+H10 -> 0 | GM10: =+GK10+GJ10+GI10+GH10+GG10 -> 0
B11: RED VELVET | E11: ='ORDER SENT'!H11 -> 0 | F11: =+C11+D11-E11 -> 0 | H11: =SUM(C11:G11) -> 0 | I11: =G11 | K11: ='ORDER SENT'!N11 -> 0 | L11: =+I11+J11-K11 -> 0 | N11: =SUM(I11:M11) -> 0 | O11: =M11 | Q11: ='ORDER SENT'!T11 -> 0 | R11: =+O11+P11-Q11 -> 0 | T11: =SUM(O11:S11) -> 0 | U11: =S11 | W11: ='ORDER SENT'!Z11 -> 0 | X11: =+U11+V11-W11 -> 0 | Z11: =SUM(U11:Y11) -> 0 | AA11: =Y11 | AC11: ='ORDER SENT'!AF11 -> 0 | AD11: =+AA11+AB11-AC11 -> 0 | AF11: =SUM(AA11:AE11) -> 0 | AG11: =AE11 | AI11: ='ORDER SENT'!AL11 -> 0 | AJ11: =+AG11+AH11-AI11 -> 0 | AL11: =SUM(AG11:AK11) -> 0 | AM11: =AK11 | AO11: ='ORDER SENT'!AR11 -> 0 | AP11: =+AM11+AN11-AO11 -> 0 | AR11: =SUM(AM11:AQ11) -> 0 | AS11: =AQ11 | AU11: ='ORDER SENT'!AX11 -> 0 | AV11: =+AS11+AT11-AU11 -> 0 | AX11: =SUM(AS11:AW11) -> 0 | AY11: =AW11 | BA11: ='ORDER SENT'!BD11 -> 0 | BB11: =+AY11+AZ11-BA11 -> 0 | BD11: =SUM(AY11:BC11) -> 0 | BE11: =BC11 | BG11: ='ORDER SENT'!BJ11 -> 0 | BH11: =+BE11+BF11-BG11 -> 0 | BJ11: =SUM(BE11:BI11) -> 0 | BK11: =BI11 | BM11: ='ORDER SENT'!BP11 -> 0 | BN11: =+BK11+BL11-BM11 -> 0 | BP11: =SUM(BK11:BO11) -> 0 | BQ11: =BO11 | BS11: ='ORDER SENT'!BV11 -> 0 | BT11: =+BQ11+BR11-BS11 -> 0 | BV11: =SUM(BQ11:BU11) -> 0 | BW11: =BU11 | BY11: ='ORDER SENT'!CB11 -> 0 | BZ11: =+BW11+BX11-BY11 -> 0 | CB11: =SUM(BW11:CA11) -> 0 | CC11: =CA11 | CE11: ='ORDER SENT'!CH11 -> 0 | CF11: =+CC11+CD11-CE11 -> 0 | CH11: =SUM(CC11:CG11) -> 0 | CI11: =CG11 | CK11: ='ORDER SENT'!CN11 -> 0 | CL11: =+CI11+CJ11-CK11 -> 0 | CN11: =SUM(CI11:CM11) -> 0 | CO11: =CM11 | CQ11: ='ORDER SENT'!CT11 -> 0 | CR11: =+CO11+CP11-CQ11 -> 0 | CT11: =SUM(CO11:CS11) -> 0 | CU11: =CS11 | CW11: ='ORDER SENT'!CZ11 -> 0 | CX11: =+CU11+CV11-CW11 -> 0 | CZ11: =SUM(CU11:CY11) -> 0 | DA11: =CY11 | DC11: ='ORDER SENT'!DF11 -> 0 | DD11: =+DA11+DB11-DC11 -> 0 | DF11: =SUM(DA11:DE11) -> 0 | DG11: =DE11 | DI11: ='ORDER SENT'!DL11 -> 0 | DJ11: =+DG11+DH11-DI11 -> 0 | DL11: =SUM(DG11:DK11) -> 0 | DM11: =DK11 | DO11: ='ORDER SENT'!DR11 -> 0 | DP11: =+DM11+DN11-DO11 -> 0 | DR11: =SUM(DM11:DQ11) -> 0 | DS11: =DQ11 | DU11: ='ORDER SENT'!DX11 -> 0 | DV11: =+DS11+DT11-DU11 -> 0 | DX11: =SUM(DS11:DW11) -> 0 | DY11: =DW11 | EA11: ='ORDER SENT'!ED11 -> 0 | EB11: =+DY11+DZ11-EA11 -> 0 | ED11: =SUM(DY11:EC11) -> 0 | EE11: =EC11 | EG11: ='ORDER SENT'!EJ11 -> 0 | EH11: =+EE11+EF11-EG11 -> 0 | EJ11: =SUM(EE11:EI11) -> 0 | EK11: =EI11 | EM11: ='ORDER SENT'!EP11 -> 0 | EN11: =+EK11+EL11-EM11 -> 0 | EP11: =SUM(EK11:EO11) -> 0 | EQ11: =EO11 | ES11: ='ORDER SENT'!EV11 -> 0 | ET11: =+EQ11+ER11-ES11 -> 0 | EV11: =SUM(EQ11:EU11) -> 0 | EW11: =EU11 | EY11: ='ORDER SENT'!FB11 -> 0 | EZ11: =+EW11+EX11-EY11 -> 0 | FB11: =SUM(EW11:FA11) -> 0 | FC11: =FA11 | FE11: ='ORDER SENT'!FH11 -> 0 | FF11: =+FC11+FD11-FE11 -> 0 | FH11: =SUM(FC11:FG11) -> 0 | FI11: =FG11 | FK11: ='ORDER SENT'!FN11 -> 0 | FL11: =+FI11+FJ11-FK11 -> 0 | FN11: =SUM(FI11:FM11) -> 0 | FO11: =FM11 | FQ11: ='ORDER SENT'!FT11 -> 0 | FR11: =+FO11+FP11-FQ11 -> 0 | FT11: =SUM(FO11:FS11) -> 0 | FU11: =FS11 | FW11: ='ORDER SENT'!FZ11 -> 0 | FX11: =+FU11+FV11-FW11 -> 0 | FZ11: =SUM(FU11:FY11) -> 0 | GA11: =FY11 | GC11: ='ORDER SENT'!GF11 -> 0 | GD11: =+GA11+GB11-GC11 -> 0 | GF11: =SUM(GA11:GE11) -> 0 | GG11: =C11 | GH11: =+GB11+FV11+FP11+FJ11+FD11+EX11+ER11+EL11+EF11+DZ11+DT11+DN11+DH11+DB11+CV11+CP11+CJ11+CD11+BX11+BR11+BL11+BF11++AZ11+AT11+AN11+AH11+AB11+V11+P11+J11+D11 -> 0 | GI11: =+GC11+FW11+FQ11+FK11+FE11+EY11+ES11+EM11+EG11+EA11+DU11+DO11+DI11+DC11+CW11+CQ11+CK11+CE11+BY11+BS11+BM11+BG11++BA11+AU11+AO11+AI11+AC11+W11+Q11+K11+E11 -> 0 | GJ11: =+GD11+FX11+FR11+FL11+FF11+EZ11+ET11+EN11+EH11+EB11+DV11+DP11+DJ11+DD11+CX11+CR11+CL11+CF11+BZ11+BT11+BN11+BH11++BB11+AV11+AP11+AJ11+AD11+X11+R11+L11+F11 -> 0 | GK11: =+GE11+FY11+FS11+FM11+FG11+FA11+EU11+EO11+EI11+EC11+DW11+DQ11+DK11+DE11+CY11+CS11+CM11+CG11+CA11+BU11+BO11+BI11++BC11+AW11+AQ11+AK11+AE11+Y11+S11+M11+G11 -> 0 | GL11: =+GF11+FZ11+FT11+FN11+FH11+FB11+EV11+EP11+EJ11+ED11+DX11+DR11+DL11+DF11+CZ11+CT11+CN11+CH11+CB11+BV11+BP11+BJ11++BD11+AX11+AR11+AL11+AF11+Z11+T11+N11+H11 -> 0 | GM11: =+GK11+GJ11+GI11+GH11+GG11 -> 0
B12: FERRARO | E12: ='ORDER SENT'!H12 -> 0 | F12: =+C12+D12-E12 -> 0 | H12: =SUM(C12:G12) -> 0 | I12: =G12 | K12: ='ORDER SENT'!N12 -> 0 | L12: =+I12+J12-K12 -> 0 | N12: =SUM(I12:M12) -> 0 | O12: =M12 | Q12: ='ORDER SENT'!T12 -> 0 | R12: =+O12+P12-Q12 -> 0 | T12: =SUM(O12:S12) -> 0 | U12: =S12 | W12: ='ORDER SENT'!Z12 -> 0 | X12: =+U12+V12-W12 -> 0 | Z12: =SUM(U12:Y12) -> 0 | AA12: =Y12 | AC12: ='ORDER SENT'!AF12 -> 0 | AD12: =+AA12+AB12-AC12 -> 0 | AF12: =SUM(AA12:AE12) -> 0 | AG12: =AE12 | AI12: ='ORDER SENT'!AL12 -> 0 | AJ12: =+AG12+AH12-AI12 -> 0 | AL12: =SUM(AG12:AK12) -> 0 | AM12: =AK12 | AO12: ='ORDER SENT'!AR12 -> 0 | AP12: =+AM12+AN12-AO12 -> 0 | AR12: =SUM(AM12:AQ12) -> 0 | AS12: =AQ12 | AU12: ='ORDER SENT'!AX12 -> 0 | AV12: =+AS12+AT12-AU12 -> 0 | AX12: =SUM(AS12:AW12) -> 0 | AY12: =AW12 | BA12: ='ORDER SENT'!BD12 -> 0 | BB12: =+AY12+AZ12-BA12 -> 0 | BD12: =SUM(AY12:BC12) -> 0 | BE12: =BC12 | BG12: ='ORDER SENT'!BJ12 -> 0 | BH12: =+BE12+BF12-BG12 -> 0 | BJ12: =SUM(BE12:BI12) -> 0 | BK12: =BI12 | BM12: ='ORDER SENT'!BP12 -> 0 | BN12: =+BK12+BL12-BM12 -> 0 | BP12: =SUM(BK12:BO12) -> 0 | BQ12: =BO12 | BS12: ='ORDER SENT'!BV12 -> 0 | BT12: =+BQ12+BR12-BS12 -> 0 | BV12: =SUM(BQ12:BU12) -> 0 | BW12: =BU12 | BY12: ='ORDER SENT'!CB12 -> 0 | BZ12: =+BW12+BX12-BY12 -> 0 | CB12: =SUM(BW12:CA12) -> 0 | CC12: =CA12 | CE12: ='ORDER SENT'!CH12 -> 0 | CF12: =+CC12+CD12-CE12 -> 0 | CH12: =SUM(CC12:CG12) -> 0 | CI12: =CG12 | CK12: ='ORDER SENT'!CN12 -> 0 | CL12: =+CI12+CJ12-CK12 -> 0 | CN12: =SUM(CI12:CM12) -> 0 | CO12: =CM12 | CQ12: ='ORDER SENT'!CT12 -> 0 | CR12: =+CO12+CP12-CQ12 -> 0 | CT12: =SUM(CO12:CS12) -> 0 | CU12: =CS12 | CW12: ='ORDER SENT'!CZ12 -> 0 | CX12: =+CU12+CV12-CW12 -> 0 | CZ12: =SUM(CU12:CY12) -> 0 | DA12: =CY12 | DC12: ='ORDER SENT'!DF12 -> 0 | DD12: =+DA12+DB12-DC12 -> 0 | DF12: =SUM(DA12:DE12) -> 0 | DG12: =DE12 | DI12: ='ORDER SENT'!DL12 -> 0 | DJ12: =+DG12+DH12-DI12 -> 0 | DL12: =SUM(DG12:DK12) -> 0 | DM12: =DK12 | DO12: ='ORDER SENT'!DR12 -> 0 | DP12: =+DM12+DN12-DO12 -> 0 | DR12: =SUM(DM12:DQ12) -> 0 | DS12: =DQ12 | DU12: ='ORDER SENT'!DX12 -> 0 | DV12: =+DS12+DT12-DU12 -> 0 | DX12: =SUM(DS12:DW12) -> 0 | DY12: =DW12 | EA12: ='ORDER SENT'!ED12 -> 0 | EB12: =+DY12+DZ12-EA12 -> 0 | ED12: =SUM(DY12:EC12) -> 0 | EE12: =EC12 | EG12: ='ORDER SENT'!EJ12 -> 0 | EH12: =+EE12+EF12-EG12 -> 0 | EJ12: =SUM(EE12:EI12) -> 0 | EK12: =EI12 | EM12: ='ORDER SENT'!EP12 -> 0 | EN12: =+EK12+EL12-EM12 -> 0 | EP12: =SUM(EK12:EO12) -> 0 | EQ12: =EO12 | ES12: ='ORDER SENT'!EV12 -> 0 | ET12: =+EQ12+ER12-ES12 -> 0 | EV12: =SUM(EQ12:EU12) -> 0 | EW12: =EU12 | EY12: ='ORDER SENT'!FB12 -> 0 | EZ12: =+EW12+EX12-EY12 -> 0 | FB12: =SUM(EW12:FA12) -> 0 | FC12: =FA12 | FE12: ='ORDER SENT'!FH12 -> 0 | FF12: =+FC12+FD12-FE12 -> 0 | FH12: =SUM(FC12:FG12) -> 0 | FI12: =FG12 | FK12: ='ORDER SENT'!FN12 -> 0 | FL12: =+FI12+FJ12-FK12 -> 0 | FN12: =SUM(FI12:FM12) -> 0 | FO12: =FM12 | FQ12: ='ORDER SENT'!FT12 -> 0 | FR12: =+FO12+FP12-FQ12 -> 0 | FT12: =SUM(FO12:FS12) -> 0 | FU12: =FS12 | FW12: ='ORDER SENT'!FZ12 -> 0 | FX12: =+FU12+FV12-FW12 -> 0 | FZ12: =SUM(FU12:FY12) -> 0 | GA12: =FY12 | GC12: ='ORDER SENT'!GF12 -> 0 | GD12: =+GA12+GB12-GC12 -> 0 | GF12: =SUM(GA12:GE12) -> 0 | GG12: =C12 | GH12: =+GB12+FV12+FP12+FJ12+FD12+EX12+ER12+EL12+EF12+DZ12+DT12+DN12+DH12+DB12+CV12+CP12+CJ12+CD12+BX12+BR12+BL12+BF12++AZ12+AT12+AN12+AH12+AB12+V12+P12+J12+D12 -> 0 | GI12: =+GC12+FW12+FQ12+FK12+FE12+EY12+ES12+EM12+EG12+EA12+DU12+DO12+DI12+DC12+CW12+CQ12+CK12+CE12+BY12+BS12+BM12+BG12++BA12+AU12+AO12+AI12+AC12+W12+Q12+K12+E12 -> 0 | GJ12: =+GD12+FX12+FR12+FL12+FF12+EZ12+ET12+EN12+EH12+EB12+DV12+DP12+DJ12+DD12+CX12+CR12+CL12+CF12+BZ12+BT12+BN12+BH12++BB12+AV12+AP12+AJ12+AD12+X12+R12+L12+F12 -> 0 | GK12: =+GE12+FY12+FS12+FM12+FG12+FA12+EU12+EO12+EI12+EC12+DW12+DQ12+DK12+DE12+CY12+CS12+CM12+CG12+CA12+BU12+BO12+BI12++BC12+AW12+AQ12+AK12+AE12+Y12+S12+M12+G12 -> 0 | GL12: =+GF12+FZ12+FT12+FN12+FH12+FB12+EV12+EP12+EJ12+ED12+DX12+DR12+DL12+DF12+CZ12+CT12+CN12+CH12+CB12+BV12+BP12+BJ12++BD12+AX12+AR12+AL12+AF12+Z12+T12+N12+H12 -> 0 | GM12: =+GK12+GJ12+GI12+GH12+GG12 -> 0
