Workbook

Sheet README
A1: FORKS N KNIVES — GULBERG — CONNECTED FINANCIAL WORKBOOK
A4: THIS WORKBOOK IS PRE-FILLED WITH SEPTEMBER 2026 ACTUALS
A6: Every real September transaction from the audited 2026-SEPTEMBER-C-5 workbook (603 expense/director/payroll
A7: lines, tying exactly to the audited Total Expense of 13,968,109) and the real September staff roster (76
A8: employees) is already loaded — see Sales, Expense Entry, Directors and Payroll. The P&L Summary and Dashboard are
A9: showing September's actual financial position right now. Keep adding new dated rows for October onward and
A10: everything recalculates live.
A12: ITEM CODES — THE BACKBONE THAT LINKS EVERYTHING
A14: Every one of the 481 real inventory items now has a permanent, professional Item Code — a 2-letter category
A15: prefix plus a 3-digit number, e.g. FD-001 (Food & Beverage), PK-014 (Packaging & Paper). The 10 categories are:
A16: FD Food & Beverage, PK Packaging & Paper, CL Cleaning & Sanitation, PT Party & Decor, ST Stationery & Office
A17: Supplies, MK Marketing & POS Materials, UN Uniform & Apparel, EQ Equipment & Smallwares, DV Vehicle & Delivery
... A133: — nothing there should ever be typed over.

Sheet Dashboard
A1: DASHBOARD — FORKS N KNIVES, GULBERG
A2: Live KPIs pulled from every tab. Nothing to enter here.
A4: Total Sales (Sales tab) | B4: =Sales!$G$3010 -> 14012331
A5: Total Cost of Goods Used (P&L) | B5: ='P&L Summary'!$B$18 -> 0
A6: Total Direct Operating Expenses (P&L) | B6: ='P&L Summary'!$B$43 -> 13510202
A7: Operating Profit | B7: ='P&L Summary'!$B$47 -> 502129
A8: Total Director Draws | B8: =Directors!$B$11 -> 457907
A9: Net Profit After Director Draws | B9: ='P&L Summary'!$B$47-Directors!$B$11 -> 44222
A10: Current Closing Cash (last entered day) | B10: =IFERROR(INDEX('Cash Book'!$F$5:$F$35,MATCH(2,1/('Cash Book'!$A$5:$A$35<>""),1)),0) -> 502129
A11: Total Inventory Value on Hand | B11: =Inventory!$L$487 -> 4433397.6
A12: Total Payables Outstanding | B12: =SUM(Payables!$F$5:$F$3000) -> 0
A13: Open / Unreceived Purchase Orders | B13: =COUNTIFS('Purchase Orders'!$L$5:$L$3000,"Ordered") -> 0

Sheet P&L Summary
A1: P&L SUMMARY — the one tab that rolls up every other tab
A2: Pulls live from Sales, Expense Entry, Issue Log, Directors and Payroll. Food/Packaging/Cleaning/Party & Decor/Stationery/Uniform/Equipment/Vehicle/Fuel costs are consumption-based (from Issue Log) when tracked item-by-item; everything else comes straight from Expense Entry.
A4: REVENUE
A5: Sales Collected (from Sales tab) | B5: =Sales!$G$3010 -> 14012331
A7: COST OF GOODS USED (consumption basis, from Issue Log)
A8: Cleaning & Sanitation | B8: =SUMIFS('Issue Log'!$G$5:$G$6000,'Issue Log'!$J$5:$J$6000,"Cleaning & Sanitation") -> 0
A9: Equipment & Smallwares | B9: =SUMIFS('Issue Log'!$G$5:$G$6000,'Issue Log'!$J$5:$J$6000,"Equipment & Smallwares") -> 0
A10: Food & Beverage | B10: =SUMIFS('Issue Log'!$G$5:$G$6000,'Issue Log'!$J$5:$J$6000,"Food & Beverage") -> 0
A11: Fuel & Gas | B11: =SUMIFS('Issue Log'!$G$5:$G$6000,'Issue Log'!$J$5:$J$6000,"Fuel & Gas") -> 0
A12: Marketing & POS Materials | B12: =SUMIFS('Issue Log'!$G$5:$G$6000,'Issue Log'!$J$5:$J$6000,"Marketing & POS Materials") -> 0
A13: Packaging & Paper | B13: =SUMIFS('Issue Log'!$G$5:$G$6000,'Issue Log'!$J$5:$J$6000,"Packaging & Paper") -> 0
A14: Party & Decor | B14: =SUMIFS('Issue Log'!$G$5:$G$6000,'Issue Log'!$J$5:$J$6000,"Party & Decor") -> 0
A15: Stationery & Office Supplies | B15: =SUMIFS('Issue Log'!$G$5:$G$6000,'Issue Log'!$J$5:$J$6000,"Stationery & Office Supplies") -> 0
A16: Uniform & Apparel | B16: =SUMIFS('Issue Log'!$G$5:$G$6000,'Issue Log'!$J$5:$J$6000,"Uniform & Apparel") -> 0
A17: Vehicle & Delivery Equipment | B17: =SUMIFS('Issue Log'!$G$5:$G$6000,'Issue Log'!$J$5:$J$6000,"Vehicle & Delivery Equipment") -> 0
A18: SUBTOTAL — COST OF GOODS USED | B18: ='P&L Summary'!$B$8+'P&L Summary'!$B$9+'P&L Summary'!$B$10+'P&L Summary'!$B$11+'P&L Summary'!$B$12+'P&L Summary'!$B$13+'P&L Summary'!$B$14+'P&L Summary'!$B$15+'P&L Summary'!$B$16+'P&L Summary'!$B$17 -> 0
A20: DIRECT OPERATING EXPENSES (from Expense Entry, cash categories)
A21: Food | B21: =SUMIFS('Expense Entry'!$K$5:$K$6000,'Expense Entry'!$E$5:$E$6000,"Food") -> 6717236
A22: Packaging | B22: =SUMIFS('Expense Entry'!$K$5:$K$6000,'Expense Entry'!$E$5:$E$6000,"Packaging") -> 418045
A23: Cleaning & Sanitation | B23: =SUMIFS('Expense Entry'!$K$5:$K$6000,'Expense Entry'!$E$5:$E$6000,"Cleaning & Sanitation") -> 160230
A24: Party & Decor | B24: =SUMIFS('Expense Entry'!$K$5:$K$6000,'Expense Entry'!$E$5:$E$6000,"Party & Decor") -> 10140
A25: Stationery & Office Supplies | B25: =SUMIFS('Expense Entry'!$K$5:$K$6000,'Expense Entry'!$E$5:$E$6000,"Stationery & Office Supplies") -> 17600
A26: Marketing | B26: =SUMIFS('Expense Entry'!$K$5:$K$6000,'Expense Entry'!$E$5:$E$6000,"Marketing") -> 9250
A27: Uniform & Apparel | B27: =SUMIFS('Expense Entry'!$K$5:$K$6000,'Expense Entry'!$E$5:$E$6000,"Uniform & Apparel") -> 140560
A28: Equipment & Smallwares | B28: =SUMIFS('Expense Entry'!$K$5:$K$6000,'Expense Entry'!$E$5:$E$6000,"Equipment & Smallwares") -> 29290
A29: Vehicle & Delivery Maintenance | B29: =SUMIFS('Expense Entry'!$K$5:$K$6000,'Expense Entry'!$E$5:$E$6000,"Vehicle & Delivery Maintenance") -> 0
A30: Fuel & Gas | B30: =SUMIFS('Expense Entry'!$K$5:$K$6000,'Expense Entry'!$E$5:$E$6000,"Fuel & Gas") -> 0
A31: Payroll | B31: =SUMIFS('Expense Entry'!$K$5:$K$6000,'Expense Entry'!$E$5:$E$6000,"Payroll") -> 2439333 | D31: Actual cash payroll paid out (per Expense Entry). The Payroll tab's base-salary roster is a separate HR reference, not re-added here.
A32: Utilities (Electricity/Water) | B32: =SUMIFS('Expense Entry'!$K$5:$K$6000,'Expense Entry'!$E$5:$E$6000,"Utilities (Electricity/Water)") -> 2048915
A33: Distribution Cost | B33: =SUMIFS('Expense Entry'!$K$5:$K$6000,'Expense Entry'!$E$5:$E$6000,"Distribution Cost") -> 11680
A34: Delivery Charges | B34: =SUMIFS('Expense Entry'!$K$5:$K$6000,'Expense Entry'!$E$5:$E$6000,"Delivery Charges") -> 1850
A35: Interstore Transfers | B35: =SUMIFS('Expense Entry'!$K$5:$K$6000,'Expense Entry'!$E$5:$E$6000,"Interstore Transfers") -> 436000
A36: Employee Meals & Medical | B36: =SUMIFS('Expense Entry'!$K$5:$K$6000,'Expense Entry'!$E$5:$E$6000,"Employee Meals & Medical") -> 24143
A37: Charge to Restaurant | B37: =SUMIFS('Expense Entry'!$K$5:$K$6000,'Expense Entry'!$E$5:$E$6000,"Charge to Restaurant") -> 45394
A38: Repairs & Maintenance | B38: =SUMIFS('Expense Entry'!$K$5:$K$6000,'Expense Entry'!$E$5:$E$6000,"Repairs & Maintenance") -> 209690
A39: Government Charges & Taxes | B39: =SUMIFS('Expense Entry'!$K$5:$K$6000,'Expense Entry'!$E$5:$E$6000,"Government Charges & Taxes") -> 602937
A40: Food Panda Commission | B40: =SUMIFS('Expense Entry'!$K$5:$K$6000,'Expense Entry'!$E$5:$E$6000,"Food Panda Commission") -> 178649
A41: Miscellaneous | B41: =SUMIFS('Expense Entry'!$K$5:$K$6000,'Expense Entry'!$E$5:$E$6000,"Miscellaneous") -> 9260
A42: Donation | B42: =SUMIFS('Expense Entry'!$K$5:$K$6000,'Expense Entry'!$E$5:$E$6000,"Donation") -> 0
A43: SUBTOTAL — DIRECT OPERATING EXPENSES | B43: ='P&L Summary'!$B$21+'P&L Summary'!$B$22+'P&L Summary'!$B$23+'P&L Summary'!$B$24+'P&L Summary'!$B$25+'P&L Summary'!$B$26+'P&L Summary'!$B$27+'P&L Summary'!$B$28+'P&L Summary'!$B$29+'P&L Summary'!$B$30+'P&L Summary'!$B$31+'P&L Summary'!$B$32+'P&L Summary'!$B$33+'P&L Summary'!$B$34+'P&L Summary'!$B$35+'P&L Summary'!$B$36+'P&L Summary'!$B$37+'P&L Summary'!$B$38+'P&L Summary'!$B$39+'P&L Summary'!$B$40+'P&L Summary'!$B$41+'P&L Summary'!$B$42 -> 13510202
A45: OPERATING RESULT
A46: TOTAL EXPENSES (COGS + Direct Opex) | B46: ='P&L Summary'!$B$18+'P&L Summary'!$B$43 -> 13510202
A47: OPERATING PROFIT (Revenue - Total Expenses) | B47: ='P&L Summary'!$B$5-'P&L Summary'!$B$46 -> 502129
A49: DIRECTOR / OWNER DRAWS
A50: Total Director Expense (from Directors tab) | B50: =Directors!$B$11 -> 457907
A52: NET RESULT
A53: NET PROFIT AFTER DIRECTOR DRAWS | B53: ='P&L Summary'!$B$47-Directors!$B$11 -> 44222
A55: MEMO — CASH POSITION (ties to Cash Book, separate from accrual P&L above)
A56: Cash In (Sales) | B56: =Sales!$G$3010 -> 14012331
A57: Cash Out (all cash-impacting Expense Entry rows) | B57: =-SUM('Expense Entry'!$P$5:$P$6000) -> 13510202
A58: Net Cash Movement | B58: =Sales!$G$3010+SUM('Expense Entry'!$P$5:$P$6000) -> 502129

Sheet Sales
A1: SALES — daily sales by channel
A2: One row per day. Total Sale is automatic and feeds the Cash Book / P&L / Dashboard. Add new dated rows as months go by.
A4: Date | B4: Dine-in | C4: Takeaway | D4: Delivery | E4: Food Panda | F4: Third Party | G4: Total Sale | H4: Notes
A5: 46266 | B5: 240340 | C5: 30409 | D5: 158049 | E5: 8036 | F5: 0 | G5: =IF($A5="","",SUM($B5:$F5)) -> 436834
A6: 46267 | B6: 205739 | C6: 14835 | D6: 204614 | E6: 10100 | F6: 0 | G6: =IF($A6="","",SUM($B6:$F6)) -> 435288
A7: 46268 | B7: 234024 | C7: 23937 | D7: 220615 | E7: 3500 | F7: 0 | G7: =IF($A7="","",SUM($B7:$F7)) -> 482076
A8: 46269 | B8: 310832 | C8: 29420 | D8: 183524 | E8: 3589 | F8: 0 | G8: =IF($A8="","",SUM($B8:$F8)) -> 527365
A9: 46270 | B9: 243677 | C9: 32128 | D9: 211739 | E9: 12056 | F9: 0 | G9: =IF($A9="","",SUM($B9:$F9)) -> 499600
A10: 46271 | B10: 254640 | C10: 29168 | D10: 218888 | E10: 8898 | F10: 0 | G10: =IF($A10="","",SUM($B10:$F10)) -> 511594
A11: 46272 | B11: 258529 | C11: 39810 | D11: 135797 | E11: 9768 | F11: 22087 | G11: =IF($A11="","",SUM($B11:$F11)) -> 465991
A12: 46273 | B12: 245296 | C12: 30606 | D12: 146125 | E12: 1829 | F12: 8318 | G12: =IF($A12="","",SUM($B12:$F12)) -> 432174
A13: 46274 | B13: 216540 | C13: 38433 | D13: 142018 | E13: 7358 | F13: 32990 | G13: =IF($A13="","",SUM($B13:$F13)) -> 437339
A14: 46275 | B14: 257101 | C14: 27110 | D14: 124540 | E14: 10017 | F14: 11118 | G14: =IF($A14="","",SUM($B14:$F14)) -> 429886
A15: 46276 | B15: 372389 | C15: 26793 | D15: 171079 | E15: 4167 | F15: 36299 | G15: =IF($A15="","",SUM($B15:$F15)) -> 610727
A16: 46277 | B16: 246019 | C16: 30190 | D16: 200757 | E16: 9705 | F16: 29264 | G16: =IF($A16="","",SUM($B16:$F16)) -> 515935
... A32: 46293 | B32: 168424 | C32: 30763 | D32: 130000 | E32: 8883 | F32: 12956 | G32: =IF($A32="","",SUM($B32:$F32)) -> 351026
A33: 46294 | B33: 402974 | C33: 0 | D33: 0 | E33: 0 | F33: 0 | G33: =IF($A33="","",SUM($B33:$F33)) -> 402974 | H33: Channel breakdown unavailable for this day — lump total per Sep detail report (booked under Dine-in)
A34: 46295 | B34: 424788 | C34: 0 | D34: 0 | E34: 0 | F34: 0 | G34: =IF($A34="","",SUM($B34:$F34)) -> 424788 | H34: Channel breakdown unavailable for this day — lump total per Sep detail report (booked under Dine-in)
G35: =IF($A35="","",SUM($B35:$F35))
G36: =IF($A36="","",SUM($B36:$F36))
G37: =IF($A37="","",SUM($B37:$F37))
G38: =IF($A38="","",SUM($B38:$F38))
G39: =IF($A39="","",SUM($B39:$F39))
G40: =IF($A40="","",SUM($B40:$F40))
G41: =IF($A41="","",SUM($B41:$F41))
G42: =IF($A42="","",SUM($B42:$F42))
G43: =IF($A43="","",SUM($B43:$F43))
G44: =IF($A44="","",SUM($B44:$F44))
G45: =IF($A45="","",SUM($B45:$F45))
G46: =IF($A46="","",SUM($B46:$F46))
... G404: =IF($A404="","",SUM($B404:$F404))
F3010: TOTAL: | G3010: =SUM($G$5:$G$3000) -> 14012331

Sheet Food Panda
A1: FOOD PANDA — settlement reconciliation (catches under-payment)
A2: Food Panda's deductions (Commission/Fee & Adjustments/Tax) are NOT a cash expense Zeeshan pays -- they are subtracted before the net amount ever reaches the bank. This tab checks two things: (1) does Food Panda's own statement add up (Gross - Commission - Fee&Adj - Tax + Refund = their stated Net Earning)? and (2) does the actual bank deposit match? Gross Sale/Total Earning is the only number you need going in -- everything else is either calculated from the pattern below or typed in once their statement arrives.
A4: PATTERN RATES (derived from real Sep-2026 statements -- edit if Food Panda changes terms)
A5: Brand | B5: Commission % | C5: Tax % | D5: Typical Fee & Adj. (PKR, flat)
A6: Frostings | B6: 0.26 | C6: 0.062 | D6: 800
A7: Pizza Kitchen | B7: 0.22 | C7: 0.037 | D7: 400
A8: Combined / Other | B8: 0.23 | C8: 0.05 | D8: 500
A10: ⚠ Found during the Sep-30 sample: Pizza Kitchen-Gulberg's own statement didn't add up internally (Total 27,429 − Commission 5,771 − Fee 400 − Tax 7,159 = 14,099, but their sheet showed Net Earning 20,271 -- a 6,172 PKR gap). Every other branch that day reconciled exactly. Worth confirming the real figure against Food Panda's own portal/PDF (a transcription slip is possible) -- and if it recurs, raise it with them directly.
A12: Period / Settlement Date | B12: Brand | C12: Gross Sale (Total Earning) | D12: Expected Net (pattern estimate) | E12: FP Reported Commission | F12: FP Reported Fee & Adj. | G12: FP Reported Tax | H12: FP Reported Refund (+) | I12: FP Reported Net Earning | J12: Recomputed Net (Gross-Comm-Fee-Tax+Refund) | K12: Statement Check | L12: Actual Bank Deposit Received | M12: Deposit vs Recomputed Variance | N12: Status | O12: Notes
A13: 30-Sep-2026 | B13: Frostings | C13: 1782 | D13: =IF($C13="","",IF($B13="","",$C13*(1-VLOOKUP($B13,$A$6:$D$8,2,0)-VLOOKUP($B13,$A$6:$D$8,3,0))-VLOOKUP($B13,$A$6:$D$8,4,0))) -> 408.196 | E13: 454 | F13: 800 | G13: 137 | H13: 0 | I13: 390 | J13: =IF($C13="","",$C13-$E13-$F13-$G13+$H13) -> 391 | K13: =IF(OR($I13="",$J13=""),"",IF(ABS($I13-$J13)<=2,"OK","⚠ FP statement doesn't add up -- verify")) -> OK | M13: =IF($L13="","",$L13-IF($J13="",$D13,$J13)) | N13: =IF($L13="","",IF($M13<-200,"⚠ SHORT -- follow up with Food Panda",IF($M13>200,"Over (unexpected)","OK"))) | O13: Worked example from the actual portal statement -- enter the real bank deposit in col L once received.
A14: 30-Sep-2026 | B14: Pizza Kitchen | C14: 27429 | D14: =IF($C14="","",IF($B14="","",$C14*(1-VLOOKUP($B14,$A$6:$D$8,2,0)-VLOOKUP($B14,$A$6:$D$8,3,0))-VLOOKUP($B14,$A$6:$D$8,4,0))) -> 19979.747 | E14: 5771 | F14: 400 | G14: 7159 | H14: 0 | I14: 20271 | J14: =IF($C14="","",$C14-$E14-$F14-$G14+$H14) -> 14099 | K14: =IF(OR($I14="",$J14=""),"",IF(ABS($I14-$J14)<=2,"OK","⚠ FP statement doesn't add up -- verify")) -> ⚠ FP statement doesn't add up -- verify | M14: =IF($L14="","",$L14-IF($J14="",$D14,$J14)) | N14: =IF($L14="","",IF($M14<-200,"⚠ SHORT -- follow up with Food Panda",IF($M14>200,"Over (unexpected)","OK"))) | O14: Worked example -- this is the row that flags the statement mismatch described above.
D15: =IF($C15="","",IF($B15="","",$C15*(1-VLOOKUP($B15,$A$6:$D$8,2,0)-VLOOKUP($B15,$A$6:$D$8,3,0))-VLOOKUP($B15,$A$6:$D$8,4,0))) | J15: =IF($C15="","",$C15-$E15-$F15-$G15+$H15) | K15: =IF(OR($I15="",$J15=""),"",IF(ABS($I15-$J15)<=2,"OK","⚠ FP statement doesn't add up -- verify")) | M15: =IF($L15="","",$L15-IF($J15="",$D15,$J15)) | N15: =IF($L15="","",IF($M15<-200,"⚠ SHORT -- follow up with Food Panda",IF($M15>200,"Over (unexpected)","OK")))
D16: =IF($C16="","",IF($B16="","",$C16*(1-VLOOKUP($B16,$A$6:$D$8,2,0)-VLOOKUP($B16,$A$6:$D$8,3,0))-VLOOKUP($B16,$A$6:$D$8,4,0))) | J16: =IF($C16="","",$C16-$E16-$F16-$G16+$H16) | K16: =IF(OR($I16="",$J16=""),"",IF(ABS($I16-$J16)<=2,"OK","⚠ FP statement doesn't add up -- verify")) | M16: =IF($L16="","",$L16-IF($J16="",$D16,$J16)) | N16: =IF($L16="","",IF($M16<-200,"⚠ SHORT -- follow up with Food Panda",IF($M16>200,"Over (unexpected)","OK")))
D17: =IF($C17="","",IF($B17="","",$C17*(1-VLOOKUP($B17,$A$6:$D$8,2,0)-VLOOKUP($B17,$A$6:$D$8,3,0))-VLOOKUP($B17,$A$6:$D$8,4,0))) | J17: =IF($C17="","",$C17-$E17-$F17-$G17+$H17) | K17: =IF(OR($I17="",$J17=""),"",IF(ABS($I17-$J17)<=2,"OK","⚠ FP statement doesn't add up -- verify")) | M17: =IF($L17="","",$L17-IF($J17="",$D17,$J17)) | N17: =IF($L17="","",IF($M17<-200,"⚠ SHORT -- follow up with Food Panda",IF($M17>200,"Over (unexpected)","OK")))
D18: =IF($C18="","",IF($B18="","",$C18*(1-VLOOKUP($B18,$A$6:$D$8,2,0)-VLOOKUP($B18,$A$6:$D$8,3,0))-VLOOKUP($B18,$A$6:$D$8,4,0))) | J18: =IF($C18="","",$C18-$E18-$F18-$G18+$H18) | K18: =IF(OR($I18="",$J18=""),"",IF(ABS($I18-$J18)<=2,"OK","⚠ FP statement doesn't add up -- verify")) | M18: =IF($L18="","",$L18-IF($J18="",$D18,$J18)) | N18: =IF($L18="","",IF($M18<-200,"⚠ SHORT -- follow up with Food Panda",IF($M18>200,"Over (unexpected)","OK")))
D19: =IF($C19="","",IF($B19="","",$C19*(1-VLOOKUP($B19,$A$6:$D$8,2,0)-VLOOKUP($B19,$A$6:$D$8,3,0))-VLOOKUP($B19,$A$6:$D$8,4,0))) | J19: =IF($C19="","",$C19-$E19-$F19-$G19+$H19) | K19: =IF(OR($I19="",$J19=""),"",IF(ABS($I19-$J19)<=2,"OK","⚠ FP statement doesn't add up -- verify")) | M19: =IF($L19="","",$L19-IF($J19="",$D19,$J19)) | N19: =IF($L19="","",IF($M19<-200,"⚠ SHORT -- follow up with Food Panda",IF($M19>200,"Over (unexpected)","OK")))
D20: =IF($C20="","",IF($B20="","",$C20*(1-VLOOKUP($B20,$A$6:$D$8,2,0)-VLOOKUP($B20,$A$6:$D$8,3,0))-VLOOKUP($B20,$A$6:$D$8,4,0))) | J20: =IF($C20="","",$C20-$E20-$F20-$G20+$H20) | K20: =IF(OR($I20="",$J20=""),"",IF(ABS($I20-$J20)<=2,"OK","⚠ FP statement doesn't add up -- verify")) | M20: =IF($L20="","",$L20-IF($J20="",$D20,$J20)) | N20: =IF($L20="","",IF($M20<-200,"⚠ SHORT -- follow up with Food Panda",IF($M20>200,"Over (unexpected)","OK")))
D21: =IF($C21="","",IF($B21="","",$C21*(1-VLOOKUP($B21,$A$6:$D$8,2,0)-VLOOKUP($B21,$A$6:$D$8,3,0))-VLOOKUP($B21,$A$6:$D$8,4,0))) | J21: =IF($C21="","",$C21-$E21-$F21-$G21+$H21) | K21: =IF(OR($I21="",$J21=""),"",IF(ABS($I21-$J21)<=2,"OK","⚠ FP statement doesn't add up -- verify")) | M21: =IF($L21="","",$L21-IF($J21="",$D21,$J21)) | N21: =IF($L21="","",IF($M21<-200,"⚠ SHORT -- follow up with Food Panda",IF($M21>200,"Over (unexpected)","OK")))
D22: =IF($C22="","",IF($B22="","",$C22*(1-VLOOKUP($B22,$A$6:$D$8,2,0)-VLOOKUP($B22,$A$6:$D$8,3,0))-VLOOKUP($B22,$A$6:$D$8,4,0))) | J22: =IF($C22="","",$C22-$E22-$F22-$G22+$H22) | K22: =IF(OR($I22="",$J22=""),"",IF(ABS($I22-$J22)<=2,"OK","⚠ FP statement doesn't add up -- verify")) | M22: =IF($L22="","",$L22-IF($J22="",$D22,$J22)) | N22: =IF($L22="","",IF($M22<-200,"⚠ SHORT -- follow up with Food Panda",IF($M22>200,"Over (unexpected)","OK")))
D23: =IF($C23="","",IF($B23="","",$C23*(1-VLOOKUP($B23,$A$6:$D$8,2,0)-VLOOKUP($B23,$A$6:$D$8,3,0))-VLOOKUP($B23,$A$6:$D$8,4,0))) | J23: =IF($C23="","",$C23-$E23-$F23-$G23+$H23) | K23: =IF(OR($I23="",$J23=""),"",IF(ABS($I23-$J23)<=2,"OK","⚠ FP statement doesn't add up -- verify")) | M23: =IF($L23="","",$L23-IF($J23="",$D23,$J23)) | N23: =IF($L23="","",IF($M23<-200,"⚠ SHORT -- follow up with Food Panda",IF($M23>200,"Over (unexpected)","OK")))
D24: =IF($C24="","",IF($B24="","",$C24*(1-VLOOKUP($B24,$A$6:$D$8,2,0)-VLOOKUP($B24,$A$6:$D$8,3,0))-VLOOKUP($B24,$A$6:$D$8,4,0))) | J24: =IF($C24="","",$C24-$E24-$F24-$G24+$H24) | K24: =IF(OR($I24="",$J24=""),"",IF(ABS($I24-$J24)<=2,"OK","⚠ FP statement doesn't add up -- verify")) | M24: =IF($L24="","",$L24-IF($J24="",$D24,$J24)) | N24: =IF($L24="","",IF($M24<-200,"⚠ SHORT -- follow up with Food Panda",IF($M24>200,"Over (unexpected)","OK")))
D25: =IF($C25="","",IF($B25="","",$C25*(1-VLOOKUP($B25,$A$6:$D$8,2,0)-VLOOKUP($B25,$A$6:$D$8,3,0))-VLOOKUP($B25,$A$6:$D$8,4,0))) | J25: =IF($C25="","",$C25-$E25-$F25-$G25+$H25) | K25: =IF(OR($I25="",$J25=""),"",IF(ABS($I25-$J25)<=2,"OK","⚠ FP statement doesn't add up -- verify")) | M25: =IF($L25="","",$L25-IF($J25="",$D25,$J25)) | N25: =IF($L25="","",IF($M25<-200,"⚠ SHORT -- follow up with Food Panda",IF($M25>200,"Over (unexpected)","OK")))
D26: =IF($C26="","",IF($B26="","",$C26*(1-VLOOKUP($B26,$A$6:$D$8,2,0)-VLOOKUP($B26,$A$6:$D$8,3,0))-VLOOKUP($B26,$A$6:$D$8,4,0))) | J26: =IF($C26="","",$C26-$E26-$F26-$G26+$H26) | K26: =IF(OR($I26="",$J26=""),"",IF(ABS($I26-$J26)<=2,"OK","⚠ FP statement doesn't add up -- verify")) | M26: =IF($L26="","",$L26-IF($J26="",$D26,$J26)) | N26: =IF($L26="","",IF($M26<-200,"⚠ SHORT -- follow up with Food Panda",IF($M26>200,"Over (unexpected)","OK")))
... D72: =IF($C72="","",IF($B72="","",$C72*(1-VLOOKUP($B72,$A$6:$D$8,2,0)-VLOOKUP($B72,$A$6:$D$8,3,0))-VLOOKUP($B72,$A$6:$D$8,4,0))) | J72: =IF($C72="","",$C72-$E72-$F72-$G72+$H72) | K72: =IF(OR($I72="",$J72=""),"",IF(ABS($I72-$J72)<=2,"OK","⚠ FP statement doesn't add up -- verify")) | M72: =IF($L72="","",$L72-IF($J72="",$D72,$J72)) | N72: =IF($L72="","",IF($M72<-200,"⚠ SHORT -- follow up with Food Panda",IF($M72>200,"Over (unexpected)","OK")))

Sheet Expense Entry
A1: EXPENSE ENTRY — single input tab (Zeeshan)
A2: Pick a Category. For 'Inventory Purchase', pick the standard Item Code (name/unit/rate fill in automatically) -> flows into the Inventory tab by code. 'Director Draw'/'Payroll/Employee Charge'=non-cash, goes to Directors/Payroll tabs. 'Payable Payment'=cash paid against a received Purchase Order (enter Linked PO#). Everything else = direct cash expense.
A4: Date | B4: # | C4: Vendor / Payee | D4: Description | E4: Category | F4: Item Code | G4: Item Name (auto) | H4: Qty | I4: Unit | J4: Rate | K4: Amount (PKR) | L4: Linked PO# (Payable Payment) | M4: Charged To (Director/Employee) | N4: Entered By | O4: Notes | P4: Cash Impact | Q4: Inventory Qty In | U4: ItemLUT (lookup table, do not edit)
A5: 46266 | B5: =IF($A5="","",ROW()-4) -> 1 | C5: - | D5: QR JAZZ CASH PAYMENT | E5: Director Draw | G5: =IFERROR(VLOOKUP($F5,ItemList_Full,2,0),"") | I5: =IFERROR(VLOOKUP($F5,ItemList_Full,3,0),"") | J5: =IFERROR(VLOOKUP($F5,ItemList_Full,4,0),"") | K5: 36390 | M5: Yasir Sb | N5: Zeeshan (Sept import) | P5: =IF($E5="","",IF(OR($E5="Director Draw",$E5="Payroll/Employee Charge"),0,-$K5)) -> 0 | Q5: =IF($E5="Inventory Purchase",$H5,0) -> 0 | U5: FD-001 | V5: CHEESE YELLOW | W5: CTN | X5: 16900 | Y5: Food & Beverage
A6: 46266 | B6: =IF($A6="","",ROW()-4) -> 2 | C6: - | D6: T.A INV# 03,17 MEAL FOR IMRAN TAHIR SB | E6: Director Draw | G6: =IFERROR(VLOOKUP($F6,ItemList_Full,2,0),"") | I6: =IFERROR(VLOOKUP($F6,ItemList_Full,3,0),"") | J6: =IFERROR(VLOOKUP($F6,ItemList_Full,4,0),"") | K6: 965 | M6: Imran Tahir | N6: Zeeshan (Sept import) | P6: =IF($E6="","",IF(OR($E6="Director Draw",$E6="Payroll/Employee Charge"),0,-$K6)) -> 0 | Q6: =IF($E6="Inventory Purchase",$H6,0) -> 0 | U6: FD-002 | V6: CHEESE GREEN | W6: CTN | X6: 16900 | Y6: Food & Beverage
A7: 46266 | B7: =IF($A7="","",ROW()-4) -> 3 | C7: FNK BAKERY | D7: FNK BAKERY BILL PAID | E7: Food | G7: =IFERROR(VLOOKUP($F7,ItemList_Full,2,0),"") | I7: =IFERROR(VLOOKUP($F7,ItemList_Full,3,0),"") | J7: =IFERROR(VLOOKUP($F7,ItemList_Full,4,0),"") | K7: 163704 | N7: Zeeshan (Sept import) | P7: =IF($E7="","",IF(OR($E7="Director Draw",$E7="Payroll/Employee Charge"),0,-$K7)) -> -163704 | Q7: =IF($E7="Inventory Purchase",$H7,0) -> 0 | U7: FD-003 | V7: MALAI BOTI | W7: KG | X7: 1400 | Y7: Food & Beverage
A8: 46266 | B8: =IF($A8="","",ROW()-4) -> 4 | C8: FNK GRILL | D8: FNK GRILL BILL PAID | E8: Food | G8: =IFERROR(VLOOKUP($F8,ItemList_Full,2,0),"") | I8: =IFERROR(VLOOKUP($F8,ItemList_Full,3,0),"") | J8: =IFERROR(VLOOKUP($F8,ItemList_Full,4,0),"") | K8: 17000 | N8: Zeeshan (Sept import) | P8: =IF($E8="","",IF(OR($E8="Director Draw",$E8="Payroll/Employee Charge"),0,-$K8)) -> -17000 | Q8: =IF($E8="Inventory Purchase",$H8,0) -> 0 | U8: FD-004 | V8: STEAK FILLET | W8: PCS | X8: 200 | Y8: Food & Beverage
A9: 46266 | B9: =IF($A9="","",ROW()-4) -> 5 | C9: FOOD PANDA | D9: FOOD PANDA SALE | E9: Food Panda Commission | G9: =IFERROR(VLOOKUP($F9,ItemList_Full,2,0),"") | I9: =IFERROR(VLOOKUP($F9,ItemList_Full,3,0),"") | J9: =IFERROR(VLOOKUP($F9,ItemList_Full,4,0),"") | K9: 13030 | N9: Zeeshan (Sept import) | P9: =IF($E9="","",IF(OR($E9="Director Draw",$E9="Payroll/Employee Charge"),0,-$K9)) -> -13030 | Q9: =IF($E9="Inventory Purchase",$H9,0) -> 0 | U9: FD-005 | V9: BEHARI CHICKEN | W9: KG | X9: 1150 | Y9: Food & Beverage
A10: 46266 | B10: =IF($A10="","",ROW()-4) -> 6 | C10: MIAN & SONS (BEVERAGES) | D10: COLA NEXT DRINK PAYMENT | E10: Food | G10: =IFERROR(VLOOKUP($F10,ItemList_Full,2,0),"") | I10: =IFERROR(VLOOKUP($F10,ItemList_Full,3,0),"") | J10: =IFERROR(VLOOKUP($F10,ItemList_Full,4,0),"") | K10: 70000 | N10: Zeeshan (Sept import) | P10: =IF($E10="","",IF(OR($E10="Director Draw",$E10="Payroll/Employee Charge"),0,-$K10)) -> -70000 | Q10: =IF($E10="Inventory Purchase",$H10,0) -> 0 | U10: FD-006 | V10: TIKKA TOPPING FISH AND CHICK | W10: KG | X10: 1150 | Y10: Food & Beverage
A11: 46266 | B11: =IF($A11="","",ROW()-4) -> 7 | C11: BAR | D11: ICE FOR BAR | E11: Food | G11: =IFERROR(VLOOKUP($F11,ItemList_Full,2,0),"") | I11: =IFERROR(VLOOKUP($F11,ItemList_Full,3,0),"") | J11: =IFERROR(VLOOKUP($F11,ItemList_Full,4,0),"") | K11: 900 | N11: Zeeshan (Sept import) | P11: =IF($E11="","",IF(OR($E11="Director Draw",$E11="Payroll/Employee Charge"),0,-$K11)) -> -900 | Q11: =IF($E11="Inventory Purchase",$H11,0) -> 0 | U11: FD-007 | V11: FAJITA TOPPING FISH AND CHICK | W11: KG | X11: 1150 | Y11: Food & Beverage
A12: 46266 | B12: =IF($A12="","",ROW()-4) -> 8 | C12: BREAD AND BEYOND | D12: BURGER BUN | E12: Food | G12: =IFERROR(VLOOKUP($F12,ItemList_Full,2,0),"") | I12: =IFERROR(VLOOKUP($F12,ItemList_Full,3,0),"") | J12: =IFERROR(VLOOKUP($F12,ItemList_Full,4,0),"") | K12: 2180 | N12: Zeeshan (Sept import) | P12: =IF($E12="","",IF(OR($E12="Director Draw",$E12="Payroll/Employee Charge"),0,-$K12)) -> -2180 | Q12: =IF($E12="Inventory Purchase",$H12,0) -> 0 | U12: FD-008 | V12: AL-TAYYAB DRUMMET | W12: KG | X12: 800 | Y12: Food & Beverage
A13: 46266 | B13: =IF($A13="","",ROW()-4) -> 9 | C13: STATIONERY ITEM | D13: BOOK BINDING SHEET AND TAPE | E13: Stationery & Office Supplies | G13: =IFERROR(VLOOKUP($F13,ItemList_Full,2,0),"") | I13: =IFERROR(VLOOKUP($F13,ItemList_Full,3,0),"") | J13: =IFERROR(VLOOKUP($F13,ItemList_Full,4,0),"") | K13: 650 | N13: Zeeshan (Sept import) | P13: =IF($E13="","",IF(OR($E13="Director Draw",$E13="Payroll/Employee Charge"),0,-$K13)) -> -650 | Q13: =IF($E13="Inventory Purchase",$H13,0) -> 0 | U13: FD-009 | V13: WINGS | W13: PKT | X13: 1260 | Y13: Food & Beverage
A14: 46266 | B14: =IF($A14="","",ROW()-4) -> 10 | C14: MATERIAL | D14: CROCKERY MATERIAL FOR KITCHEN | E14: Equipment & Smallwares | G14: =IFERROR(VLOOKUP($F14,ItemList_Full,2,0),"") | I14: =IFERROR(VLOOKUP($F14,ItemList_Full,3,0),"") | J14: =IFERROR(VLOOKUP($F14,ItemList_Full,4,0),"") | K14: 29000 | N14: Zeeshan (Sept import) | P14: =IF($E14="","",IF(OR($E14="Director Draw",$E14="Payroll/Employee Charge"),0,-$K14)) -> -29000 | Q14: =IF($E14="Inventory Purchase",$H14,0) -> 0 | U14: FD-010 | V14: DRUMMETTE | W14: PKT | X14: 1301 | Y14: Food & Beverage
A15: 46266 | B15: =IF($A15="","",ROW()-4) -> 11 | C15: MANAGEMENT | D15: AHSAN ZAIDI RGM | E15: Payroll | G15: =IFERROR(VLOOKUP($F15,ItemList_Full,2,0),"") | I15: =IFERROR(VLOOKUP($F15,ItemList_Full,3,0),"") | J15: =IFERROR(VLOOKUP($F15,ItemList_Full,4,0),"") | K15: 600 | N15: Zeeshan (Sept import) | P15: =IF($E15="","",IF(OR($E15="Director Draw",$E15="Payroll/Employee Charge"),0,-$K15)) -> -600 | Q15: =IF($E15="Inventory Purchase",$H15,0) -> 0 | U15: FD-011 | V15: SMOKED CHICKEN | W15: KG | X15: 1344 | Y15: Food & Beverage
A16: 46266 | B16: =IF($A16="","",ROW()-4) -> 12 | C16: BOH | D16: ZEESHAN K/M | E16: Payroll | G16: =IFERROR(VLOOKUP($F16,ItemList_Full,2,0),"") | I16: =IFERROR(VLOOKUP($F16,ItemList_Full,3,0),"") | J16: =IFERROR(VLOOKUP($F16,ItemList_Full,4,0),"") | K16: 200 | N16: Zeeshan (Sept import) | P16: =IF($E16="","",IF(OR($E16="Director Draw",$E16="Payroll/Employee Charge"),0,-$K16)) -> -200 | Q16: =IF($E16="Inventory Purchase",$H16,0) -> 0 | U16: FD-012 | V16: SAUSAGE | W16: KG | X16: 1088 | Y16: Food & Beverage
A17: 46266 | B17: =IF($A17="","",ROW()-4) -> 13 | C17: GENSET | D17: BETTERY FOR GENERATOR | E17: Repairs & Maintenance | G17: =IFERROR(VLOOKUP($F17,ItemList_Full,2,0),"") | I17: =IFERROR(VLOOKUP($F17,ItemList_Full,3,0),"") | J17: =IFERROR(VLOOKUP($F17,ItemList_Full,4,0),"") | K17: 25000 | N17: Zeeshan (Sept import) | P17: =IF($E17="","",IF(OR($E17="Director Draw",$E17="Payroll/Employee Charge"),0,-$K17)) -> -25000 | Q17: =IF($E17="Inventory Purchase",$H17,0) -> 0 | U17: FD-013 | V17: CHICKEN QEEMA K&NS | W17: KG | X17: 1122 | Y17: Food & Beverage
A18: 46266 | B18: =IF($A18="","",ROW()-4) -> 14 | C18: THERMAL PRINTER | D18: PRINTER INTERNET CONNECTOR CHANGE | E18: Repairs & Maintenance | G18: =IFERROR(VLOOKUP($F18,ItemList_Full,2,0),"") | I18: =IFERROR(VLOOKUP($F18,ItemList_Full,3,0),"") | J18: =IFERROR(VLOOKUP($F18,ItemList_Full,4,0),"") | K18: 1300 | N18: Zeeshan (Sept import) | P18: =IF($E18="","",IF(OR($E18="Director Draw",$E18="Payroll/Employee Charge"),0,-$K18)) -> -1300 | Q18: =IF($E18="Inventory Purchase",$H18,0) -> 0 | U18: FD-014 | V18: BIG BIRD KABAB | W18: PKT | X18: 1400.6 | Y18: Food & Beverage
... A23: 46267 | B23: =IF($A23="","",ROW()-4) -> 19 | C23: FOOD PANDA | D23: FOOD PANDA SALE | E23: Food Panda Commission | G23: =IFERROR(VLOOKUP($F23,ItemList_Full,2,0),"") | I23: =IFERROR(VLOOKUP($F23,ItemList_Full,3,0),"") | J23: =IFERROR(VLOOKUP($F23,ItemList_Full,4,0),"") | K23: 10100 | N23: Zeeshan (Sept import) | P23: =IF($E23="","",IF(OR($E23="Director Draw",$E23="Payroll/Employee Charge"),0,-$K23)) -> -10100 | Q23: =IF($E23="Inventory Purchase",$H23,0) -> 0 | U23: FD-019 | V23: 9 PIECE CUT | W23: PKT | X23: 1587 | Y23: Food & Beverage
A24: 46267 | B24: =IF($A24="","",ROW()-4) -> 20 | C24: - | D24: PARCAL PAYMENT FOR YASIR SB | E24: Director Draw | G24: =IFERROR(VLOOKUP($F24,ItemList_Full,2,0),"") | I24: =IFERROR(VLOOKUP($F24,ItemList_Full,3,0),"") | J24: =IFERROR(VLOOKUP($F24,ItemList_Full,4,0),"") | K24: 2880 | M24: Yasir Sb | N24: Zeeshan (Sept import) | P24: =IF($E24="","",IF(OR($E24="Director Draw",$E24="Payroll/Employee Charge"),0,-$K24)) -> 0 | Q24: =IF($E24="Inventory Purchase",$H24,0) -> 0 | U24: FD-020 | V24: REGULAR BONLESS THIGHS | W24: PKT | X24: 2410 | Y24: Food & Beverage
A25: 46267 | B25: =IF($A25="","",ROW()-4) -> 21 | C25: - | D25: DESI CHICKEN FOR BOSS HOME | E25: Director Draw | G25: =IFERROR(VLOOKUP($F25,ItemList_Full,2,0),"") | I25: =IFERROR(VLOOKUP($F25,ItemList_Full,3,0),"") | J25: =IFERROR(VLOOKUP($F25,ItemList_Full,4,0),"") | K25: 13000 | M25: Yasir Sb | N25: Zeeshan (Sept import) | P25: =IF($E25="","",IF(OR($E25="Director Draw",$E25="Payroll/Employee Charge"),0,-$K25)) -> 0 | Q25: =IF($E25="Inventory Purchase",$H25,0) -> 0 | U25: FD-021 | V25: COLA NEXT 2.25 ML | W25: PET | X25: 720 | Y25: Food & Beverage
A26: 46267 | B26: =IF($A26="","",ROW()-4) -> 22 | C26: - | D26: QR JAZZ CASH PAYMENT | E26: Director Draw | G26: =IFERROR(VLOOKUP($F26,ItemList_Full,2,0),"") | I26: =IFERROR(VLOOKUP($F26,ItemList_Full,3,0),"") | J26: =IFERROR(VLOOKUP($F26,ItemList_Full,4,0),"") | K26: 840 | M26: Yasir Sb | N26: Zeeshan (Sept import) | P26: =IF($E26="","",IF(OR($E26="Director Draw",$E26="Payroll/Employee Charge"),0,-$K26)) -> 0 | Q26: =IF($E26="Inventory Purchase",$H26,0) -> 0 | U26: FD-022 | V26: FIZUP 2.25 ML | W26: PET | X26: 720 | Y26: Food & Beverage
A27: 46267 | B27: =IF($A27="","",ROW()-4) -> 23 | C27: - | D27: T.A INV# 09 WATER FOR IMRAN TAHIR SB | E27: Director Draw | G27: =IFERROR(VLOOKUP($F27,ItemList_Full,2,0),"") | I27: =IFERROR(VLOOKUP($F27,ItemList_Full,3,0),"") | J27: =IFERROR(VLOOKUP($F27,ItemList_Full,4,0),"") | K27: 95 | M27: Imran Tahir | N27: Zeeshan (Sept import) | P27: =IF($E27="","",IF(OR($E27="Director Draw",$E27="Payroll/Employee Charge"),0,-$K27)) -> 0 | Q27: =IF($E27="Inventory Purchase",$H27,0) -> 0 | U27: FD-023 | V27: COLA NEXT 1500 ML | W27: PET | X27: 720 | Y27: Food & Beverage
A28: 46267 | B28: =IF($A28="","",ROW()-4) -> 24 | C28: ASIF ENTERPRISES (OMORE) | D28: ICE CREAM FOR BAR | E28: Food | G28: =IFERROR(VLOOKUP($F28,ItemList_Full,2,0),"") | I28: =IFERROR(VLOOKUP($F28,ItemList_Full,3,0),"") | J28: =IFERROR(VLOOKUP($F28,ItemList_Full,4,0),"") | K28: 11160 | N28: Zeeshan (Sept import) | P28: =IF($E28="","",IF(OR($E28="Director Draw",$E28="Payroll/Employee Charge"),0,-$K28)) -> -11160 | Q28: =IF($E28="Inventory Purchase",$H28,0) -> 0 | U28: FD-024 | V28: FIZE UP 1500 ML | W28: PET | X28: 720 | Y28: Food & Beverage
A29: 46267 | B29: =IF($A29="","",ROW()-4) -> 25 | C29: BAR | D29: ICE FOR BAR | E29: Food | G29: =IFERROR(VLOOKUP($F29,ItemList_Full,2,0),"") | I29: =IFERROR(VLOOKUP($F29,ItemList_Full,3,0),"") | J29: =IFERROR(VLOOKUP($F29,ItemList_Full,4,0),"") | K29: 1800 | N29: Zeeshan (Sept import) | P29: =IF($E29="","",IF(OR($E29="Director Draw",$E29="Payroll/Employee Charge"),0,-$K29)) -> -1800 | Q29: =IF($E29="Inventory Purchase",$H29,0) -> 0 | U29: FD-025 | V29: COLA NEXT 1000 ML | W29: PET | X29: 600 | Y29: Food & Beverage
A30: 46267 | B30: =IF($A30="","",ROW()-4) -> 26 | C30: FNK GRILL | D30: FNK GRILL BILL PAID | E30: Food | G30: =IFERROR(VLOOKUP($F30,ItemList_Full,2,0),"") | I30: =IFERROR(VLOOKUP($F30,ItemList_Full,3,0),"") | J30: =IFERROR(VLOOKUP($F30,ItemList_Full,4,0),"") | K30: 11000 | N30: Zeeshan (Sept import) | P30: =IF($E30="","",IF(OR($E30="Director Draw",$E30="Payroll/Employee Charge"),0,-$K30)) -> -11000 | Q30: =IF($E30="Inventory Purchase",$H30,0) -> 0 | U30: FD-026 | V30: FIZE UP 1000 ML | W30: PET | X30: 600 | Y30: Food & Beverage
A31: 46267 | B31: =IF($A31="","",ROW()-4) -> 27 | C31: K&N'S | D31: K&Ns BILL PAID | E31: Food | G31: =IFERROR(VLOOKUP($F31,ItemList_Full,2,0),"") | I31: =IFERROR(VLOOKUP($F31,ItemList_Full,3,0),"") | J31: =IFERROR(VLOOKUP($F31,ItemList_Full,4,0),"") | K31: 169000 | N31: Zeeshan (Sept import) | P31: =IF($E31="","",IF(OR($E31="Director Draw",$E31="Payroll/Employee Charge"),0,-$K31)) -> -169000 | Q31: =IF($E31="Inventory Purchase",$H31,0) -> 0 | U31: FD-027 | V31: COLA NEXT 500 ML | W31: PET | X31: 770 | Y31: Food & Beverage
A32: 46267 | B32: =IF($A32="","",ROW()-4) -> 28 | C32: CLEANING | D32: FUMIGATION CHARGES PAID | E32: Cleaning & Sanitation | G32: =IFERROR(VLOOKUP($F32,ItemList_Full,2,0),"") | I32: =IFERROR(VLOOKUP($F32,ItemList_Full,3,0),"") | J32: =IFERROR(VLOOKUP($F32,ItemList_Full,4,0),"") | K32: 10000 | N32: Zeeshan (Sept import) | P32: =IF($E32="","",IF(OR($E32="Director Draw",$E32="Payroll/Employee Charge"),0,-$K32)) -> -10000 | Q32: =IF($E32="Inventory Purchase",$H32,0) -> 0 | U32: FD-028 | V32: FIZE UP 500 ML | W32: PET | X32: 770 | Y32: Food & Beverage
A33: 46267 | B33: =IF($A33="","",ROW()-4) -> 29 | C33: WALK-IN | D33: WARMA AND RUBBET FOR MAKE TABLE AND WALKING DOOR | E33: Repairs & Maintenance | G33: =IFERROR(VLOOKUP($F33,ItemList_Full,2,0),"") | I33: =IFERROR(VLOOKUP($F33,ItemList_Full,3,0),"") | J33: =IFERROR(VLOOKUP($F33,ItemList_Full,4,0),"") | K33: 140 | N33: Zeeshan (Sept import) | P33: =IF($E33="","",IF(OR($E33="Director Draw",$E33="Payroll/Employee Charge"),0,-$K33)) -> -140 | Q33: =IF($E33="Inventory Purchase",$H33,0) -> 0 | U33: FD-029 | V33: COLA NEXT 300 ML | W33: PET | X33: 560 | Y33: Food & Beverage
A34: 46267 | B34: =IF($A34="","",ROW()-4) -> 30 | C34: KITCHEN WIRING | D34: DUCKET,FLEX PIPE AND DOUBLE BOARD SHEET FOR KITCHEN | E34: Repairs & Maintenance | G34: =IFERROR(VLOOKUP($F34,ItemList_Full,2,0),"") | I34: =IFERROR(VLOOKUP($F34,ItemList_Full,3,0),"") | J34: =IFERROR(VLOOKUP($F34,ItemList_Full,4,0),"") | K34: 2580 | N34: Zeeshan (Sept import) | P34: =IF($E34="","",IF(OR($E34="Director Draw",$E34="Payroll/Employee Charge"),0,-$K34)) -> -2580 | Q34: =IF($E34="Inventory Purchase",$H34,0) -> 0 | U34: FD-030 | V34: FIZE UP 300 ML | W34: PET | X34: 560 | Y34: Food & Beverage
A35: 46267 | B35: =IF($A35="","",ROW()-4) -> 31 | C35: MANAGEMENT | D35: AHSAN ZAIDI RGM | E35: Payroll | G35: =IFERROR(VLOOKUP($F35,ItemList_Full,2,0),"") | I35: =IFERROR(VLOOKUP($F35,ItemList_Full,3,0),"") | J35: =IFERROR(VLOOKUP($F35,ItemList_Full,4,0),"") | K35: 650 | N35: Zeeshan (Sept import) | P35: =IF($E35="","",IF(OR($E35="Director Draw",$E35="Payroll/Employee Charge"),0,-$K35)) -> -650 | Q35: =IF($E35="Inventory Purchase",$H35,0) -> 0 | U35: FD-031 | V35: WATER 1500 ML | W35: PET | X35: 380 | Y35: Food & Beverage
A36: 46267 | B36: =IF($A36="","",ROW()-4) -> 32 | C36: FOH | D36: NABEEL FOH SUPERVISOR | E36: Payroll | G36: =IFERROR(VLOOKUP($F36,ItemList_Full,2,0),"") | I36: =IFERROR(VLOOKUP($F36,ItemList_Full,3,0),"") | J36: =IFERROR(VLOOKUP($F36,ItemList_Full,4,0),"") | K36: 550 | N36: Zeeshan (Sept import) | P36: =IF($E36="","",IF(OR($E36="Director Draw",$E36="Payroll/Employee Charge"),0,-$K36)) -> -550 | Q36: =IF($E36="Inventory Purchase",$H36,0) -> 0 | U36: FD-032 | V36: WATER 500 ML | W36: PET | X36: 380 | Y36: Food & Beverage
A37: 46267 | B37: =IF($A37="","",ROW()-4) -> 33 | C37: FOH | D37: KHALIL CASHIER | E37: Payroll | G37: =IFERROR(VLOOKUP($F37,ItemList_Full,2,0),"") | I37: =IFERROR(VLOOKUP($F37,ItemList_Full,3,0),"") | J37: =IFERROR(VLOOKUP($F37,ItemList_Full,4,0),"") | K37: 1450 | N37: Zeeshan (Sept import) | P37: =IF($E37="","",IF(OR($E37="Director Draw",$E37="Payroll/Employee Charge"),0,-$K37)) -> -1450 | Q37: =IF($E37="Inventory Purchase",$H37,0) -> 0 | U37: FD-033 | V37: AL BARKA WATER BAR | W37: BOT | X37: 16000 | Y37: Food & Beverage
A38: 46267 | B38: =IF($A38="","",ROW()-4) -> 34 | C38: BOH | D38: ARSLAN ALI K/A | E38: Payroll | G38: =IFERROR(VLOOKUP($F38,ItemList_Full,2,0),"") | I38: =IFERROR(VLOOKUP($F38,ItemList_Full,3,0),"") | J38: =IFERROR(VLOOKUP($F38,ItemList_Full,4,0),"") | K38: 2000 | N38: Zeeshan (Sept import) | P38: =IF($E38="","",IF(OR($E38="Director Draw",$E38="Payroll/Employee Charge"),0,-$K38)) -> -2000 | Q38: =IF($E38="Inventory Purchase",$H38,0) -> 0 | U38: FD-034 | V38: MIRINDA FEGILE | W38: CYL | X38: 8211 | Y38: Food & Beverage
A39: 46267 | B39: =IF($A39="","",ROW()-4) -> 35 | C39: DELIVERY | D39: TAYYAB RIDER | E39: Payroll | G39: =IFERROR(VLOOKUP($F39,ItemList_Full,2,0),"") | I39: =IFERROR(VLOOKUP($F39,ItemList_Full,3,0),"") | J39: =IFERROR(VLOOKUP($F39,ItemList_Full,4,0),"") | K39: 550 | N39: Zeeshan (Sept import) | P39: =IF($E39="","",IF(OR($E39="Director Draw",$E39="Payroll/Employee Charge"),0,-$K39)) -> -550 | Q39: =IF($E39="Inventory Purchase",$H39,0) -> 0 | U39: FD-035 | V39: PEPSI 1500 ML | W39: PET | X39: 891 | Y39: Food & Beverage
... A42: 46267 | B42: =IF($A42="","",ROW()-4) -> 38 | C42: SIM | D42: NEW SIM PURCHASE FOR JAZZ CASH | E42: Utilities (Electricity/Water) | G42: =IFERROR(VLOOKUP($F42,ItemList_Full,2,0),"") | I42: =IFERROR(VLOOKUP($F42,ItemList_Full,3,0),"") | J42: =IFERROR(VLOOKUP($F42,ItemList_Full,4,0),"") | K42: 2100 | N42: Zeeshan (Sept import) | P42: =IF($E42="","",IF(OR($E42="Director Draw",$E42="Payroll/Employee Charge"),0,-$K42)) -> -2100 | Q42: =IF($E42="Inventory Purchase",$H42,0) -> 0 | U42: FD-038 | V42: GOURMENT 345 ML | W42: PET | X42: 610 | Y42: Food & Beverage
A43: 46268 | B43: =IF($A43="","",ROW()-4) -> 39 | C43: - | D43: QR JAZZ CASH PAYMENT | E43: Director Draw | G43: =IFERROR(VLOOKUP($F43,ItemList_Full,2,0),"") | I43: =IFERROR(VLOOKUP($F43,ItemList_Full,3,0),"") | J43: =IFERROR(VLOOKUP($F43,ItemList_Full,4,0),"") | K43: 13560 | M43: Yasir Sb | N43: Zeeshan (Sept import) | P43: =IF($E43="","",IF(OR($E43="Director Draw",$E43="Payroll/Employee Charge"),0,-$K43)) -> 0 | Q43: =IF($E43="Inventory Purchase",$H43,0) -> 0 | U43: FD-039 | V43: NUGGETS | W43: PKT | X43: 975 | Y43: Food & Beverage
A44: 46268 | B44: =IF($A44="","",ROW()-4) -> 40 | C44: - | D44: CASH GIVEN TO YASIR SB | E44: Director Draw | G44: =IFERROR(VLOOKUP($F44,ItemList_Full,2,0),"") | I44: =IFERROR(VLOOKUP($F44,ItemList_Full,3,0),"") | J44: =IFERROR(VLOOKUP($F44,ItemList_Full,4,0),"") | K44: 10000 | M44: Yasir Sb | N44: Zeeshan (Sept import) | P44: =IF($E44="","",IF(OR($E44="Director Draw",$E44="Payroll/Employee Charge"),0,-$K44)) -> 0 | Q44: =IF($E44="Inventory Purchase",$H44,0) -> 0 | U44: FD-040 | V44: FRIED FLOUR | W44: KG | X44: 166.5 | Y44: Food & Beverage
A45: 46268 | B45: =IF($A45="","",ROW()-4) -> 41 | C45: - | D45: PARCAL PAYMENT FOR YASIR SB | E45: Director Draw | G45: =IFERROR(VLOOKUP($F45,ItemList_Full,2,0),"") | I45: =IFERROR(VLOOKUP($F45,ItemList_Full,3,0),"") | J45: =IFERROR(VLOOKUP($F45,ItemList_Full,4,0),"") | K45: 4630 | M45: Yasir Sb | N45: Zeeshan (Sept import) | P45: =IF($E45="","",IF(OR($E45="Director Draw",$E45="Payroll/Employee Charge"),0,-$K45)) -> 0 | Q45: =IF($E45="Inventory Purchase",$H45,0) -> 0 | U45: FD-041 | V45: MARINATED FRIED FLOUR | W45: BAG | X45: 2250 | Y45: Food & Beverage
A46: 46268 | B46: =IF($A46="","",ROW()-4) -> 42 | C46: - | D46: DELIVERY INV# 39 MEAL FOR HASSAN NASIR SB | E46: Director Draw | G46: =IFERROR(VLOOKUP($F46,ItemList_Full,2,0),"") | I46: =IFERROR(VLOOKUP($F46,ItemList_Full,3,0),"") | J46: =IFERROR(VLOOKUP($F46,ItemList_Full,4,0),"") | K46: 3015 | M46: Hassan Nasir | N46: Zeeshan (Sept import) | P46: =IF($E46="","",IF(OR($E46="Director Draw",$E46="Payroll/Employee Charge"),0,-$K46)) -> 0 | Q46: =IF($E46="Inventory Purchase",$H46,0) -> 0 | U46: FD-042 | V46: OIL 16 LITTER'S | W46: TIN | X46: 8000 | Y46: Food & Beverage
A47: 46268 | B47: =IF($A47="","",ROW()-4) -> 43 | C47: - | D47: T.A INV# 04 MEAL FOR IMRAN TAHIR SB | E47: Director Draw | G47: =IFERROR(VLOOKUP($F47,ItemList_Full,2,0),"") | I47: =IFERROR(VLOOKUP($F47,ItemList_Full,3,0),"") | J47: =IFERROR(VLOOKUP($F47,ItemList_Full,4,0),"") | K47: 620 | M47: Imran Tahir | N47: Zeeshan (Sept import) | P47: =IF($E47="","",IF(OR($E47="Director Draw",$E47="Payroll/Employee Charge"),0,-$K47)) -> 0 | Q47: =IF($E47="Inventory Purchase",$H47,0) -> 0 | U47: FD-043 | V47: GOLDEN BROWN FRIES | W47: PKT | X47: 937.5 | Y47: Food & Beverage
A48: 46268 | B48: =IF($A48="","",ROW()-4) -> 44 | C48: FOOD PANDA | D48: FOOD PANDA SALE | E48: Food Panda Commission | G48: =IFERROR(VLOOKUP($F48,ItemList_Full,2,0),"") | I48: =IFERROR(VLOOKUP($F48,ItemList_Full,3,0),"") | J48: =IFERROR(VLOOKUP($F48,ItemList_Full,4,0),"") | K48: 3500 | N48: Zeeshan (Sept import) | P48: =IF($E48="","",IF(OR($E48="Director Draw",$E48="Payroll/Employee Charge"),0,-$K48)) -> -3500 | Q48: =IF($E48="Inventory Purchase",$H48,0) -> 0 | U48: FD-044 | V48: BREAD CRUMBS | W48: PKT | X48: 740 | Y48: Food & Beverage
A49: 46268 | B49: =IF($A49="","",ROW()-4) -> 45 | C49: FNK BAKERY | D49: FNK BAKERY BILL PAID | E49: Food | G49: =IFERROR(VLOOKUP($F49,ItemList_Full,2,0),"") | I49: =IFERROR(VLOOKUP($F49,ItemList_Full,3,0),"") | J49: =IFERROR(VLOOKUP($F49,ItemList_Full,4,0),"") | K49: 70497 | N49: Zeeshan (Sept import) | P49: =IF($E49="","",IF(OR($E49="Director Draw",$E49="Payroll/Employee Charge"),0,-$K49)) -> -70497 | Q49: =IF($E49="Inventory Purchase",$H49,0) -> 0 | U49: FD-045 | V49: OPA FRIES | W49: PKT | X49: 950 | Y49: Food & Beverage
A50: 46268 | B50: =IF($A50="","",ROW()-4) -> 46 | C50: FNK GRILL | D50: FNK GRILL BILL PAID | E50: Food | G50: =IFERROR(VLOOKUP($F50,ItemList_Full,2,0),"") | I50: =IFERROR(VLOOKUP($F50,ItemList_Full,3,0),"") | J50: =IFERROR(VLOOKUP($F50,ItemList_Full,4,0),"") | K50: 30000 | N50: Zeeshan (Sept import) | P50: =IF($E50="","",IF(OR($E50="Director Draw",$E50="Payroll/Employee Charge"),0,-$K50)) -> -30000 | Q50: =IF($E50="Inventory Purchase",$H50,0) -> 0 | U50: FD-046 | V50: LONDON CAKE | W50: PCS | X50: 1999 | Y50: Food & Beverage
A51: 46268 | B51: =IF($A51="","",ROW()-4) -> 47 | C51: BAR | D51: MINT FOR BAR | E51: Food | G51: =IFERROR(VLOOKUP($F51,ItemList_Full,2,0),"") | I51: =IFERROR(VLOOKUP($F51,ItemList_Full,3,0),"") | J51: =IFERROR(VLOOKUP($F51,ItemList_Full,4,0),"") | K51: 750 | N51: Zeeshan (Sept import) | P51: =IF($E51="","",IF(OR($E51="Director Draw",$E51="Payroll/Employee Charge"),0,-$K51)) -> -750 | Q51: =IF($E51="Inventory Purchase",$H51,0) -> 0 | U51: FD-047 | V51: MUFFIN | W51: PCS | X51: 240 | Y51: Food & Beverage
A52: 46268 | B52: =IF($A52="","",ROW()-4) -> 48 | C52: BREAD AND BEYOND | D52: BURGER BUN | E52: Food | G52: =IFERROR(VLOOKUP($F52,ItemList_Full,2,0),"") | I52: =IFERROR(VLOOKUP($F52,ItemList_Full,3,0),"") | J52: =IFERROR(VLOOKUP($F52,ItemList_Full,4,0),"") | K52: 2180 | N52: Zeeshan (Sept import) | P52: =IF($E52="","",IF(OR($E52="Director Draw",$E52="Payroll/Employee Charge"),0,-$K52)) -> -2180 | Q52: =IF($E52="Inventory Purchase",$H52,0) -> 0 | U52: FD-048 | V52: SUNDAE | W52: PCS | X52: 240 | Y52: Food & Beverage
A53: 46268 | B53: =IF($A53="","",ROW()-4) -> 49 | C53: BOH PAPER | D53: P-1 | E53: Packaging | G53: =IFERROR(VLOOKUP($F53,ItemList_Full,2,0),"") | I53: =IFERROR(VLOOKUP($F53,ItemList_Full,3,0),"") | J53: =IFERROR(VLOOKUP($F53,ItemList_Full,4,0),"") | K53: 1200 | N53: Zeeshan (Sept import) | P53: =IF($E53="","",IF(OR($E53="Director Draw",$E53="Payroll/Employee Charge"),0,-$K53)) -> -1200 | Q53: =IF($E53="Inventory Purchase",$H53,0) -> 0 | U53: FD-049 | V53: KIT KAT CAKE | W53: PCS | X53: 1999 | Y53: Food & Beverage
A54: 46268 | B54: =IF($A54="","",ROW()-4) -> 50 | C54: MANAGEMENT | D54: AHSAN ZAIDI RGM | E54: Payroll | G54: =IFERROR(VLOOKUP($F54,ItemList_Full,2,0),"") | I54: =IFERROR(VLOOKUP($F54,ItemList_Full,3,0),"") | J54: =IFERROR(VLOOKUP($F54,ItemList_Full,4,0),"") | K54: 100000 | N54: Zeeshan (Sept import) | P54: =IF($E54="","",IF(OR($E54="Director Draw",$E54="Payroll/Employee Charge"),0,-$K54)) -> -100000 | Q54: =IF($E54="Inventory Purchase",$H54,0) -> 0 | U54: FD-050 | V54: ALMOND CAKE | W54: PCS | X54: 1999 | Y54: Food & Beverage
A55: 46268 | B55: =IF($A55="","",ROW()-4) -> 51 | C55: MANAGEMENT | D55: AHSAN ZAIDI RGM | E55: Payroll | G55: =IFERROR(VLOOKUP($F55,ItemList_Full,2,0),"") | I55: =IFERROR(VLOOKUP($F55,ItemList_Full,3,0),"") | J55: =IFERROR(VLOOKUP($F55,ItemList_Full,4,0),"") | K55: 800 | N55: Zeeshan (Sept import) | P55: =IF($E55="","",IF(OR($E55="Director Draw",$E55="Payroll/Employee Charge"),0,-$K55)) -> -800 | Q55: =IF($E55="Inventory Purchase",$H55,0) -> 0 | U55: FD-051 | V55: RED VELVET CAKE | W55: PCS | X55: 1999 | Y55: Food & Beverage
A56: 46268 | B56: =IF($A56="","",ROW()-4) -> 52 | C56: FOH | D56: USMAN SERVER | E56: Payroll | G56: =IFERROR(VLOOKUP($F56,ItemList_Full,2,0),"") | I56: =IFERROR(VLOOKUP($F56,ItemList_Full,3,0),"") | J56: =IFERROR(VLOOKUP($F56,ItemList_Full,4,0),"") | K56: 1000 | N56: Zeeshan (Sept import) | P56: =IF($E56="","",IF(OR($E56="Director Draw",$E56="Payroll/Employee Charge"),0,-$K56)) -> -1000 | Q56: =IF($E56="Inventory Purchase",$H56,0) -> 0 | U56: FD-052 | V56: BUTTER SCOTCH | W56: PCS | X56: 1699 | Y56: Food & Beverage
A57: 46268 | B57: =IF($A57="","",ROW()-4) -> 53 | C57: KITCHEN WIRING | D57: BOARD FOR KITCHEN | E57: Repairs & Maintenance | G57: =IFERROR(VLOOKUP($F57,ItemList_Full,2,0),"") | I57: =IFERROR(VLOOKUP($F57,ItemList_Full,3,0),"") | J57: =IFERROR(VLOOKUP($F57,ItemList_Full,4,0),"") | K57: 80 | N57: Zeeshan (Sept import) | P57: =IF($E57="","",IF(OR($E57="Director Draw",$E57="Payroll/Employee Charge"),0,-$K57)) -> -80 | Q57: =IF($E57="Inventory Purchase",$H57,0) -> 0 | U57: FD-053 | V57: FRERRO ROACHER CAKE | W57: KG | X57: 1899 | Y57: Food & Beverage
A58: 46268 | B58: =IF($A58="","",ROW()-4) -> 54 | C58: CASH COUNTER | D58: LIGHT FOR CASH COUNTER AND DISPATCH AREA | E58: Repairs & Maintenance | G58: =IFERROR(VLOOKUP($F58,ItemList_Full,2,0),"") | I58: =IFERROR(VLOOKUP($F58,ItemList_Full,3,0),"") | J58: =IFERROR(VLOOKUP($F58,ItemList_Full,4,0),"") | K58: 1200 | N58: Zeeshan (Sept import) | P58: =IF($E58="","",IF(OR($E58="Director Draw",$E58="Payroll/Employee Charge"),0,-$K58)) -> -1200 | Q58: =IF($E58="Inventory Purchase",$H58,0) -> 0 | U58: FD-054 | V58: PISTACHEW CAKE | W58: PCS | X58: 1999 | Y58: Food & Beverage
A59: 46268 | B59: =IF($A59="","",ROW()-4) -> 55 | C59: GMSA (LPG CYLINDERS) | D59: GMSA LPG CYLINDER BILL PAID | E59: Utilities (Electricity/Water) | G59: =IFERROR(VLOOKUP($F59,ItemList_Full,2,0),"") | I59: =IFERROR(VLOOKUP($F59,ItemList_Full,3,0),"") | J59: =IFERROR(VLOOKUP($F59,ItemList_Full,4,0),"") | K59: 87168 | N59: Zeeshan (Sept import) | P59: =IF($E59="","",IF(OR($E59="Director Draw",$E59="Payroll/Employee Charge"),0,-$K59)) -> -87168 | Q59: =IF($E59="Inventory Purchase",$H59,0) -> 0 | U59: FD-055 | V59: LOUTUS CAKE | W59: PCS | X59: 1999 | Y59: Food & Beverage
... A62: 46268 | B62: =IF($A62="","",ROW()-4) -> 58 | C62: PROMO MEAL | D62: T.A INV# 02 DRINK FOR JAZZ CASH TEAM | E62: Employee Meals & Medical | G62: =IFERROR(VLOOKUP($F62,ItemList_Full,2,0),"") | I62: =IFERROR(VLOOKUP($F62,ItemList_Full,3,0),"") | J62: =IFERROR(VLOOKUP($F62,ItemList_Full,4,0),"") | K62: 1400 | N62: Zeeshan (Sept import) | P62: =IF($E62="","",IF(OR($E62="Director Draw",$E62="Payroll/Employee Charge"),0,-$K62)) -> -1400 | Q62: =IF($E62="Inventory Purchase",$H62,0) -> 0 | U62: FD-058 | V62: CHOCOLATE CHIP CAKE | W62: PCS | X62: 1799 | Y62: Food & Beverage
A63: 46269 | B63: =IF($A63="","",ROW()-4) -> 59 | C63: - | D63: QR JAZZ CASH PAYMENT | E63: Director Draw | G63: =IFERROR(VLOOKUP($F63,ItemList_Full,2,0),"") | I63: =IFERROR(VLOOKUP($F63,ItemList_Full,3,0),"") | J63: =IFERROR(VLOOKUP($F63,ItemList_Full,4,0),"") | K63: 5855 | M63: Yasir Sb | N63: Zeeshan (Sept import) | P63: =IF($E63="","",IF(OR($E63="Director Draw",$E63="Payroll/Employee Charge"),0,-$K63)) -> 0 | Q63: =IF($E63="Inventory Purchase",$H63,0) -> 0 | U63: FD-059 | V63: TIRAMISU CAKE | W63: PCS | X63: 1999 | Y63: Food & Beverage
A64: 46269 | B64: =IF($A64="","",ROW()-4) -> 60 | C64: - | D64: DINE-IN INV# 52 MEAL FOR YASIR SB | E64: Director Draw | G64: =IFERROR(VLOOKUP($F64,ItemList_Full,2,0),"") | I64: =IFERROR(VLOOKUP($F64,ItemList_Full,3,0),"") | J64: =IFERROR(VLOOKUP($F64,ItemList_Full,4,0),"") | K64: 1305 | M64: Yasir Sb | N64: Zeeshan (Sept import) | P64: =IF($E64="","",IF(OR($E64="Director Draw",$E64="Payroll/Employee Charge"),0,-$K64)) -> 0 | Q64: =IF($E64="Inventory Purchase",$H64,0) -> 0 | U64: FD-060 | V64: KULFA CAKE | W64: PCS | X64: 1599 | Y64: Food & Beverage
A65: 46269 | B65: =IF($A65="","",ROW()-4) -> 61 | C65: - | D65: MEAL FOR YASIR SB | E65: Director Draw | G65: =IFERROR(VLOOKUP($F65,ItemList_Full,2,0),"") | I65: =IFERROR(VLOOKUP($F65,ItemList_Full,3,0),"") | J65: =IFERROR(VLOOKUP($F65,ItemList_Full,4,0),"") | K65: 3276 | M65: Yasir Sb | N65: Zeeshan (Sept import) | P65: =IF($E65="","",IF(OR($E65="Director Draw",$E65="Payroll/Employee Charge"),0,-$K65)) -> 0 | Q65: =IF($E65="Inventory Purchase",$H65,0) -> 0 | U65: FD-061 | V65: CLASSIC CHOCOLATE | W65: PCS | X65: 1599 | Y65: Food & Beverage
A66: 46269 | B66: =IF($A66="","",ROW()-4) -> 62 | C66: - | D66: T.A INV# 02 MEAL FOR IMRAN TAHIR SB | E66: Director Draw | G66: =IFERROR(VLOOKUP($F66,ItemList_Full,2,0),"") | I66: =IFERROR(VLOOKUP($F66,ItemList_Full,3,0),"") | J66: =IFERROR(VLOOKUP($F66,ItemList_Full,4,0),"") | K66: 395 | M66: Imran Tahir | N66: Zeeshan (Sept import) | P66: =IF($E66="","",IF(OR($E66="Director Draw",$E66="Payroll/Employee Charge"),0,-$K66)) -> 0 | Q66: =IF($E66="Inventory Purchase",$H66,0) -> 0 | U66: FD-062 | V66: COOKIES CREAM | W66: PCS | X66: 1699 | Y66: Food & Beverage
A67: 46269 | B67: =IF($A67="","",ROW()-4) -> 63 | C67: FOOD PANDA | D67: FOOD PANDA SALE | E67: Food Panda Commission | G67: =IFERROR(VLOOKUP($F67,ItemList_Full,2,0),"") | I67: =IFERROR(VLOOKUP($F67,ItemList_Full,3,0),"") | J67: =IFERROR(VLOOKUP($F67,ItemList_Full,4,0),"") | K67: 3589 | N67: Zeeshan (Sept import) | P67: =IF($E67="","",IF(OR($E67="Director Draw",$E67="Payroll/Employee Charge"),0,-$K67)) -> -3589 | Q67: =IF($E67="Inventory Purchase",$H67,0) -> 0 | U67: FD-063 | V67: CUSTOMIZED CAKE | W67: PCS | X67: 1200 | Y67: Food & Beverage
A68: 46269 | B68: =IF($A68="","",ROW()-4) -> 64 | C68: SAUCE MATERIAL | D68: HONEY,BREAD CRUMS AND TOTRILLA WRAP BREAD | E68: Food | G68: =IFERROR(VLOOKUP($F68,ItemList_Full,2,0),"") | I68: =IFERROR(VLOOKUP($F68,ItemList_Full,3,0),"") | J68: =IFERROR(VLOOKUP($F68,ItemList_Full,4,0),"") | K68: 3330 | N68: Zeeshan (Sept import) | P68: =IF($E68="","",IF(OR($E68="Director Draw",$E68="Payroll/Employee Charge"),0,-$K68)) -> -3330 | Q68: =IF($E68="Inventory Purchase",$H68,0) -> 0 | U68: FD-064 | V68: CUSTOMIZED MUFFIN | W68: PCS | X68: 320 | Y68: Food & Beverage
A69: 46269 | B69: =IF($A69="","",ROW()-4) -> 65 | C69: BAR | D69: ICE FOR BAR | E69: Food | G69: =IFERROR(VLOOKUP($F69,ItemList_Full,2,0),"") | I69: =IFERROR(VLOOKUP($F69,ItemList_Full,3,0),"") | J69: =IFERROR(VLOOKUP($F69,ItemList_Full,4,0),"") | K69: 540 | N69: Zeeshan (Sept import) | P69: =IF($E69="","",IF(OR($E69="Director Draw",$E69="Payroll/Employee Charge"),0,-$K69)) -> -540 | Q69: =IF($E69="Inventory Purchase",$H69,0) -> 0 | U69: FD-065 | V69: CHOCO BALL | W69: PCS | X69: 120 | Y69: Food & Beverage
A70: 46269 | B70: =IF($A70="","",ROW()-4) -> 66 | C70: KOHINOOR | D70: DELUXE SAUCE PAYMENT | E70: Food | G70: =IFERROR(VLOOKUP($F70,ItemList_Full,2,0),"") | I70: =IFERROR(VLOOKUP($F70,ItemList_Full,3,0),"") | J70: =IFERROR(VLOOKUP($F70,ItemList_Full,4,0),"") | K70: 2500 | N70: Zeeshan (Sept import) | P70: =IF($E70="","",IF(OR($E70="Director Draw",$E70="Payroll/Employee Charge"),0,-$K70)) -> -2500 | Q70: =IF($E70="Inventory Purchase",$H70,0) -> 0 | U70: FD-066 | V70: LAVA CAKE | W70: PCS | X70: 300 | Y70: Food & Beverage
A71: 46269 | B71: =IF($A71="","",ROW()-4) -> 67 | C71: LOCAL MARKET | D71: EGGS FOR KITCHEN | E71: Food | G71: =IFERROR(VLOOKUP($F71,ItemList_Full,2,0),"") | I71: =IFERROR(VLOOKUP($F71,ItemList_Full,3,0),"") | J71: =IFERROR(VLOOKUP($F71,ItemList_Full,4,0),"") | K71: 562 | N71: Zeeshan (Sept import) | P71: =IF($E71="","",IF(OR($E71="Director Draw",$E71="Payroll/Employee Charge"),0,-$K71)) -> -562 | Q71: =IF($E71="Inventory Purchase",$H71,0) -> 0 | U71: FD-067 | V71: 2 POUND ORDER CAKE | W71: PCS | X71: 2499 | Y71: Food & Beverage
A72: 46269 | B72: =IF($A72="","",ROW()-4) -> 68 | C72: BREAD AND BEYOND | D72: BURGER BUN | E72: Food | G72: =IFERROR(VLOOKUP($F72,ItemList_Full,2,0),"") | I72: =IFERROR(VLOOKUP($F72,ItemList_Full,3,0),"") | J72: =IFERROR(VLOOKUP($F72,ItemList_Full,4,0),"") | K72: 3270 | N72: Zeeshan (Sept import) | P72: =IF($E72="","",IF(OR($E72="Director Draw",$E72="Payroll/Employee Charge"),0,-$K72)) -> -3270 | Q72: =IF($E72="Inventory Purchase",$H72,0) -> 0 | U72: FD-068 | V72: THREE MILK CAKE SLICE | W72: PCS | X72: 375 | Y72: Food & Beverage
A73: 46269 | B73: =IF($A73="","",ROW()-4) -> 69 | C73: FNK GRILL | D73: FNK GRILL BILL PAID | E73: Food | G73: =IFERROR(VLOOKUP($F73,ItemList_Full,2,0),"") | I73: =IFERROR(VLOOKUP($F73,ItemList_Full,3,0),"") | J73: =IFERROR(VLOOKUP($F73,ItemList_Full,4,0),"") | K73: 10000 | N73: Zeeshan (Sept import) | P73: =IF($E73="","",IF(OR($E73="Director Draw",$E73="Payroll/Employee Charge"),0,-$K73)) -> -10000 | Q73: =IF($E73="Inventory Purchase",$H73,0) -> 0 | U73: FD-069 | V73: CAKE DIMI | W73: PCS | X73: 2000 | Y73: Food & Beverage
A74: 46269 | B74: =IF($A74="","",ROW()-4) -> 70 | C74: FOH | D74: KHALIL CASHIER | E74: Payroll | G74: =IFERROR(VLOOKUP($F74,ItemList_Full,2,0),"") | I74: =IFERROR(VLOOKUP($F74,ItemList_Full,3,0),"") | J74: =IFERROR(VLOOKUP($F74,ItemList_Full,4,0),"") | K74: 2450 | N74: Zeeshan (Sept import) | P74: =IF($E74="","",IF(OR($E74="Director Draw",$E74="Payroll/Employee Charge"),0,-$K74)) -> -2450 | Q74: =IF($E74="Inventory Purchase",$H74,0) -> 0 | U74: FD-070 | V74: DOUBLE CHOCLATE FUDGE | W74: PCS | X74: 1999 | Y74: Food & Beverage
A75: 46269 | B75: =IF($A75="","",ROW()-4) -> 71 | C75: FOH | D75: SAQIB CASHIER | E75: Payroll | G75: =IFERROR(VLOOKUP($F75,ItemList_Full,2,0),"") | I75: =IFERROR(VLOOKUP($F75,ItemList_Full,3,0),"") | J75: =IFERROR(VLOOKUP($F75,ItemList_Full,4,0),"") | K75: 2453 | N75: Zeeshan (Sept import) | P75: =IF($E75="","",IF(OR($E75="Director Draw",$E75="Payroll/Employee Charge"),0,-$K75)) -> -2453 | Q75: =IF($E75="Inventory Purchase",$H75,0) -> 0 | U75: FD-071 | V75: CADBURY CAKE | W75: PCS | X75: 1999 | Y75: Food & Beverage
A76: 46269 | B76: =IF($A76="","",ROW()-4) -> 72 | C76: BOH | D76: TALHA K/A | E76: Payroll | G76: =IFERROR(VLOOKUP($F76,ItemList_Full,2,0),"") | I76: =IFERROR(VLOOKUP($F76,ItemList_Full,3,0),"") | J76: =IFERROR(VLOOKUP($F76,ItemList_Full,4,0),"") | K76: 1150 | N76: Zeeshan (Sept import) | P76: =IF($E76="","",IF(OR($E76="Director Draw",$E76="Payroll/Employee Charge"),0,-$K76)) -> -1150 | Q76: =IF($E76="Inventory Purchase",$H76,0) -> 0 | U76: FD-072 | V76: SPECIAL CAKE SLICE | W76: PCS | X76: 500 | Y76: Food & Beverage
A77: 46269 | B77: =IF($A77="","",ROW()-4) -> 73 | C77: FOH | D77: LIGHTS,BOARD FOR FRONT AREA BULDING | E77: Repairs & Maintenance | G77: =IFERROR(VLOOKUP($F77,ItemList_Full,2,0),"") | I77: =IFERROR(VLOOKUP($F77,ItemList_Full,3,0),"") | J77: =IFERROR(VLOOKUP($F77,ItemList_Full,4,0),"") | K77: 7150 | N77: Zeeshan (Sept import) | P77: =IF($E77="","",IF(OR($E77="Director Draw",$E77="Payroll/Employee Charge"),0,-$K77)) -> -7150 | Q77: =IF($E77="Inventory Purchase",$H77,0) -> 0 | U77: FD-073 | V77: RICH CHOCOLATE | W77: PCS | X77: 1599 | Y77: Food & Beverage
A78: 46269 | B78: =IF($A78="","",ROW()-4) -> 74 | C78: PROMO MEAL | D78: DINE-IN INV# 82 MEAL FOR AHSAN ZAIDI RGM | E78: Employee Meals & Medical | G78: =IFERROR(VLOOKUP($F78,ItemList_Full,2,0),"") | I78: =IFERROR(VLOOKUP($F78,ItemList_Full,3,0),"") | J78: =IFERROR(VLOOKUP($F78,ItemList_Full,4,0),"") | K78: 550 | N78: Zeeshan (Sept import) | P78: =IF($E78="","",IF(OR($E78="Director Draw",$E78="Payroll/Employee Charge"),0,-$K78)) -> -550 | Q78: =IF($E78="Inventory Purchase",$H78,0) -> 0 | U78: FD-074 | V78: GALAXY CHOCLATE | W78: PCS | X78: 1599 | Y78: Food & Beverage
... A82: 46269 | B82: =IF($A82="","",ROW()-4) -> 78 | C82: COMPLAIN | D82: DINE-IN INV# 76 PIZZA TASTE WAS DRY AND TESTLESS | E82: Charge to Restaurant | G82: =IFERROR(VLOOKUP($F82,ItemList_Full,2,0),"") | I82: =IFERROR(VLOOKUP($F82,ItemList_Full,3,0),"") | J82: =IFERROR(VLOOKUP($F82,ItemList_Full,4,0),"") | K82: 2695 | N82: Zeeshan (Sept import) | P82: =IF($E82="","",IF(OR($E82="Director Draw",$E82="Payroll/Employee Charge"),0,-$K82)) -> -2695 | Q82: =IF($E82="Inventory Purchase",$H82,0) -> 0 | U82: FD-078 | V82: DALDA OIL 5 LTR | W82: BOT | X82: 2890.0645 | Y82: Food & Beverage
A83: 46270 | B83: =IF($A83="","",ROW()-4) -> 79 | C83: - | D83: DINE-IN INV# 27 MEAL FOR BOSS YASIR SB | E83: Director Draw | G83: =IFERROR(VLOOKUP($F83,ItemList_Full,2,0),"") | I83: =IFERROR(VLOOKUP($F83,ItemList_Full,3,0),"") | J83: =IFERROR(VLOOKUP($F83,ItemList_Full,4,0),"") | K83: 11925 | M83: Yasir Sb | N83: Zeeshan (Sept import) | P83: =IF($E83="","",IF(OR($E83="Director Draw",$E83="Payroll/Employee Charge"),0,-$K83)) -> 0 | Q83: =IF($E83="Inventory Purchase",$H83,0) -> 0 | U83: FD-079 | V83: NIDO MILK | W83: PKT | X83: 2400 | Y83: Food & Beverage
A84: 46270 | B84: =IF($A84="","",ROW()-4) -> 80 | C84: BAR | D84: OREO BISCUT FOR BAR | E84: Food | G84: =IFERROR(VLOOKUP($F84,ItemList_Full,2,0),"") | I84: =IFERROR(VLOOKUP($F84,ItemList_Full,3,0),"") | J84: =IFERROR(VLOOKUP($F84,ItemList_Full,4,0),"") | K84: 100 | N84: Zeeshan (Sept import) | P84: =IF($E84="","",IF(OR($E84="Director Draw",$E84="Payroll/Employee Charge"),0,-$K84)) -> -100 | Q84: =IF($E84="Inventory Purchase",$H84,0) -> 0 | U84: FD-080 | V84: DOUGH BLEND | W84: PKT | X84: 900 | Y84: Food & Beverage
A85: 46270 | B85: =IF($A85="","",ROW()-4) -> 81 | C85: FOOD PANDA | D85: FOOD PANDA SALE | E85: Food Panda Commission | G85: =IFERROR(VLOOKUP($F85,ItemList_Full,2,0),"") | I85: =IFERROR(VLOOKUP($F85,ItemList_Full,3,0),"") | J85: =IFERROR(VLOOKUP($F85,ItemList_Full,4,0),"") | K85: 12056 | N85: Zeeshan (Sept import) | P85: =IF($E85="","",IF(OR($E85="Director Draw",$E85="Payroll/Employee Charge"),0,-$K85)) -> -12056 | Q85: =IF($E85="Inventory Purchase",$H85,0) -> 0 | U85: FD-081 | V85: SUFI SOYBEAN OIL 3 LTR | W85: BOTTLE | X85: 1800 | Y85: Food & Beverage
A86: 46270 | B86: =IF($A86="","",ROW()-4) -> 82 | C86: BAR | D86: ICE FOR BAR | E86: Food | G86: =IFERROR(VLOOKUP($F86,ItemList_Full,2,0),"") | I86: =IFERROR(VLOOKUP($F86,ItemList_Full,3,0),"") | J86: =IFERROR(VLOOKUP($F86,ItemList_Full,4,0),"") | K86: 540 | N86: Zeeshan (Sept import) | P86: =IF($E86="","",IF(OR($E86="Director Draw",$E86="Payroll/Employee Charge"),0,-$K86)) -> -540 | Q86: =IF($E86="Inventory Purchase",$H86,0) -> 0 | U86: FD-082 | V86: CORN FLOUR | W86: KG | X86: 200 | Y86: Food & Beverage
A87: 46270 | B87: =IF($A87="","",ROW()-4) -> 83 | C87: BAR | D87: TEA BAGS FOR BAR | E87: Food | G87: =IFERROR(VLOOKUP($F87,ItemList_Full,2,0),"") | I87: =IFERROR(VLOOKUP($F87,ItemList_Full,3,0),"") | J87: =IFERROR(VLOOKUP($F87,ItemList_Full,4,0),"") | K87: 300 | N87: Zeeshan (Sept import) | P87: =IF($E87="","",IF(OR($E87="Director Draw",$E87="Payroll/Employee Charge"),0,-$K87)) -> -300 | Q87: =IF($E87="Inventory Purchase",$H87,0) -> 0 | U87: FD-083 | V87: EUROPEAN BLACK OLIVES | W87: TIN | X87: 2250 | Y87: Food & Beverage
A88: 46270 | B88: =IF($A88="","",ROW()-4) -> 84 | C88: BAR | D88: MINT FOR BAR | E88: Food | G88: =IFERROR(VLOOKUP($F88,ItemList_Full,2,0),"") | I88: =IFERROR(VLOOKUP($F88,ItemList_Full,3,0),"") | J88: =IFERROR(VLOOKUP($F88,ItemList_Full,4,0),"") | K88: 750 | N88: Zeeshan (Sept import) | P88: =IF($E88="","",IF(OR($E88="Director Draw",$E88="Payroll/Employee Charge"),0,-$K88)) -> -750 | Q88: =IF($E88="Inventory Purchase",$H88,0) -> 0 | U88: FD-084 | V88: BLACK OLIVES | W88: TIN | X88: 2420 | Y88: Food & Beverage
A89: 46270 | B89: =IF($A89="","",ROW()-4) -> 85 | C89: FOH | D89: RUBBER BAND FOR CASH COUNTER | E89: Stationery & Office Supplies | G89: =IFERROR(VLOOKUP($F89,ItemList_Full,2,0),"") | I89: =IFERROR(VLOOKUP($F89,ItemList_Full,3,0),"") | J89: =IFERROR(VLOOKUP($F89,ItemList_Full,4,0),"") | K89: 1000 | N89: Zeeshan (Sept import) | P89: =IF($E89="","",IF(OR($E89="Director Draw",$E89="Payroll/Employee Charge"),0,-$K89)) -> -1000 | Q89: =IF($E89="Inventory Purchase",$H89,0) -> 0 | U89: FD-085 | V89: JALAPENO | W89: TIN | X89: 1150 | Y89: Food & Beverage
A90: 46270 | B90: =IF($A90="","",ROW()-4) -> 86 | C90: SHOE POLISH | D90: SHOE POLISH FOR STAFF | E90: Miscellaneous | G90: =IFERROR(VLOOKUP($F90,ItemList_Full,2,0),"") | I90: =IFERROR(VLOOKUP($F90,ItemList_Full,3,0),"") | J90: =IFERROR(VLOOKUP($F90,ItemList_Full,4,0),"") | K90: 180 | N90: Zeeshan (Sept import) | P90: =IF($E90="","",IF(OR($E90="Director Draw",$E90="Payroll/Employee Charge"),0,-$K90)) -> -180 | Q90: =IF($E90="Inventory Purchase",$H90,0) -> 0 | U90: FD-086 | V90: FRUIT COCKTAIL | W90: TIN | X90: 1075 | Y90: Food & Beverage
A91: 46270 | B91: =IF($A91="","",ROW()-4) -> 87 | C91: FREEZER | D91: UNIVERSAL SWITCH FOR BAR FREEZER | E91: Repairs & Maintenance | G91: =IFERROR(VLOOKUP($F91,ItemList_Full,2,0),"") | I91: =IFERROR(VLOOKUP($F91,ItemList_Full,3,0),"") | J91: =IFERROR(VLOOKUP($F91,ItemList_Full,4,0),"") | K91: 150 | N91: Zeeshan (Sept import) | P91: =IF($E91="","",IF(OR($E91="Director Draw",$E91="Payroll/Employee Charge"),0,-$K91)) -> -150 | Q91: =IF($E91="Inventory Purchase",$H91,0) -> 0 | U91: FD-087 | V91: SWEET CORN | W91: TIN | X91: 1225 | Y91: Food & Beverage
A92: 46270 | B92: =IF($A92="","",ROW()-4) -> 88 | C92: FOH | D92: FREEZER FOR BAR REPAIRING | E92: Repairs & Maintenance | G92: =IFERROR(VLOOKUP($F92,ItemList_Full,2,0),"") | I92: =IFERROR(VLOOKUP($F92,ItemList_Full,3,0),"") | J92: =IFERROR(VLOOKUP($F92,ItemList_Full,4,0),"") | K92: 500 | N92: Zeeshan (Sept import) | P92: =IF($E92="","",IF(OR($E92="Director Draw",$E92="Payroll/Employee Charge"),0,-$K92)) -> -500 | Q92: =IF($E92="Inventory Purchase",$H92,0) -> 0 | U92: FD-088 | V92: TOMATO PASTE | W92: 800GM | X92: 340 | Y92: Food & Beverage
A93: 46270 | B93: =IF($A93="","",ROW()-4) -> 89 | C93: FNK SPICE | D93: INDIRVE CHARGES PAID FOR SPICE BUILTY TO LHR | E93: Distribution Cost | G93: =IFERROR(VLOOKUP($F93,ItemList_Full,2,0),"") | I93: =IFERROR(VLOOKUP($F93,ItemList_Full,3,0),"") | J93: =IFERROR(VLOOKUP($F93,ItemList_Full,4,0),"") | K93: 250 | N93: Zeeshan (Sept import) | P93: =IF($E93="","",IF(OR($E93="Director Draw",$E93="Payroll/Employee Charge"),0,-$K93)) -> -250 | Q93: =IF($E93="Inventory Purchase",$H93,0) -> 0 | U93: FD-089 | V93: JALAPENO (3KG) | W93: POUCH | X93: 1050 | Y93: Food & Beverage
A94: 46270 | B94: =IF($A94="","",ROW()-4) -> 90 | C94: AUTO RENT | D94: AUTO RENT FOR CHICKEN POWDER PURCHASE | E94: Distribution Cost | G94: =IFERROR(VLOOKUP($F94,ItemList_Full,2,0),"") | I94: =IFERROR(VLOOKUP($F94,ItemList_Full,3,0),"") | J94: =IFERROR(VLOOKUP($F94,ItemList_Full,4,0),"") | K94: 150 | N94: Zeeshan (Sept import) | P94: =IF($E94="","",IF(OR($E94="Director Draw",$E94="Payroll/Employee Charge"),0,-$K94)) -> -150 | Q94: =IF($E94="Inventory Purchase",$H94,0) -> 0 | U94: FD-090 | V94: SHANGRILLA TOMATO PASTE | W94: CAN | X94: 1710 | Y94: Food & Beverage
A95: 46270 | B95: =IF($A95="","",ROW()-4) -> 91 | C95: RIDER MILK | D95: MILK FOR RIDERS | E95: Employee Meals & Medical | G95: =IFERROR(VLOOKUP($F95,ItemList_Full,2,0),"") | I95: =IFERROR(VLOOKUP($F95,ItemList_Full,3,0),"") | J95: =IFERROR(VLOOKUP($F95,ItemList_Full,4,0),"") | K95: 200 | N95: Zeeshan (Sept import) | P95: =IF($E95="","",IF(OR($E95="Director Draw",$E95="Payroll/Employee Charge"),0,-$K95)) -> -200 | Q95: =IF($E95="Inventory Purchase",$H95,0) -> 0 | U95: FD-091 | V95: PINEAPPLE | W95: TIN | X95: 1370 | Y95: Food & Beverage
... A97: 46270 | B97: =IF($A97="","",ROW()-4) -> 93 | C97: FOH | D97: AFZAL SERVER | E97: Payroll | G97: =IFERROR(VLOOKUP($F97,ItemList_Full,2,0),"") | I97: =IFERROR(VLOOKUP($F97,ItemList_Full,3,0),"") | J97: =IFERROR(VLOOKUP($F97,ItemList_Full,4,0),"") | K97: 1890 | N97: Zeeshan (Sept import) | P97: =IF($E97="","",IF(OR($E97="Director Draw",$E97="Payroll/Employee Charge"),0,-$K97)) -> -1890 | Q97: =IF($E97="Inventory Purchase",$H97,0) -> 0 | U97: FD-093 | V97: CHEDDER CHEESE | W97: BLOCK | X97: 2842 | Y97: Food & Beverage
A98: 46271 | B98: =IF($A98="","",ROW()-4) -> 94 | C98: - | D98: MILK FOR YASIR SB | E98: Director Draw | G98: =IFERROR(VLOOKUP($F98,ItemList_Full,2,0),"") | I98: =IFERROR(VLOOKUP($F98,ItemList_Full,3,0),"") | J98: =IFERROR(VLOOKUP($F98,ItemList_Full,4,0),"") | K98: 401 | M98: Yasir Sb | N98: Zeeshan (Sept import) | P98: =IF($E98="","",IF(OR($E98="Director Draw",$E98="Payroll/Employee Charge"),0,-$K98)) -> 0 | Q98: =IF($E98="Inventory Purchase",$H98,0) -> 0 | U98: FD-094 | V98: IRC BUTTER | W98: PKT | X98: 1800 | Y98: Food & Beverage
A99: 46271 | B99: =IF($A99="","",ROW()-4) -> 95 | C99: - | D99: QR JAZZ CASH PAYMENT | E99: Director Draw | G99: =IFERROR(VLOOKUP($F99,ItemList_Full,2,0),"") | I99: =IFERROR(VLOOKUP($F99,ItemList_Full,3,0),"") | J99: =IFERROR(VLOOKUP($F99,ItemList_Full,4,0),"") | K99: 17045 | M99: Yasir Sb | N99: Zeeshan (Sept import) | P99: =IF($E99="","",IF(OR($E99="Director Draw",$E99="Payroll/Employee Charge"),0,-$K99)) -> 0 | Q99: =IF($E99="Inventory Purchase",$H99,0) -> 0 | U99: FD-095 | V99: OLPER MILK | W99: 1.5 LTR | X99: 518.75 | Y99: Food & Beverage
A100: 46271 | B100: =IF($A100="","",ROW()-4) -> 96 | C100: - | D100: PARCAL PAYMENT FOR YASIR SB | E100: Director Draw | G100: =IFERROR(VLOOKUP($F100,ItemList_Full,2,0),"") | I100: =IFERROR(VLOOKUP($F100,ItemList_Full,3,0),"") | J100: =IFERROR(VLOOKUP($F100,ItemList_Full,4,0),"") | K100: 10260 | M100: Yasir Sb | N100: Zeeshan (Sept import) | P100: =IF($E100="","",IF(OR($E100="Director Draw",$E100="Payroll/Employee Charge"),0,-$K100)) -> 0 | Q100: =IF($E100="Inventory Purchase",$H100,0) -> 0 | U100: FD-096 | V100: DONER SAUCE | W100: LITER | X100: 1000 | Y100: Food & Beverage
A101: 46271 | B101: =IF($A101="","",ROW()-4) -> 97 | C101: BAR | D101: ICE | E101: Food | G101: =IFERROR(VLOOKUP($F101,ItemList_Full,2,0),"") | I101: =IFERROR(VLOOKUP($F101,ItemList_Full,3,0),"") | J101: =IFERROR(VLOOKUP($F101,ItemList_Full,4,0),"") | K101: 900 | N101: Zeeshan (Sept import) | P101: =IF($E101="","",IF(OR($E101="Director Draw",$E101="Payroll/Employee Charge"),0,-$K101)) -> -900 | Q101: =IF($E101="Inventory Purchase",$H101,0) -> 0 | U101: FD-097 | V101: FRESH CREAM (200 ML) | W101: 200 ML | X101: 212.5 | Y101: Food & Beverage
A102: 46271 | B102: =IF($A102="","",ROW()-4) -> 98 | C102: FNK GRILL | D102: FNK GRILL BILL PAID | E102: Food | G102: =IFERROR(VLOOKUP($F102,ItemList_Full,2,0),"") | I102: =IFERROR(VLOOKUP($F102,ItemList_Full,3,0),"") | J102: =IFERROR(VLOOKUP($F102,ItemList_Full,4,0),"") | K102: 38200 | N102: Zeeshan (Sept import) | P102: =IF($E102="","",IF(OR($E102="Director Draw",$E102="Payroll/Employee Charge"),0,-$K102)) -> -38200 | Q102: =IF($E102="Inventory Purchase",$H102,0) -> 0 | U102: FD-098 | V102: BBQ SAUCE | W102: BOT | X102: 1465 | Y102: Food & Beverage
A103: 46271 | B103: =IF($A103="","",ROW()-4) -> 99 | C103: FOOD PANDA | D103: FOOD PANDA SALE | E103: Food Panda Commission | G103: =IFERROR(VLOOKUP($F103,ItemList_Full,2,0),"") | I103: =IFERROR(VLOOKUP($F103,ItemList_Full,3,0),"") | J103: =IFERROR(VLOOKUP($F103,ItemList_Full,4,0),"") | K103: 8898 | N103: Zeeshan (Sept import) | P103: =IF($E103="","",IF(OR($E103="Director Draw",$E103="Payroll/Employee Charge"),0,-$K103)) -> -8898 | Q103: =IF($E103="Inventory Purchase",$H103,0) -> 0 | U103: FD-099 | V103: CHILLI SAUCE | W103: BOT | X103: 280 | Y103: Food & Beverage
A104: 46271 | B104: =IF($A104="","",ROW()-4) -> 100 | C104: SOCIAL SECURITY | D104: SOCIAL SECURITY ADUIT YEARLY | E104: Government Charges & Taxes | G104: =IFERROR(VLOOKUP($F104,ItemList_Full,2,0),"") | I104: =IFERROR(VLOOKUP($F104,ItemList_Full,3,0),"") | J104: =IFERROR(VLOOKUP($F104,ItemList_Full,4,0),"") | K104: 250000 | N104: Zeeshan (Sept import) | P104: =IF($E104="","",IF(OR($E104="Director Draw",$E104="Payroll/Employee Charge"),0,-$K104)) -> -250000 | Q104: =IF($E104="Inventory Purchase",$H104,0) -> 0 | U104: FD-100 | V104: NATIONAL KETCHUP | W104: POUCH | X104: 1330 | Y104: Food & Beverage
A105: 46271 | B105: =IF($A105="","",ROW()-4) -> 101 | C105: EMPOLYEE SALARY | D105: EMPOLYEE SALARY JUN | E105: Payroll | G105: =IFERROR(VLOOKUP($F105,ItemList_Full,2,0),"") | I105: =IFERROR(VLOOKUP($F105,ItemList_Full,3,0),"") | J105: =IFERROR(VLOOKUP($F105,ItemList_Full,4,0),"") | K105: 1680000 | N105: Zeeshan (Sept import) | P105: =IF($E105="","",IF(OR($E105="Director Draw",$E105="Payroll/Employee Charge"),0,-$K105)) -> -1680000 | Q105: =IF($E105="Inventory Purchase",$H105,0) -> 0 | U105: FD-101 | V105: EGGS | W105: PCS | X105: 25.383333 | Y105: Food & Beverage
A106: 46271 | B106: =IF($A106="","",ROW()-4) -> 102 | C106: PROMO MEAL | D106: DINE IN INV#15 MEAL FOR MANAGEMENT | E106: Employee Meals & Medical | G106: =IFERROR(VLOOKUP($F106,ItemList_Full,2,0),"") | I106: =IFERROR(VLOOKUP($F106,ItemList_Full,3,0),"") | J106: =IFERROR(VLOOKUP($F106,ItemList_Full,4,0),"") | K106: 1300 | N106: Zeeshan (Sept import) | P106: =IF($E106="","",IF(OR($E106="Director Draw",$E106="Payroll/Employee Charge"),0,-$K106)) -> -1300 | Q106: =IF($E106="Inventory Purchase",$H106,0) -> 0 | U106: FD-102 | V106: YELLOW MUSTERD | W106: JAR | X106: 4800 | Y106: Food & Beverage
A107: 46271 | B107: =IF($A107="","",ROW()-4) -> 103 | C107: RIDER MILK | D107: MILK FOR RIDERS | E107: Employee Meals & Medical | G107: =IFERROR(VLOOKUP($F107,ItemList_Full,2,0),"") | I107: =IFERROR(VLOOKUP($F107,ItemList_Full,3,0),"") | J107: =IFERROR(VLOOKUP($F107,ItemList_Full,4,0),"") | K107: 200 | N107: Zeeshan (Sept import) | P107: =IF($E107="","",IF(OR($E107="Director Draw",$E107="Payroll/Employee Charge"),0,-$K107)) -> -200 | Q107: =IF($E107="Inventory Purchase",$H107,0) -> 0 | U107: FD-103 | V107: HONEY | W107: BOT | X107: 740 | Y107: Food & Beverage
A108: 46271 | B108: =IF($A108="","",ROW()-4) -> 104 | C108: LOCAL MARKET | D108: SCORING PAD | E108: Cleaning & Sanitation | G108: =IFERROR(VLOOKUP($F108,ItemList_Full,2,0),"") | I108: =IFERROR(VLOOKUP($F108,ItemList_Full,3,0),"") | J108: =IFERROR(VLOOKUP($F108,ItemList_Full,4,0),"") | K108: 8800 | N108: Zeeshan (Sept import) | P108: =IF($E108="","",IF(OR($E108="Director Draw",$E108="Payroll/Employee Charge"),0,-$K108)) -> -8800 | Q108: =IF($E108="Inventory Purchase",$H108,0) -> 0 | U108: FD-104 | V108: TANDOORI SAUCE | W108: KG | X108: 670 | Y108: Food & Beverage
A109: 46271 | B109: =IF($A109="","",ROW()-4) -> 105 | C109: SCRUBING BRUSH | D109: SCRUBING BRUSH FOR BAR | E109: Cleaning & Sanitation | G109: =IFERROR(VLOOKUP($F109,ItemList_Full,2,0),"") | I109: =IFERROR(VLOOKUP($F109,ItemList_Full,3,0),"") | J109: =IFERROR(VLOOKUP($F109,ItemList_Full,4,0),"") | K109: 800 | N109: Zeeshan (Sept import) | P109: =IF($E109="","",IF(OR($E109="Director Draw",$E109="Payroll/Employee Charge"),0,-$K109)) -> -800 | Q109: =IF($E109="Inventory Purchase",$H109,0) -> 0 | U109: FD-105 | V109: DELUX SAUCE | W109: KG | X109: 1160 | Y109: Food & Beverage
A110: 46271 | B110: =IF($A110="","",ROW()-4) -> 106 | C110: FRYER | D110: SWITCH FOR FRYER | E110: Repairs & Maintenance | G110: =IFERROR(VLOOKUP($F110,ItemList_Full,2,0),"") | I110: =IFERROR(VLOOKUP($F110,ItemList_Full,3,0),"") | J110: =IFERROR(VLOOKUP($F110,ItemList_Full,4,0),"") | K110: 200 | N110: Zeeshan (Sept import) | P110: =IF($E110="","",IF(OR($E110="Director Draw",$E110="Payroll/Employee Charge"),0,-$K110)) -> -200 | Q110: =IF($E110="Inventory Purchase",$H110,0) -> 0 | U110: FD-106 | V110: WHITE SAUCE | W110: KG | X110: 1000 | Y110: Food & Beverage
A111: 46271 | B111: =IF($A111="","",ROW()-4) -> 107 | C111: JUICER BASE | D111: BAR JUICER BLADE BASE | E111: Repairs & Maintenance | G111: =IFERROR(VLOOKUP($F111,ItemList_Full,2,0),"") | I111: =IFERROR(VLOOKUP($F111,ItemList_Full,3,0),"") | J111: =IFERROR(VLOOKUP($F111,ItemList_Full,4,0),"") | K111: 900 | N111: Zeeshan (Sept import) | P111: =IF($E111="","",IF(OR($E111="Director Draw",$E111="Payroll/Employee Charge"),0,-$K111)) -> -900 | Q111: =IF($E111="Inventory Purchase",$H111,0) -> 0 | U111: FD-107 | V111: PIZZA SAUCE | W111: BOT | X111: 1050 | Y111: Food & Beverage
A112: 46271 | B112: =IF($A112="","",ROW()-4) -> 108 | C112: LOCAL MARKET | D112: SCOTCH TAPE | E112: Party & Decor | G112: =IFERROR(VLOOKUP($F112,ItemList_Full,2,0),"") | I112: =IFERROR(VLOOKUP($F112,ItemList_Full,3,0),"") | J112: =IFERROR(VLOOKUP($F112,ItemList_Full,4,0),"") | K112: 480 | N112: Zeeshan (Sept import) | P112: =IF($E112="","",IF(OR($E112="Director Draw",$E112="Payroll/Employee Charge"),0,-$K112)) -> -480 | Q112: =IF($E112="Inventory Purchase",$H112,0) -> 0 | U112: FD-108 | V112: PERI PERI SAUCE | W112: KG | X112: 1000 | Y112: Food & Beverage
... A118: 46272 | B118: =IF($A118="","",ROW()-4) -> 114 | C118: DELIVERY | D118: ANEES DELIVERY SUPERVISOR | E118: Payroll | G118: =IFERROR(VLOOKUP($F118,ItemList_Full,2,0),"") | I118: =IFERROR(VLOOKUP($F118,ItemList_Full,3,0),"") | J118: =IFERROR(VLOOKUP($F118,ItemList_Full,4,0),"") | K118: 1050 | N118: Zeeshan (Sept import) | P118: =IF($E118="","",IF(OR($E118="Director Draw",$E118="Payroll/Employee Charge"),0,-$K118)) -> -1050 | Q118: =IF($E118="Inventory Purchase",$H118,0) -> 0 | U118: FD-114 | V118: DIP ITT PERI PERI SAUCE | W118: BOTT | X118: 457.66667 | Y118: Food & Beverage
...

Sheet Purchase Orders
A1: PURCHASE ORDERS — demand -> authorize -> receive
A2: Hammad raises demand, Imran/Owner authorizes, Store person marks Received when goods arrive. Pick the standard Item Code. A row with Status=Received automatically creates a Payable and adds stock to the Inventory tab.
A4: PO# | B4: Date Ordered | C4: Vendor | D4: Item Code | E4: Item Name (auto) | F4: Qty | G4: Unit | H4: Rate | I4: Amount (PKR) | J4: Requested By | K4: Authorized By | L4: Status | M4: Date Received
A5: =IF($C5="","","PO-"&TEXT(ROW()-4,"000")) | E5: =IFERROR(VLOOKUP($D5,ItemList_Full,2,0),"") | G5: =IFERROR(VLOOKUP($D5,ItemList_Full,3,0),"") | H5: =IFERROR(VLOOKUP($D5,ItemList_Full,4,0),"") | I5: =IF(OR($F5="",$H5=""),"",$F5*$H5)
A6: =IF($C6="","","PO-"&TEXT(ROW()-4,"000")) | E6: =IFERROR(VLOOKUP($D6,ItemList_Full,2,0),"") | G6: =IFERROR(VLOOKUP($D6,ItemList_Full,3,0),"") | H6: =IFERROR(VLOOKUP($D6,ItemList_Full,4,0),"") | I6: =IF(OR($F6="",$H6=""),"",$F6*$H6)
A7: =IF($C7="","","PO-"&TEXT(ROW()-4,"000")) | E7: =IFERROR(VLOOKUP($D7,ItemList_Full,2,0),"") | G7: =IFERROR(VLOOKUP($D7,ItemList_Full,3,0),"") | H7: =IFERROR(VLOOKUP($D7,ItemList_Full,4,0),"") | I7: =IF(OR($F7="",$H7=""),"",$F7*$H7)
A8: =IF($C8="","","PO-"&TEXT(ROW()-4,"000")) | E8: =IFERROR(VLOOKUP($D8,ItemList_Full,2,0),"") | G8: =IFERROR(VLOOKUP($D8,ItemList_Full,3,0),"") | H8: =IFERROR(VLOOKUP($D8,ItemList_Full,4,0),"") | I8: =IF(OR($F8="",$H8=""),"",$F8*$H8)
A9: =IF($C9="","","PO-"&TEXT(ROW()-4,"000")) | E9: =IFERROR(VLOOKUP($D9,ItemList_Full,2,0),"") | G9: =IFERROR(VLOOKUP($D9,ItemList_Full,3,0),"") | H9: =IFERROR(VLOOKUP($D9,ItemList_Full,4,0),"") | I9: =IF(OR($F9="",$H9=""),"",$F9*$H9)
A10: =IF($C10="","","PO-"&TEXT(ROW()-4,"000")) | E10: =IFERROR(VLOOKUP($D10,ItemList_Full,2,0),"") | G10: =IFERROR(VLOOKUP($D10,ItemList_Full,3,0),"") | H10: =IFERROR(VLOOKUP($D10,ItemList_Full,4,0),"") | I10: =IF(OR($F10="",$H10=""),"",$F10*$H10)
A11: =IF($C11="","","PO-"&TEXT(ROW()-4,"000")) | E11: =IFERROR(VLOOKUP($D11,ItemList_Full,2,0),"") | G11: =IFERROR(VLOOKUP($D11,ItemList_Full,3,0),"") | H11: =IFERROR(VLOOKUP($D11,ItemList_Full,4,0),"") | I11: =IF(OR($F11="",$H11=""),"",$F11*$H11)
A12: =IF($C12="","","PO-"&TEXT(ROW()-4,"000")) | E12: =IFERROR(VLOOKUP($D12,ItemList_Full,2,0),"") | G12: =IFERROR(VLOOKUP($D12,ItemList_Full,3,0),"") | H12: =IFERROR(VLOOKUP($D12,ItemList_Full,4,0),"") | I12: =IF(OR($F12="",$H12=""),"",$F12*$H12)
A13: =IF($C13="","","PO-"&TEXT(ROW()-4,"000")) | E13: =IFERROR(VLOOKUP($D13,ItemList_Full,2,0),"") | G13: =IFERROR(VLOOKUP($D13,ItemList_Full,3,0),"") | H13: =IFERROR(VLOOKUP($D13,ItemList_Full,4,0),"") | I13: =IF(OR($F13="",$H13=""),"",$F13*$H13)
A14: =IF($C14="","","PO-"&TEXT(ROW()-4,"000")) | E14: =IFERROR(VLOOKUP($D14,ItemList_Full,2,0),"") | G14: =IFERROR(VLOOKUP($D14,ItemList_Full,3,0),"") | H14: =IFERROR(VLOOKUP($D14,ItemList_Full,4,0),"") | I14: =IF(OR($F14="",$H14=""),"",$F14*$H14)
A15: =IF($C15="","","PO-"&TEXT(ROW()-4,"000")) | E15: =IFERROR(VLOOKUP($D15,ItemList_Full,2,0),"") | G15: =IFERROR(VLOOKUP($D15,ItemList_Full,3,0),"") | H15: =IFERROR(VLOOKUP($D15,ItemList_Full,4,0),"") | I15: =IF(OR($F15="",$H15=""),"",$F15*$H15)
A16: =IF($C16="","","PO-"&TEXT(ROW()-4,"000")) | E16: =IFERROR(VLOOKUP($D16,ItemList_Full,2,0),"") | G16: =IFERROR(VLOOKUP($D16,ItemList_Full,3,0),"") | H16: =IFERROR(VLOOKUP($D16,ItemList_Full,4,0),"") | I16: =IF(OR($F16="",$H16=""),"",$F16*$H16)
... A304: =IF($C304="","","PO-"&TEXT(ROW()-4,"000")) | E304: =IFERROR(VLOOKUP($D304,ItemList_Full,2,0),"") | G304: =IFERROR(VLOOKUP($D304,ItemList_Full,3,0),"") | H304: =IFERROR(VLOOKUP($D304,ItemList_Full,4,0),"") | I304: =IF(OR($F304="",$H304=""),"",$F304*$H304)

Sheet Payables
A1: PAYABLES — auto-generated from Received Purchase Orders
A2: One row per Purchase Order marked Received. 'Paid to Date' pulls Payable Payment entries from Expense Entry linked by PO#.
A4: PO# | B4: Vendor | C4: Item Code | D4: Item Name | E4: Amount Owed | F4: Paid to Date | G4: Balance | H4: Status
A5: =IF('Purchase Orders'!$L5="Received",'Purchase Orders'!$A5,"") | B5: =IF($A5="","",'Purchase Orders'!$C5) | C5: =IF($A5="","",'Purchase Orders'!$D5) | D5: =IF($A5="","",'Purchase Orders'!$E5) | E5: =IF($A5="","",'Purchase Orders'!$I5) | F5: =IF($A5="","",SUMIFS('Expense Entry'!$K$5:$K$6000,'Expense Entry'!$E$5:$E$6000,"Payable Payment",'Expense Entry'!$L$5:$L$6000,$A5)) | G5: =IF($A5="","",$E5-$F5) | H5: =IF($A5="","",IF($G5<=0,"Paid",IF($F5>0,"Partial","Unpaid")))
A6: =IF('Purchase Orders'!$L6="Received",'Purchase Orders'!$A6,"") | B6: =IF($A6="","",'Purchase Orders'!$C6) | C6: =IF($A6="","",'Purchase Orders'!$D6) | D6: =IF($A6="","",'Purchase Orders'!$E6) | E6: =IF($A6="","",'Purchase Orders'!$I6) | F6: =IF($A6="","",SUMIFS('Expense Entry'!$K$5:$K$6000,'Expense Entry'!$E$5:$E$6000,"Payable Payment",'Expense Entry'!$L$5:$L$6000,$A6)) | G6: =IF($A6="","",$E6-$F6) | H6: =IF($A6="","",IF($G6<=0,"Paid",IF($F6>0,"Partial","Unpaid")))
A7: =IF('Purchase Orders'!$L7="Received",'Purchase Orders'!$A7,"") | B7: =IF($A7="","",'Purchase Orders'!$C7) | C7: =IF($A7="","",'Purchase Orders'!$D7) | D7: =IF($A7="","",'Purchase Orders'!$E7) | E7: =IF($A7="","",'Purchase Orders'!$I7) | F7: =IF($A7="","",SUMIFS('Expense Entry'!$K$5:$K$6000,'Expense Entry'!$E$5:$E$6000,"Payable Payment",'Expense Entry'!$L$5:$L$6000,$A7)) | G7: =IF($A7="","",$E7-$F7) | H7: =IF($A7="","",IF($G7<=0,"Paid",IF($F7>0,"Partial","Unpaid")))
A8: =IF('Purchase Orders'!$L8="Received",'Purchase Orders'!$A8,"") | B8: =IF($A8="","",'Purchase Orders'!$C8) | C8: =IF($A8="","",'Purchase Orders'!$D8) | D8: =IF($A8="","",'Purchase Orders'!$E8) | E8: =IF($A8="","",'Purchase Orders'!$I8) | F8: =IF($A8="","",SUMIFS('Expense Entry'!$K$5:$K$6000,'Expense Entry'!$E$5:$E$6000,"Payable Payment",'Expense Entry'!$L$5:$L$6000,$A8)) | G8: =IF($A8="","",$E8-$F8) | H8: =IF($A8="","",IF($G8<=0,"Paid",IF($F8>0,"Partial","Unpaid")))
A9: =IF('Purchase Orders'!$L9="Received",'Purchase Orders'!$A9,"") | B9: =IF($A9="","",'Purchase Orders'!$C9) | C9: =IF($A9="","",'Purchase Orders'!$D9) | D9: =IF($A9="","",'Purchase Orders'!$E9) | E9: =IF($A9="","",'Purchase Orders'!$I9) | F9: =IF($A9="","",SUMIFS('Expense Entry'!$K$5:$K$6000,'Expense Entry'!$E$5:$E$6000,"Payable Payment",'Expense Entry'!$L$5:$L$6000,$A9)) | G9: =IF($A9="","",$E9-$F9) | H9: =IF($A9="","",IF($G9<=0,"Paid",IF($F9>0,"Partial","Unpaid")))
A10: =IF('Purchase Orders'!$L10="Received",'Purchase Orders'!$A10,"") | B10: =IF($A10="","",'Purchase Orders'!$C10) | C10: =IF($A10="","",'Purchase Orders'!$D10) | D10: =IF($A10="","",'Purchase Orders'!$E10) | E10: =IF($A10="","",'Purchase Orders'!$I10) | F10: =IF($A10="","",SUMIFS('Expense Entry'!$K$5:$K$6000,'Expense Entry'!$E$5:$E$6000,"Payable Payment",'Expense Entry'!$L$5:$L$6000,$A10)) | G10: =IF($A10="","",$E10-$F10) | H10: =IF($A10="","",IF($G10<=0,"Paid",IF($F10>0,"Partial","Unpaid")))
A11: =IF('Purchase Orders'!$L11="Received",'Purchase Orders'!$A11,"") | B11: =IF($A11="","",'Purchase Orders'!$C11) | C11: =IF($A11="","",'Purchase Orders'!$D11) | D11: =IF($A11="","",'Purchase Orders'!$E11) | E11: =IF($A11="","",'Purchase Orders'!$I11) | F11: =IF($A11="","",SUMIFS('Expense Entry'!$K$5:$K$6000,'Expense Entry'!$E$5:$E$6000,"Payable Payment",'Expense Entry'!$L$5:$L$6000,$A11)) | G11: =IF($A11="","",$E11-$F11) | H11: =IF($A11="","",IF($G11<=0,"Paid",IF($F11>0,"Partial","Unpaid")))
A12: =IF('Purchase Orders'!$L12="Received",'Purchase Orders'!$A12,"") | B12: =IF($A12="","",'Purchase Orders'!$C12) | C12: =IF($A12="","",'Purchase Orders'!$D12) | D12: =IF($A12="","",'Purchase Orders'!$E12) | E12: =IF($A12="","",'Purchase Orders'!$I12) | F12: =IF($A12="","",SUMIFS('Expense Entry'!$K$5:$K$6000,'Expense Entry'!$E$5:$E$6000,"Payable Payment",'Expense Entry'!$L$5:$L$6000,$A12)) | G12: =IF($A12="","",$E12-$F12) | H12: =IF($A12="","",IF($G12<=0,"Paid",IF($F12>0,"Partial","Unpaid")))
A13: =IF('Purchase Orders'!$L13="Received",'Purchase Orders'!$A13,"") | B13: =IF($A13="","",'Purchase Orders'!$C13) | C13: =IF($A13="","",'Purchase Orders'!$D13) | D13: =IF($A13="","",'Purchase Orders'!$E13) | E13: =IF($A13="","",'Purchase Orders'!$I13) | F13: =IF($A13="","",SUMIFS('Expense Entry'!$K$5:$K$6000,'Expense Entry'!$E$5:$E$6000,"Payable Payment",'Expense Entry'!$L$5:$L$6000,$A13)) | G13: =IF($A13="","",$E13-$F13) | H13: =IF($A13="","",IF($G13<=0,"Paid",IF($F13>0,"Partial","Unpaid")))
A14: =IF('Purchase Orders'!$L14="Received",'Purchase Orders'!$A14,"") | B14: =IF($A14="","",'Purchase Orders'!$C14) | C14: =IF($A14="","",'Purchase Orders'!$D14) | D14: =IF($A14="","",'Purchase Orders'!$E14) | E14: =IF($A14="","",'Purchase Orders'!$I14) | F14: =IF($A14="","",SUMIFS('Expense Entry'!$K$5:$K$6000,'Expense Entry'!$E$5:$E$6000,"Payable Payment",'Expense Entry'!$L$5:$L$6000,$A14)) | G14: =IF($A14="","",$E14-$F14) | H14: =IF($A14="","",IF($G14<=0,"Paid",IF($F14>0,"Partial","Unpaid")))
A15: =IF('Purchase Orders'!$L15="Received",'Purchase Orders'!$A15,"") | B15: =IF($A15="","",'Purchase Orders'!$C15) | C15: =IF($A15="","",'Purchase Orders'!$D15) | D15: =IF($A15="","",'Purchase Orders'!$E15) | E15: =IF($A15="","",'Purchase Orders'!$I15) | F15: =IF($A15="","",SUMIFS('Expense Entry'!$K$5:$K$6000,'Expense Entry'!$E$5:$E$6000,"Payable Payment",'Expense Entry'!$L$5:$L$6000,$A15)) | G15: =IF($A15="","",$E15-$F15) | H15: =IF($A15="","",IF($G15<=0,"Paid",IF($F15>0,"Partial","Unpaid")))
A16: =IF('Purchase Orders'!$L16="Received",'Purchase Orders'!$A16,"") | B16: =IF($A16="","",'Purchase Orders'!$C16) | C16: =IF($A16="","",'Purchase Orders'!$D16) | D16: =IF($A16="","",'Purchase Orders'!$E16) | E16: =IF($A16="","",'Purchase Orders'!$I16) | F16: =IF($A16="","",SUMIFS('Expense Entry'!$K$5:$K$6000,'Expense Entry'!$E$5:$E$6000,"Payable Payment",'Expense Entry'!$L$5:$L$6000,$A16)) | G16: =IF($A16="","",$E16-$F16) | H16: =IF($A16="","",IF($G16<=0,"Paid",IF($F16>0,"Partial","Unpaid")))
... A304: =IF('Purchase Orders'!$L304="Received",'Purchase Orders'!$A304,"") | B304: =IF($A304="","",'Purchase Orders'!$C304) | C304: =IF($A304="","",'Purchase Orders'!$D304) | D304: =IF($A304="","",'Purchase Orders'!$E304) | E304: =IF($A304="","",'Purchase Orders'!$I304) | F304: =IF($A304="","",SUMIFS('Expense Entry'!$K$5:$K$6000,'Expense Entry'!$E$5:$E$6000,"Payable Payment",'Expense Entry'!$L$5:$L$6000,$A304)) | G304: =IF($A304="","",$E304-$F304) | H304: =IF($A304="","",IF($G304<=0,"Paid",IF($F304>0,"Partial","Unpaid")))

Sheet Issue Log
A1: ISSUE LOG — stock issued from store to kitchen (becomes cost of goods used)
A2: Store person logs what leaves the store room each day, by Item Code. This is what actually drives Food/Packaging/Cleaning/etc. cost in the P&L — not the purchase date.
A4: Date | B4: Item Code | C4: Item Name (auto) | D4: Unit | E4: Qty Issued | F4: Rate | G4: Value (PKR) | H4: Issued By | I4: Notes | J4: Category (lookup, hidden)
C5: =IFERROR(VLOOKUP($B5,ItemList_Full,2,0),"") | D5: =IFERROR(VLOOKUP($B5,ItemList_Full,3,0),"") | F5: =IFERROR(VLOOKUP($B5,ItemList_Full,4,0),"") | G5: =IF(OR($E5="",$F5=""),"",$E5*$F5) | J5: =IFERROR(VLOOKUP($B5,ItemList_Full,5,0),"")
C6: =IFERROR(VLOOKUP($B6,ItemList_Full,2,0),"") | D6: =IFERROR(VLOOKUP($B6,ItemList_Full,3,0),"") | F6: =IFERROR(VLOOKUP($B6,ItemList_Full,4,0),"") | G6: =IF(OR($E6="",$F6=""),"",$E6*$F6) | J6: =IFERROR(VLOOKUP($B6,ItemList_Full,5,0),"")
C7: =IFERROR(VLOOKUP($B7,ItemList_Full,2,0),"") | D7: =IFERROR(VLOOKUP($B7,ItemList_Full,3,0),"") | F7: =IFERROR(VLOOKUP($B7,ItemList_Full,4,0),"") | G7: =IF(OR($E7="",$F7=""),"",$E7*$F7) | J7: =IFERROR(VLOOKUP($B7,ItemList_Full,5,0),"")
C8: =IFERROR(VLOOKUP($B8,ItemList_Full,2,0),"") | D8: =IFERROR(VLOOKUP($B8,ItemList_Full,3,0),"") | F8: =IFERROR(VLOOKUP($B8,ItemList_Full,4,0),"") | G8: =IF(OR($E8="",$F8=""),"",$E8*$F8) | J8: =IFERROR(VLOOKUP($B8,ItemList_Full,5,0),"")
C9: =IFERROR(VLOOKUP($B9,ItemList_Full,2,0),"") | D9: =IFERROR(VLOOKUP($B9,ItemList_Full,3,0),"") | F9: =IFERROR(VLOOKUP($B9,ItemList_Full,4,0),"") | G9: =IF(OR($E9="",$F9=""),"",$E9*$F9) | J9: =IFERROR(VLOOKUP($B9,ItemList_Full,5,0),"")
C10: =IFERROR(VLOOKUP($B10,ItemList_Full,2,0),"") | D10: =IFERROR(VLOOKUP($B10,ItemList_Full,3,0),"") | F10: =IFERROR(VLOOKUP($B10,ItemList_Full,4,0),"") | G10: =IF(OR($E10="",$F10=""),"",$E10*$F10) | J10: =IFERROR(VLOOKUP($B10,ItemList_Full,5,0),"")
C11: =IFERROR(VLOOKUP($B11,ItemList_Full,2,0),"") | D11: =IFERROR(VLOOKUP($B11,ItemList_Full,3,0),"") | F11: =IFERROR(VLOOKUP($B11,ItemList_Full,4,0),"") | G11: =IF(OR($E11="",$F11=""),"",$E11*$F11) | J11: =IFERROR(VLOOKUP($B11,ItemList_Full,5,0),"")
C12: =IFERROR(VLOOKUP($B12,ItemList_Full,2,0),"") | D12: =IFERROR(VLOOKUP($B12,ItemList_Full,3,0),"") | F12: =IFERROR(VLOOKUP($B12,ItemList_Full,4,0),"") | G12: =IF(OR($E12="",$F12=""),"",$E12*$F12) | J12: =IFERROR(VLOOKUP($B12,ItemList_Full,5,0),"")
C13: =IFERROR(VLOOKUP($B13,ItemList_Full,2,0),"") | D13: =IFERROR(VLOOKUP($B13,ItemList_Full,3,0),"") | F13: =IFERROR(VLOOKUP($B13,ItemList_Full,4,0),"") | G13: =IF(OR($E13="",$F13=""),"",$E13*$F13) | J13: =IFERROR(VLOOKUP($B13,ItemList_Full,5,0),"")
C14: =IFERROR(VLOOKUP($B14,ItemList_Full,2,0),"") | D14: =IFERROR(VLOOKUP($B14,ItemList_Full,3,0),"") | F14: =IFERROR(VLOOKUP($B14,ItemList_Full,4,0),"") | G14: =IF(OR($E14="",$F14=""),"",$E14*$F14) | J14: =IFERROR(VLOOKUP($B14,ItemList_Full,5,0),"")
C15: =IFERROR(VLOOKUP($B15,ItemList_Full,2,0),"") | D15: =IFERROR(VLOOKUP($B15,ItemList_Full,3,0),"") | F15: =IFERROR(VLOOKUP($B15,ItemList_Full,4,0),"") | G15: =IF(OR($E15="",$F15=""),"",$E15*$F15) | J15: =IFERROR(VLOOKUP($B15,ItemList_Full,5,0),"")
C16: =IFERROR(VLOOKUP($B16,ItemList_Full,2,0),"") | D16: =IFERROR(VLOOKUP($B16,ItemList_Full,3,0),"") | F16: =IFERROR(VLOOKUP($B16,ItemList_Full,4,0),"") | G16: =IF(OR($E16="",$F16=""),"",$E16*$F16) | J16: =IFERROR(VLOOKUP($B16,ItemList_Full,5,0),"")
... C604: =IFERROR(VLOOKUP($B604,ItemList_Full,2,0),"") | D604: =IFERROR(VLOOKUP($B604,ItemList_Full,3,0),"") | F604: =IFERROR(VLOOKUP($B604,ItemList_Full,4,0),"") | G604: =IF(OR($E604="",$F604=""),"",$E604*$F604) | J604: =IFERROR(VLOOKUP($B604,ItemList_Full,5,0),"")

Sheet Inventory
A1: INVENTORY — live stock ledger, one row per item code
A2: Opening Stock: enter once at month start. Received columns and Issued pull automatically from Expense Entry / Purchase Orders / Issue Log, matched by Item Code.
A4: Item Code | B4: Item Name | C4: Category | D4: Unit | E4: Std Rate | F4: Opening Stock | G4: Received (Cash Purchase) | H4: Received (via PO) | I4: Total Received | J4: Issued | K4: Closing Stock | L4: Closing Value (PKR)
A5: FD-001 | B5: CHEESE YELLOW | C5: Food & Beverage | D5: CTN | E5: 16900 | F5: 23 | G5: =SUMIFS('Expense Entry'!$H$5:$H$6000,'Expense Entry'!$E$5:$E$6000,"Inventory Purchase",'Expense Entry'!$F$5:$F$6000,$A5) -> 0 | H5: =SUMIFS('Purchase Orders'!$F$5:$F$3000,'Purchase Orders'!$L$5:$L$3000,"Received",'Purchase Orders'!$D$5:$D$3000,$A5) -> 0 | I5: =$G5+$H5 -> 0 | J5: =SUMIFS('Issue Log'!$E$5:$E$6000,'Issue Log'!$B$5:$B$6000,$A5) -> 0 | K5: =$F5+$I5-$J5 -> 23 | L5: =$K5*$E5 -> 388700
A6: FD-002 | B6: CHEESE GREEN | C6: Food & Beverage | D6: CTN | E6: 16900 | F6: 26 | G6: =SUMIFS('Expense Entry'!$H$5:$H$6000,'Expense Entry'!$E$5:$E$6000,"Inventory Purchase",'Expense Entry'!$F$5:$F$6000,$A6) -> 0 | H6: =SUMIFS('Purchase Orders'!$F$5:$F$3000,'Purchase Orders'!$L$5:$L$3000,"Received",'Purchase Orders'!$D$5:$D$3000,$A6) -> 0 | I6: =$G6+$H6 -> 0 | J6: =SUMIFS('Issue Log'!$E$5:$E$6000,'Issue Log'!$B$5:$B$6000,$A6) -> 0 | K6: =$F6+$I6-$J6 -> 26 | L6: =$K6*$E6 -> 439400
A7: FD-003 | B7: MALAI BOTI | C7: Food & Beverage | D7: KG | E7: 1400 | F7: 25 | G7: =SUMIFS('Expense Entry'!$H$5:$H$6000,'Expense Entry'!$E$5:$E$6000,"Inventory Purchase",'Expense Entry'!$F$5:$F$6000,$A7) -> 0 | H7: =SUMIFS('Purchase Orders'!$F$5:$F$3000,'Purchase Orders'!$L$5:$L$3000,"Received",'Purchase Orders'!$D$5:$D$3000,$A7) -> 0 | I7: =$G7+$H7 -> 0 | J7: =SUMIFS('Issue Log'!$E$5:$E$6000,'Issue Log'!$B$5:$B$6000,$A7) -> 0 | K7: =$F7+$I7-$J7 -> 25 | L7: =$K7*$E7 -> 35000
A8: FD-004 | B8: STEAK FILLET | C8: Food & Beverage | D8: PCS | E8: 200 | F8: 45 | G8: =SUMIFS('Expense Entry'!$H$5:$H$6000,'Expense Entry'!$E$5:$E$6000,"Inventory Purchase",'Expense Entry'!$F$5:$F$6000,$A8) -> 0 | H8: =SUMIFS('Purchase Orders'!$F$5:$F$3000,'Purchase Orders'!$L$5:$L$3000,"Received",'Purchase Orders'!$D$5:$D$3000,$A8) -> 0 | I8: =$G8+$H8 -> 0 | J8: =SUMIFS('Issue Log'!$E$5:$E$6000,'Issue Log'!$B$5:$B$6000,$A8) -> 0 | K8: =$F8+$I8-$J8 -> 45 | L8: =$K8*$E8 -> 9000
A9: FD-005 | B9: BEHARI CHICKEN | C9: Food & Beverage | D9: KG | E9: 1150 | F9: 0 | G9: =SUMIFS('Expense Entry'!$H$5:$H$6000,'Expense Entry'!$E$5:$E$6000,"Inventory Purchase",'Expense Entry'!$F$5:$F$6000,$A9) -> 0 | H9: =SUMIFS('Purchase Orders'!$F$5:$F$3000,'Purchase Orders'!$L$5:$L$3000,"Received",'Purchase Orders'!$D$5:$D$3000,$A9) -> 0 | I9: =$G9+$H9 -> 0 | J9: =SUMIFS('Issue Log'!$E$5:$E$6000,'Issue Log'!$B$5:$B$6000,$A9) -> 0 | K9: =$F9+$I9-$J9 -> 0 | L9: =$K9*$E9 -> 0
A10: FD-006 | B10: TIKKA TOPPING FISH AND CHICK | C10: Food & Beverage | D10: KG | E10: 1150 | F10: 0 | G10: =SUMIFS('Expense Entry'!$H$5:$H$6000,'Expense Entry'!$E$5:$E$6000,"Inventory Purchase",'Expense Entry'!$F$5:$F$6000,$A10) -> 0 | H10: =SUMIFS('Purchase Orders'!$F$5:$F$3000,'Purchase Orders'!$L$5:$L$3000,"Received",'Purchase Orders'!$D$5:$D$3000,$A10) -> 0 | I10: =$G10+$H10 -> 0 | J10: =SUMIFS('Issue Log'!$E$5:$E$6000,'Issue Log'!$B$5:$B$6000,$A10) -> 0 | K10: =$F10+$I10-$J10 -> 0 | L10: =$K10*$E10 -> 0
A11: FD-007 | B11: FAJITA TOPPING FISH AND CHICK | C11: Food & Beverage | D11: KG | E11: 1150 | F11: 0 | G11: =SUMIFS('Expense Entry'!$H$5:$H$6000,'Expense Entry'!$E$5:$E$6000,"Inventory Purchase",'Expense Entry'!$F$5:$F$6000,$A11) -> 0 | H11: =SUMIFS('Purchase Orders'!$F$5:$F$3000,'Purchase Orders'!$L$5:$L$3000,"Received",'Purchase Orders'!$D$5:$D$3000,$A11) -> 0 | I11: =$G11+$H11 -> 0 | J11: =SUMIFS('Issue Log'!$E$5:$E$6000,'Issue Log'!$B$5:$B$6000,$A11) -> 0 | K11: =$F11+$I11-$J11 -> 0 | L11: =$K11*$E11 -> 0
A12: FD-008 | B12: AL-TAYYAB DRUMMET | C12: Food & Beverage | D12: KG | E12: 800 | F12: 0 | G12: =SUMIFS('Expense Entry'!$H$5:$H$6000,'Expense Entry'!$E$5:$E$6000,"Inventory Purchase",'Expense Entry'!$F$5:$F$6000,$A12) -> 0 | H12: =SUMIFS('Purchase Orders'!$F$5:$F$3000,'Purchase Orders'!$L$5:$L$3000,"Received",'Purchase Orders'!$D$5:$D$3000,$A12) -> 0 | I12: =$G12+$H12 -> 0 | J12: =SUMIFS('Issue Log'!$E$5:$E$6000,'Issue Log'!$B$5:$B$6000,$A12) -> 0 | K12: =$F12+$I12-$J12 -> 0 | L12: =$K12*$E12 -> 0
A13: FD-009 | B13: WINGS | C13: Food & Beverage | D13: PKT | E13: 1260 | F13: 4 | G13: =SUMIFS('Expense Entry'!$H$5:$H$6000,'Expense Entry'!$E$5:$E$6000,"Inventory Purchase",'Expense Entry'!$F$5:$F$6000,$A13) -> 0 | H13: =SUMIFS('Purchase Orders'!$F$5:$F$3000,'Purchase Orders'!$L$5:$L$3000,"Received",'Purchase Orders'!$D$5:$D$3000,$A13) -> 0 | I13: =$G13+$H13 -> 0 | J13: =SUMIFS('Issue Log'!$E$5:$E$6000,'Issue Log'!$B$5:$B$6000,$A13) -> 0 | K13: =$F13+$I13-$J13 -> 4 | L13: =$K13*$E13 -> 5040
A14: FD-010 | B14: DRUMMETTE | C14: Food & Beverage | D14: PKT | E14: 1301 | F14: 16 | G14: =SUMIFS('Expense Entry'!$H$5:$H$6000,'Expense Entry'!$E$5:$E$6000,"Inventory Purchase",'Expense Entry'!$F$5:$F$6000,$A14) -> 0 | H14: =SUMIFS('Purchase Orders'!$F$5:$F$3000,'Purchase Orders'!$L$5:$L$3000,"Received",'Purchase Orders'!$D$5:$D$3000,$A14) -> 0 | I14: =$G14+$H14 -> 0 | J14: =SUMIFS('Issue Log'!$E$5:$E$6000,'Issue Log'!$B$5:$B$6000,$A14) -> 0 | K14: =$F14+$I14-$J14 -> 16 | L14: =$K14*$E14 -> 20816
A15: FD-011 | B15: SMOKED CHICKEN | C15: Food & Beverage | D15: KG | E15: 1344 | F15: 7 | G15: =SUMIFS('Expense Entry'!$H$5:$H$6000,'Expense Entry'!$E$5:$E$6000,"Inventory Purchase",'Expense Entry'!$F$5:$F$6000,$A15) -> 0 | H15: =SUMIFS('Purchase Orders'!$F$5:$F$3000,'Purchase Orders'!$L$5:$L$3000,"Received",'Purchase Orders'!$D$5:$D$3000,$A15) -> 0 | I15: =$G15+$H15 -> 0 | J15: =SUMIFS('Issue Log'!$E$5:$E$6000,'Issue Log'!$B$5:$B$6000,$A15) -> 0 | K15: =$F15+$I15-$J15 -> 7 | L15: =$K15*$E15 -> 9408
A16: FD-012 | B16: SAUSAGE | C16: Food & Beverage | D16: KG | E16: 1088 | F16: 6 | G16: =SUMIFS('Expense Entry'!$H$5:$H$6000,'Expense Entry'!$E$5:$E$6000,"Inventory Purchase",'Expense Entry'!$F$5:$F$6000,$A16) -> 0 | H16: =SUMIFS('Purchase Orders'!$F$5:$F$3000,'Purchase Orders'!$L$5:$L$3000,"Received",'Purchase Orders'!$D$5:$D$3000,$A16) -> 0 | I16: =$G16+$H16 -> 0 | J16: =SUMIFS('Issue Log'!$E$5:$E$6000,'Issue Log'!$B$5:$B$6000,$A16) -> 0 | K16: =$F16+$I16-$J16 -> 6 | L16: =$K16*$E16 -> 6528
... A485: FG-002 | B485: LPG CYLINDERS | C485: Fuel & Gas | D485: CYL | E485: 17025 | F485: 5 | G485: =SUMIFS('Expense Entry'!$H$5:$H$6000,'Expense Entry'!$E$5:$E$6000,"Inventory Purchase",'Expense Entry'!$F$5:$F$6000,$A485) -> 0 | H485: =SUMIFS('Purchase Orders'!$F$5:$F$3000,'Purchase Orders'!$L$5:$L$3000,"Received",'Purchase Orders'!$D$5:$D$3000,$A485) -> 0 | I485: =$G485+$H485 -> 0 | J485: =SUMIFS('Issue Log'!$E$5:$E$6000,'Issue Log'!$B$5:$B$6000,$A485) -> 0 | K485: =$F485+$I485-$J485 -> 5 | L485: =$K485*$E485 -> 85125
A487: TOTAL | K487: =SUM($K$5:$K$485) -> 68993.7 | L487: =SUM($L$5:$L$485) -> 4433397.6

Sheet Directors
A1: DIRECTORS — owner / director draws
A2: Auto-totals every 'Director Draw' row from Expense Entry charged to each name. Detail lives in Expense Entry.
A4: Director | B4: Total Charged This Month (PKR)
A5: Hassan Nasir | B5: =SUMIFS('Expense Entry'!$K$5:$K$6000,'Expense Entry'!$E$5:$E$6000,"Director Draw",'Expense Entry'!$M$5:$M$6000,$A5) -> 35765
A6: Ali Tahir | B6: =SUMIFS('Expense Entry'!$K$5:$K$6000,'Expense Entry'!$E$5:$E$6000,"Director Draw",'Expense Entry'!$M$5:$M$6000,$A6) -> 165
A7: Imran Tahir | B7: =SUMIFS('Expense Entry'!$K$5:$K$6000,'Expense Entry'!$E$5:$E$6000,"Director Draw",'Expense Entry'!$M$5:$M$6000,$A7) -> 17520
A8: Nasir Sb | B8: =SUMIFS('Expense Entry'!$K$5:$K$6000,'Expense Entry'!$E$5:$E$6000,"Director Draw",'Expense Entry'!$M$5:$M$6000,$A8) -> 1999
A9: Riaz Sb | B9: =SUMIFS('Expense Entry'!$K$5:$K$6000,'Expense Entry'!$E$5:$E$6000,"Director Draw",'Expense Entry'!$M$5:$M$6000,$A9) -> 1750
A10: Yasir Sb | B10: =SUMIFS('Expense Entry'!$K$5:$K$6000,'Expense Entry'!$E$5:$E$6000,"Director Draw",'Expense Entry'!$M$5:$M$6000,$A10) -> 400708
A11: TOTAL DIRECTOR EXPENSE | B11: =SUM($B$5:$B$10) -> 457907

Sheet Payroll
A1: PAYROLL — staff roster with charge-to-salary deductions
A2: Base Monthly Salary pre-filled from the September staff roster. 'Charges This Month' auto-pulls 'Payroll/Employee Charge' rows from Expense Entry. Net Pay = Base - Charges. Note: actual cash PAYROLL paid out in September (overtime, delivery riders, advances) is booked separately in Expense Entry under category 'Payroll' and flows to the P&L directly — this roster is the base-salary reference.
A4: Employee | B4: Department | C4: Designation | D4: Base Monthly Salary (PKR) | E4: Charges This Month (PKR) | F4: Net Pay Due (PKR)
A5: Ahsan Zadi | B5: Management | C5: Rgm | D5: 95000 | E5: =SUMIFS('Expense Entry'!$K$5:$K$6000,'Expense Entry'!$E$5:$E$6000,"Payroll/Employee Charge",'Expense Entry'!$M$5:$M$6000,$A5) -> 0 | F5: =$D5-$E5 -> 95000
A6: Abdullah | B6: Cash | C6: Cashier | D6: 27000 | E6: =SUMIFS('Expense Entry'!$K$5:$K$6000,'Expense Entry'!$E$5:$E$6000,"Payroll/Employee Charge",'Expense Entry'!$M$5:$M$6000,$A6) -> 0 | F6: =$D6-$E6 -> 27000
A7: Saqib | B7: Cash | C7: Cashier | D7: 27000 | E7: =SUMIFS('Expense Entry'!$K$5:$K$6000,'Expense Entry'!$E$5:$E$6000,"Payroll/Employee Charge",'Expense Entry'!$M$5:$M$6000,$A7) -> 0 | F7: =$D7-$E7 -> 27000
A8: Kahleer | C8: Cashier | D8: 25000 | E8: =SUMIFS('Expense Entry'!$K$5:$K$6000,'Expense Entry'!$E$5:$E$6000,"Payroll/Employee Charge",'Expense Entry'!$M$5:$M$6000,$A8) -> 0 | F8: =$D8-$E8 -> 25000
A9: Aqib | B9: Supervizer | C9: Supervisor | D9: 55000 | E9: =SUMIFS('Expense Entry'!$K$5:$K$6000,'Expense Entry'!$E$5:$E$6000,"Payroll/Employee Charge",'Expense Entry'!$M$5:$M$6000,$A9) -> 0 | F9: =$D9-$E9 -> 55000
A10: Nabeeel | B10: Foh | C10: Supervisor | D10: 45000 | E10: =SUMIFS('Expense Entry'!$K$5:$K$6000,'Expense Entry'!$E$5:$E$6000,"Payroll/Employee Charge",'Expense Entry'!$M$5:$M$6000,$A10) -> 0 | F10: =$D10-$E10 -> 45000
A11: Salman Sitaar | B11: Foh | C11: Server | D11: 38500 | E11: =SUMIFS('Expense Entry'!$K$5:$K$6000,'Expense Entry'!$E$5:$E$6000,"Payroll/Employee Charge",'Expense Entry'!$M$5:$M$6000,$A11) -> 0 | F11: =$D11-$E11 -> 38500
A12: Sohail | B12: Foh | C12: Server | D12: 34500 | E12: =SUMIFS('Expense Entry'!$K$5:$K$6000,'Expense Entry'!$E$5:$E$6000,"Payroll/Employee Charge",'Expense Entry'!$M$5:$M$6000,$A12) -> 0 | F12: =$D12-$E12 -> 34500
A13: Usman Mahmood | B13: Foh | C13: Server | D13: 26000 | E13: =SUMIFS('Expense Entry'!$K$5:$K$6000,'Expense Entry'!$E$5:$E$6000,"Payroll/Employee Charge",'Expense Entry'!$M$5:$M$6000,$A13) -> 0 | F13: =$D13-$E13 -> 26000
A14: Ali Raza | B14: Foh | C14: Server | D14: 24000 | E14: =SUMIFS('Expense Entry'!$K$5:$K$6000,'Expense Entry'!$E$5:$E$6000,"Payroll/Employee Charge",'Expense Entry'!$M$5:$M$6000,$A14) -> 0 | F14: =$D14-$E14 -> 24000
A15: Ahad | B15: Foh | C15: Server | D15: 24000 | E15: =SUMIFS('Expense Entry'!$K$5:$K$6000,'Expense Entry'!$E$5:$E$6000,"Payroll/Employee Charge",'Expense Entry'!$M$5:$M$6000,$A15) -> 0 | F15: =$D15-$E15 -> 24000
A16: Faisal | B16: Foh | C16: Server | D16: 25000 | E16: =SUMIFS('Expense Entry'!$K$5:$K$6000,'Expense Entry'!$E$5:$E$6000,"Payroll/Employee Charge",'Expense Entry'!$M$5:$M$6000,$A16) -> 0 | F16: =$D16-$E16 -> 25000
A17: Anas | C17: Server | D17: 16000 | E17: =SUMIFS('Expense Entry'!$K$5:$K$6000,'Expense Entry'!$E$5:$E$6000,"Payroll/Employee Charge",'Expense Entry'!$M$5:$M$6000,$A17) -> 0 | F17: =$D17-$E17 -> 16000
A18: Umair | C18: Server | D18: 22000 | E18: =SUMIFS('Expense Entry'!$K$5:$K$6000,'Expense Entry'!$E$5:$E$6000,"Payroll/Employee Charge",'Expense Entry'!$M$5:$M$6000,$A18) -> 0 | F18: =$D18-$E18 -> 22000
A19: Asif | C19: Server | D19: 22000 | E19: =SUMIFS('Expense Entry'!$K$5:$K$6000,'Expense Entry'!$E$5:$E$6000,"Payroll/Employee Charge",'Expense Entry'!$M$5:$M$6000,$A19) -> 0 | F19: =$D19-$E19 -> 22000
A20: Bashrat | C20: Server | D20: 24000 | E20: =SUMIFS('Expense Entry'!$K$5:$K$6000,'Expense Entry'!$E$5:$E$6000,"Payroll/Employee Charge",'Expense Entry'!$M$5:$M$6000,$A20) -> 0 | F20: =$D20-$E20 -> 24000
A21: Hassan | C21: Takeaway | D21: 25000 | E21: =SUMIFS('Expense Entry'!$K$5:$K$6000,'Expense Entry'!$E$5:$E$6000,"Payroll/Employee Charge",'Expense Entry'!$M$5:$M$6000,$A21) -> 0 | F21: =$D21-$E21 -> 25000
A22: Yashwa | C22: Cleaner | D22: 24000 | E22: =SUMIFS('Expense Entry'!$K$5:$K$6000,'Expense Entry'!$E$5:$E$6000,"Payroll/Employee Charge",'Expense Entry'!$M$5:$M$6000,$A22) -> 0 | F22: =$D22-$E22 -> 24000
A23: Kamran | B23: Foh | C23: Bakery Bar | D23: 28000 | E23: =SUMIFS('Expense Entry'!$K$5:$K$6000,'Expense Entry'!$E$5:$E$6000,"Payroll/Employee Charge",'Expense Entry'!$M$5:$M$6000,$A23) -> 0 | F23: =$D23-$E23 -> 28000
A24: Qasim | C24: Bakery Bar | D24: 28000 | E24: =SUMIFS('Expense Entry'!$K$5:$K$6000,'Expense Entry'!$E$5:$E$6000,"Payroll/Employee Charge",'Expense Entry'!$M$5:$M$6000,$A24) -> 0 | F24: =$D24-$E24 -> 28000
A25: Ahmad | C25: Drink Bar | D25: 24000 | E25: =SUMIFS('Expense Entry'!$K$5:$K$6000,'Expense Entry'!$E$5:$E$6000,"Payroll/Employee Charge",'Expense Entry'!$M$5:$M$6000,$A25) -> 0 | F25: =$D25-$E25 -> 24000
A26: Zarish | B26: Foh | C26: Gro | D26: 26000 | E26: =SUMIFS('Expense Entry'!$K$5:$K$6000,'Expense Entry'!$E$5:$E$6000,"Payroll/Employee Charge",'Expense Entry'!$M$5:$M$6000,$A26) -> 0 | F26: =$D26-$E26 -> 26000
A27: Sohail (2) | B27: Foh | C27: Drink Bar | D27: 16000 | E27: =SUMIFS('Expense Entry'!$K$5:$K$6000,'Expense Entry'!$E$5:$E$6000,"Payroll/Employee Charge",'Expense Entry'!$M$5:$M$6000,$A27) -> 0 | F27: =$D27-$E27 -> 16000
A28: Masoom | C28: Diswasher | D28: 26000 | E28: =SUMIFS('Expense Entry'!$K$5:$K$6000,'Expense Entry'!$E$5:$E$6000,"Payroll/Employee Charge",'Expense Entry'!$M$5:$M$6000,$A28) -> 0 | F28: =$D28-$E28 -> 26000
A29: Dawood | C29: Dispatcher | D29: 24000 | E29: =SUMIFS('Expense Entry'!$K$5:$K$6000,'Expense Entry'!$E$5:$E$6000,"Payroll/Employee Charge",'Expense Entry'!$M$5:$M$6000,$A29) -> 0 | F29: =$D29-$E29 -> 24000
A30: Dawood (2) | C30: Dispatcher | D30: 16000 | E30: =SUMIFS('Expense Entry'!$K$5:$K$6000,'Expense Entry'!$E$5:$E$6000,"Payroll/Employee Charge",'Expense Entry'!$M$5:$M$6000,$A30) -> 0 | F30: =$D30-$E30 -> 16000
A31: Akash | C31: Takeaway | D31: 15000 | E31: =SUMIFS('Expense Entry'!$K$5:$K$6000,'Expense Entry'!$E$5:$E$6000,"Payroll/Employee Charge",'Expense Entry'!$M$5:$M$6000,$A31) -> 0 | F31: =$D31-$E31 -> 15000
A32: Ashiq | C32: Diswasher | D32: 29000 | E32: =SUMIFS('Expense Entry'!$K$5:$K$6000,'Expense Entry'!$E$5:$E$6000,"Payroll/Employee Charge",'Expense Entry'!$M$5:$M$6000,$A32) -> 0 | F32: =$D32-$E32 -> 29000
A33: Usman | C33: Dishwasher | D33: 26000 | E33: =SUMIFS('Expense Entry'!$K$5:$K$6000,'Expense Entry'!$E$5:$E$6000,"Payroll/Employee Charge",'Expense Entry'!$M$5:$M$6000,$A33) -> 0 | F33: =$D33-$E33 -> 26000
A34: Vishal | C34: Cleaner | D34: 32000 | E34: =SUMIFS('Expense Entry'!$K$5:$K$6000,'Expense Entry'!$E$5:$E$6000,"Payroll/Employee Charge",'Expense Entry'!$M$5:$M$6000,$A34) -> 0 | F34: =$D34-$E34 -> 32000
A35: Zeeshan Akram | B35: Boh | C35: Supervisor | D35: 58000 | E35: =SUMIFS('Expense Entry'!$K$5:$K$6000,'Expense Entry'!$E$5:$E$6000,"Payroll/Employee Charge",'Expense Entry'!$M$5:$M$6000,$A35) -> 0 | F35: =$D35-$E35 -> 58000
A36: Nabeel Ismail | B36: Boh | C36: Supervisor | D36: 53000 | E36: =SUMIFS('Expense Entry'!$K$5:$K$6000,'Expense Entry'!$E$5:$E$6000,"Payroll/Employee Charge",'Expense Entry'!$M$5:$M$6000,$A36) -> 0 | F36: =$D36-$E36 -> 53000
A37: Mujahid | B37: Boh | C37: Kitchen Assistant | D37: 34000 | E37: =SUMIFS('Expense Entry'!$K$5:$K$6000,'Expense Entry'!$E$5:$E$6000,"Payroll/Employee Charge",'Expense Entry'!$M$5:$M$6000,$A37) -> 0 | F37: =$D37-$E37 -> 34000
A38: Adnan Younis | B38: Boh | C38: Kitchen Assistant | D38: 34000 | E38: =SUMIFS('Expense Entry'!$K$5:$K$6000,'Expense Entry'!$E$5:$E$6000,"Payroll/Employee Charge",'Expense Entry'!$M$5:$M$6000,$A38) -> 0 | F38: =$D38-$E38 -> 34000
A39: Arslan Ali | B39: Boh | C39: Kitchen Assistant | D39: 32000 | E39: =SUMIFS('Expense Entry'!$K$5:$K$6000,'Expense Entry'!$E$5:$E$6000,"Payroll/Employee Charge",'Expense Entry'!$M$5:$M$6000,$A39) -> 0 | F39: =$D39-$E39 -> 32000
A40: Hamza Saeed | B40: Boh | C40: Kitchen Assistant | D40: 25000 | E40: =SUMIFS('Expense Entry'!$K$5:$K$6000,'Expense Entry'!$E$5:$E$6000,"Payroll/Employee Charge",'Expense Entry'!$M$5:$M$6000,$A40) -> 0 | F40: =$D40-$E40 -> 25000
A41: Ahsaan | B41: Boh | C41: Kitchen Assistant | D41: 28000 | E41: =SUMIFS('Expense Entry'!$K$5:$K$6000,'Expense Entry'!$E$5:$E$6000,"Payroll/Employee Charge",'Expense Entry'!$M$5:$M$6000,$A41) -> 0 | F41: =$D41-$E41 -> 28000
A42: Hassnain Ali | B42: Boh | C42: Kitchen Assistant | D42: 25000 | E42: =SUMIFS('Expense Entry'!$K$5:$K$6000,'Expense Entry'!$E$5:$E$6000,"Payroll/Employee Charge",'Expense Entry'!$M$5:$M$6000,$A42) -> 0 | F42: =$D42-$E42 -> 25000
A43: Nouman | B43: Boh | C43: Kitchen Assistant | D43: 33000 | E43: =SUMIFS('Expense Entry'!$K$5:$K$6000,'Expense Entry'!$E$5:$E$6000,"Payroll/Employee Charge",'Expense Entry'!$M$5:$M$6000,$A43) -> 0 | F43: =$D43-$E43 -> 33000
A44: Aman Ul Llaha | C44: Kitchen Assistant | D44: 24000 | E44: =SUMIFS('Expense Entry'!$K$5:$K$6000,'Expense Entry'!$E$5:$E$6000,"Payroll/Employee Charge",'Expense Entry'!$M$5:$M$6000,$A44) -> 0 | F44: =$D44-$E44 -> 24000
A45: Waqar | B45: Boh | C45: Kitchen Assistant | D45: 30000 | E45: =SUMIFS('Expense Entry'!$K$5:$K$6000,'Expense Entry'!$E$5:$E$6000,"Payroll/Employee Charge",'Expense Entry'!$M$5:$M$6000,$A45) -> 0 | F45: =$D45-$E45 -> 30000
A46: Imran | C46: Kitchen Assistant | D46: 24000 | E46: =SUMIFS('Expense Entry'!$K$5:$K$6000,'Expense Entry'!$E$5:$E$6000,"Payroll/Employee Charge",'Expense Entry'!$M$5:$M$6000,$A46) -> 0 | F46: =$D46-$E46 -> 24000
A47: Hamza Night | C47: Kitchen Assistant | D47: 27000 | E47: =SUMIFS('Expense Entry'!$K$5:$K$6000,'Expense Entry'!$E$5:$E$6000,"Payroll/Employee Charge",'Expense Entry'!$M$5:$M$6000,$A47) -> 0 | F47: =$D47-$E47 -> 27000
A48: Haider | C48: Kitchen Assistant | D48: 24000 | E48: =SUMIFS('Expense Entry'!$K$5:$K$6000,'Expense Entry'!$E$5:$E$6000,"Payroll/Employee Charge",'Expense Entry'!$M$5:$M$6000,$A48) -> 0 | F48: =$D48-$E48 -> 24000
A49: Salman | C49: Kitchen Assistant | D49: 24000 | E49: =SUMIFS('Expense Entry'!$K$5:$K$6000,'Expense Entry'!$E$5:$E$6000,"Payroll/Employee Charge",'Expense Entry'!$M$5:$M$6000,$A49) -> 0 | F49: =$D49-$E49 -> 24000
A50: Aftab | B50: Boh | C50: Kitchen Assistant | D50: 26000 | E50: =SUMIFS('Expense Entry'!$K$5:$K$6000,'Expense Entry'!$E$5:$E$6000,"Payroll/Employee Charge",'Expense Entry'!$M$5:$M$6000,$A50) -> 0 | F50: =$D50-$E50 -> 26000
A51: Ahmad (2) | C51: Kitchen Assistant | D51: 24000 | E51: =SUMIFS('Expense Entry'!$K$5:$K$6000,'Expense Entry'!$E$5:$E$6000,"Payroll/Employee Charge",'Expense Entry'!$M$5:$M$6000,$A51) -> 0 | F51: =$D51-$E51 -> 24000
A52: Subhan Tanveer | C52: Kitchen Assistant | D52: 24000 | E52: =SUMIFS('Expense Entry'!$K$5:$K$6000,'Expense Entry'!$E$5:$E$6000,"Payroll/Employee Charge",'Expense Entry'!$M$5:$M$6000,$A52) -> 0 | F52: =$D52-$E52 -> 24000
A53: Talha | C53: Kitchen Assistant | D53: 24000 | E53: =SUMIFS('Expense Entry'!$K$5:$K$6000,'Expense Entry'!$E$5:$E$6000,"Payroll/Employee Charge",'Expense Entry'!$M$5:$M$6000,$A53) -> 0 | F53: =$D53-$E53 -> 24000
A54: Anjum | B54: Delivery | C54: Supervisor | D54: 50000 | E54: =SUMIFS('Expense Entry'!$K$5:$K$6000,'Expense Entry'!$E$5:$E$6000,"Payroll/Employee Charge",'Expense Entry'!$M$5:$M$6000,$A54) -> 0 | F54: =$D54-$E54 -> 50000
A55: Umair Aslam | B55: Delivery | C55: Rider | D55: 26500 | E55: =SUMIFS('Expense Entry'!$K$5:$K$6000,'Expense Entry'!$E$5:$E$6000,"Payroll/Employee Charge",'Expense Entry'!$M$5:$M$6000,$A55) -> 0 | F55: =$D55-$E55 -> 26500
A56: Tayyab | B56: Delivery | C56: Rider | D56: 25000 | E56: =SUMIFS('Expense Entry'!$K$5:$K$6000,'Expense Entry'!$E$5:$E$6000,"Payroll/Employee Charge",'Expense Entry'!$M$5:$M$6000,$A56) -> 0 | F56: =$D56-$E56 -> 25000
A57: Shakeel | B57: Delivery | C57: Rider | D57: 25000 | E57: =SUMIFS('Expense Entry'!$K$5:$K$6000,'Expense Entry'!$E$5:$E$6000,"Payroll/Employee Charge",'Expense Entry'!$M$5:$M$6000,$A57) -> 0 | F57: =$D57-$E57 -> 25000
A58: M.Shahbaz | B58: Delivery | C58: Rider | D58: 25000 | E58: =SUMIFS('Expense Entry'!$K$5:$K$6000,'Expense Entry'!$E$5:$E$6000,"Payroll/Employee Charge",'Expense Entry'!$M$5:$M$6000,$A58) -> 0 | F58: =$D58-$E58 -> 25000
A59: Umair Ramzan | B59: Delivery | C59: Rider | D59: 25000 | E59: =SUMIFS('Expense Entry'!$K$5:$K$6000,'Expense Entry'!$E$5:$E$6000,"Payroll/Employee Charge",'Expense Entry'!$M$5:$M$6000,$A59) -> 0 | F59: =$D59-$E59 -> 25000
A60: Saim Raza | B60: Delivery | C60: Rider | D60: 25000 | E60: =SUMIFS('Expense Entry'!$K$5:$K$6000,'Expense Entry'!$E$5:$E$6000,"Payroll/Employee Charge",'Expense Entry'!$M$5:$M$6000,$A60) -> 0 | F60: =$D60-$E60 -> 25000
A61: M.Feroz Zaheer | B61: Delivery | C61: Rider | D61: 25000 | E61: =SUMIFS('Expense Entry'!$K$5:$K$6000,'Expense Entry'!$E$5:$E$6000,"Payroll/Employee Charge",'Expense Entry'!$M$5:$M$6000,$A61) -> 0 | F61: =$D61-$E61 -> 25000
A62: M.Faizan | B62: Delivery | C62: Rider | D62: 25000 | E62: =SUMIFS('Expense Entry'!$K$5:$K$6000,'Expense Entry'!$E$5:$E$6000,"Payroll/Employee Charge",'Expense Entry'!$M$5:$M$6000,$A62) -> 0 | F62: =$D62-$E62 -> 25000
A63: Aman | C63: Rider | D63: 25000 | E63: =SUMIFS('Expense Entry'!$K$5:$K$6000,'Expense Entry'!$E$5:$E$6000,"Payroll/Employee Charge",'Expense Entry'!$M$5:$M$6000,$A63) -> 0 | F63: =$D63-$E63 -> 25000
A64: Numan | B64: Delivery | C64: Rider | D64: 25000 | E64: =SUMIFS('Expense Entry'!$K$5:$K$6000,'Expense Entry'!$E$5:$E$6000,"Payroll/Employee Charge",'Expense Entry'!$M$5:$M$6000,$A64) -> 0 | F64: =$D64-$E64 -> 25000
A65: Zeeshan Haider | B65: Delivery | C65: Rider | D65: 25000 | E65: =SUMIFS('Expense Entry'!$K$5:$K$6000,'Expense Entry'!$E$5:$E$6000,"Payroll/Employee Charge",'Expense Entry'!$M$5:$M$6000,$A65) -> 0 | F65: =$D65-$E65 -> 25000
A66: Ahsan Ali | C66: Rider | D66: 16500 | E66: =SUMIFS('Expense Entry'!$K$5:$K$6000,'Expense Entry'!$E$5:$E$6000,"Payroll/Employee Charge",'Expense Entry'!$M$5:$M$6000,$A66) -> 0 | F66: =$D66-$E66 -> 16500
A67: Abuhunana | C67: Rider | D67: 16500 | E67: =SUMIFS('Expense Entry'!$K$5:$K$6000,'Expense Entry'!$E$5:$E$6000,"Payroll/Employee Charge",'Expense Entry'!$M$5:$M$6000,$A67) -> 0 | F67: =$D67-$E67 -> 16500
A68: Afzal | C68: Rider | D68: 25000 | E68: =SUMIFS('Expense Entry'!$K$5:$K$6000,'Expense Entry'!$E$5:$E$6000,"Payroll/Employee Charge",'Expense Entry'!$M$5:$M$6000,$A68) -> 0 | F68: =$D68-$E68 -> 25000
A69: Abdul Hanan | C69: Rider | D69: 25000 | E69: =SUMIFS('Expense Entry'!$K$5:$K$6000,'Expense Entry'!$E$5:$E$6000,"Payroll/Employee Charge",'Expense Entry'!$M$5:$M$6000,$A69) -> 0 | F69: =$D69-$E69 -> 25000
A70: M.Yousaf | C70: Rider | D70: 16500 | E70: =SUMIFS('Expense Entry'!$K$5:$K$6000,'Expense Entry'!$E$5:$E$6000,"Payroll/Employee Charge",'Expense Entry'!$M$5:$M$6000,$A70) -> 0 | F70: =$D70-$E70 -> 16500
A71: Ali Haider | C71: Rider | D71: 16500 | E71: =SUMIFS('Expense Entry'!$K$5:$K$6000,'Expense Entry'!$E$5:$E$6000,"Payroll/Employee Charge",'Expense Entry'!$M$5:$M$6000,$A71) -> 0 | F71: =$D71-$E71 -> 16500
A72: Taufeeq | B72: Other Faculty | C72: Store Keeper | D72: 50000 | E72: =SUMIFS('Expense Entry'!$K$5:$K$6000,'Expense Entry'!$E$5:$E$6000,"Payroll/Employee Charge",'Expense Entry'!$M$5:$M$6000,$A72) -> 0 | F72: =$D72-$E72 -> 50000
A73: Afzal (2) | B73: Other Faculty | C73: Guard | D73: 29000 | E73: =SUMIFS('Expense Entry'!$K$5:$K$6000,'Expense Entry'!$E$5:$E$6000,"Payroll/Employee Charge",'Expense Entry'!$M$5:$M$6000,$A73) -> 0 | F73: =$D73-$E73 -> 29000
A74: Butt | C74: Guard | D74: 30000 | E74: =SUMIFS('Expense Entry'!$K$5:$K$6000,'Expense Entry'!$E$5:$E$6000,"Payroll/Employee Charge",'Expense Entry'!$M$5:$M$6000,$A74) -> 0 | F74: =$D74-$E74 -> 30000
A75: Fahad | B75: Other Faculty | C75: Electration | D75: 55000 | E75: =SUMIFS('Expense Entry'!$K$5:$K$6000,'Expense Entry'!$E$5:$E$6000,"Payroll/Employee Charge",'Expense Entry'!$M$5:$M$6000,$A75) -> 0 | F75: =$D75-$E75 -> 55000
A76: Sherri | B76: Other Faculty | C76: Purchasing | D76: 13500 | E76: =SUMIFS('Expense Entry'!$K$5:$K$6000,'Expense Entry'!$E$5:$E$6000,"Payroll/Employee Charge",'Expense Entry'!$M$5:$M$6000,$A76) -> 0 | F76: =$D76-$E76 -> 13500
A77: Qari Sb | B77: Other Faculty | C77: Hafiz | D77: 2000 | E77: =SUMIFS('Expense Entry'!$K$5:$K$6000,'Expense Entry'!$E$5:$E$6000,"Payroll/Employee Charge",'Expense Entry'!$M$5:$M$6000,$A77) -> 0 | F77: =$D77-$E77 -> 2000
A78: Gardener | B78: Other Faculty | C78: Gadner | D78: 3500 | E78: =SUMIFS('Expense Entry'!$K$5:$K$6000,'Expense Entry'!$E$5:$E$6000,"Payroll/Employee Charge",'Expense Entry'!$M$5:$M$6000,$A78) -> 0 | F78: =$D78-$E78 -> 3500
A79: Zeshan Azam | B79: Cash Department | C79: Cash Orgainzer | D79: 35000 | E79: =SUMIFS('Expense Entry'!$K$5:$K$6000,'Expense Entry'!$E$5:$E$6000,"Payroll/Employee Charge",'Expense Entry'!$M$5:$M$6000,$A79) -> 0 | F79: =$D79-$E79 -> 35000
A80: Hammad Sb | B80: Other Faculty | C80: Hr | D80: 10000 | E80: =SUMIFS('Expense Entry'!$K$5:$K$6000,'Expense Entry'!$E$5:$E$6000,"Payroll/Employee Charge",'Expense Entry'!$M$5:$M$6000,$A80) -> 0 | F80: =$D80-$E80 -> 10000
A81: TOTAL | D81: =SUM($D$5:$D$80) -> 2112500 | E81: =SUM($E$5:$E$80) -> 0 | F81: =SUM($F$5:$F$80) -> 2112500

Sheet Cash Book
A1: CASH BOOK — daily petty cash reconciliation
A2: Enter each day's Date. Sales Collected pulls automatically from the Sales tab for that date. Opening Cash carries from the prior day's Closing. Cash Out pulls every cash-impacting row from Expense Entry for that date.
A4: Date | B4: Opening balance -> | C4: Sales Collected (auto, from Sales tab) | D4: Total Cash In | E4: Cash Out (auto) | F4: Closing Cash
A5: 46266 | B5: 0 | C5: =IF($A5="",0,SUMIFS(Sales!$G$5:$G$3000,Sales!$A$5:$A$3000,$A5)) -> 436834 | D5: =$B5+$C5 -> 436834 | E5: =IF($A5="",0,-SUMIFS('Expense Entry'!$P$5:$P$6000,'Expense Entry'!$A$5:$A$6000,$A5)) -> 327559 | F5: =$D5-$E5 -> 109275
A6: 46267 | B6: =$F5 -> 109275 | C6: =IF($A6="",0,SUMIFS(Sales!$G$5:$G$3000,Sales!$A$5:$A$3000,$A6)) -> 435288 | D6: =$B6+$C6 -> 544563 | E6: =IF($A6="",0,-SUMIFS('Expense Entry'!$P$5:$P$6000,'Expense Entry'!$A$5:$A$6000,$A6)) -> 223880 | F6: =$D6-$E6 -> 320683
A7: 46268 | B7: =$F6 -> 320683 | C7: =IF($A7="",0,SUMIFS(Sales!$G$5:$G$3000,Sales!$A$5:$A$3000,$A7)) -> 482076 | D7: =$B7+$C7 -> 802759 | E7: =IF($A7="",0,-SUMIFS('Expense Entry'!$P$5:$P$6000,'Expense Entry'!$A$5:$A$6000,$A7)) -> 300175 | F7: =$D7-$E7 -> 502584
A8: 46269 | B8: =$F7 -> 502584 | C8: =IF($A8="",0,SUMIFS(Sales!$G$5:$G$3000,Sales!$A$5:$A$3000,$A8)) -> 527365 | D8: =$B8+$C8 -> 1029949 | E8: =IF($A8="",0,-SUMIFS('Expense Entry'!$P$5:$P$6000,'Expense Entry'!$A$5:$A$6000,$A8)) -> 41243 | F8: =$D8-$E8 -> 988706
A9: 46270 | B9: =$F8 -> 988706 | C9: =IF($A9="",0,SUMIFS(Sales!$G$5:$G$3000,Sales!$A$5:$A$3000,$A9)) -> 499600 | D9: =$B9+$C9 -> 1488306 | E9: =IF($A9="",0,-SUMIFS('Expense Entry'!$P$5:$P$6000,'Expense Entry'!$A$5:$A$6000,$A9)) -> 18566 | F9: =$D9-$E9 -> 1469740
A10: 46271 | B10: =$F9 -> 1469740 | C10: =IF($A10="",0,SUMIFS(Sales!$G$5:$G$3000,Sales!$A$5:$A$3000,$A10)) -> 511594 | D10: =$B10+$C10 -> 1981334 | E10: =IF($A10="",0,-SUMIFS('Expense Entry'!$P$5:$P$6000,'Expense Entry'!$A$5:$A$6000,$A10)) -> 1998348 | F10: =$D10-$E10 -> -17014
A11: 46272 | B11: =$F10 -> -17014 | C11: =IF($A11="",0,SUMIFS(Sales!$G$5:$G$3000,Sales!$A$5:$A$3000,$A11)) -> 465991 | D11: =$B11+$C11 -> 448977 | E11: =IF($A11="",0,-SUMIFS('Expense Entry'!$P$5:$P$6000,'Expense Entry'!$A$5:$A$6000,$A11)) -> 51035 | F11: =$D11-$E11 -> 397942
A12: 46273 | B12: =$F11 -> 397942 | C12: =IF($A12="",0,SUMIFS(Sales!$G$5:$G$3000,Sales!$A$5:$A$3000,$A12)) -> 432174 | D12: =$B12+$C12 -> 830116 | E12: =IF($A12="",0,-SUMIFS('Expense Entry'!$P$5:$P$6000,'Expense Entry'!$A$5:$A$6000,$A12)) -> 120402 | F12: =$D12-$E12 -> 709714
A13: 46274 | B13: =$F12 -> 709714 | C13: =IF($A13="",0,SUMIFS(Sales!$G$5:$G$3000,Sales!$A$5:$A$3000,$A13)) -> 437339 | D13: =$B13+$C13 -> 1147053 | E13: =IF($A13="",0,-SUMIFS('Expense Entry'!$P$5:$P$6000,'Expense Entry'!$A$5:$A$6000,$A13)) -> 207079 | F13: =$D13-$E13 -> 939974
A14: 46275 | B14: =$F13 -> 939974 | C14: =IF($A14="",0,SUMIFS(Sales!$G$5:$G$3000,Sales!$A$5:$A$3000,$A14)) -> 429886 | D14: =$B14+$C14 -> 1369860 | E14: =IF($A14="",0,-SUMIFS('Expense Entry'!$P$5:$P$6000,'Expense Entry'!$A$5:$A$6000,$A14)) -> 485635 | F14: =$D14-$E14 -> 884225
A15: 46276 | B15: =$F14 -> 884225 | C15: =IF($A15="",0,SUMIFS(Sales!$G$5:$G$3000,Sales!$A$5:$A$3000,$A15)) -> 610727 | D15: =$B15+$C15 -> 1494952 | E15: =IF($A15="",0,-SUMIFS('Expense Entry'!$P$5:$P$6000,'Expense Entry'!$A$5:$A$6000,$A15)) -> 266190 | F15: =$D15-$E15 -> 1228762
A16: 46277 | B16: =$F15 -> 1228762 | C16: =IF($A16="",0,SUMIFS(Sales!$G$5:$G$3000,Sales!$A$5:$A$3000,$A16)) -> 515935 | D16: =$B16+$C16 -> 1744697 | E16: =IF($A16="",0,-SUMIFS('Expense Entry'!$P$5:$P$6000,'Expense Entry'!$A$5:$A$6000,$A16)) -> 14745 | F16: =$D16-$E16 -> 1729952
A17: 46278 | B17: =$F16 -> 1729952 | C17: =IF($A17="",0,SUMIFS(Sales!$G$5:$G$3000,Sales!$A$5:$A$3000,$A17)) -> 587921 | D17: =$B17+$C17 -> 2317873 | E17: =IF($A17="",0,-SUMIFS('Expense Entry'!$P$5:$P$6000,'Expense Entry'!$A$5:$A$6000,$A17)) -> 266721 | F17: =$D17-$E17 -> 2051152
... A34: 46295 | B34: =$F33 -> 956577 | C34: =IF($A34="",0,SUMIFS(Sales!$G$5:$G$3000,Sales!$A$5:$A$3000,$A34)) -> 424788 | D34: =$B34+$C34 -> 1381365 | E34: =IF($A34="",0,-SUMIFS('Expense Entry'!$P$5:$P$6000,'Expense Entry'!$A$5:$A$6000,$A34)) -> 879236 | F34: =$D34-$E34 -> 502129
B35: =$F34 -> 502129 | C35: =IF($A35="",0,SUMIFS(Sales!$G$5:$G$3000,Sales!$A$5:$A$3000,$A35)) -> 0 | D35: =$B35+$C35 -> 502129 | E35: =IF($A35="",0,-SUMIFS('Expense Entry'!$P$5:$P$6000,'Expense Entry'!$A$5:$A$6000,$A35)) -> 0 | F35: =$D35-$E35 -> 502129
C3010: Total Sales this month: | D3010: =SUM($C$5:$C$35) -> 14012331

Sheet Lists
A1: Categories | B1: ItemCodes | C1: ItemUnit | D1: ItemRate | E1: ItemCategory | F1: Directors | G1: Employees | H1: POStatus | I1: PayableStatus | J1: ChargedToAll | K1: ItemName
A2: Inventory Purchase | B2: FD-001 | C2: CTN | D2: 16900 | E2: Food & Beverage | F2: Hassan Nasir | G2: Ahsan Zadi | H2: Ordered | I2: Unpaid | J2: Hassan Nasir | K2: CHEESE YELLOW
A3: Director Draw | B3: FD-002 | C3: CTN | D3: 16900 | E3: Food & Beverage | F3: Ali Tahir | G3: Abdullah | H3: Received | I3: Partial | J3: Ali Tahir | K3: CHEESE GREEN
A4: Payroll/Employee Charge | B4: FD-003 | C4: KG | D4: 1400 | E4: Food & Beverage | F4: Imran Tahir | G4: Saqib | H4: Cancelled | I4: Paid | J4: Imran Tahir | K4: MALAI BOTI
A5: Payable Payment | B5: FD-004 | C5: PCS | D5: 200 | E5: Food & Beverage | F5: Nasir Sb | G5: Kahleer | J5: Nasir Sb | K5: STEAK FILLET
A6: Food | B6: FD-005 | C6: KG | D6: 1150 | E6: Food & Beverage | F6: Riaz Sb | G6: Aqib | J6: Riaz Sb | K6: BEHARI CHICKEN
A7: Packaging | B7: FD-006 | C7: KG | D7: 1150 | E7: Food & Beverage | F7: Yasir Sb | G7: Nabeeel | J7: Yasir Sb | K7: TIKKA TOPPING FISH AND CHICK
A8: Cleaning & Sanitation | B8: FD-007 | C8: KG | D8: 1150 | E8: Food & Beverage | G8: Salman Sitaar | J8: Ahsan Zadi | K8: FAJITA TOPPING FISH AND CHICK
A9: Party & Decor | B9: FD-008 | C9: KG | D9: 800 | E9: Food & Beverage | G9: Sohail | J9: Abdullah | K9: AL-TAYYAB DRUMMET
A10: Stationery & Office Supplies | B10: FD-009 | C10: PKT | D10: 1260 | E10: Food & Beverage | G10: Usman Mahmood | J10: Saqib | K10: WINGS
A11: Marketing | B11: FD-010 | C11: PKT | D11: 1301 | E11: Food & Beverage | G11: Ali Raza | J11: Kahleer | K11: DRUMMETTE
A12: Uniform & Apparel | B12: FD-011 | C12: KG | D12: 1344 | E12: Food & Beverage | G12: Ahad | J12: Aqib | K12: SMOKED CHICKEN
A13: Equipment & Smallwares | B13: FD-012 | C13: KG | D13: 1088 | E13: Food & Beverage | G13: Faisal | J13: Nabeeel | K13: SAUSAGE
A14: Vehicle & Delivery Maintenance | B14: FD-013 | C14: KG | D14: 1122 | E14: Food & Beverage | G14: Anas | J14: Salman Sitaar | K14: CHICKEN QEEMA K&NS
A15: Fuel & Gas | B15: FD-014 | C15: PKT | D15: 1400.6 | E15: Food & Beverage | G15: Umair | J15: Sohail | K15: BIG BIRD KABAB
A16: Payroll | B16: FD-015 | C16: PKT | D16: 1800 | E16: Food & Beverage | G16: Asif | J16: Usman Mahmood | K16: BROAST CUT 9 PCS
A17: Utilities (Electricity/Water) | B17: FD-016 | C17: PKT | D17: 1150 | E17: Food & Beverage | G17: Bashrat | J17: Ali Raza | K17: TIKKA TOPPING AL-TAYYAB
A18: Distribution Cost | B18: FD-017 | C18: PKT | D18: 1150 | E18: Food & Beverage | G18: Hassan | J18: Ahad | K18: FAJITA TOPPING AL-TAYYAB
A19: Delivery Charges | B19: FD-018 | C19: PKT | D19: 974 | E19: Food & Beverage | G19: Yashwa | J19: Faisal | K19: CHICKEN STRIPS
... A27: Donation | B27: FD-026 | C27: PET | D27: 600 | E27: Food & Beverage | G27: Dawood (2) | J27: Qasim | K27: FIZE UP 1000 ML
B28: FD-027 | C28: PET | D28: 770 | E28: Food & Beverage | G28: Akash | J28: Ahmad | K28: COLA NEXT 500 ML
B29: FD-028 | C29: PET | D29: 770 | E29: Food & Beverage | G29: Ashiq | J29: Zarish | K29: FIZE UP 500 ML
B30: FD-029 | C30: PET | D30: 560 | E30: Food & Beverage | G30: Usman | J30: Sohail (2) | K30: COLA NEXT 300 ML
B31: FD-030 | C31: PET | D31: 560 | E31: Food & Beverage | G31: Vishal | J31: Masoom | K31: FIZE UP 300 ML
B32: FD-031 | C32: PET | D32: 380 | E32: Food & Beverage | G32: Zeeshan Akram | J32: Dawood | K32: WATER 1500 ML
B33: FD-032 | C33: PET | D33: 380 | E33: Food & Beverage | G33: Nabeel Ismail | J33: Dawood (2) | K33: WATER 500 ML
B34: FD-033 | C34: BOT | D34: 16000 | E34: Food & Beverage | G34: Mujahid | J34: Akash | K34: AL BARKA WATER BAR
B35: FD-034 | C35: CYL | D35: 8211 | E35: Food & Beverage | G35: Adnan Younis | J35: Ashiq | K35: MIRINDA FEGILE
B36: FD-035 | C36: PET | D36: 891 | E36: Food & Beverage | G36: Arslan Ali | J36: Usman | K36: PEPSI 1500 ML
B37: FD-036 | C37: PET | D37: 751.66667 | E37: Food & Beverage | G37: Hamza Saeed | J37: Vishal | K37: PEPSI 1000 ML
B38: FD-037 | C38: PET | D38: 990 | E38: Food & Beverage | G38: Ahsaan | J38: Zeeshan Akram | K38: PEPSI 500 ML
B39: FD-038 | C39: PET | D39: 610 | E39: Food & Beverage | G39: Hassnain Ali | J39: Nabeel Ismail | K39: GOURMENT 345 ML
... B77: FD-076 | C77: BOTTLE | D77: 2740 | E77: Food & Beverage | G77: Hammad Sb | J77: Butt | K77: OIL 4.5 LITER
B78: FD-077 | C78: BAG | D78: 8250 | E78: Food & Beverage | J78: Fahad | K78: PIZZA FLOUR
B79: FD-078 | C79: BOT | D79: 2890.0645 | E79: Food & Beverage | J79: Sherri | K79: DALDA OIL 5 LTR
B80: FD-079 | C80: PKT | D80: 2400 | E80: Food & Beverage | J80: Qari Sb | K80: NIDO MILK
B81: FD-080 | C81: PKT | D81: 900 | E81: Food & Beverage | J81: Gardener | K81: DOUGH BLEND
B82: FD-081 | C82: BOTTLE | D82: 1800 | E82: Food & Beverage | J82: Zeshan Azam | K82: SUFI SOYBEAN OIL 3 LTR
B83: FD-082 | C83: KG | D83: 200 | E83: Food & Beverage | J83: Hammad Sb | K83: CORN FLOUR
B84: FD-083 | C84: TIN | D84: 2250 | E84: Food & Beverage | K84: EUROPEAN BLACK OLIVES
B85: FD-084 | C85: TIN | D85: 2420 | E85: Food & Beverage | K85: BLACK OLIVES
B86: FD-085 | C86: TIN | D86: 1150 | E86: Food & Beverage | K86: JALAPENO
B87: FD-086 | C87: TIN | D87: 1075 | E87: Food & Beverage | K87: FRUIT COCKTAIL
B88: FD-087 | C88: TIN | D88: 1225 | E88: Food & Beverage | K88: SWEET CORN
B89: FD-088 | C89: 800GM | D89: 340 | E89: Food & Beverage | K89: TOMATO PASTE
B90: FD-089 | C90: POUCH | D90: 1050 | E90: Food & Beverage | K90: JALAPENO (3KG)
B91: FD-090 | C91: CAN | D91: 1710 | E91: Food & Beverage | K91: SHANGRILLA TOMATO PASTE
B92: FD-091 | C92: TIN | D92: 1370 | E92: Food & Beverage | K92: PINEAPPLE
B93: FD-092 | C93: POUCH | D93: 2512.5 | E93: Food & Beverage | K93: WARDAH MAYONNAISE
B94: FD-093 | C94: BLOCK | D94: 2842 | E94: Food & Beverage | K94: CHEDDER CHEESE
B95: FD-094 | C95: PKT | D95: 1800 | E95: Food & Beverage | K95: IRC BUTTER
... B482: FG-002 | C482: CYL | D482: 17025 | E482: Fuel & Gas | K482: LPG CYLINDERS
